Workbook

Sheet Parameters
A2: Production function
A3: δ | B3: 0.04 | C3: decay rate of capital | M3: MAC | Q3: TAC
A4: δ+g_L+g | B4: =B3+B53+B51 -> 0.0629 | C4: decay rate of capital per unit of effective labour | L4: emissions | M4: Model | N4: MedianIPCC | O4: P25_IPCC | P4: P75_IPCC | Q4: Model | R4: MedianIPCC | S4: P25_IPCC | T4: P75_IPCC
A5: χ | B5: 1 | C5: investment adjustment cost | L5: -2.5 | M5: =_xlfn.XLOOKUP($L5,'6states'!$L$4:$L$154,'6states'!BA$4:BA$154,,-1) -> #N/A | N5: 830.6485 | O5: 534.3041 | P5: 1319.8 | Q5: =_xlfn.XLOOKUP($L5,'6states'!$L$4:$L$104,'6states'!AR$4:AR$104,,-1) -> #N/A | R5: 0.0282474 | S5: 0.0203494 | T5: 0.0396778
A6: χ_s | B6: 5 | C6: investment adjustment cost for negative investments | L6: 2.5 | M6: =_xlfn.XLOOKUP($L6,'6states'!$L$4:$L$154,'6states'!BA$4:BA$154,,-1) -> 2701.6073 | N6: 606.6119 | O6: 387.1183 | P6: 1117.905 | Q6: =_xlfn.XLOOKUP($L6,'6states'!$L$4:$L$104,'6states'!AR$4:AR$104,,-1) -> #N/A | R6: 0.0266951 | S6: 0.0180696 | T6: 0.0408597
A7: α | B7: 0.3 | C7: share of capital income in national income | L7: 7.5 | M7: =_xlfn.XLOOKUP($L7,'6states'!$L$4:$L$154,'6states'!BA$4:BA$154,,-1) -> 819.76523 | N7: 417.0838 | O7: 242.3764 | P7: 684.3727 | Q7: =_xlfn.XLOOKUP($L7,'6states'!$L$4:$L$104,'6states'!AX$4:AX$104,,-1) -> 0.094165303 | R7: 0.0196925 | S7: 0.0123111 | T7: 0.0283897
A8: σ_f | B8: 0.2 | C8: elasticity of substitution between energy and final capital | L8: 12.5 | M8: =_xlfn.XLOOKUP($L8,'6states'!$L$4:$L$154,'6states'!BA$4:BA$154,,-1) -> 513.1788 | N8: 369.451 | O8: 259.5315 | P8: 657.7192 | Q8: =_xlfn.XLOOKUP($L8,'6states'!$L$4:$L$104,'6states'!AX$4:AX$104,,-1) -> 0.087999722 | R8: 0.0201464 | S8: 0.0142053 | T8: 0.0303724
A9: ε_f | B9: =1-1/B8 -> -4 | C9: 1-1/sigma | L9: 17.5 | M9: =_xlfn.XLOOKUP($L9,'6states'!$L$4:$L$154,'6states'!BA$4:BA$154,,-1) -> 372.20983 | N9: 279.1021 | O9: 194.9201 | P9: 471.1751 | Q9: =_xlfn.XLOOKUP($L9,'6states'!$L$4:$L$104,'6states'!AX$4:AX$104,,-1) -> 0.077164021 | R9: 0.0194575 | S9: 0.0137847 | T9: 0.0288798
A10: φ_f | B10: =1-B11 -> 0.99994397 | C10: share parameter of final-good capital | L10: 22.5 | M10: =_xlfn.XLOOKUP($L10,'6states'!$L$4:$L$154,'6states'!BA$4:BA$154,,-1) -> 274.09097 | N10: 201.3134 | O10: 145.1962 | P10: 330 | Q10: =_xlfn.XLOOKUP($L10,'6states'!$L$4:$L$104,'6states'!AX$4:AX$104,,-1) -> 0.060566036 | R10: 0.0183307 | S10: 0.0123982 | T10: 0.0285
A11: φ_E | B11: =1/(1+(B18*B16^B13+B19*B14^B13)^(B9/B13-1)*B18*B16^(B13-1)) -> 5.603267e-05 | C11: share parameter of energy capital, using Y_k_f=Y_k_c | L11: 27.5 | M11: =_xlfn.XLOOKUP($L11,'6states'!$L$4:$L$154,'6states'!BA$4:BA$154,,-1) -> 226.11165 | N11: 158.2803 | O11: 107.6669 | P11: 245.52 | Q11: =_xlfn.XLOOKUP($L11,'6states'!$L$4:$L$104,'6states'!AX$4:AX$104,,-1) -> 0.04190191 | R11: 0.0160009 | S11: 0.0110032 | T11: 0.0237186
A12: σ[0] | B12: 2 | C12: elasticity of substitution between clean and dirty capital in energy sector (initially 2) | L12: 32.5 | M12: =_xlfn.XLOOKUP($L12,'6states'!$L$4:$L$154,'6states'!BA$4:BA$154,,-1) -> 210.18249 | N12: 112.6412 | O12: 81.44473 | P12: 177.918 | Q12: =_xlfn.XLOOKUP($L12,'6states'!$L$4:$L$104,'6states'!AX$4:AX$104,,-1) -> 0.030196495 | R12: 0.0121626 | S12: 0.008787 | T12: 0.0173682
A13: ε[0] | B13: =1-1/B12 -> 0.5 | C13: 1-1/sigma | L13: 37.5 | M13: =_xlfn.XLOOKUP($L13,'6states'!$L$4:$L$154,'6states'!BA$4:BA$154,,-1) -> 195.2725 | N13: 89.53163 | O13: 58.81897 | P13: 159.2609 | Q13: =_xlfn.XLOOKUP($L13,'6states'!$L$4:$L$104,'6states'!AX$4:AX$104,,-1) -> 0.016993446 | R13: 0.0082251 | S13: 0.0056994 | T13: 0.0138741
A14: θ_d | B14: 0.1841 | C14: ratio of dirty capital over final capital (k_d+xi)/k_f | L14: 42.5 | M14: =_xlfn.XLOOKUP($L14,'6states'!$L$4:$L$154,'6states'!BA$4:BA$154,,-1) -> 185.85283 | N14: 74.8676 | O14: 47.31793 | P14: 131.6824 | Q14: =_xlfn.XLOOKUP($L14,'6states'!$L$4:$L$104,'6states'!AX$4:AX$104,,-1) -> 0.006131762 | R14: 0.006194 | S14: 0.0038782 | T14: 0.0092856
A15: k_c/(k_c+k_d+ξ) | B15: 0.16 | C15: ratio of renewable over all energy from IEA (should be 0.16) | L15: 47.5 | M15: =_xlfn.XLOOKUP($L15,'6states'!$L$4:$L$154,'6states'!BA$4:BA$154,,-1) -> 185.85283 | N15: 32.49194 | O15: 10.02872 | P15: 64.102 | Q15: =_xlfn.XLOOKUP($L15,'6states'!$L$4:$L$104,'6states'!AX$4:AX$104,,-1) -> 0.006131762 | R15: 0.0027149 | S15: 0.0007531 | T15: 0.0051001
A16: θ_c | B16: =B14*B15/(1-B15) -> 0.035066667 | C16: ratio of renewable capital over final capital k_c/k_f | L16: 52.5 | M16: =_xlfn.XLOOKUP($L16,'6states'!$L$4:$L$154,'6states'!BA$4:BA$154,,-1) -> 185.85283 | N16: 1.7695 | O16: 0 | P16: 12.83052 | Q16: =_xlfn.XLOOKUP($L16,'6states'!$L$4:$L$104,'6states'!AX$4:AX$104,,-1) -> 0.006131762 | R16: 0 | S16: 0 | T16: 0.0005013
A17: k_c/(k_d+ξ) | B17: =B16/B14 -> 0.19047619 | C17: ratio of renewable over clean energy | L17: 57.5 | M17: =_xlfn.XLOOKUP($L17,'6states'!$L$4:$L$154,'6states'!BA$4:BA$154,,-1) -> 181.28957 | N17: 2.24156 | O17: 0 | P17: 11.00962 | Q17: =_xlfn.XLOOKUP($L17,'6states'!$L$4:$L$104,'6states'!AX$4:AX$104,,-1) -> 0 | R17: 0 | S17: 0 | T17: 1e-05
A18: φ_c | B18: =1-B19 -> 0.30383243 | C18: share parameter of clean capital | D18: =B18^(1/B13) -> 0.092314148
A19: φ_d | B19: =1/((B17)^(1-B13)+1) -> 0.69616757 | C19: share parameter of dirty capital | D19: =B18^(1/0.77) -> 0.21286109 | L19: Squared Error | M19: =SUMXMY2(M6:M16,N6:N16)/11/1000 -> 425.52744 | Q19: =SUMXMY2(Q7:Q16,R7:R16)/10*10000 -> 16.386383
A20: ξ | B20: 0.01 | C20: shift in the MAC curve (0.01) | L20: combined error | M20: =M19+Q19 -> 441.91382
A21: varespilon | B21: 300 | C21: parameter in softplus function
A22: vareps2 | B22: 0.004 | C22: shift in softplus of stranding (0.004)
A24: Initial states
A25: k_d[0] | B25: =B27*B14-B20 -> 0.790835 | C25: initial dirty capital (ss in constantT&epsilon sheet) | D25: K_d[0] | E25: =B25*B$28*B$29 -> 58.418283 | F25: k_d[0] theory | G25: =B14*G27 -> 1.0792327
A26: k_c[0] | B26: =B27*B16 -> 0.15254 | C26: initial clean capital (ss in constantT&epsilon sheet) | D26: K_c[0] | E26: =B26*B$28*B$29 -> 11.267995 | F26: k_c[0] theory | G26: =B16*G27 -> 0.20556814
A27: k_f[0] | B27: 4.35 | C27: initial final capital (ss in constantT&epsilon sheet) | D27: K_f[0] | E27: =B27*B$28*B$29 -> 321.33066 | F27: k_f[0] theory | G27: =(B7*(B10+B11*(B18*B16^B13+B19*B14^B13)^(B9/B13))^(B7/B9)*EXP(-B46/2*B47^2) / (B56+B5*(B56)^2)) ^ (1/(1-B7)) -> 5.8622094
A28: L[0] | B28: 8.16 | C28: initial Labour | D28: K[0]=(k_f[0]+k_d[0]+k_c[0])*A[0]L[0] | E28: =(B25+B26+B27)*B28*B29 -> 391.01694 | F28: total capital
A29: A[0] | B29: =B30*EXP(B46/2*B47^2)/B28/(Parameters!$B$10*B27^Parameters!$B$9+B11*E30^Parameters!$B$9)^(Parameters!$B$7/Parameters!$B$9) -> 9.0525879 | C29: tfp (targeting Y0) | D29: k_ramsey | E29: =((Parameters!B3+Parameters!B50+Parameters!B52*Parameters!B53)/Parameters!B7)^(1/(Parameters!B7-1)) -> 6.8509746 | F29: k steady state in Ramsey model (without energy)k=((sigma+delta+etag)/alpha)^(1/alpha-1)
A30: Y[0] | B30: 110.98 | C30: initial GDP (trillion $, MERs) | D30: E[0] | E30: =(B18*B26^B13+B19*(B25+B20)^B13)^(1/B13) -> 0.55006251
A31: P_BAU | B31: 53.2 | C31: initial business as usual emissions | D31: k_c/(k_c+k_d) | E31: =B26/(B26+B25) -> 0.16169604 | F31: slightly higher than in theory, due to effect of z
D32: Y_E*E/Y | E32: =B7*B11*E30^(B9-1)/(B10*B27^B9+B11*E30^B9) * E30 -> 0.05393028 | F32: share of energy capital in GDP
D33: Y_kf*kf/Y | E33: =B7*B10*B27^(B9-1)/(B10*B27^B9+B11*E30^B9) * B27 -> 0.24606972 | F33: share of final capital income in GDP
A34: Stranding costs
A35: A[0]L[0]ψ/(σ+g_ψ) | B35: =Parameters!B29*Parameters!B28*Parameters!B41/(Parameters!B3+B42) -> 1345.4134 | C35: cumulative stranded emissions per unit of stranded capital k_s at time zero
A36: Intercept | B36: =6.1198+0.7666 -> 6.8864 | C36: highest carbon intensity in GtCO2/T$, that is kg per $ (sum of a and c from calibration)
A37: ψ_1 | B37: =B36-B39 -> 6.1194186
A38: ψ_2 | B38: 0.729 | C38: degrowth rate of psi as a function of cumulative stranded emissions (calibrated parameter per Billion $ multiplied by 1000)
A39: ψ_3 | B39: =(B31-B36/B38*(1-EXP(-B38*E25)))/(E25-(1-EXP(-B38*E25))/B38) -> 0.76698139
A40: ψ_min | B40: =B37*EXP(-B38*E25)+B39 -> 0.76698139 | C40: lowest emissions intensity of capital at start
A41: \bar{ψ} | B41: =B31/B28/B29/B25 -> 0.9106738 | C41: mean emissions intensity at start
A42: g_ψ | B42: 0.01 | C42: autonomous decrease in carbon intensity
A44: Damages
A45: ζ | B45: 0.0006 | C45: TCRE
A46: γ | B46: 0.0201 | C46: total damage for 1°C/2 (0.0154 before)
A47: T[0] | B47: 1.38 | C47: initial temperature
A49: Discount rate
A50: ρ | B50: =0.011 -> 0.011 | C50: pure time preference rate
A51: g_L | B51: 0.0029 | C51: labour growth
A52: η | B52: 1.35 | C52: elasticity of marginal utility of consumption
A53: g | B53: 0.02 | C53: productivity growth
A54: r | B54: =B50-B51+B52*B53 -> 0.0351
A55: r-g | B55: =B50-B51+(B52-1)*B53 -> 0.0151
A56: r+δ+g_L | B56: =B54+B3+B51 -> 0.078
A57: β | B57: =EXP(-B55) -> 0.98501343 | C57: discount factor
A59: Technical change
A60: g_σ | B60: 0.027 | C60: growth rate of exogenous TC
A61: ω | B61: 0.5 | C61: share of exogenous TC
A62: M[0] | B62: 50 | C62: initial cumulative abatement
A63: ρ | B63: 0.1 | C63: elasticity of endogenous TC
A65: time step | B65: 1

Sheet 6states
A1: 6 states: k_f, k_d, k_c, k_s, T, time | BF1: ss lambdaT | BG1: =-W204*X204^(-Parameters!B$52)*Parameters!B$46*Parameters!B$45*N204/Parameters!B45/Parameters!B55 -> -2.5272931
BF2: endog TC missing
A3: Period | B3: Year | C3: i_d[t] | D3: i_c[t] | E3: i_f[t] | F3: k_d[t] | G3: k_c[t] | H3: k_f[t] | I3: k_s[t] | J3: L[t] | K3: A[t] | L3: P[t] | M3: S[t] | N3: T[t] | O3: Ω[t] | P3: M[t]/M[0] | Q3: ω*exp(g_σ)*t | R3: ω*M[t]^-ρ | S3: TC[t] | T3: ε[t] | U3: σ[t] | V3: E[t]/(A[t]*L[t]) | W3: y[t] | X3: c[t] | Y3: β^t | Z3: β^t * u(c[t]) | AA3: W | AC3: I_d[t] | AD3: I_c[t] | AE3: K_s[t] | AF3: K_d[t] | AG3: K_c[t] | AH3: E[t] | AI3: E[t]/E[0] | AJ3: Y[t] | AK3: C[t] | AL3: g_Y[t] | AM3: g_C[t] | AN3: g_Y[t] (5-year moving average) | AO3: g_C[t] (5-year moving average) | AQ3: y_kd-y_kc | AR3: change id ic | AS3: id² ic² | AT3: dP/dKd | AU3: dP/dkd | AV3: MAC[t] | AW3: TAC[t] | AX3: Mgl damage[t] (utils) | AY3: Mgl damage[t] ($) | BA3: SCC[t] | BB3: s[t] | BC3: Dirty adjustment costs (% of investment) | BD3: Clean adj costs (% of investment) | BE3: ratio clean/dirty adj costs | BF3: lambdaS | BG3: lambdaT | BH3: g_lambdaT | BI3: lmbdks-lmbdkd | BJ3: U_c | BK3: dP/dKs | BL3: dP/dks | BM3: ks/(kd+ks) | BN3: dP/Ks-dP/dKd | BS3: lambdaS*dP/dks | BT3: lambdaks | BU3: lambdakc | BV3: g_lambdakc | BW3: lambdakf | BX3: g_lambdakf | BY3: lambdakd | BZ3: g_lambdakd | CA3: d_lambdakd | CB3: elasticity wrt M for LT clean productivity | CC3: E_kc at initial capital ratios | CD3: LR elasticity wrt M for initial clean productivity | CE3: Learning rate | CF3: Learning rate at initial k_j
A4: 0 | B4: 2025 | C4: -0.030791 | D4: 0.037975028 | E4: 0.25186597 | F4: =Parameters!B25 -> 0.790835 | G4: =Parameters!B26 -> 0.15254 | H4: =Parameters!B27 -> 4.35 | I4: 0 | J4: =Parameters!B28 -> 8.16 | K4: =Parameters!B29 -> 9.0525879 | L4: =J4*K4*EXP(-Parameters!$B$42*'6states'!A4)*(Parameters!$B$37/Parameters!$B$38*('6states'!F4+'6states'!I4)/Parameters!$E$25*(EXP(-Parameters!$B$38*Parameters!$E$25*'6states'!I4/('6states'!F4+'6states'!I4))-EXP(-Parameters!$B$38*Parameters!$E$25)) + Parameters!$B$39*'6states'!F4) -> 53.2 | M4: =N4/Parameters!$B$45 -> 2300 | N4: =Parameters!B47 -> 1.38 | O4: =EXP(-Parameters!$B$46/2*N4^2) -> 0.98104277 | P4: =MAX((Parameters!$B$62 + Parameters!$B$31*'6states'!A4 - '6states'!M4 + Parameters!$B$47/Parameters!$B$45)/Parameters!B$62,1) -> 1 | Q4: =Parameters!B$61*EXP(-Parameters!B$60*A4) -> 0.5 | R4: =(1-Parameters!B$61)*P4^-Parameters!B$63 -> 0.5 | S4: =Parameters!B$61*EXP(-Parameters!B$60*A4)+(1-Parameters!B$61)*P4^-Parameters!B$63 -> 1 | T4: =1-S4/Parameters!$B$12 -> 0.5 | U4: =1/(1-T4) -> 2 | V4: =(Parameters!$B$19*(F4+Parameters!$B$20)^T4+Parameters!$B$18*G4^T4)^(1/T4) -> 0.55006251 | W4: =(Parameters!$B$10*H4^Parameters!$B$9+Parameters!$B$11*V4^Parameters!$B$9)^(Parameters!$B$7/Parameters!$B$9)*O4 -> 1.502387 | X4: =W4 - D4 - E4 - LN(1+EXP(Parameters!$B$21*C4))/Parameters!$B$21 - IF(C4>0, 0,Parameters!$B$6*C4^2/F4) -> 1.2065515 | Y4: =EXP(-Parameters!$B$55*A4) -> 1 | Z4: =IF(X4>0,X4^(1-Parameters!$B$52)/(1-Parameters!$B$52)*Y4*Parameters!$B$65,-10+X4*1000) -> -2.6754135 | AA4: =SUM(Z4:Z204)*Parameters!$B$65 -> -185.78348 | AC4: =C4*$J4*$K4 -> -2.274504 | AD4: =D4*$J4*$K4 -> 2.8051818 | AE4: =I4*J4*K4 -> 0 | AF4: =F4*J4*K4 -> 58.418283 | AG4: =G4*J4*K4 -> 11.267995 | AH4: =V4*J4*K4 -> 40.632632 | AI4: =AH4/AH$4*100 -> 100 | AJ4: =W4*J4*K4 -> 110.98 | AK4: =X4*J4*K4 -> 89.126891 | AQ4: =W4*K4*J4 -> 110.98 | AR4: =Parameters!$B$7*W4*(W4/O4)^(-Parameters!$B$9/Parameters!$B$7)*Parameters!$B$11*(V4)^(Parameters!$B$9-T4)*((1-2*Parameters!$B$5*C4/F4)*Parameters!$B$19*(F4+Parameters!$B$20)^(T4-1)-(1-2*Parameters!$B$5*D4/G4)*(Parameters!$B$18)*(G4)^(T4-1)) -> 0.048932949 | AU4: =EXP(-Parameters!$B$42*'6states'!A4)*(Parameters!$B$37*EXP(-Parameters!$B$38*Parameters!$E$25*'6states'!I4/('6states'!F4+'6states'!I4))*(1/Parameters!$B$38/Parameters!$E$25+'6states'!I4/('6states'!F4+'6states'!I4))-Parameters!$B$37/Parameters!$B$38/Parameters!$E$25*EXP(-Parameters!$B$38*Parameters!$E$25)+Parameters!$B$39) -> 0.9106738 | AV4: =J4*K4*EXP(-Parameters!$B$42*'6states'!A4)*(Parameters!$B$37*EXP(-Parameters!$B$38*Parameters!$E$25*'6states'!I4/('6states'!F4+'6states'!I4))*(1/Parameters!$B$38/Parameters!$E$25+'6states'!I4/('6states'!F4+'6states'!I4))-Parameters!$B$37/Parameters!$B$38/Parameters!$E$25*EXP(-Parameters!$B$38*Parameters!$E$25)+Parameters!$B$39) -> 67.27067 | AX4: =1-W4/'6states,ExoDamages'!T4 -> 0 | AZ4: =1000*EXP(-(Parameters!$B$54)*'6states'!A4)*AQ4*Parameters!B$46*Parameters!B$45*N4 -> 1.8470179 | BA4: =SUM(AZ4:AZ$204)*EXP(Parameters!$B$54*A4) -> 181.28957 | BB4: =((C4>0)*C4+D4+E4)/W4 -> 0.19292033 | BC4: =Parameters!$B$6*C4/F4 -> -0.19467399 | BD4: =Parameters!$B$5*D4/G4 -> 0.24895128 | BE4: =(1-2*BD4)/(1-2*BC4) -> 0.3613907 | BF4: =SUM(AY4:AY202)/Y4 -> -0.0018421522 | BG4: =BF4/Parameters!$B$45 -> -3.0702537 | BI4: =-2*Parameters!B$6 * C4/F4*X4^-Parameters!B$52 -> 0.30216977 | BJ4: =X4^-Parameters!B$52 -> 0.77609181 | BK4: =-EXP(-Parameters!B$42*'6states'!A4)*(-Parameters!B$37/Parameters!B$38/Parameters!E$25*(EXP(-Parameters!B$38*Parameters!E$25*'6states'!I4/('6states'!F4+'6states'!I4))-EXP(-Parameters!B$38*Parameters!E$25)) + Parameters!B$37*'6states'!F4/('6states'!F4+'6states'!I4)*EXP(-Parameters!B$38*Parameters!E$25*'6states'!I4/('6states'!F4+'6states'!I4))) -> -5.9757262 | BL4: =-J4*K4*EXP(-Parameters!B$42*'6states'!A4)*(-Parameters!B$37/Parameters!B$38/Parameters!E$25*(EXP(-Parameters!B$38*Parameters!E$25*'6states'!I4/('6states'!F4+'6states'!I4))-EXP(-Parameters!B$38*Parameters!E$25)) + Parameters!B$37*'6states'!F4/('6states'!F4+'6states'!I4)*EXP(-Parameters!B$38*Parameters!E$25*'6states'!I4/('6states'!F4+'6states'!I4))) -> -441.42162 | BM4: =I4/(F4+I4) -> 0 | BN4: =BK4-AU4 -> -6.8864 | BS4: =EXP(-Parameters!$B$56*A4)*BF4*BL4 -> 0.8131658 | BT4: =-EXP((Parameters!$B$56)*F4)*SUM(BS4:BS12) -> -1.1781449 | BU4: =$X4^-Parameters!$B$52/(1-2*Parameters!$B$5*'6states'!$D4/'6states'!$G4) -> 1.5456996 | BW4: =$X4^-Parameters!$B$52/(1-2*Parameters!$B$5*'6states'!$E4/'6states'!$H4) -> 0.87773378 | BY4: =($X4^-Parameters!$B$52*(1/(1+EXP(-C4)) + IF(C4<0,2*Parameters!$B$6*C4/F4,0)) + BQ4*(1/(1+EXP((C4-Parameters!$B$22)*Parameters!$B$21))))/(1-IF(C4>0,2*Parameters!$B$5*C4/F4,0)) -> 0.079902445 | CC4: =(Parameters!$B$18*'6states'!T4^+Parameters!$B$19*Parameters!$B$25^'6states'!T4)^((1-'6states'!T4)/'6states'!T4)*Parameters!$B$18*Parameters!$B$26^('6states'!T4-1) -> 0.12973347
A5: =A4+Parameters!$B$65 -> 1 | B5: 2026 | C5: -0.013294684 | D5: 0.041248303 | E5: 0.24555224 | F5: =MAX((1-Parameters!$B$4)^Parameters!B$65*F4 + C4*Parameters!B$65 - IF(C4>0,Parameters!$B$5,0)*C4^2/F4*Parameters!B$65, 0.0001) -> 0.71030048 | G5: =(1-Parameters!$B$4)^Parameters!B$65*G4+D4*Parameters!B$65-Parameters!$B$5*D4^2/G4*Parameters!B$65 -> 0.17146633 | H5: =(1-Parameters!$B$4)^Parameters!B$65*H4+E4*Parameters!B$65-Parameters!$B$5*E4^2/H4*Parameters!B$65 -> 4.3136679 | I5: =I4 *(1-Parameters!$B$4)-C4*(C4<0)*Parameters!B$65 -> 0.030791 | J5: =J4*(1+Parameters!$B$51)^Parameters!B$65 -> 8.183664 | K5: =K4*(1+Parameters!$B$53)^Parameters!B$65 -> 9.2336396 | L5: =J5*K5*EXP(-Parameters!$B$42*'6states'!A5)*(Parameters!$B$37/Parameters!$B$38*('6states'!F5+'6states'!I5)/Parameters!$E$25*(EXP(-Parameters!$B$38*Parameters!$E$25*'6states'!I5/('6states'!F5+'6states'!I5))-EXP(-Parameters!$B$38*Parameters!$E$25)) + Parameters!$B$39*'6states'!F5) -> 42.115043 | M5: =M4+L5*Parameters!B$65 -> 2342.115 | N5: =M5*Parameters!$B$45 -> 1.405269 | O5: =EXP(-Parameters!$B$46/2*N5^2) -> 0.9803491 | P5: =MAX((Parameters!$B$62 + Parameters!$B$31*'6states'!A5 - '6states'!M5 + Parameters!$B$47/Parameters!$B$45)/Parameters!B$62,1) -> 1.2216991 | Q5: =Parameters!B$61*EXP(-Parameters!B$60*A5) -> 0.48668062 | R5: =(1-Parameters!B$61)*P5^-Parameters!B$63 -> 0.49008745 | S5: =Parameters!B$61*EXP(-Parameters!B$60*A5)+(1-Parameters!B$61)*P5^-Parameters!B$63 -> 0.97676807 | T5: =1-S5/Parameters!$B$12 -> 0.51161597 | U5: =1/(1-T5) -> 2.047569 | V5: =(Parameters!$B$19*(F5+Parameters!$B$20)^T5+Parameters!$B$18*G5^T5)^(1/T5) -> 0.51461926 | W5: =(Parameters!$B$10*H5^Parameters!$B$9+Parameters!$B$11*V5^Parameters!$B$9)^(Parameters!$B$7/Parameters!$B$9)*O5 -> 1.4923874 | X5: =W5 - D5 - E5 - LN(1+EXP(Parameters!$B$21*C5))/Parameters!$B$21 - IF(C5>0, 0,Parameters!$B$6*C5^2/F5) -> 1.2042814 | Y5: =EXP(-Parameters!$B$55*A5) -> 0.98501343 | Z5: =IF(X5>0,X5^(1-Parameters!$B$52)/(1-Parameters!$B$52)*Y5*Parameters!$B$65,-10+X5*1000) -> -2.6370557 | AC5: =C5*$J5*$K5 -> -1.0046128 | AD5: =D5*$J5*$K5 -> 3.1169281 | AE5: =I5*J5*K5 -> 2.3267221 | AF5: =F5*J5*K5 -> 53.673859 | AG5: =G5*J5*K5 -> 12.956854 | AH5: =V5*J5*K5 -> 38.887207 | AI5: =AH5/AH$4*100 -> 95.704376 | AJ5: =W5*J5*K5 -> 112.77226 | AK5: =X5*J5*K5 -> 91.001532 | AL5: =LN(AJ5)-LN(AJ4) -> 0.016020359 | AM5: =LN(AK5)-LN(AK4) -> 0.020815248 | AQ5: =W5*K5*J5 -> 112.77226 | AR5: =Parameters!$B$7*W5*(W5/O5)^(-Parameters!$B$9/Parameters!$B$7)*Parameters!$B$11*(V5)^(Parameters!$B$9-T5)*((1-2*Parameters!$B$5*C5/F5)*Parameters!$B$19*(F5+Parameters!$B$20)^(T5-1)-(1-2*Parameters!$B$5*D5/G5)*(Parameters!$B$18)*(G5)^(T5-1)) -> 0.064700083 | AS5: =((C6-C4)/2-(F6-F4)/F5/2*C5)/(F5/2/Parameters!$B$5-C5)-((D6-D4)/D5-(G6-G4)/G5)/(G5/2/Parameters!$B$5/D5-1) -> 0.098586218 | AT5: =+Parameters!$B$5*C5^2/F5^2-Parameters!$B$5*D5^2/G5^2 -> -0.057519804 | AU5: =EXP(-Parameters!$B$42*'6states'!A5)*(Parameters!$B$37*EXP(-Parameters!$B$38*Parameters!$E$25*'6states'!I5/('6states'!F5+'6states'!I5))*(1/Parameters!$B$38/Parameters!$E$25+'6states'!I5/('6states'!F5+'6states'!I5))-Parameters!$B$37/Parameters!$B$38/Parameters!$E$25*EXP(-Parameters!$B$38*Parameters!$E$25)+Parameters!$B$39) -> 0.82649784 | AV5: =J5*K5*EXP(-Parameters!$B$42*'6states'!A5)*(Parameters!$B$37*EXP(-Parameters!$B$38*Parameters!$E$25*'6states'!I5/('6states'!F5+'6states'!I5))*(1/Parameters!$B$38/Parameters!$E$25+'6states'!I5/('6states'!F5+'6states'!I5))-Parameters!$B$37/Parameters!$B$38/Parameters!$E$25*EXP(-Parameters!$B$38*Parameters!$E$25)+Parameters!$B$39) -> 62.454313 | AW5: =1000*(AR5+AS5+AT5)/AU5 -> 127.96948 | AX5: =1-W5/'6states,ExoDamages'!T5 -> 0.006131762 | AY5: =-Y5*W5*X5^(-Parameters!B$52)*Parameters!B$46*Parameters!B$45*N5 -> -1.9384192e-05 | AZ5: =1000*EXP(-(Parameters!$B$54)*'6states'!A5)*AQ5*Parameters!B$46*Parameters!B$45*N5 -> 1.8452929 | BA5: =SUM(AZ5:AZ$204)*EXP(Parameters!$B$54*A5) -> 185.85283 | BB5: =((C5>0)*C5+D5+E5)/W5 -> 0.19217567 | BC5: =Parameters!$B$6*C5/F5 -> -0.093584928 | BD5: =Parameters!$B$5*D5/G5 -> 0.24056211 | BE5: =(1-2*BD5)/(1-2*BC5) -> 0.43706954 | BF5: =SUM(AY5:AY203)/Y5 -> -0.0018734178 | BG5: =BF5/Parameters!$B$45 -> -3.1223629 | BH5: =1-BG4/BG5 -> 0.016689052 | BI5: =-2*Parameters!B$6 * C5/F5*X5^-Parameters!B$52 -> 0.14563076 | BJ5: =X5^-Parameters!B$52 -> 0.77806738 | BK5: =-EXP(-Parameters!B$42*'6states'!A5)*(-Parameters!B$37/Parameters!B$38/Parameters!E$25*(EXP(-Parameters!B$38*Parameters!E$25*'6states'!AE5/('6states'!F5+'6states'!AE5))-EXP(-Parameters!B$38*Parameters!E$25))+Parameters!B$37*'6states'!F5/('6states'!F5+'6states'!AE5)*EXP(-Parameters!B$38*Parameters!E$25*'6states'!I5/('6states'!F5+'6states'!AE5))) -> -0.92012354 | BL5: =-J5*K5*EXP(-Parameters!B$42*'6states'!A5)*(-Parameters!B$37/Parameters!B$38/Parameters!E$25*(EXP(-Parameters!B$38*Parameters!E$25*'6states'!I5/('6states'!F5+'6states'!I5))-EXP(-Parameters!B$38*Parameters!E$25)) + Parameters!B$37*'6states'!F5/('6states'!F5+'6states'!I5)*EXP(-Parameters!B$38*Parameters!E$25*'6states'!I5/('6states'!F5+'6states'!I5))) -> -72.95266 | BM5: =I5/(F5+I5) -> 0.041548177 | BN5: =BK5-AU5 -> -1.7466214 | BS5: =EXP(-Parameters!$B$56*A5)*BF5*BL5 -> 0.12641564 | BT5: =-EXP((Parameters!$B$56)*F5)*SUM(BS5:BS13) -> -0.32245872 | BU5: =X5^-Parameters!B$52/(1-2*Parameters!B$5*'6states'!D5/'6states'!G5) -> 1.4995253 | BV5: =BU5/BU4 -> 0.97012728 | BW5: =$X5^-Parameters!$B$52/(1-2*Parameters!$B$5*'6states'!$E5/'6states'!$H5) -> 0.87802972 | BX5: =BW5/BW4 -> 1.0003372 | BY5: =($X5^-Parameters!$B$52*(1/(1+EXP(-C5)) + IF(C5<0,2*Parameters!$B$6*C5/F5,0)) + BQ5*(1/(1+EXP((C5-Parameters!$B$22)*Parameters!$B$21))))/(1-IF(C5>0,2*Parameters!$B$5*C5/F5,0)) -> 0.24081693 | BZ5: =BY5/BY4 -> 3.0138868 | CA5: =BY5-BY4 -> 0.16091448 | CB5: =(1/$T5-1/Parameters!$B$13) * LN(Parameters!$B$18) / LN(P5) -> 0.27014578 | CC5: =(Parameters!$B$18*'6states'!T5^+Parameters!$B$19*Parameters!$B$25^'6states'!T5)^((1-'6states'!T5)/'6states'!T5)*Parameters!$B$18*Parameters!$B$26^('6states'!T5-1) -> 0.13944009 | CD5: =(LN(CC5)-LN(CC$4))/ LN(P5) -> 0.36032768 | CE5: =1-2^-CB5 -> 0.17076425 | CF5: =1-2^-CC5 -> 0.092128568
A6: =A5+Parameters!$B$65 -> 2 | B6: 2027 | C6: -0.0085753021 | D6: 0.044268233 | E6: 0.24016693 | F6: =MAX((1-Parameters!$B$4)^Parameters!B$65*F5 + C5*Parameters!B$65 - IF(C5>0,Parameters!$B$5,0)*C5^2/F5*Parameters!B$65, 0.0001) -> 0.65232789 | G6: =(1-Parameters!$B$4)^Parameters!B$65*G5+D5*Parameters!B$65-Parameters!$B$5*D5^2/G5*Parameters!B$65 -> 0.19200662 | H6: =(1-Parameters!$B$4)^Parameters!B$65*H5+E5*Parameters!B$65-Parameters!$B$5*E5^2/H5*Parameters!B$65 -> 4.2739125 | I6: =I5 *(1-Parameters!$B$4)-C5*(C5<0)*Parameters!B$65 -> 0.04214893 | J6: =J5*(1+Parameters!$B$51)^Parameters!B$65 -> 8.2073966 | K6: =K5*(1+Parameters!$B$53)^Parameters!B$65 -> 9.4183124 | L6: =J6*K6*EXP(-Parameters!$B$42*'6states'!A6)*(Parameters!$B$37/Parameters!$B$38*('6states'!F6+'6states'!I6)/Parameters!$E$25*(EXP(-Parameters!$B$38*Parameters!$E$25*'6states'!I6/('6states'!F6+'6states'!I6))-EXP(-Parameters!$B$38*Parameters!$E$25)) + Parameters!$B$39*'6states'!F6) -> 38.479358 | M6: =M5+L6*Parameters!B$65 -> 2380.5944 | N6: =M6*Parameters!$B$45 -> 1.4283566 | O6: =EXP(-Parameters!$B$46/2*N6^2) -> 0.97970474 | P6: =MAX((Parameters!$B$62 + Parameters!$B$31*'6states'!A6 - '6states'!M6 + Parameters!$B$47/Parameters!$B$45)/Parameters!B$62,1) -> 1.516112 | Q6: =Parameters!B$61*EXP(-Parameters!B$60*A6) -> 0.47371605 | R6: =(1-Parameters!B$61)*P6^-Parameters!B$63 -> 0.47961955 | S6: =Parameters!B$61*EXP(-Parameters!B$60*A6)+(1-Parameters!B$61)*P6^-Parameters!B$63 -> 0.9533356 | T6: =1-S6/Parameters!$B$12 -> 0.5233322 | U6: =1/(1-T6) -> 2.0978971 | V6: =(Parameters!$B$19*(F6+Parameters!$B$20)^T6+Parameters!$B$18*G6^T6)^(1/T6) -> 0.49109712 | W6: =(Parameters!$B$10*H6^Parameters!$B$9+Parameters!$B$11*V6^Parameters!$B$9)^(Parameters!$B$7/Parameters!$B$9)*O6 -> 1.483427 | X6: =W6 - D6 - E6 - LN(1+EXP(Parameters!$B$21*C6))/Parameters!$B$21 - IF(C6>0, 0,Parameters!$B$6*C6^2/F6) -> 1.198183 | Y6: =EXP(-Parameters!$B$55*A6) -> 0.97025146 | Z6: =IF(X6>0,X6^(1-Parameters!$B$52)/(1-Parameters!$B$52)*Y6*Parameters!$B$65,-10+X6*1000) -> -2.602155 | AC6: =C6*$J6*$K6 -> -0.66286935 | AD6: =D6*$J6*$K6 -> 3.4219267 | AE6: =I6*J6*K6 -> 3.2581049 | AF6: =F6*J6*K6 -> 50.424832 | AG6: =G6*J6*K6 -> 14.842078 | AH6: =V6*J6*K6 -> 37.961722 | AI6: =AH6/AH$4*100 -> 93.426687 | AJ6: =W6*J6*K6 -> 114.66865 | AK6: =X6*J6*K6 -> 92.619338 | AL6: =LN(AJ6)-LN(AJ5) -> 0.016676307 | AM6: =LN(AK6)-LN(AK5) -> 0.017621611 | AQ6: =W6*K6*J6 -> 114.66865 | AR6: =Parameters!$B$7*W6*(W6/O6)^(-Parameters!$B$9/Parameters!$B$7)*Parameters!$B$11*(V6)^(Parameters!$B$9-T6)*((1-2*Parameters!$B$5*C6/F6)*Parameters!$B$19*(F6+Parameters!$B$20)^(T6-1)-(1-2*Parameters!$B$5*D6/G6)*(Parameters!$B$18)*(G6)^(T6-1)) -> 0.08009383 | AS6: =((C7-C5)/2-(F7-F5)/F6/2*C6)/(F6/2/Parameters!$B$5-C6)-((D7-D5)/D6-(G7-G5)/G6)/(G6/2/Parameters!$B$5/D6-1) -> 0.10710763 | AT6: =+Parameters!$B$5*C6^2/F6^2-Parameters!$B$5*D6^2/G6^2 -> -0.052983149 | AU6: =EXP(-Parameters!$B$42*'6states'!A6)*(Parameters!$B$37*EXP(-Parameters!$B$38*Parameters!$E$25*'6states'!I6/('6states'!F6+'6states'!I6))*(1/Parameters!$B$38/Parameters!$E$25+'6states'!I6/('6states'!F6+'6states'!I6))-Parameters!$B$37/Parameters!$B$38/Parameters!$E$25*EXP(-Parameters!$B$38*Parameters!$E$25)+Parameters!$B$39) -> 0.78987346 | AV6: =J6*K6*EXP(-Parameters!$B$42*'6states'!A6)*(Parameters!$B$37*EXP(-Parameters!$B$38*Parameters!$E$25*'6states'!I6/('6states'!F6+'6states'!I6))*(1/Parameters!$B$38/Parameters!$E$25+'6states'!I6/('6states'!F6+'6states'!I6))-Parameters!$B$37/Parameters!$B$38/Parameters!$E$25*EXP(-Parameters!$B$38*Parameters!$E$25)+Parameters!$B$39) -> 61.057081 | AW6: =1000*(AR6+AS6+AT6)/AU6 -> 169.92382 | AX6: =1-W6/'6states,ExoDamages'!T6 -> 0.011604402 | AY6: =-Y6*W6*X6^(-Parameters!B$52)*Parameters!B$46*Parameters!B$45*N6 -> -1.9423532e-05 | AZ6: =1000*EXP(-(Parameters!$B$54)*'6states'!A6)*AQ6*Parameters!B$46*Parameters!B$45*N6 -> 1.8413706 | BA6: =SUM(AZ6:AZ$204)*EXP(Parameters!$B$54*A6) -> 190.51261 | BB6: =((C6>0)*C6+D6+E6)/W6 -> 0.19174193 | BC6: =Parameters!$B$6*C6/F6 -> -0.065728464 | BD6: =Parameters!$B$5*D6/G6 -> 0.23055576 | BE6: =(1-2*BD6)/(1-2*BC6) -> 0.47627839 | BF6: =SUM(AY6:AY204)/Y6 -> -0.0018830942 | BG6: =BF6/Parameters!$B$45 -> -3.1384903 | BH6: =1-BG5/BG6 -> 0.0051385735 | BI6: =-2*Parameters!B$6 * C6/F6*X6^-Parameters!B$52 -> 0.10298577 | BJ6: =X6^-Parameters!B$52 -> 0.78341834 | BK6: =-EXP(-Parameters!B$42*'6states'!A6)*(-Parameters!B$37/Parameters!B$38/Parameters!E$25*(EXP(-Parameters!B$38*Parameters!E$25*'6states'!AE6/('6states'!F6+'6states'!AE6))-EXP(-Parameters!B$38*Parameters!E$25))+Parameters!B$37*'6states'!F6/('6states'!F6+'6states'!AE6)*EXP(-Parameters!B$38*Parameters!E$25*'6states'!I6/('6states'!F6+'6states'!AE6))) -> -0.63228458 | BL6: =-J6*K6*EXP(-Parameters!B$42*'6states'!A6)*(-Parameters!B$37/Parameters!B$38/Parameters!E$25*(EXP(-Parameters!B$38*Parameters!E$25*'6states'!I6/('6states'!F6+'6states'!I6))-EXP(-Parameters!B$38*Parameters!E$25)) + Parameters!B$37*'6states'!F6/('6states'!F6+'6states'!I6)*EXP(-Parameters!B$38*Parameters!E$25*'6states'!I6/('6states'!F6+'6states'!I6))) -> -32.026411 | BM6: =I6/(F6+I6) -> 0.060691629 | BN6: =BK6-AU6 -> -1.422158 | BS6: =EXP(-Parameters!$B$56*A6)*BF6*BL6 -> 0.051597704 | BT6: =-EXP((Parameters!$B$56)*F6)*SUM(BS6:BS14) -> -0.19933421 | BU6: =X6^-Parameters!B$52/(1-2*Parameters!B$5*'6states'!D6/'6states'!G6) -> 1.4537671 | BV6: =BU6/BU5 -> 0.96948484 | BW6: =$X6^-Parameters!$B$52/(1-2*Parameters!$B$5*'6states'!$E6/'6states'!$H6) -> 0.8826129 | BX6: =BW6/BW5 -> 1.0052198 | BY6: =($X6^-Parameters!$B$52 * (1/(1+EXP(-C6)) + IF(C6<0,2*Parameters!$B$6*C6/F6,0)) + BQ6 * (1/(1+EXP((C6-Parameters!$B$22)*Parameters!$B$21)))) / (1-IF(C6>0,2*Parameters!$B$5*C6/F6,0)) -> 0.2870439 | BZ6: =BY6/BY5 -> 1.191959 | CA6: =BY6-BY5 -> 0.046226971 | CB6: =(1/$T6-1/Parameters!$B$13) * LN(Parameters!$B$18) / LN(P6) -> 0.25525406 | CC6: =(Parameters!$B$18*'6states'!T6^+Parameters!$B$19*Parameters!$B$25^'6states'!T6)^((1-'6states'!T6)/'6states'!T6)*Parameters!$B$18*Parameters!$B$26^('6states'!T6-1) -> 0.14919534 | CD6: =(LN(CC6)-LN(CC$4))/ LN(P6) -> 0.3358756 | CE6: =1-2^-CB6 -> 0.16216042 | CF6: =1-2^-CC6 -> 0.098246724
A7: =A6+Parameters!$B$65 -> 3 | B7: 2028 | C7: 0.0053725717 | D7: 0.046844726 | E7: 0.23367109 | F7: =MAX((1-Parameters!$B$4)^Parameters!B$65*F6 + C6*Parameters!B$65 - IF(C6>0,Parameters!$B$5,0)*C6^2/F6*Parameters!B$65, 0.0001) -> 0.60272117 | G7: =(1-Parameters!$B$4)^Parameters!B$65*G6+D6*Parameters!B$65-Parameters!$B$5*D6^2/G6*Parameters!B$65 -> 0.21399134 | H7: =(1-Parameters!$B$4)^Parameters!B$65*H6+E6*Parameters!B$65-Parameters!$B$5*E6^2/H6*Parameters!B$65 -> 4.2317545 | I7: =I6 *(1-Parameters!$B$4)-C6*(C6<0)*Parameters!B$65 -> 0.048073064 | J7: =J6*(1+Parameters!$B$51)^Parameters!B$65 -> 8.2311981 | K7: =K6*(1+Parameters!$B$53)^Parameters!B$65 -> 9.6066786 | L7: =J7*K7*EXP(-Parameters!$B$42*'6states'!A7)*(Parameters!$B$37/Parameters!$B$38*('6states'!F7+'6states'!I7)/Parameters!$E$25*(EXP(-Parameters!$B$38*Parameters!$E$25*'6states'!I7/('6states'!F7+'6states'!I7))-EXP(-Parameters!$B$38*Parameters!$E$25)) + Parameters!$B$39*'6states'!F7) -> 35.78268 | M7: =M6+L7*Parameters!B$65 -> 2416.3771 | N7: =M7*Parameters!$B$45 -> 1.4498262 | O7: =EXP(-Parameters!$B$46/2*N7^2) -> 0.97909651 | P7: =MAX((Parameters!$B$62 + Parameters!$B$31*'6states'!A7 - '6states'!M7 + Parameters!$B$47/Parameters!$B$45)/Parameters!B$62,1) -> 1.8644584 | Q7: =Parameters!B$61*EXP(-Parameters!B$60*A7) -> 0.46109685 | R7: =(1-Parameters!B$61)*P7^-Parameters!B$63 -> 0.46980186 | S7: =Parameters!B$61*EXP(-Parameters!B$60*A7)+(1-Parameters!B$61)*P7^-Parameters!B$63 -> 0.93089871 | T7: =1-S7/Parameters!$B$12 -> 0.53455065 | U7: =1/(1-T7) -> 2.1484615 | V7: =(Parameters!$B$19*(F7+Parameters!$B$20)^T7+Parameters!$B$18*G7^T7)^(1/T7) -> 0.4714978 | W7: =(Parameters!$B$10*H7^Parameters!$B$9+Parameters!$B$11*V7^Parameters!$B$9)^(Parameters!$B$7/Parameters!$B$9)*O7 -> 1.4746259 | X7: =W7 - D7 - E7 - LN(1+EXP(Parameters!$B$21*C7))/Parameters!$B$21 - IF(C7>0, 0,Parameters!$B$6*C7^2/F7) -> 1.188131 | Y7: =EXP(-Parameters!$B$55*A7) -> 0.95571073 | Z7: =IF(X7>0,X7^(1-Parameters!$B$52)/(1-Parameters!$B$52)*Y7*Parameters!$B$65,-10+X7*1000) -> -2.5707266 | AC7: =C7*$J7*$K7 -> 0.42483329 | AD7: =D7*$J7*$K7 -> 3.7042221 | AE7: =I7*J7*K7 -> 3.8013523 | AF7: =F7*J7*K7 -> 47.65986 | AG7: =G7*J7*K7 -> 16.921253 | AH7: =V7*J7*K7 -> 37.283441 | AI7: =AH7/AH$4*100 -> 91.757388 | AJ7: =W7*J7*K7 -> 116.60526 | AK7: =X7*J7*K7 -> 93.950837 | AL7: =LN(AJ7)-LN(AJ6) -> 0.016747755 | AM7: =LN(AK7)-LN(AK6) -> 0.014273678 | AN7: =AVERAGE(AL5:AL9) -> 0.017107318 | AO7: =AVERAGE(AM5:AM9) -> 0.017396171 | AQ7: =W7*K7*J7 -> 116.60526 | AR7: =Parameters!$B$7*W7*(W7/O7)^(-Parameters!$B$9/Parameters!$B$7)*Parameters!$B$11*(V7)^(Parameters!$B$9-T7)*((1-2*Parameters!$B$5*C7/F7)*Parameters!$B$19*(F7+Parameters!$B$20)^(T7-1)-(1-2*Parameters!$B$5*D7/G7)*(Parameters!$B$18)*(G7)^(T7-1)) -> 0.089702438 | AS7: =((C8-C6)/2-(F8-F6)/F7/2*C7)/(F7/2/Parameters!$B$5-C7)-((D8-D6)/D7-(G8-G6)/G7)/(G7/2/Parameters!$B$5/D7-1) -> 0.10292869 | AT7: =+Parameters!$B$5*C7^2/F7^2-Parameters!$B$5*D7^2/G7^2 -> -0.047841888 | AU7: =EXP(-Parameters!$B$42*'6states'!A7)*(Parameters!$B$37*EXP(-Parameters!$B$38*Parameters!$E$25*'6states'!I7/('6states'!F7+'6states'!I7))*(1/Parameters!$B$38/Parameters!$E$25+'6states'!I7/('6states'!F7+'6states'!I7))-Parameters!$B$37/Parameters!$B$38/Parameters!$E$25*EXP(-Parameters!$B$38*Parameters!$E$25)+Parameters!$B$39) -> 0.76919088 | AV7: =J7*K7*EXP(-Parameters!$B$42*'6states'!A7)*(Parameters!$B$37*EXP(-Parameters!$B$38*Parameters!$E$25*'6states'!I7/('6states'!F7+'6states'!I7))*(1/Parameters!$B$38/Parameters!$E$25+'6states'!I7/('6states'!F7+'6states'!I7))-Parameters!$B$37/Parameters!$B$38/Parameters!$E$25*EXP(-Parameters!$B$38*Parameters!$E$25)+Parameters!$B$39) -> 60.823365 | AW7: =1000*(AR7+AS7+AT7)/AU7 -> 188.23577 | AX7: =1-W7/'6states,ExoDamages'!T7 -> 0.016993446 | AY7: =-Y7*W7*X7^(-Parameters!B$52)*Parameters!B$46*Parameters!B$45*N7 -> -1.9525615e-05 | AZ7: =1000*EXP(-(Parameters!$B$54)*'6states'!A7)*AQ7*Parameters!B$46*Parameters!B$45*N7 -> 1.8350598 | BA7: =SUM(AZ7:AZ$204)*EXP(Parameters!$B$54*A7) -> 195.2725 | BB7: =((C7>0)*C7+D7+E7)/W7 -> 0.19387181 | BF7: =SUM(AY7:AY205)/Y7 -> -0.001891421 | BG7: =BF7/Parameters!$B$45 -> -3.1523684 | BH7: =1-BG6/BG7 -> 0.0044024242 | BK7: =-EXP(-Parameters!B$42*'6states'!A7)*(-Parameters!B$37/Parameters!B$38/Parameters!E$25*(EXP(-Parameters!B$38*Parameters!E$25*'6states'!AE7/('6states'!F7+'6states'!AE7))-EXP(-Parameters!B$38*Parameters!E$25))+Parameters!B$37*'6states'!F7/('6states'!F7+'6states'!AE7)*EXP(-Parameters!B$38*Parameters!E$25*'6states'!I7/('6states'!F7+'6states'!AE7))) -> -0.51057135 | BL7: =-J7*K7*EXP(-Parameters!B$42*'6states'!A7)*(-Parameters!B$37/Parameters!B$38/Parameters!E$25*(EXP(-Parameters!B$38*Parameters!E$25*'6states'!I7/('6states'!F7+'6states'!I7))-EXP(-Parameters!B$38*Parameters!E$25)) + Parameters!B$37*'6states'!F7/('6states'!F7+'6states'!I7)*EXP(-Parameters!B$38*Parameters!E$25*'6states'!I7/('6states'!F7+'6states'!I7))) -> -18.239929 | BM7: =I7/(F7+I7) -> 0.073868301 | BN7: =BK7-AU7 -> -1.2797622 | BS7: =EXP(-Parameters!$B$56*A7)*BF7*BL7 -> 0.027301497 | BT7: =-EXP((Parameters!$B$56)*F7)*SUM(BS7:BS15) -> -0.15602895 | BU7: =X7^-Parameters!B$52/(1-2*Parameters!B$5*'6states'!D7/'6states'!G7) -> 1.4094734 | BV7: =BU7/BU6 -> 0.96953181 | BW7: =$X7^-Parameters!$B$52/(1-2*Parameters!$B$5*'6states'!$E7/'6states'!$H7) -> 0.89075122 | BX7: =BW7/BW6 -> 1.0092207 | BY7: =($X7^-Parameters!$B$52*(1/(1+EXP(-C7)) + IF(C7<0,2*Parameters!$B$6*C7/F7,0)) + BQ7*(1/(1+EXP((C7-Parameters!$B$22)*Parameters!$B$21))))/(1-IF(C7>0,2*Parameters!$B$5*C7/F7,0)) -> 0.40446463 | BZ7: =BY7/BY6 -> 1.4090689 | CA7: =BY7-BY6 -> 0.11742073 | CB7: =(1/$T7-1/Parameters!$B$13) * LN(Parameters!$B$18) / LN(P7) -> 0.24719701 | CC7: =(Parameters!$B$18*'6states'!T7^+Parameters!$B$19*Parameters!$B$25^'6states'!T7)^((1-'6states'!T7)/'6states'!T7)*Parameters!$B$18*Parameters!$B$26^('6states'!T7-1) -> 0.15845999 | CD7: =(LN(CC7)-LN(CC$4))/ LN(P7) -> 0.32107466 | CE7: =1-2^-CB7 -> 0.15746823 | CF7: =1-2^-CC7 -> 0.10401902
A8: =A7+Parameters!$B$65 -> 4 | B8: 2029 | C8: 0.006670523 | D8: 0.049576576 | E8: 0.2287485 | F8: =MAX((1-Parameters!$B$4)^Parameters!B$65*F7 + C7*Parameters!B$65 - IF(C7>0,Parameters!$B$5,0)*C7^2/F7*Parameters!B$65, 0.0001) -> 0.57013469 | G8: =(1-Parameters!$B$4)^Parameters!B$65*G7+D7*Parameters!B$65-Parameters!$B$5*D7^2/G7*Parameters!B$65 -> 0.23712126 | H8: =(1-Parameters!$B$4)^Parameters!B$65*H7+E7*Parameters!B$65-Parameters!$B$5*E7^2/H7*Parameters!B$65 -> 4.1863453 | I8: =I7 *(1-Parameters!$B$4)-C7*(C7<0)*Parameters!B$65 -> 0.045049269 | J8: =J7*(1+Parameters!$B$51)^Parameters!B$65 -> 8.2550686 | K8: =K7*(1+Parameters!$B$53)^Parameters!B$65 -> 9.7988122 | L8: =J8*K8*EXP(-Parameters!$B$42*'6states'!A8)*(Parameters!$B$37/Parameters!$B$38*('6states'!F8+'6states'!I8)/Parameters!$E$25*(EXP(-Parameters!$B$38*Parameters!$E$25*'6states'!I8/('6states'!F8+'6states'!I8))-EXP(-Parameters!$B$38*Parameters!$E$25)) + Parameters!$B$39*'6states'!F8) -> 34.288582 | M8: =M7+L8*Parameters!B$65 -> 2450.6657 | N8: =M8*Parameters!$B$45 -> 1.4703994 | O8: =EXP(-Parameters!$B$46/2*N8^2) -> 0.97850552 | P8: =MAX((Parameters!$B$62 + Parameters!$B$31*'6states'!A8 - '6states'!M8 + Parameters!$B$47/Parameters!$B$45)/Parameters!B$62,1) -> 2.2426867 | Q8: =Parameters!B$61*EXP(-Parameters!B$60*A8) -> 0.4488138 | R8: =(1-Parameters!B$61)*P8^-Parameters!B$63 -> 0.46120408 | S8: =Parameters!B$61*EXP(-Parameters!B$60*A8)+(1-Parameters!B$61)*P8^-Parameters!B$63 -> 0.91001788 | T8: =1-S8/Parameters!$B$12 -> 0.54499106 | U8: =1/(1-T8) -> 2.197759 | V8: =(Parameters!$B$19*(F8+Parameters!$B$20)^T8+Parameters!$B$18*G8^T8)^(1/T8) -> 0.46147468 | W8: =(Parameters!$B$10*H8^Parameters!$B$9+Parameters!$B$11*V8^Parameters!$B$9)^(Parameters!$B$7/Parameters!$B$9)*O8 -> 1.4676971 | X8: =W8 - D8 - E8 - LN(1+EXP(Parameters!$B$21*C8))/Parameters!$B$21 - IF(C8>0, 0,Parameters!$B$6*C8^2/F8) -> 1.1822789 | Y8: =EXP(-Parameters!$B$55*A8) -> 0.9413879 | Z8: =IF(X8>0,X8^(1-Parameters!$B$52)/(1-Parameters!$B$52)*Y8*Parameters!$B$65,-10+X8*1000) -> -2.5365802 | AC8: =C8*$J8*$K8 -> 0.53957772 | AD8: =D8*$J8*$K8 -> 4.0102426 | AE8: =I8*J8*K8 -> 3.6440293 | AF8: =F8*J8*K8 -> 46.118119 | AG8: =G8*J8*K8 -> 19.180707 | AH8: =V8*J8*K8 -> 37.328625 | AI8: =AH8/AH$4*100 -> 91.868589 | AJ8: =W8*J8*K8 -> 118.72182 | AK8: =X8*J8*K8 -> 95.63438 | AL8: =LN(AJ8)-LN(AJ7) -> 0.017988712 | AM8: =LN(AK8)-LN(AK7) -> 0.017760751 | AN8: =AVERAGE(AL6:AL10) -> 0.017309372 | AO8: =AVERAGE(AM6:AM10) -> 0.017174286 | AQ8: =W8*K8*J8 -> 118.72182 | AR8: =Parameters!$B$7*W8*(W8/O8)^(-Parameters!$B$9/Parameters!$B$7)*Parameters!$B$11*(V8)^(Parameters!$B$9-T8)*((1-2*Parameters!$B$5*C8/F8)*Parameters!$B$19*(F8+Parameters!$B$20)^(T8-1)-(1-2*Parameters!$B$5*D8/G8)*(Parameters!$B$18)*(G8)^(T8-1)) -> 0.097986481 | AS8: =((C9-C7)/2-(F9-F7)/F8/2*C8)/(F8/2/Parameters!$B$5-C8)-((D9-D7)/D8-(G9-G7)/G8)/(G8/2/Parameters!$B$5/D8-1) -> 0.05064868 | AT8: =+Parameters!$B$5*C8^2/F8^2-Parameters!$B$5*D8^2/G8^2 -> -0.043576259 | AU8: =EXP(-Parameters!$B$42*'6states'!A8)*(Parameters!$B$37*EXP(-Parameters!$B$38*Parameters!$E$25*'6states'!I8/('6states'!F8+'6states'!I8))*(1/Parameters!$B$38/Parameters!$E$25+'6states'!I8/('6states'!F8+'6states'!I8))-Parameters!$B$37/Parameters!$B$38/Parameters!$E$25*EXP(-Parameters!$B$38*Parameters!$E$25)+Parameters!$B$39) -> 0.76205092 | AV8: =J8*K8*EXP(-Parameters!$B$42*'6states'!A8)*(Parameters!$B$37*EXP(-Parameters!$B$38*Parameters!$E$25*'6states'!I8/('6states'!F8+'6states'!I8))*(1/Parameters!$B$38/Parameters!$E$25+'6states'!I8/('6states'!F8+'6states'!I8))-Parameters!$B$37/Parameters!$B$38/Parameters!$E$25*EXP(-Parameters!$B$38*Parameters!$E$25)+Parameters!$B$39) -> 61.642197 | AW8: =1000*(AR8+AS8+AT8)/AU8 -> 137.86336 | AX8: =1-W8/'6states,ExoDamages'!T8 -> 0.021138107 | AY8: =-Y8*W8*X8^(-Parameters!B$52)*Parameters!B$46*Parameters!B$45*N8 -> -1.9544104e-05 | AZ8: =1000*EXP(-(Parameters!$B$54)*'6states'!A8)*AQ8*Parameters!B$46*Parameters!B$45*N8 -> 1.8295245 | BA8: =SUM(AZ8:AZ$204)*EXP(Parameters!$B$54*A8) -> 200.13661 | BB8: =((C8>0)*C8+D8+E8)/W8 -> 0.19417876 | BF8: =SUM(AY8:AY206)/Y8 -> -0.0018994569 | BG8: =BF8/Parameters!$B$45 -> -3.1657615 | BH8: =1-BG7/BG8 -> 0.0042306157 | BK8: =-EXP(-Parameters!B$42*'6states'!A8)*(-Parameters!B$37/Parameters!B$38/Parameters!E$25*(EXP(-Parameters!B$38*Parameters!E$25*'6states'!AE8/('6states'!F8+'6states'!AE8))-EXP(-Parameters!B$38*Parameters!E$25))+Parameters!B$37*'6states'!F8/('6states'!F8+'6states'!AE8)*EXP(-Parameters!B$38*Parameters!E$25*'6states'!I8/('6states'!F8+'6states'!AE8))) -> -0.50453423 | BL8: =-J8*K8*EXP(-Parameters!B$42*'6states'!A8)*(-Parameters!B$37/Parameters!B$38/Parameters!E$25*(EXP(-Parameters!B$38*Parameters!E$25*'6states'!I8/('6states'!F8+'6states'!I8))-EXP(-Parameters!B$38*Parameters!E$25)) + Parameters!B$37*'6states'!F8/('6states'!F8+'6states'!I8)*EXP(-Parameters!B$38*Parameters!E$25*'6states'!I8/('6states'!F8+'6states'!I8))) -> -18.996373 | BM8: =I8/(F8+I8) -> 0.073228939 | BN8: =BK8-AU8 -> -1.2665851 | BS8: =EXP(-Parameters!$B$56*A8)*BF8*BL8 -> 0.026411937 | BT8: =-EXP((Parameters!$B$56)*F8)*SUM(BS8:BS16) -> -0.13886768 | BU8: =X8^-Parameters!B$52/(1-2*Parameters!B$5*'6states'!D8/'6states'!G8) -> 1.3709445 | BV8: =BU8/BU7 -> 0.97266432 | BW8: =$X8^-Parameters!$B$52/(1-2*Parameters!$B$5*'6states'!$E8/'6states'!$H8) -> 0.89554709 | BX8: =BW8/BW7 -> 1.0053841 | BY8: =($X8^-Parameters!$B$52*(1/(1+EXP(-C8)) + IF(C8<0,2*Parameters!$B$6*C8/F8,0)) + BQ8*(1/(1+EXP((C8-Parameters!$B$22)*Parameters!$B$21))))/(1-IF(C8>0,2*Parameters!$B$5*C8/F8,0)) -> 0.40975793 | BZ8: =BY8/BY7 -> 1.0130872 | CA8: =BY8-BY7 -> 0.0052933001 | CB8: =(1/$T8-1/Parameters!$B$13) * LN(Parameters!$B$18) / LN(P8) -> 0.24352519 | CC8: =(Parameters!$B$18*'6states'!T8^+Parameters!$B$19*Parameters!$B$25^'6states'!T8)^((1-'6states'!T8)/'6states'!T8)*Parameters!$B$18*Parameters!$B$26^('6states'!T8-1) -> 0.16698137 | CD8: =(LN(CC8)-LN(CC$4))/ LN(P8) -> 0.31250231 | CE8: =1-2^-CB8 -> 0.15532116 | CF8: =1-2^-CC8 -> 0.1092956
A9: =A8+Parameters!$B$65 -> 5 | B9: 2030 | C9: -0.0049074835 | D9: 0.052082521 | E9: 0.23299044 | F9: =MAX((1-Parameters!$B$4)^Parameters!B$65*F8 + C8*Parameters!B$65 - IF(C8>0,Parameters!$B$5,0)*C8^2/F8*Parameters!B$65, 0.0001) -> 0.54086569 | G9: =(1-Parameters!$B$4)^Parameters!B$65*G8+D8*Parameters!B$65-Parameters!$B$5*D8^2/G8*Parameters!B$65 -> 0.26141759 | H9: =(1-Parameters!$B$4)^Parameters!B$65*H8+E8*Parameters!B$65-Parameters!$B$5*E8^2/H8*Parameters!B$65 -> 4.1392735 | I9: =I8 *(1-Parameters!$B$4)-C8*(C8<0)*Parameters!B$65 -> 0.04221567 | J9: =J8*(1+Parameters!$B$51)^Parameters!B$65 -> 8.2790082 | K9: =K8*(1+Parameters!$B$53)^Parameters!B$65 -> 9.9947885 | L9: =J9*K9*EXP(-Parameters!$B$42*'6states'!A9)*(Parameters!$B$37/Parameters!$B$38*('6states'!F9+'6states'!I9)/Parameters!$E$25*(EXP(-Parameters!$B$38*Parameters!$E$25*'6states'!I9/('6states'!F9+'6states'!I9))-EXP(-Parameters!$B$38*Parameters!$E$25)) + Parameters!$B$39*'6states'!F9) -> 32.954207 | M9: =M8+L9*Parameters!B$65 -> 2483.6199 | N9: =M9*Parameters!$B$45 -> 1.4901719 | O9: =EXP(-Parameters!$B$46/2*N9^2) -> 0.97793003 | P9: =MAX((Parameters!$B$62 + Parameters!$B$31*'6states'!A9 - '6states'!M9 + Parameters!$B$47/Parameters!$B$45)/Parameters!B$62,1) -> 2.6476026 | Q9: =Parameters!B$61*EXP(-Parameters!B$60*A9) -> 0.43685796 | R9: =(1-Parameters!B$61)*P9^-Parameters!B$63 -> 0.4536122 | S9: =Parameters!B$61*EXP(-Parameters!B$60*A9)+(1-Parameters!B$61)*P9^-Parameters!B$63 -> 0.89047015 | T9: =1-S9/Parameters!$B$12 -> 0.55476492 | U9: =1/(1-T9) -> 2.2460045 | V9: =(Parameters!$B$19*(F9+Parameters!$B$20)^T9+Parameters!$B$18*G9^T9)^(1/T9) -> 0.45293778 | W9: =(Parameters!$B$10*H9^Parameters!$B$9+Parameters!$B$11*V9^Parameters!$B$9)^(Parameters!$B$7/Parameters!$B$9)*O9 -> 1.4609686 | X9: =W9 - D9 - E9 - LN(1+EXP(Parameters!$B$21*C9))/Parameters!$B$21 - IF(C9>0, 0,Parameters!$B$6*C9^2/F9) -> 1.1749845 | Y9: =EXP(-Parameters!$B$55*A9) -> 0.92727973 | Z9: =IF(X9>0,X9^(1-Parameters!$B$52)/(1-Parameters!$B$52)*Y9*Parameters!$B$65,-10+X9*1000) -> -2.5039836 | AC9: =C9*$J9*$K9 -> -0.40607923 | AD9: =D9*$J9*$K9 -> 4.3096691 | AE9: =I9*J9*K9 -> 3.4932173 | AF9: =F9*J9*K9 -> 44.754979 | AG9: =G9*J9*K9 -> 21.631505 | AH9: =V9*J9*K9 -> 37.479213 | AI9: =AH9/AH$4*100 -> 92.239197 | AJ9: =W9*J9*K9 -> 120.89067 | AK9: =X9*J9*K9 -> 97.226368 | AL9: =LN(AJ9)-LN(AJ8) -> 0.018103457 | AM9: =LN(AK9)-LN(AK8) -> 0.016509565 | AN9: =AVERAGE(AL7:AL11) -> 0.017329605 | AO9: =AVERAGE(AM7:AM11) -> 0.015952865 | AQ9: =W9*K9*J9 -> 120.89067 | AR9: =Parameters!$B$7*W9*(W9/O9)^(-Parameters!$B$9/Parameters!$B$7)*Parameters!$B$11*(V9)^(Parameters!$B$9-T9)*((1-2*Parameters!$B$5*C9/F9)*Parameters!$B$19*(F9+Parameters!$B$20)^(T9-1)-(1-2*Parameters!$B$5*D9/G9)*(Parameters!$B$18)*(G9)^(T9-1)) -> 0.11317706 | AS9: =((C10-C8)/2-(F10-F8)/F9/2*C9)/(F9/2/Parameters!$B$5-C9)-((D10-D8)/D9-(G10-G8)/G9)/(G9/2/Parameters!$B$5/D9-1) -> 0.040254691 | AT9: =+Parameters!$B$5*C9^2/F9^2-Parameters!$B$5*D9^2/G9^2 -> -0.039610715 | AU9: =EXP(-Parameters!$B$42*'6states'!A9)*(Parameters!$B$37*EXP(-Parameters!$B$38*Parameters!$E$25*'6states'!I9/('6states'!F9+'6states'!I9))*(1/Parameters!$B$38/Parameters!$E$25+'6states'!I9/('6states'!F9+'6states'!I9))-Parameters!$B$37/Parameters!$B$38/Parameters!$E$25*EXP(-Parameters!$B$38*Parameters!$E$25)+Parameters!$B$39) -> 0.75514101 | AV9: =J9*K9*EXP(-Parameters!$B$42*'6states'!A9)*(Parameters!$B$37*EXP(-Parameters!$B$38*Parameters!$E$25*'6states'!I9/('6states'!F9+'6states'!I9))*(1/Parameters!$B$38/Parameters!$E$25+'6states'!I9/('6states'!F9+'6states'!I9))-Parameters!$B$37/Parameters!$B$38/Parameters!$E$25*EXP(-Parameters!$B$38*Parameters!$E$25)+Parameters!$B$39) -> 62.485605 | AW9: =1000*(AR9+AS9+AT9)/AU9 -> 150.72819 | AX9: =1-W9/'6states,ExoDamages'!T9 -> 0.025150376 | AY9: =-Y9*W9*X9^(-Parameters!B$52)*Parameters!B$46*Parameters!B$45*N9 -> -1.9583573e-05 | AZ9: =1000*EXP(-(Parameters!$B$54)*'6states'!A9)*AQ9*Parameters!B$46*Parameters!B$45*N9 -> 1.8228788 | BA9: =SUM(AZ9:AZ$204)*EXP(Parameters!$B$54*A9) -> 205.10564 | BB9: =((C9>0)*C9+D9+E9)/W9 -> 0.19512601 | BF9: =SUM(AY9:AY207)/Y9 -> -0.0019072795 | BG9: =BF9/Parameters!$B$45 -> -3.1787992 | BH9: =1-BG8/BG9 -> 0.0041014569 | BK9: =-EXP(-Parameters!B$42*'6states'!A9)*(-Parameters!B$37/Parameters!B$38/Parameters!E$25*(EXP(-Parameters!B$38*Parameters!E$25*'6states'!AE9/('6states'!F9+'6states'!AE9))-EXP(-Parameters!B$38*Parameters!E$25))+Parameters!B$37*'6states'!F9/('6states'!F9+'6states'!AE9)*EXP(-Parameters!B$38*Parameters!E$25*'6states'!I9/('6states'!F9+'6states'!AE9))) -> -0.49979475 | BL9: =-J9*K9*EXP(-Parameters!B$42*'6states'!A9)*(-Parameters!B$37/Parameters!B$38/Parameters!E$25*(EXP(-Parameters!B$38*Parameters!E$25*'6states'!I9/('6states'!F9+'6states'!I9))-EXP(-Parameters!B$38*Parameters!E$25)) + Parameters!B$37*'6states'!F9/('6states'!F9+'6states'!I9)*EXP(-Parameters!B$38*Parameters!E$25*'6states'!I9/('6states'!F9+'6states'!I9))) -> -19.94787 | BM9: =I9/(F9+I9) -> 0.072400993 | BN9: =BK9-AU9 -> -1.2549358 | BS9: =EXP(-Parameters!$B$56*A9)*BF9*BL9 -> 0.025759417 | BT9: =-EXP((Parameters!$B$56)*F9)*SUM(BS9:BS17) -> -0.12303632 | BU9: =X9^-Parameters!B$52/(1-2*Parameters!B$5*'6states'!D9/'6states'!G9) -> 1.3371919 | BV9: =BU9/BU8 -> 0.97538 | BW9: =$X9^-Parameters!$B$52/(1-2*Parameters!$B$5*'6states'!$E9/'6states'!$H9) -> 0.90641109 | BX9: =BW9/BW8 -> 1.0121311 | BY9: =($X9^-Parameters!$B$52*(1/(1+EXP(-C9)) + IF(C9<0,2*Parameters!$B$6*C9/F9,0)) + BQ9*(1/(1+EXP((C9-Parameters!$B$22)*Parameters!$B$21))))/(1-IF(C9>0,2*Parameters!$B$5*C9/F9,0)) -> 0.32821511 | BZ9: =BY9/BY8 -> 0.80099758 | CA9: =BY9-BY8 -> -0.081542821 | CB9: =(1/$T9-1/Parameters!$B$13) * LN(Parameters!$B$18) / LN(P9) -> 0.24156391 | CC9: =(Parameters!$B$18*'6states'!T9^+Parameters!$B$19*Parameters!$B$25^'6states'!T9)^((1-'6states'!T9)/'6states'!T9)*Parameters!$B$18*Parameters!$B$26^('6states'!T9-1) -> 0.17484503 | CD9: =(LN(CC9)-LN(CC$4))/ LN(P9) -> 0.30649266 | CE9: =1-2^-CB9 -> 0.15417208 | CF9: =1-2^-CC9 -> 0.11413733
A10: =A9+Parameters!$B$65 -> 6 | B10: 2031 | C10: -0.004751195 | D10: 0.054566096 | E10: 0.22572886 | F10: =MAX((1-Parameters!$B$4)^Parameters!B$65*F9 + C9*Parameters!B$65 - IF(C9>0,Parameters!$B$5,0)*C9^2/F9*Parameters!B$65, 0.0001) -> 0.50193776 | G10: =(1-Parameters!$B$4)^Parameters!B$65*G9+D9*Parameters!B$65-Parameters!$B$5*D9^2/G9*Parameters!B$65 -> 0.28668049 | H10: =(1-Parameters!$B$4)^Parameters!B$65*H9+E9*Parameters!B$65-Parameters!$B$5*E9^2/H9*Parameters!B$65 -> 4.0987891 | I10: =I9 *(1-Parameters!$B$4)-C9*(C9<0)*Parameters!B$65 -> 0.044467788 | J10: =J9*(1+Parameters!$B$51)^Parameters!B$65 -> 8.3030174 | K10: =K9*(1+Parameters!$B$53)^Parameters!B$65 -> 10.194684 | L10: =J10*K10*EXP(-Parameters!$B$42*'6states'!A10)*(Parameters!$B$37/Parameters!$B$38*('6states'!F10+'6states'!I10)/Parameters!$E$25*(EXP(-Parameters!$B$38*Parameters!$E$25*'6states'!I10/('6states'!F10+'6states'!I10))-EXP(-Parameters!$B$38*Parameters!$E$25)) + Parameters!$B$39*'6states'!F10) -> 30.884858 | M10: =M9+L10*Parameters!B$65 -> 2514.5047 | N10: =M10*Parameters!$B$45 -> 1.5087028 | O10: =EXP(-Parameters!$B$46/2*N10^2) -> 0.97738401 | P10: =MAX((Parameters!$B$62 + Parameters!$B$31*'6states'!A10 - '6states'!M10 + Parameters!$B$47/Parameters!$B$45)/Parameters!B$62,1) -> 3.0939054 | Q10: =Parameters!B$61*EXP(-Parameters!B$60*A10) -> 0.4252206 | R10: =(1-Parameters!B$61)*P10^-Parameters!B$63 -> 0.4466006 | S10: =Parameters!B$61*EXP(-Parameters!B$60*A10)+(1-Parameters!B$61)*P10^-Parameters!B$63 -> 0.8718212 | T10: =1-S10/Parameters!$B$12 -> 0.5640894 | U10: =1/(1-T10) -> 2.2940484 | V10: =(Parameters!$B$19*(F10+Parameters!$B$20)^T10+Parameters!$B$18*G10^T10)^(1/T10) -> 0.43754904 | W10: =(Parameters!$B$10*H10^Parameters!$B$9+Parameters!$B$11*V10^Parameters!$B$9)^(Parameters!$B$7/Parameters!$B$9)*O10 -> 1.4527115 | X10: =W10 - D10 - E10 - LN(1+EXP(Parameters!$B$21*C10))/Parameters!$B$21 - IF(C10>0, 0,Parameters!$B$6*C10^2/F10) -> 1.1714735 | Y10: =EXP(-Parameters!$B$55*A10) -> 0.91338299 | Z10: =IF(X10>0,X10^(1-Parameters!$B$52)/(1-Parameters!$B$52)*Y10*Parameters!$B$65,-10+X10*1000) -> -2.4690422 | AC10: =C10*$J10*$K10 -> -0.40217269 | AD10: =D10*$J10*$K10 -> 4.6188367 | AE10: =I10*J10*K10 -> 3.7640488 | AF10: =F10*J10*K10 -> 42.487345 | AG10: =G10*J10*K10 -> 24.26654 | AH10: =V10*J10*K10 -> 37.037056 | AI10: =AH10/AH$4*100 -> 91.151015 | AJ10: =W10*J10*K10 -> 122.96715 | AK10: =X10*J10*K10 -> 99.161296 | AL10: =LN(AJ10)-LN(AJ9) -> 0.017030626 | AM10: =LN(AK10)-LN(AK9) -> 0.019705825 | AN10: =AVERAGE(AL8:AL12) -> 0.017739177 | AO10: =AVERAGE(AM8:AM12) -> 0.016756481 | AQ10: =W10*K10*J10 -> 122.96715 | AR10: =Parameters!$B$7*W10*(W10/O10)^(-Parameters!$B$9/Parameters!$B$7)*Parameters!$B$11*(V10)^(Parameters!$B$9-T10)*((1-2*Parameters!$B$5*C10/F10)*Parameters!$B$19*(F10+Parameters!$B$20)^(T10-1)-(1-2*Parameters!$B$5*D10/G10)*(Parameters!$B$18)*(G10)^(T10-1)) -> 0.13095282 | AS10: =((C11-C9)/2-(F11-F9)/F10/2*C10)/(F10/2/Parameters!$B$5-C10)-((D11-D9)/D10-(G11-G9)/G10)/(G10/2/Parameters!$B$5/D10-1) -> 0.099217782 | AT10: =+Parameters!$B$5*C10^2/F10^2-Parameters!$B$5*D10^2/G10^2 -> -0.03613883 | AU10: =EXP(-Parameters!$B$42*'6states'!A10)*(Parameters!$B$37*EXP(-Parameters!$B$38*Parameters!$E$25*'6states'!I10/('6states'!F10+'6states'!I10))*(1/Parameters!$B$38/Parameters!$E$25+'6states'!I10/('6states'!F10+'6states'!I10))-Parameters!$B$37/Parameters!$B$38/Parameters!$E$25*EXP(-Parameters!$B$38*Parameters!$E$25)+Parameters!$B$39) -> 0.74119965 | AV10: =J10*K10*EXP(-Parameters!$B$42*'6states'!A10)*(Parameters!$B$37*EXP(-Parameters!$B$38*Parameters!$E$25*'6states'!I10/('6states'!F10+'6states'!I10))*(1/Parameters!$B$38/Parameters!$E$25+'6states'!I10/('6states'!F10+'6states'!I10))-Parameters!$B$37/Parameters!$B$38/Parameters!$E$25*EXP(-Parameters!$B$38*Parameters!$E$25)+Parameters!$B$39) -> 62.74006 | AW10: =1000*(AR10+AS10+AT10)/AU10 -> 261.78072 | AX10: =1-W10/'6states,ExoDamages'!T10 -> 0.030196495 | AY10: =-Y10*W10*X10^(-Parameters!B$52)*Parameters!B$46*Parameters!B$45*N10 -> -1.9498198e-05 | AZ10: =1000*EXP(-(Parameters!$B$54)*'6states'!A10)*AQ10*Parameters!B$46*Parameters!B$45*N10 -> 1.8124987 | BA10: =SUM(AZ10:AZ$204)*EXP(Parameters!$B$54*A10) -> 210.18249 | BB10: =((C10>0)*C10+D10+E10)/W10 -> 0.19294606 | BF10: =SUM(AY10:AY208)/Y10 -> -0.0019148573 | BG10: =BF10/Parameters!$B$45 -> -3.1914288 | BH10: =1-BG9/BG10 -> 0.0039573478 | BK10: =-EXP(-Parameters!B$42*'6states'!A10)*(-Parameters!B$37/Parameters!B$38/Parameters!E$25*(EXP(-Parameters!B$38*Parameters!E$25*'6states'!AE10/('6states'!F10+'6states'!AE10))-EXP(-Parameters!B$38*Parameters!E$25))+Parameters!B$37*'6states'!F10/('6states'!F10+'6states'!AE10)*EXP(-Parameters!B$38*Parameters!E$25*'6states'!I10/('6states'!F10+'6states'!AE10))) -> -0.43500266 | BL10: =-J10*K10*EXP(-Parameters!B$42*'6states'!A10)*(-Parameters!B$37/Parameters!B$38/Parameters!E$25*(EXP(-Parameters!B$38*Parameters!E$25*'6states'!I10/('6states'!F10+'6states'!I10))-EXP(-Parameters!B$38*Parameters!E$25)) + Parameters!B$37*'6states'!F10/('6states'!F10+'6states'!I10)*EXP(-Parameters!B$38*Parameters!E$25*'6states'!I10/('6states'!F10+'6states'!I10))) -> -13.644647 | BM10: =I10/(F10+I10) -> 0.081382387 | BN10: =BK10-AU10 -> -1.1762023 | BS10: =EXP(-Parameters!$B$56*A10)*BF10*BL10 -> 0.016362471 | BT10: =-EXP((Parameters!$B$56)*F10)*SUM(BS10:BS18) -> -0.10817001 | BU10: =X10^-Parameters!B$52/(1-2*Parameters!B$5*'6states'!D10/'6states'!G10) -> 1.3040457 | BV10: =BU10/BU9 -> 0.97521208 | BW10: =$X10^-Parameters!$B$52/(1-2*Parameters!$B$5*'6states'!$E10/'6states'!$H10) -> 0.9075938 | BX10: =BW10/BW9 -> 1.0013048 | BY10: =($X10^-Parameters!$B$52*(1/(1+EXP(-C10)) + IF(C10<0,2*Parameters!$B$6*C10/F10,0)) + BQ10*(1/(1+EXP((C10-Parameters!$B$22)*Parameters!$B$21))))/(1-IF(C10>0,2*Parameters!$B$5*C10/F10,0)) -> 0.32640687 | BZ10: =BY10/BY9 -> 0.99449068 | CA10: =BY10-BY9 -> -0.001808243 | CB10: =(1/$T10-1/Parameters!$B$13) * LN(Parameters!$B$18) / LN(P10) -> 0.23967393 | CC10: =(Parameters!$B$18*'6states'!T10^+Parameters!$B$19*Parameters!$B$25^'6states'!T10)^((1-'6states'!T10)/'6states'!T10)*Parameters!$B$18*Parameters!$B$26^('6states'!T10-1) -> 0.18222472 | CD10: =(LN(CC10)-LN(CC$4))/ LN(P10) -> 0.30082194 | CE10: =1-2^-CB10 -> 0.15306329 | CF10: =1-2^-CC10 -> 0.11865714
A11: =A10+Parameters!$B$65 -> 7 | B11: 2032 | C11: 0.0094400994 | D11: 0.055426729 | E11: 0.22063307 | F11: =MAX((1-Parameters!$B$4)^Parameters!B$65*F10 + C10*Parameters!B$65 - IF(C10>0,Parameters!$B$5,0)*C10^2/F10*Parameters!B$65, 0.0001) -> 0.46561468 | G11: =(1-Parameters!$B$4)^Parameters!B$65*G10+D10*Parameters!B$65-Parameters!$B$5*D10^2/G10*Parameters!B$65 -> 0.3128284 | H11: =(1-Parameters!$B$4)^Parameters!B$65*H10+E10*Parameters!B$65-Parameters!$B$5*E10^2/H10*Parameters!B$65 -> 4.0542728 | I11: =I10 *(1-Parameters!$B$4)-C10*(C10<0)*Parameters!B$65 -> 0.046421959 | J11: =J10*(1+Parameters!$B$51)^Parameters!B$65 -> 8.3270961 | K11: =K10*(1+Parameters!$B$53)^Parameters!B$65 -> 10.398578 | L11: =J11*K11*EXP(-Parameters!$B$42*'6states'!A11)*(Parameters!$B$37/Parameters!$B$38*('6states'!F11+'6states'!I11)/Parameters!$E$25*(EXP(-Parameters!$B$38*Parameters!$E$25*'6states'!I11/('6states'!F11+'6states'!I11))-EXP(-Parameters!$B$38*Parameters!$E$25)) + Parameters!$B$39*'6states'!F11) -> 28.957266 | M11: =M10+L11*Parameters!B$65 -> 2543.462 | N11: =M11*Parameters!$B$45 -> 1.5260772 | O11: =EXP(-Parameters!$B$46/2*N11^2) -> 0.97686622 | P11: =MAX((Parameters!$B$62 + Parameters!$B$31*'6states'!A11 - '6states'!M11 + Parameters!$B$47/Parameters!$B$45)/Parameters!B$62,1) -> 3.5787601 | Q11: =Parameters!B$61*EXP(-Parameters!B$60*A11) -> 0.41389325 | R11: =(1-Parameters!B$61)*P11^-Parameters!B$63 -> 0.44014599 | S11: =Parameters!B$61*EXP(-Parameters!B$60*A11)+(1-Parameters!B$61)*P11^-Parameters!B$63 -> 0.85403924 | T11: =1-S11/Parameters!$B$12 -> 0.57298038 | U11: =1/(1-T11) -> 2.3418128 | V11: =(Parameters!$B$19*(F11+Parameters!$B$20)^T11+Parameters!$B$18*G11^T11)^(1/T11) -> 0.42309914 | W11: =(Parameters!$B$10*H11^Parameters!$B$9+Parameters!$B$11*V11^Parameters!$B$9)^(Parameters!$B$7/Parameters!$B$9)*O11 -> 1.4441355 | X11: =W11 - D11 - E11 - LN(1+EXP(Parameters!$B$21*C11))/Parameters!$B$21 - IF(C11>0, 0,Parameters!$B$6*C11^2/F11) -> 1.1584448 | Y11: =EXP(-Parameters!$B$55*A11) -> 0.89969452 | Z11: =IF(X11>0,X11^(1-Parameters!$B$52)/(1-Parameters!$B$52)*Y11*Parameters!$B$65,-10+X11*1000) -> -2.4415783 | AC11: =C11*$J11*$K11 -> 0.81741781 | AD11: =D11*$J11*$K11 -> 4.7993981 | AE11: =I11*J11*K11 -> 4.0196754 | AF11: =F11*J11*K11 -> 40.317555 | AG11: =G11*J11*K11 -> 27.087798 | AH11: =V11*J11*K11 -> 36.636137 | AI11: =AH11/AH$4*100 -> 90.164321 | AJ11: =W11*J11*K11 -> 125.04763 | AK11: =X11*J11*K11 -> 100.30969 | AL11: =LN(AJ11)-LN(AJ10) -> 0.016777473 | AM11: =LN(AK11)-LN(AK10) -> 0.011514508 | AN11: =AVERAGE(AL9:AL13) -> 0.017926911 | AO11: =AVERAGE(AM9:AM13) -> 0.016271371 | AQ11: =W11*K11*J11 -> 125.04763 | AR11: =Parameters!$B$7*W11*(W11/O11)^(-Parameters!$B$9/Parameters!$B$7)*Parameters!$B$11*(V11)^(Parameters!$B$9-T11)*((1-2*Parameters!$B$5*C11/F11)*Parameters!$B$19*(F11+Parameters!$B$20)^(T11-1)-(1-2*Parameters!$B$5*D11/G11)*(Parameters!$B$18)*(G11)^(T11-1)) -> 0.13543489 | AS11: =((C12-C10)/2-(F12-F10)/F11/2*C11)/(F11/2/Parameters!$B$5-C11)-((D12-D10)/D11-(G12-G10)/G11)/(G11/2/Parameters!$B$5/D11-1) -> 0.10223141 | AT11: =+Parameters!$B$5*C11^2/F11^2-Parameters!$B$5*D11^2/G11^2 -> -0.030981463 | AU11: =EXP(-Parameters!$B$42*'6states'!A11)*(Parameters!$B$37*EXP(-Parameters!$B$38*Parameters!$E$25*'6states'!I11/('6states'!F11+'6states'!I11))*(1/Parameters!$B$38/Parameters!$E$25+'6states'!I11/('6states'!F11+'6states'!I11))-Parameters!$B$37/Parameters!$B$38/Parameters!$E$25*EXP(-Parameters!$B$38*Parameters!$E$25)+Parameters!$B$39) -> 0.72883598 | AV11: =J11*K11*EXP(-Parameters!$B$42*'6states'!A11)*(Parameters!$B$37*EXP(-Parameters!$B$38*Parameters!$E$25*'6states'!I11/('6states'!F11+'6states'!I11))*(1/Parameters!$B$38/Parameters!$E$25+'6states'!I11/('6states'!F11+'6states'!I11))-Parameters!$B$37/Parameters!$B$38/Parameters!$E$25*EXP(-Parameters!$B$38*Parameters!$E$25)+Parameters!$B$39) -> 63.109877 | AW11: =1000*(AR11+AS11+AT11)/AU11 -> 283.58209 | AX11: =1-W11/'6states,ExoDamages'!T11 -> 0.035465733 | AY11: =-Y11*W11*X11^(-Parameters!B$52)*Parameters!B$46*Parameters!B$45*N11 -> -1.9606275e-05 | AZ11: =1000*EXP(-(Parameters!$B$54)*'6states'!A11)*AQ11*Parameters!B$46*Parameters!B$45*N11 -> 1.8000854 | BA11: =SUM(AZ11:AZ$204)*EXP(Parameters!$B$54*A11) -> 215.37359 | BB11: =((C11>0)*C11+D11+E11)/W11 -> 0.19769606 | BF11: =SUM(AY11:AY209)/Y11 -> -0.001922319 | BG11: =BF11/Parameters!$B$45 -> -3.203865 | BH11: =1-BG10/BG11 -> 0.0038816297 | BK11: =-EXP(-Parameters!B$42*'6states'!A11)*(-Parameters!B$37/Parameters!B$38/Parameters!E$25*(EXP(-Parameters!B$38*Parameters!E$25*'6states'!AE11/('6states'!F11+'6states'!AE11))-EXP(-Parameters!B$38*Parameters!E$25))+Parameters!B$37*'6states'!F11/('6states'!F11+'6states'!AE11)*EXP(-Parameters!B$38*Parameters!E$25*'6states'!I11/('6states'!F11+'6states'!AE11))) -> -0.3811737 | BL11: =-J11*K11*EXP(-Parameters!B$42*'6states'!A11)*(-Parameters!B$37/Parameters!B$38/Parameters!E$25*(EXP(-Parameters!B$38*Parameters!E$25*'6states'!I11/('6states'!F11+'6states'!I11))-EXP(-Parameters!B$38*Parameters!E$25)) + Parameters!B$37*'6states'!F11/('6states'!F11+'6states'!I11)*EXP(-Parameters!B$38*Parameters!E$25*'6states'!I11/('6states'!F11+'6states'!I11))) -> -9.2115753 | BM11: =I11/(F11+I11) -> 0.090661401 | BN11: =BK11-AU11 -> -1.1100097 | BS11: =EXP(-Parameters!$B$56*A11)*BF11*BL11 -> 0.010257336 | BT11: =-EXP((Parameters!$B$56)*F11)*SUM(BS11:BS19) -> -0.10345627 | BU11: =X11^-Parameters!B$52/(1-2*Parameters!B$5*'6states'!D11/'6states'!G11) -> 1.2699217 | BV11: =BU11/BU10 -> 0.97383226 | BW11: =$X11^-Parameters!$B$52/(1-2*Parameters!$B$5*'6states'!$E11/'6states'!$H11) -> 0.92005223 | BX11: =BW11/BW10 -> 1.0137269 | BY11: =($X11^-Parameters!$B$52*(1/(1+EXP(-C11)) + IF(C11<0,2*Parameters!$B$6*C11/F11,0)) + BQ11*(1/(1+EXP((C11-Parameters!$B$22)*Parameters!$B$21))))/(1-IF(C11>0,2*Parameters!$B$5*C11/F11,0)) -> 0.42929964 | BZ11: =BY11/BY10 -> 1.3152286 | CA11: =BY11-BY10 -> 0.10289277 | CB11: =(1/$T11-1/Parameters!$B$13) * LN(Parameters!$B$18) / LN(P11) -> 0.23800937 | CC11: =(Parameters!$B$18*'6states'!T11^+Parameters!$B$19*Parameters!$B$25^'6states'!T11)^((1-'6states'!T11)/'6states'!T11)*Parameters!$B$18*Parameters!$B$26^('6states'!T11-1) -> 0.18913427 | CD11: =(LN(CC11)-LN(CC$4))/ LN(P11) -> 0.29566294 | CE11: =1-2^-CB11 -> 0.15208554 | CF11: =1-2^-CC11 -> 0.12286809
A12: =A11+Parameters!$B$65 -> 8 | B12: 2033 | C12: 0.0097384106 | D12: 0.057002813 | E12: 0.21824303 | F12: =MAX((1-Parameters!$B$4)^Parameters!B$65*F11 + C11*Parameters!B$65 - IF(C11>0,Parameters!$B$5,0)*C11^2/F11*Parameters!B$65, 0.0001) -> 0.44557622 | G12: =(1-Parameters!$B$4)^Parameters!B$65*G11+D11*Parameters!B$65-Parameters!$B$5*D11^2/G11*Parameters!B$65 -> 0.33875775 | H12: =(1-Parameters!$B$4)^Parameters!B$65*H11+E11*Parameters!B$65-Parameters!$B$5*E11^2/H11*Parameters!B$65 -> 4.0078852 | I12: =I11 *(1-Parameters!$B$4)-C11*(C11<0)*Parameters!B$65 -> 0.043502017 | J12: =J11*(1+Parameters!$B$51)^Parameters!B$65 -> 8.3512447 | K12: =K11*(1+Parameters!$B$53)^Parameters!B$65 -> 10.606549 | L12: =J12*K12*EXP(-Parameters!$B$42*'6states'!A12)*(Parameters!$B$37/Parameters!$B$38*('6states'!F12+'6states'!I12)/Parameters!$E$25*(EXP(-Parameters!$B$38*Parameters!$E$25*'6states'!I12/('6states'!F12+'6states'!I12))-EXP(-Parameters!$B$38*Parameters!$E$25)) + Parameters!$B$39*'6states'!F12) -> 28.074108 | M12: =M11+L12*Parameters!B$65 -> 2571.5361 | N12: =M12*Parameters!$B$45 -> 1.5429217 | O12: =EXP(-Parameters!$B$46/2*N12^2) -> 0.97635883 | P12: =MAX((Parameters!$B$62 + Parameters!$B$31*'6states'!A12 - '6states'!M12 + Parameters!$B$47/Parameters!$B$45)/Parameters!B$62,1) -> 4.081278 | Q12: =Parameters!B$61*EXP(-Parameters!B$60*A12) -> 0.40286765 | R12: =(1-Parameters!B$61)*P12^-Parameters!B$63 -> 0.43440057 | S12: =Parameters!B$61*EXP(-Parameters!B$60*A12)+(1-Parameters!B$61)*P12^-Parameters!B$63 -> 0.83726822 | T12: =1-S12/Parameters!$B$12 -> 0.58136589 | U12: =1/(1-T12) -> 2.3887208 | V12: =(Parameters!$B$19*(F12+Parameters!$B$20)^T12+Parameters!$B$18*G12^T12)^(1/T12) -> 0.41855844 | W12: =(Parameters!$B$10*H12^Parameters!$B$9+Parameters!$B$11*V12^Parameters!$B$9)^(Parameters!$B$7/Parameters!$B$9)*O12 -> 1.4385103 | X12: =W12 - D12 - E12 - LN(1+EXP(Parameters!$B$21*C12))/Parameters!$B$21 - IF(C12>0, 0,Parameters!$B$6*C12^2/F12) -> 1.1533512 | Y12: =EXP(-Parameters!$B$55*A12) -> 0.88621118 | Z12: =IF(X12>0,X12^(1-Parameters!$B$52)/(1-Parameters!$B$52)*Y12*Parameters!$B$65,-10+X12*1000) -> -2.4086996 | AC12: =C12*$J12*$K12 -> 0.86260787 | AD12: =D12*$J12*$K12 -> 5.0491889 | AE12: =I12*J12*K12 -> 3.8533169 | AF12: =F12*J12*K12 -> 39.468202 | AG12: =G12*J12*K12 -> 30.006447 | AH12: =V12*J12*K12 -> 37.075023 | AI12: =AH12/AH$4*100 -> 91.244454 | AJ12: =W12*J12*K12 -> 127.4202 | AK12: =X12*J12*K12 -> 102.16141 | AL12: =LN(AJ12)-LN(AJ11) -> 0.018795616 | AM12: =LN(AK12)-LN(AK11) -> 0.018291754 | AN12: =AVERAGE(AL10:AL14) -> 0.018144716 | AO12: =AVERAGE(AM10:AM14) -> 0.016554473 | AQ12: =W12*K12*J12 -> 127.4202 | AR12: =Parameters!$B$7*W12*(W12/O12)^(-Parameters!$B$9/Parameters!$B$7)*Parameters!$B$11*(V12)^(Parameters!$B$9-T12)*((1-2*Parameters!$B$5*C12/F12)*Parameters!$B$19*(F12+Parameters!$B$20)^(T12-1)-(1-2*Parameters!$B$5*D12/G12)*(Parameters!$B$18)*(G12)^(T12-1)) -> 0.13942768 | AS12: =((C13-C11)/2-(F13-F11)/F12/2*C12)/(F12/2/Parameters!$B$5-C12)-((D13-D11)/D12-(G13-G11)/G12)/(G12/2/Parameters!$B$5/D12-1) -> 0.059923041 | AT12: =+Parameters!$B$5*C12^2/F12^2-Parameters!$B$5*D12^2/G12^2 -> -0.027837165 | AU12: =EXP(-Parameters!$B$42*'6states'!A12)*(Parameters!$B$37*EXP(-Parameters!$B$38*Parameters!$E$25*'6states'!I12/('6states'!F12+'6states'!I12))*(1/Parameters!$B$38/Parameters!$E$25+'6states'!I12/('6states'!F12+'6states'!I12))-Parameters!$B$37/Parameters!$B$38/Parameters!$E$25*EXP(-Parameters!$B$38*Parameters!$E$25)+Parameters!$B$39) -> 0.72239259 | AV12: =J12*K12*EXP(-Parameters!$B$42*'6states'!A12)*(Parameters!$B$37*EXP(-Parameters!$B$38*Parameters!$E$25*'6states'!I12/('6states'!F12+'6states'!I12))*(1/Parameters!$B$38/Parameters!$E$25+'6states'!I12/('6states'!F12+'6states'!I12))-Parameters!$B$37/Parameters!$B$38/Parameters!$E$25*EXP(-Parameters!$B$38*Parameters!$E$25)+Parameters!$B$39) -> 63.988011 | AW12: =1000*(AR12+AS12+AT12)/AU12 -> 237.4243 | AX12: =1-W12/'6states,ExoDamages'!T12 -> 0.038750869 | AY12: =-Y12*W12*X12^(-Parameters!B$52)*Parameters!B$46*Parameters!B$45*N12 -> -1.9565605e-05 | AZ12: =1000*EXP(-(Parameters!$B$54)*'6states'!A12)*AQ12*Parameters!B$46*Parameters!B$45*N12 -> 1.7905217 | BA12: =SUM(AZ12:AZ$204)*EXP(Parameters!$B$54*A12) -> 220.68379 | BB12: =((C12>0)*C12+D12+E12)/W12 -> 0.19811069 | BF12: =SUM(AY12:AY210)/Y12 -> -0.0019294426 | BG12: =BF12/Parameters!$B$45 -> -3.2157376 | BH12: =1-BG11/BG12 -> 0.0036920367 | BK12: =-EXP(-Parameters!B$42*'6states'!A12)*(-Parameters!B$37/Parameters!B$38/Parameters!E$25*(EXP(-Parameters!B$38*Parameters!E$25*'6states'!AE12/('6states'!F12+'6states'!AE12))-EXP(-Parameters!B$38*Parameters!E$25))+Parameters!B$37*'6states'!F12/('6states'!F12+'6states'!AE12)*EXP(-Parameters!B$38*Parameters!E$25*'6states'!I12/('6states'!F12+'6states'!AE12))) -> -0.38051503 | BL12: =-J12*K12*EXP(-Parameters!B$42*'6states'!A12)*(-Parameters!B$37/Parameters!B$38/Parameters!E$25*(EXP(-Parameters!B$38*Parameters!E$25*'6states'!I12/('6states'!F12+'6states'!I12))-EXP(-Parameters!B$38*Parameters!E$25)) + Parameters!B$37*'6states'!F12/('6states'!F12+'6states'!I12)*EXP(-Parameters!B$38*Parameters!E$25*'6states'!I12/('6states'!F12+'6states'!I12))) -> -10.055362 | BM12: =I12/(F12+I12) -> 0.08894695 | BN12: =BK12-AU12 -> -1.1029076 | BS12: =EXP(-Parameters!$B$56*A12)*BF12*BL12 -> 0.010395127 | BT12: =-EXP((Parameters!$B$56)*F12)*SUM(BS12:BS20) -> -0.10552664 | BU12: =X12^-Parameters!B$52/(1-2*Parameters!B$5*'6states'!D12/'6states'!G12) -> 1.2431895 | BV12: =BU12/BU11 -> 0.9789497 | BW12: =$X12^-Parameters!$B$52/(1-2*Parameters!$B$5*'6states'!$E12/'6states'!$H12) -> 0.92561159 | BX12: =BW12/BW11 -> 1.0060424 | BY12: =($X12^-Parameters!$B$52*(1/(1+EXP(-C12)) + IF(C12<0,2*Parameters!$B$6*C12/F12,0)) + BQ12*(1/(1+EXP((C12-Parameters!$B$22)*Parameters!$B$21))))/(1-IF(C12>0,2*Parameters!$B$5*C12/F12,0)) -> 0.4333537 | BZ12: =BY12/BY11 -> 1.0094434 | CA12: =BY12-BY11 -> 0.0040540599 | CB12: =(1/$T12-1/Parameters!$B$13) * LN(Parameters!$B$18) / LN(P12) -> 0.23709603 | CC12: =(Parameters!$B$18*'6states'!T12^+Parameters!$B$19*Parameters!$B$25^'6states'!T12)^((1-'6states'!T12)/'6states'!T12)*Parameters!$B$18*Parameters!$B$26^('6states'!T12-1) -> 0.19552512 | CD12: =(LN(CC12)-LN(CC$4))/ LN(P12) -> 0.29166938 | CE12: =1-2^-CB12 -> 0.15154858 | CF12: =1-2^-CC12 -> 0.12674501
A13: =A12+Parameters!$B$65 -> 9 | B13: 2034 | C13: 0.0097406584 | D13: 0.057749729 | E13: 0.2205407 | F13: =MAX((1-Parameters!$B$4)^Parameters!B$65*F12 + C12*Parameters!B$65 - IF(C12>0,Parameters!$B$5,0)*C12^2/F12*Parameters!B$65, 0.0001) -> 0.42707505 | G13: =(1-Parameters!$B$4)^Parameters!B$65*G12+D12*Parameters!B$65-Parameters!$B$5*D12^2/G12*Parameters!B$65 -> 0.36486083 | H13: =(1-Parameters!$B$4)^Parameters!B$65*H12+E12*Parameters!B$65-Parameters!$B$5*E12^2/H12*Parameters!B$65 -> 3.9621482 | I13: =I12 *(1-Parameters!$B$4)-C12*(C12<0)*Parameters!B$65 -> 0.040765741 | J13: =J12*(1+Parameters!$B$51)^Parameters!B$65 -> 8.3754633 | K13: =K12*(1+Parameters!$B$53)^Parameters!B$65 -> 10.81868 | L13: =J13*K13*EXP(-Parameters!$B$42*'6states'!A13)*(Parameters!$B$37/Parameters!$B$38*('6states'!F13+'6states'!I13)/Parameters!$E$25*(EXP(-Parameters!$B$38*Parameters!$E$25*'6states'!I13/('6states'!F13+'6states'!I13))-EXP(-Parameters!$B$38*Parameters!$E$25)) + Parameters!$B$39*'6states'!F13) -> 27.262146 | M13: =M12+L13*Parameters!B$65 -> 2598.7982 | N13: =M13*Parameters!$B$45 -> 1.5592789 | O13: =EXP(-Parameters!$B$46/2*N13^2) -> 0.97586104 | P13: =MAX((Parameters!$B$62 + Parameters!$B$31*'6states'!A13 - '6states'!M13 + Parameters!$B$47/Parameters!$B$45)/Parameters!B$62,1) -> 4.600035 | Q13: =Parameters!B$61*EXP(-Parameters!B$60*A13) -> 0.39213576 | R13: =(1-Parameters!B$61)*P13^-Parameters!B$63 -> 0.42923378 | S13: =Parameters!B$61*EXP(-Parameters!B$60*A13)+(1-Parameters!B$61)*P13^-Parameters!B$63 -> 0.82136953 | T13: =1-S13/Parameters!$B$12 -> 0.58931523 | U13: =1/(1-T13) -> 2.4349576 | V13: =(Parameters!$B$19*(F13+Parameters!$B$20)^T13+Parameters!$B$18*G13^T13)^(1/T13) -> 0.41456921 | W13: =(Parameters!$B$10*H13^Parameters!$B$9+Parameters!$B$11*V13^Parameters!$B$9)^(Parameters!$B$7/Parameters!$B$9)*O13 -> 1.4330958 | X13: =W13 - D13 - E13 - LN(1+EXP(Parameters!$B$21*C13))/Parameters!$B$21 - IF(C13>0, 0,Parameters!$B$6*C13^2/F13) -> 1.14489 | Y13: =EXP(-Parameters!$B$55*A13) -> 0.87292992 | Z13: =IF(X13>0,X13^(1-Parameters!$B$52)/(1-Parameters!$B$52)*Y13*Parameters!$B$65,-10+X13*1000) -> -2.3787238 | AC13: =C13*$J13*$K13 -> 0.88261529 | AD13: =D13*$J13*$K13 -> 5.2327874 | AE13: =I13*J13*K13 -> 3.6938433 | AF13: =F13*J13*K13 -> 38.697894 | AG13: =G13*J13*K13 -> 33.060573 | AH13: =V13*J13*K13 -> 37.564722 | AI13: =AH13/AH$4*100 -> 92.449641 | AJ13: =W13*J13*K13 -> 129.8549 | AK13: =X13*J13*K13 -> 103.74015 | AL13: =LN(AJ13)-LN(AJ12) -> 0.018927383 | AM13: =LN(AK13)-LN(AK12) -> 0.015335206 | AN13: =AVERAGE(AL11:AL15) -> 0.018607586 | AO13: =AVERAGE(AM11:AM15) -> 0.015937648 | AQ13: =W13*K13*J13 -> 129.8549 | AR13: =Parameters!$B$7*W13*(W13/O13)^(-Parameters!$B$9/Parameters!$B$7)*Parameters!$B$11*(V13)^(Parameters!$B$9-T13)*((1-2*Parameters!$B$5*C13/F13)*Parameters!$B$19*(F13+Parameters!$B$20)^(T13-1)-(1-2*Parameters!$B$5*D13/G13)*(Parameters!$B$18)*(G13)^(T13-1)) -> 0.14249584 | AS13: =((C14-C12)/2-(F14-F12)/F13/2*C13)/(F13/2/Parameters!$B$5-C13)-((D14-D12)/D13-(G14-G12)/G13)/(G13/2/Parameters!$B$5/D13-1) -> 0.053003362 | AT13: =+Parameters!$B$5*C13^2/F13^2-Parameters!$B$5*D13^2/G13^2 -> -0.024531977 | AU13: =EXP(-Parameters!$B$42*'6states'!A13)*(Parameters!$B$37*EXP(-Parameters!$B$38*Parameters!$E$25*'6states'!I13/('6states'!F13+'6states'!I13))*(1/Parameters!$B$38/Parameters!$E$25+'6states'!I13/('6states'!F13+'6states'!I13))-Parameters!$B$37/Parameters!$B$38/Parameters!$E$25*EXP(-Parameters!$B$38*Parameters!$E$25)+Parameters!$B$39) -> 0.7160984 | AV13: =J13*K13*EXP(-Parameters!$B$42*'6states'!A13)*(Parameters!$B$37*EXP(-Parameters!$B$38*Parameters!$E$25*'6states'!I13/('6states'!F13+'6states'!I13))*(1/Parameters!$B$38/Parameters!$E$25+'6states'!I13/('6states'!F13+'6states'!I13))-Parameters!$B$37/Parameters!$B$38/Parameters!$E$25*EXP(-Parameters!$B$38*Parameters!$E$25)+Parameters!$B$39) -> 64.886723 | AW13: =1000*(AR13+AS13+AT13)/AU13 -> 238.74823 | AX13: =1-W13/'6states,ExoDamages'!T13 -> 0.04190191 | AY13: =-Y13*W13*X13^(-Parameters!B$52)*Parameters!B$46*Parameters!B$45*N13 -> -1.9597229e-05 | AZ13: =1000*EXP(-(Parameters!$B$54)*'6states'!A13)*AQ13*Parameters!B$46*Parameters!B$45*N13 -> 1.7804749 | BA13: =SUM(AZ13:AZ$204)*EXP(Parameters!$B$54*A13) -> 226.11165 | BB13: =((C13>0)*C13+D13+E13)/W13 -> 0.20098523 | BF13: =SUM(AY13:AY211)/Y13 -> -0.0019363845 | BG13: =BF13/Parameters!$B$45 -> -3.2273075 | BH13: =1-BG12/BG13 -> 0.0035850023 | BK13: =-EXP(-Parameters!B$42*'6states'!A13)*(-Parameters!B$37/Parameters!B$38/Parameters!E$25*(EXP(-Parameters!B$38*Parameters!E$25*'6states'!AE13/('6states'!F13+'6states'!AE13))-EXP(-Parameters!B$38*Parameters!E$25))+Parameters!B$37*'6states'!F13/('6states'!F13+'6states'!AE13)*EXP(-Parameters!B$38*Parameters!E$25*'6states'!I13/('6states'!F13+'6states'!AE13))) -> -0.38033947 | BL13: =-J13*K13*EXP(-Parameters!B$42*'6states'!A13)*(-Parameters!B$37/Parameters!B$38/Parameters!E$25*(EXP(-Parameters!B$38*Parameters!E$25*'6states'!I13/('6states'!F13+'6states'!I13))-EXP(-Parameters!B$38*Parameters!E$25)) + Parameters!B$37*'6states'!F13/('6states'!F13+'6states'!I13)*EXP(-Parameters!B$38*Parameters!E$25*'6states'!I13/('6states'!F13+'6states'!I13))) -> -11.022831 | BM13: =I13/(F13+I13) -> 0.087135927 | BN13: =BK13-AU13 -> -1.0964379 | BS13: =EXP(-Parameters!$B$56*A13)*BF13*BL13 -> 0.010578157 | BT13: =-EXP((Parameters!$B$56)*F13)*SUM(BS13:BS21) -> -0.10775793 | BU13: =X13^-Parameters!B$52/(1-2*Parameters!B$5*'6states'!D13/'6states'!G13) -> 1.218897 | BV13: =BU13/BU12 -> 0.98045953 | BW13: =$X13^-Parameters!$B$52/(1-2*Parameters!$B$5*'6states'!$E13/'6states'!$H13) -> 0.93740096 | BX13: =BW13/BW12 -> 1.0127368 | BY13: =($X13^-Parameters!$B$52*(1/(1+EXP(-C13)) + IF(C13<0,2*Parameters!$B$6*C13/F13,0)) + BQ13*(1/(1+EXP((C13-Parameters!$B$22)*Parameters!$B$21))))/(1-IF(C13>0,2*Parameters!$B$5*C13/F13,0)) -> 0.4385566 | BZ13: =BY13/BY12 -> 1.0120061 | CA13: =BY13-BY12 -> 0.005202903 | CB13: =(1/$T13-1/Parameters!$B$13) * LN(Parameters!$B$18) / LN(P13) -> 0.23661845 | CC13: =(Parameters!$B$18*'6states'!T13^+Parameters!$B$19*Parameters!$B$25^'6states'!T13)^((1-'6states'!T13)/'6states'!T13)*Parameters!$B$18*Parameters!$B$26^('6states'!T13-1) -> 0.20146127 | CD13: =(LN(CC13)-LN(CC$4))/ LN(P13) -> 0.28839885 | CE13: =1-2^-CB13 -> 0.15126766 | CF13: =1-2^-CC13 -> 0.13033075
A14: =A13+Parameters!$B$65 -> 10 | B14: 2035 | C14: 0.0098467391 | D14: 0.058870449 | E14: 0.21975562 | F14: =MAX((1-Parameters!$B$4)^Parameters!B$65*F13 + C13*Parameters!B$65 - IF(C13>0,Parameters!$B$5,0)*C13^2/F13*Parameters!B$65, 0.0001) -> 0.40973052 | G14: =(1-Parameters!$B$4)^Parameters!B$65*G13+D13*Parameters!B$65-Parameters!$B$5*D13^2/G13*Parameters!B$65 -> 0.39052025 | H14: =(1-Parameters!$B$4)^Parameters!B$65*H13+E13*Parameters!B$65-Parameters!$B$5*E13^2/H13*Parameters!B$65 -> 3.9211941 | I14: =I13 *(1-Parameters!$B$4)-C13*(C13<0)*Parameters!B$65 -> 0.038201576 | J14: =J13*(1+Parameters!$B$51)^Parameters!B$65 -> 8.3997522 | K14: =K13*(1+Parameters!$B$53)^Parameters!B$65 -> 11.035054 | L14: =J14*K14*EXP(-Parameters!$B$42*'6states'!A14)*(Parameters!$B$37/Parameters!$B$38*('6states'!F14+'6states'!I14)/Parameters!$E$25*(EXP(-Parameters!$B$38*Parameters!$E$25*'6states'!I14/('6states'!F14+'6states'!I14))-EXP(-Parameters!$B$38*Parameters!$E$25)) + Parameters!$B$39*'6states'!F14) -> 26.499775 | M14: =M13+L14*Parameters!B$65 -> 2625.298 | N14: =M14*Parameters!$B$45 -> 1.5751788 | O14: =EXP(-Parameters!$B$46/2*N14^2) -> 0.97537239 | P14: =MAX((Parameters!$B$62 + Parameters!$B$31*'6states'!A14 - '6states'!M14 + Parameters!$B$47/Parameters!$B$45)/Parameters!B$62,1) -> 5.1340395 | Q14: =Parameters!B$61*EXP(-Parameters!B$60*A14) -> 0.38168975 | R14: =(1-Parameters!B$61)*P14^-Parameters!B$63 -> 0.42454535 | S14: =Parameters!B$61*EXP(-Parameters!B$60*A14)+(1-Parameters!B$61)*P14^-Parameters!B$63 -> 0.80623509 | T14: =1-S14/Parameters!$B$12 -> 0.59688245 | U14: =1/(1-T14) -> 2.480666 | V14: =(Parameters!$B$19*(F14+Parameters!$B$20)^T14+Parameters!$B$18*G14^T14)^(1/T14) -> 0.41076576 | W14: =(Parameters!$B$10*H14^Parameters!$B$9+Parameters!$B$11*V14^Parameters!$B$9)^(Parameters!$B$7/Parameters!$B$9)*O14 -> 1.4280802 | X14: =W14 - D14 - E14 - LN(1+EXP(Parameters!$B$21*C14))/Parameters!$B$21 - IF(C14>0, 0,Parameters!$B$6*C14^2/F14) -> 1.139438 | Y14: =EXP(-Parameters!$B$55*A14) -> 0.8598477 | Z14: =IF(X14>0,X14^(1-Parameters!$B$52)/(1-Parameters!$B$52)*Y14*Parameters!$B$65,-10+X14*1000) -> -2.3469927 | AC14: =C14*$J14*$K14 -> 0.91271117 | AD14: =D14*$J14*$K14 -> 5.4568032 | AE14: =I14*J14*K14 -> 3.5409697 | AF14: =F14*J14*K14 -> 37.978627 | AG14: =G14*J14*K14 -> 36.197994 | AH14: =V14*J14*K14 -> 38.074584 | AI14: =AH14/AH$4*100 -> 93.704451 | AJ14: =W14*J14*K14 -> 132.37121 | AK14: =X14*J14*K14 -> 105.61647 | AL14: =LN(AJ14)-LN(AJ13) -> 0.019192482 | AM14: =LN(AK14)-LN(AK13) -> 0.017925073 | AN14: =AVERAGE(AL12:AL16) -> 0.019163746 | AO14: =AVERAGE(AM12:AM16) -> 0.017393878 | AQ14: =W14*K14*J14 -> 132.37121 | AR14: =Parameters!$B$7*W14*(W14/O14)^(-Parameters!$B$9/Parameters!$B$7)*Parameters!$B$11*(V14)^(Parameters!$B$9-T14)*((1-2*Parameters!$B$5*C14/F14)*Parameters!$B$19*(F14+Parameters!$B$20)^(T14-1)-(1-2*Parameters!$B$5*D14/G14)*(Parameters!$B$18)*(G14)^(T14-1)) -> 0.14585506 | AS14: =((C15-C13)/2-(F15-F13)/F14/2*C14)/(F14/2/Parameters!$B$5-C14)-((D15-D13)/D14-(G15-G13)/G14)/(G14/2/Parameters!$B$5/D14-1) -> 0.047776096 | AT14: =+Parameters!$B$5*C14^2/F14^2-Parameters!$B$5*D14^2/G14^2 -> -0.022147644 | AU14: =EXP(-Parameters!$B$42*'6states'!A14)*(Parameters!$B$37*EXP(-Parameters!$B$38*Parameters!$E$25*'6states'!I14/('6states'!F14+'6states'!I14))*(1/Parameters!$B$38/Parameters!$E$25+'6states'!I14/('6states'!F14+'6states'!I14))-Parameters!$B$37/Parameters!$B$38/Parameters!$E$25*EXP(-Parameters!$B$38*Parameters!$E$25)+Parameters!$B$39) -> 0.70993083 | AV14: =J14*K14*EXP(-Parameters!$B$42*'6states'!A14)*(Parameters!$B$37*EXP(-Parameters!$B$38*Parameters!$E$25*'6states'!I14/('6states'!F14+'6states'!I14))*(1/Parameters!$B$38/Parameters!$E$25+'6states'!I14/('6states'!F14+'6states'!I14))-Parameters!$B$37/Parameters!$B$38/Parameters!$E$25*EXP(-Parameters!$B$38*Parameters!$E$25)+Parameters!$B$39) -> 65.804709 | AW14: =1000*(AR14+AS14+AT14)/(EXP(-Parameters!$B$42*A14)*((C14<0)*Parameters!$B$37*EXP(-Parameters!$B$38*AF14)+(C14>=0)*Parameters!$B$41)) -> 208.1081 | AX14: =1-W14/'6states,ExoDamages'!T14 -> 0.044809168 | AY14: =-Y14*W14*X14^(-Parameters!B$52)*Parameters!B$46*Parameters!B$45*N14 -> -1.9557748e-05 | AZ14: =1000*EXP(-(Parameters!$B$54)*'6states'!A14)*AQ14*Parameters!B$46*Parameters!B$45*N14 -> 1.7702449 | BA14: =SUM(AZ14:AZ$204)*EXP(Parameters!$B$54*A14) -> 231.65996 | BB14: =(C14+D14+E14)/W14 -> 0.20200043 | BF14: =SUM(AY14:AY212)/Y14 -> -0.0019430543 | BG14: =BF14/Parameters!$B$45 -> -3.2384238 | BH14: =1-BG13/BG14 -> 0.0034326203 | BK14: =-EXP(-Parameters!B$42*'6states'!A14)*(-Parameters!B$37/Parameters!B$38/Parameters!E$25*(EXP(-Parameters!B$38*Parameters!E$25*'6states'!AE14/('6states'!F14+'6states'!AE14))-EXP(-Parameters!B$38*Parameters!E$25))+Parameters!B$37*'6states'!F14/('6states'!F14+'6states'!AE14)*EXP(-Parameters!B$38*Parameters!E$25*'6states'!I14/('6states'!F14+'6states'!AE14))) -> -0.38042027 | BL14: =-J14*K14*EXP(-Parameters!B$42*'6states'!A14)*(-Parameters!B$37/Parameters!B$38/Parameters!E$25*(EXP(-Parameters!B$38*Parameters!E$25*'6states'!I14/('6states'!F14+'6states'!I14))-EXP(-Parameters!B$38*Parameters!E$25)) + Parameters!B$37*'6states'!F14/('6states'!F14+'6states'!I14)*EXP(-Parameters!B$38*Parameters!E$25*'6states'!I14/('6states'!F14+'6states'!I14))) -> -12.104799 | BM14: =I14/(F14+I14) -> 0.0852843 | BN14: =BK14-AU14 -> -1.0903511 | BS14: =EXP(-Parameters!$B$56*A14)*BF14*BL14 -> 0.010781838 | BT14: =-EXP((Parameters!$B$56)*F14)*SUM(BS14:BS22) -> -0.11011467 | BU14: =X14^-Parameters!B$52/(1-2*Parameters!B$5*'6states'!D14/'6states'!G14) -> 1.2003271 | BV14: =BU14/BU13 -> 0.984765 | BW14: =$X14^-Parameters!$B$52/(1-2*Parameters!$B$5*'6states'!$E14/'6states'!$H14) -> 0.94427106 | BX14: =BW14/BW13 -> 1.0073289 | BY14: =($X14^-Parameters!$B$52*(1/(1+EXP(-C14)) + IF(C14<0,2*Parameters!$B$6*C14/F14,0)) + BQ14*(1/(1+EXP((C14-Parameters!$B$22)*Parameters!$B$21))))/(1-IF(C14>0,2*Parameters!$B$5*C14/F14,0)) -> 0.44255061 | BZ14: =BY14/BY13 -> 1.0091072 | CA14: =BY14-BY13 -> 0.0039940062 | CB14: =(1/$T14-1/Parameters!$B$13) * LN(Parameters!$B$18) / LN(P14) -> 0.23639862 | CC14: =(Parameters!$B$18*'6states'!T14^+Parameters!$B$19*Parameters!$B$25^'6states'!T14)^((1-'6states'!T14)/'6states'!T14)*Parameters!$B$18*Parameters!$B$26^('6states'!T14-1) -> 0.20699413 | CD14: =(LN(CC14)-LN(CC$4))/ LN(P14) -> 0.2855984 | CE14: =1-2^-CB14 -> 0.15113833 | CF14: =1-2^-CC14 -> 0.13365962
A15: =A14+Parameters!$B$65 -> 11 | B15: 2036 | C15: 0.0098007764 | D15: 0.059238145 | E15: 0.22155368 | F15: =MAX((1-Parameters!$B$4)^Parameters!B$65*F14 + C14*Parameters!B$65 - IF(C14>0,Parameters!$B$5,0)*C14^2/F14*Parameters!B$65, 0.0001) -> 0.39356857 | G15: =(1-Parameters!$B$4)^Parameters!B$65*G14+D14*Parameters!B$65-Parameters!$B$5*D14^2/G14*Parameters!B$65 -> 0.41595233 | H15: =(1-Parameters!$B$4)^Parameters!B$65*H14+E14*Parameters!B$65-Parameters!$B$5*E14^2/H14*Parameters!B$65 -> 3.8819908 | I15: =I14 *(1-Parameters!$B$4)-C14*(C14<0)*Parameters!B$65 -> 0.035798696 | J15: =J14*(1+Parameters!$B$51)^Parameters!B$65 -> 8.4241114 | K15: =K14*(1+Parameters!$B$53)^Parameters!B$65 -> 11.255755 | L15: =J15*K15*EXP(-Parameters!$B$42*'6states'!A15)*(Parameters!$B$37/Parameters!$B$38*('6states'!F15+'6states'!I15)/Parameters!$E$25*(EXP(-Parameters!$B$38*Parameters!$E$25*'6states'!I15/('6states'!F15+'6states'!I15))-EXP(-Parameters!$B$38*Parameters!$E$25)) + Parameters!$B$39*'6states'!F15) -> 25.791232 | M15: =M14+L15*Parameters!B$65 -> 2651.0893 | N15: =M15*Parameters!$B$45 -> 1.5906536 | O15: =EXP(-Parameters!$B$46/2*N15^2) -> 0.97489228 | P15: =MAX((Parameters!$B$62 + Parameters!$B$31*'6states'!A15 - '6states'!M15 + Parameters!$B$47/Parameters!$B$45)/Parameters!B$62,1) -> 5.6822149 | Q15: =Parameters!B$61*EXP(-Parameters!B$60*A15) -> 0.37152201 | R15: =(1-Parameters!B$61)*P15^-Parameters!B$63 -> 0.42026018 | S15: =Parameters!B$61*EXP(-Parameters!B$60*A15)+(1-Parameters!B$61)*P15^-Parameters!B$63 -> 0.79178218 | T15: =1-S15/Parameters!$B$12 -> 0.60410891 | U15: =1/(1-T15) -> 2.5259472 | V15: =(Parameters!$B$19*(F15+Parameters!$B$20)^T15+Parameters!$B$18*G15^T15)^(1/T15) -> 0.40731548 | W15: =(Parameters!$B$10*H15^Parameters!$B$9+Parameters!$B$11*V15^Parameters!$B$9)^(Parameters!$B$7/Parameters!$B$9)*O15 -> 1.4232992 | X15: =W15 - D15 - E15 - LN(1+EXP(Parameters!$B$21*C15))/Parameters!$B$21 - IF(C15>0, 0,Parameters!$B$6*C15^2/F15) -> 1.132535 | Y15: =EXP(-Parameters!$B$55*A15) -> 0.84696153 | Z15: =IF(X15>0,X15^(1-Parameters!$B$52)/(1-Parameters!$B$52)*Y15*Parameters!$B$65,-10+X15*1000) -> -2.3167415 | AC15: =C15*$J15*$K15 -> 0.92930703 | AD15: =D15*$J15*$K15 -> 5.6169452 | AE15: =I15*J15*K15 -> 3.3944229 | AF15: =F15*J15*K15 -> 37.318068 | AG15: =G15*J15*K15 -> 39.44049 | AH15: =V15*J15*K15 -> 38.621546 | AI15: =AH15/AH$4*100 -> 95.050566 | AJ15: =W15*J15*K15 -> 134.95686 | AK15: =X15*J15*K15 -> 107.38667 | AL15: =LN(AJ15)-LN(AJ14) -> 0.019344977 | AM15: =LN(AK15)-LN(AK14) -> 0.016621702 | AN15: =AVERAGE(AL13:AL17) -> 0.019339539 | AO15: =AVERAGE(AM13:AM17) -> 0.017276153 | AQ15: =W15*K15*J15 -> 134.95686 | AR15: =Parameters!$B$7*W15*(W15/O15)^(-Parameters!$B$9/Parameters!$B$7)*Parameters!$B$11*(V15)^(Parameters!$B$9-T15)*((1-2*Parameters!$B$5*C15/F15)*Parameters!$B$19*(F15+Parameters!$B$20)^(T15-1)-(1-2*Parameters!$B$5*D15/G15)*(Parameters!$B$18)*(G15)^(T15-1)) -> 0.14862414 | AS15: =((C16-C14)/2-(F16-F14)/F15/2*C15)/(F15/2/Parameters!$B$5-C15)-((D16-D14)/D15-(G16-G14)/G15)/(G15/2/Parameters!$B$5/D15-1) -> 0.039056776 | AT15: =+Parameters!$B$5*C15^2/F15^2-Parameters!$B$5*D15^2/G15^2 -> -0.019662107 | AU15: =EXP(-Parameters!$B$42*'6states'!A15)*(Parameters!$B$37*EXP(-Parameters!$B$38*Parameters!$E$25*'6states'!I15/('6states'!F15+'6states'!I15))*(1/Parameters!$B$38/Parameters!$E$25+'6states'!I15/('6states'!F15+'6states'!I15))-Parameters!$B$37/Parameters!$B$38/Parameters!$E$25*EXP(-Parameters!$B$38*Parameters!$E$25)+Parameters!$B$39) -> 0.70390279 | AV15: =J15*K15*EXP(-Parameters!$B$42*'6states'!A15)*(Parameters!$B$37*EXP(-Parameters!$B$38*Parameters!$E$25*'6states'!I15/('6states'!F15+'6states'!I15))*(1/Parameters!$B$38/Parameters!$E$25+'6states'!I15/('6states'!F15+'6states'!I15))-Parameters!$B$37/Parameters!$B$38/Parameters!$E$25*EXP(-Parameters!$B$38*Parameters!$E$25)+Parameters!$B$39) -> 66.743876 | AW15: =1000*(AR15+AS15+AT15)/(EXP(-Parameters!$B$42*A15)*((C15<0)*Parameters!$B$37*EXP(-Parameters!$B$38*AF15)+(C15>=0)*Parameters!$B$41)) -> 205.95268 | AX15: =1-W15/'6states,ExoDamages'!T15 -> 0.047556937 | AY15: =-Y15*W15*X15^(-Parameters!B$52)*Parameters!B$46*Parameters!B$45*N15 -> -1.9548486e-05 | AZ15: =1000*EXP(-(Parameters!$B$54)*'6states'!A15)*AQ15*Parameters!B$46*Parameters!B$45*N15 -> 1.7596924 | BA15: =SUM(AZ15:AZ$204)*EXP(Parameters!$B$54*A15) -> 237.33117 | BB15: =(C15+D15+E15)/W15 -> 0.20416831 | BF15: =SUM(AY15:AY213)/Y15 -> -0.0019495254 | BG15: =BF15/Parameters!$B$45 -> -3.249209 | BH15: =1-BG14/BG15 -> 0.0033193187 | BK15: =-EXP(-Parameters!B$42*'6states'!A15)*(-Parameters!B$37/Parameters!B$38/Parameters!E$25*(EXP(-Parameters!B$38*Parameters!E$25*'6states'!AE15/('6states'!F15+'6states'!AE15))-EXP(-Parameters!B$38*Parameters!E$25))+Parameters!B$37*'6states'!F15/('6states'!F15+'6states'!AE15)*EXP(-Parameters!B$38*Parameters!E$25*'6states'!I15/('6states'!F15+'6states'!AE15))) -> -0.38085378 | BL15: =-J15*K15*EXP(-Parameters!B$42*'6states'!A15)*(-Parameters!B$37/Parameters!B$38/Parameters!E$25*(EXP(-Parameters!B$38*Parameters!E$25*'6states'!I15/('6states'!F15+'6states'!I15))-EXP(-Parameters!B$38*Parameters!E$25)) + Parameters!B$37*'6states'!F15/('6states'!F15+'6states'!I15)*EXP(-Parameters!B$38*Parameters!E$25*'6states'!I15/('6states'!F15+'6states'!I15))) -> -13.326189 | BM15: =I15/(F15+I15) -> 0.083375467 | BN15: =BK15-AU15 -> -1.0847566 | BS15: =EXP(-Parameters!$B$56*A15)*BF15*BL15 -> 0.011015652 | BT15: =-EXP((Parameters!$B$56)*F15)*SUM(BS15:BS23) -> -0.11258183 | BU15: =X15^-Parameters!B$52/(1-2*Parameters!B$5*'6states'!D15/'6states'!G15) -> 1.182012 | BV15: =BU15/BU14 -> 0.98474158 | BW15: =$X15^-Parameters!$B$52/(1-2*Parameters!$B$5*'6states'!$E15/'6states'!$H15) -> 0.95426142 | BX15: =BW15/BW14 -> 1.01058 | BY15: =($X15^-Parameters!$B$52*(1/(1+EXP(-C15)) + IF(C15<0,2*Parameters!$B$6*C15/F15,0)) + BQ15*(1/(1+EXP((C15-Parameters!$B$22)*Parameters!$B$21))))/(1-IF(C15>0,2*Parameters!$B$5*C15/F15,0)) -> 0.44700299 | BZ15: =BY15/BY14 -> 1.0100607 | CA15: =BY15-BY14 -> 0.0044523822 | CB15: =(1/$T15-1/Parameters!$B$13) * LN(Parameters!$B$18) / LN(P15) -> 0.23633662 | CC15: =(Parameters!$B$18*'6states'!T15^+Parameters!$B$19*Parameters!$B$25^'6states'!T15)^((1-'6states'!T15)/'6states'!T15)*Parameters!$B$18*Parameters!$B$26^('6states'!T15-1) -> 0.21216465 | CD15: =(LN(CC15)-LN(CC$4))/ LN(P15) -> 0.28312262 | CE15: =1-2^-CB15 -> 0.15110185 | CF15: =1-2^-CC15 -> 0.13675897
A16: =A15+Parameters!$B$65 -> 12 | B16: 2037 | C16: 0.0098272189 | D16: 0.060494876 | E16: 0.22022087 | F16: =MAX((1-Parameters!$B$4)^Parameters!B$65*F15 + C15*Parameters!B$65 - IF(C15>0,Parameters!$B$5,0)*C15^2/F15*Parameters!B$65, 0.0001) -> 0.37836982 | G16: =(1-Parameters!$B$4)^Parameters!B$65*G15+D15*Parameters!B$65-Parameters!$B$5*D15^2/G15*Parameters!B$65 -> 0.44059063 | H16: =(1-Parameters!$B$4)^Parameters!B$65*H15+E15*Parameters!B$65-Parameters!$B$5*E15^2/H15*Parameters!B$65 -> 3.8467227 | I16: =I15 *(1-Parameters!$B$4)-C15*(C15<0)*Parameters!B$65 -> 0.033546958 | J16: =J15*(1+Parameters!$B$51)^Parameters!B$65 -> 8.4485414 | K16: =K15*(1+Parameters!$B$53)^Parameters!B$65 -> 11.48087 | L16: =J16*K16*EXP(-Parameters!$B$42*'6states'!A16)*(Parameters!$B$37/Parameters!$B$38*('6states'!F16+'6states'!I16)/Parameters!$E$25*(EXP(-Parameters!$B$38*Parameters!$E$25*'6states'!I16/('6states'!F16+'6states'!I16))-EXP(-Parameters!$B$38*Parameters!$E$25)) + Parameters!$B$39*'6states'!F16) -> 25.124341 | M16: =M15+L16*Parameters!B$65 -> 2676.2136 | N16: =M16*Parameters!$B$45 -> 1.6057282 | O16: =EXP(-Parameters!$B$46/2*N16^2) -> 0.9744203 | P16: =MAX((Parameters!$B$62 + Parameters!$B$31*'6states'!A16 - '6states'!M16 + Parameters!$B$47/Parameters!$B$45)/Parameters!B$62,1) -> 6.2437281 | Q16: =Parameters!B$61*EXP(-Parameters!B$60*A16) -> 0.36162512 | R16: =(1-Parameters!B$61)*P16^-Parameters!B$63 -> 0.4163184 | S16: =Parameters!B$61*EXP(-Parameters!B$60*A16)+(1-Parameters!B$61)*P16^-Parameters!B$63 -> 0.77794352 | T16: =1-S16/Parameters!$B$12 -> 0.61102824 | U16: =1/(1-T16) -> 2.5708807 | V16: =(Parameters!$B$19*(F16+Parameters!$B$20)^T16+Parameters!$B$18*G16^T16)^(1/T16) -> 0.40396479 | W16: =(Parameters!$B$10*H16^Parameters!$B$9+Parameters!$B$11*V16^Parameters!$B$9)^(Parameters!$B$7/Parameters!$B$9)*O16 -> 1.4188369 | X16: =W16 - D16 - E16 - LN(1+EXP(Parameters!$B$21*C16))/Parameters!$B$21 - IF(C16>0, 0,Parameters!$B$6*C16^2/F16) -> 1.1281235 | Y16: =EXP(-Parameters!$B$55*A16) -> 0.83426849 | Z16: =IF(X16>0,X16^(1-Parameters!$B$52)/(1-Parameters!$B$52)*Y16*Parameters!$B$65,-10+X16*1000) -> -2.2851408 | AC16: =C16*$J16*$K16 -> 0.95320689 | AD16: =D16*$J16*$K16 -> 5.8677977 | AE16: =I16*J16*K16 -> 3.2539411 | AF16: =F16*J16*K16 -> 36.700589 | AG16: =G16*J16*K16 -> 42.735797 | AH16: =V16*J16*K16 -> 39.183214 | AI16: =AH16/AH$4*100 -> 96.432872 | AJ16: =W16*J16*K16 -> 137.62236 | AK16: =X16*J16*K16 -> 109.42416 | AL16: =LN(AJ16)-LN(AJ15) -> 0.019558273 | AM16: =LN(AK16)-LN(AK15) -> 0.018795658 | AN16: =AVERAGE(AL14:AL18) -> 0.019522811 | AO16: =AVERAGE(AM14:AM18) -> 0.017748082 | AQ16: =W16*K16*J16 -> 137.62236 | AR16: =Parameters!$B$7*W16*(W16/O16)^(-Parameters!$B$9/Parameters!$B$7)*Parameters!$B$11*(V16)^(Parameters!$B$9-T16)*((1-2*Parameters!$B$5*C16/F16)*Parameters!$B$19*(F16+Parameters!$B$20)^(T16-1)-(1-2*Parameters!$B$5*D16/G16)*(Parameters!$B$18)*(G16)^(T16-1)) -> 0.15191895 | AS16: =((C17-C15)/2-(F17-F15)/F16/2*C16)/(F16/2/Parameters!$B$5-C16)-((D17-D15)/D16-(G17-G15)/G16)/(G16/2/Parameters!$B$5/D16-1) -> 0.033316003 | AT16: =+Parameters!$B$5*C16^2/F16^2-Parameters!$B$5*D16^2/G16^2 -> -0.018177829 | AU16: =EXP(-Parameters!$B$42*'6states'!A16)*(Parameters!$B$37*EXP(-Parameters!$B$38*Parameters!$E$25*'6states'!I16/('6states'!F16+'6states'!I16))*(1/Parameters!$B$38/Parameters!$E$25+'6states'!I16/('6states'!F16+'6states'!I16))-Parameters!$B$37/Parameters!$B$38/Parameters!$E$25*EXP(-Parameters!$B$38*Parameters!$E$25)+Parameters!$B$39) -> 0.69800106 | AV16: =J16*K16*EXP(-Parameters!$B$42*'6states'!A16)*(Parameters!$B$37*EXP(-Parameters!$B$38*Parameters!$E$25*'6states'!I16/('6states'!F16+'6states'!I16))*(1/Parameters!$B$38/Parameters!$E$25+'6states'!I16/('6states'!F16+'6states'!I16))-Parameters!$B$37/Parameters!$B$38/Parameters!$E$25*EXP(-Parameters!$B$38*Parameters!$E$25)+Parameters!$B$39) -> 67.703734 | AW16: =1000*(AR16+AS16+AT16)/(EXP(-Parameters!$B$42*A16)*((C16<0)*Parameters!$B$37*EXP(-Parameters!$B$38*AF16)+(C16>=0)*Parameters!$B$41)) -> 206.83189 | AX16: =1-W16/'6states,ExoDamages'!T16 -> 0.050089966 | AY16: =-Y16*W16*X16^(-Parameters!B$52)*Parameters!B$46*Parameters!B$45*N16 -> -1.9479425e-05 | AZ16: =1000*EXP(-(Parameters!$B$54)*'6states'!A16)*AQ16*Parameters!B$46*Parameters!B$45*N16 -> 1.7489746 | BA16: =SUM(AZ16:AZ$204)*EXP(Parameters!$B$54*A16) -> 243.12801 | BB16: =(C16+D16+E16)/W16 -> 0.20477545 | BF16: =SUM(AY16:AY214)/Y16 -> -0.0019557547 | BG16: =BF16/Parameters!$B$45 -> -3.2595912 | BH16: =1-BG15/BG16 -> 0.0031851251 | BK16: =-EXP(-Parameters!B$42*'6states'!A16)*(-Parameters!B$37/Parameters!B$38/Parameters!E$25*(EXP(-Parameters!B$38*Parameters!E$25*'6states'!AE16/('6states'!F16+'6states'!AE16))-EXP(-Parameters!B$38*Parameters!E$25))+Parameters!B$37*'6states'!F16/('6states'!F16+'6states'!AE16)*EXP(-Parameters!B$38*Parameters!E$25*'6states'!I16/('6states'!F16+'6states'!AE16))) -> -0.38151483 | BL16: =-J16*K16*EXP(-Parameters!B$42*'6states'!A16)*(-Parameters!B$37/Parameters!B$38/Parameters!E$25*(EXP(-Parameters!B$38*Parameters!E$25*'6states'!I16/('6states'!F16+'6states'!I16))-EXP(-Parameters!B$38*Parameters!E$25)) + Parameters!B$37*'6states'!F16/('6states'!F16+'6states'!I16)*EXP(-Parameters!B$38*Parameters!E$25*'6states'!I16/('6states'!F16+'6states'!I16))) -> -14.68713 | BM16: =I16/(F16+I16) -> 0.081441106 | BN16: =BK16-AU16 -> -1.0795159 | BS16: =EXP(-Parameters!$B$56*A16)*BF16*BL16 -> 0.011265531 | BT16: =-EXP((Parameters!$B$56)*F16)*SUM(BS16:BS24) -> -0.11509393 | BU16: =X16^-Parameters!B$52/(1-2*Parameters!B$5*'6states'!D16/'6states'!G16) -> 1.1715094 | BV16: =BU16/BU15 -> 0.99111468 | BW16: =$X16^-Parameters!$B$52/(1-2*Parameters!$B$5*'6states'!$E16/'6states'!$H16) -> 0.95968546 | BX16: =BW16/BW15 -> 1.005684 | BY16: =($X16^-Parameters!$B$52*(1/(1+EXP(-C16)) + IF(C16<0,2*Parameters!$B$6*C16/F16,0)) + BQ16*(1/(1+EXP((C16-Parameters!$B$22)*Parameters!$B$21))))/(1-IF(C16>0,2*Parameters!$B$5*C16/F16,0)) -> 0.45038478 | BZ16: =BY16/BY15 -> 1.0075655 | CA16: =BY16-BY15 -> 0.0033817915 | CB16: =(1/$T16-1/Parameters!$B$13) * LN(Parameters!$B$18) / LN(P16) -> 0.2363689 | CC16: =(Parameters!$B$18*'6states'!T16^+Parameters!$B$19*Parameters!$B$25^'6states'!T16)^((1-'6states'!T16)/'6states'!T16)*Parameters!$B$18*Parameters!$B$26^('6states'!T16-1) -> 0.21700721 | CD16: =(LN(CC16)-LN(CC$4))/ LN(P16) -> 0.28087729 | CE16: =1-2^-CB16 -> 0.15112084 | CF16: =1-2^-CC16 -> 0.13965167
A17: =A16+Parameters!$B$65 -> 13 | B17: 2038 | C17: 0.0097505416 | D17: 0.060975851 | E17: 0.22115011 | F17: =MAX((1-Parameters!$B$4)^Parameters!B$65*F16 + C16*Parameters!B$65 - IF(C16>0,Parameters!$B$5,0)*C16^2/F16*Parameters!B$65, 0.0001) -> 0.36414234 | G17: =(1-Parameters!$B$4)^Parameters!B$65*G16+D16*Parameters!B$65-Parameters!$B$5*D16^2/G16*Parameters!B$65 -> 0.46506617 | H17: =(1-Parameters!$B$4)^Parameters!B$65*H16+E16*Parameters!B$65-Parameters!$B$5*E16^2/H16*Parameters!B$65 -> 3.8123773 | I17: =I16 *(1-Parameters!$B$4)-C16*(C16<0)*Parameters!B$65 -> 0.031436855 | J17: =J16*(1+Parameters!$B$51)^Parameters!B$65 -> 8.4730421 | K17: =K16*(1+Parameters!$B$53)^Parameters!B$65 -> 11.710488 | L17: =J17*K17*EXP(-Parameters!$B$42*'6states'!A17)*(Parameters!$B$37/Parameters!$B$38*('6states'!F17+'6states'!I17)/Parameters!$E$25*(EXP(-Parameters!$B$38*Parameters!$E$25*'6states'!I17/('6states'!F17+'6states'!I17))-EXP(-Parameters!$B$38*Parameters!$E$25)) + Parameters!$B$39*'6states'!F17) -> 24.501799 | M17: =M16+L17*Parameters!B$65 -> 2700.7154 | N17: =M17*Parameters!$B$45 -> 1.6204292 | O17: =EXP(-Parameters!$B$46/2*N17^2) -> 0.97395595 | P17: =MAX((Parameters!$B$62 + Parameters!$B$31*'6states'!A17 - '6states'!M17 + Parameters!$B$47/Parameters!$B$45)/Parameters!B$62,1) -> 6.8176921 | Q17: =Parameters!B$61*EXP(-Parameters!B$60*A17) -> 0.35199188 | R17: =(1-Parameters!B$61)*P17^-Parameters!B$63 -> 0.4126732 | S17: =Parameters!B$61*EXP(-Parameters!B$60*A17)+(1-Parameters!B$61)*P17^-Parameters!B$63 -> 0.76466508 | T17: =1-S17/Parameters!$B$12 -> 0.61766746 | U17: =1/(1-T17) -> 2.6155242 | V17: =(Parameters!$B$19*(F17+Parameters!$B$20)^T17+Parameters!$B$18*G17^T17)^(1/T17) -> 0.40096635 | W17: =(Parameters!$B$10*H17^Parameters!$B$9+Parameters!$B$11*V17^Parameters!$B$9)^(Parameters!$B$7/Parameters!$B$9)*O17 -> 1.414553 | X17: =W17 - D17 - E17 - LN(1+EXP(Parameters!$B$21*C17))/Parameters!$B$21 - IF(C17>0, 0,Parameters!$B$6*C17^2/F17) -> 1.1225023 | Y17: =EXP(-Parameters!$B$55*A17) -> 0.82176567 | Z17: =IF(X17>0,X17^(1-Parameters!$B$52)/(1-Parameters!$B$52)*Y17*Parameters!$B$65,-10+X17*1000) -> -2.2548332 | AC17: =C17*$J17*$K17 -> 0.96748243 | AD17: =D17*$J17*$K17 -> 6.0502346 | AE17: =I17*J17*K17 -> 3.1192734 | AF17: =F17*J17*K17 -> 36.131461 | AG17: =G17*J17*K17 -> 46.145472 | AH17: =V17*J17*K17 -> 39.785267 | AI17: =AH17/AH$4*100 -> 97.914571 | AJ17: =W17*J17*K17 -> 140.35684 | AK17: =X17*J17*K17 -> 111.37855 | AL17: =LN(AJ17)-LN(AJ16) -> 0.019674582 | AM17: =LN(AK17)-LN(AK16) -> 0.017703124 | AN17: =AVERAGE(AL15:AL19) -> 0.01968727 | AO17: =AVERAGE(AM15:AM19) -> 0.018014916 | AQ17: =W17*K17*J17 -> 140.35684 | AR17: =Parameters!$B$7*W17*(W17/O17)^(-Parameters!$B$9/Parameters!$B$7)*Parameters!$B$11*(V17)^(Parameters!$B$9-T17)*((1-2*Parameters!$B$5*C17/F17)*Parameters!$B$19*(F17+Parameters!$B$20)^(T17-1)-(1-2*Parameters!$B$5*D17/G17)*(Parameters!$B$18)*(G17)^(T17-1)) -> 0.15450191 | AS17: =((C18-C16)/2-(F18-F16)/F17/2*C17)/(F17/2/Parameters!$B$5-C17)-((D18-D16)/D17-(G18-G16)/G17)/(G17/2/Parameters!$B$5/D17-1) -> 0.032642178 | AT17: =+Parameters!$B$5*C17^2/F17^2-Parameters!$B$5*D17^2/G17^2 -> -0.016473417 | AU17: =EXP(-Parameters!$B$42*'6states'!A17)*(Parameters!$B$37*EXP(-Parameters!$B$38*Parameters!$E$25*'6states'!I17/('6states'!F17+'6states'!I17))*(1/Parameters!$B$38/Parameters!$E$25+'6states'!I17/('6states'!F17+'6states'!I17))-Parameters!$B$37/Parameters!$B$38/Parameters!$E$25*EXP(-Parameters!$B$38*Parameters!$E$25)+Parameters!$B$39) -> 0.69223533 | AV17: =J17*K17*EXP(-Parameters!$B$42*'6states'!A17)*(Parameters!$B$37*EXP(-Parameters!$B$38*Parameters!$E$25*'6states'!I17/('6states'!F17+'6states'!I17))*(1/Parameters!$B$38/Parameters!$E$25+'6states'!I17/('6states'!F17+'6states'!I17))-Parameters!$B$37/Parameters!$B$38/Parameters!$E$25*EXP(-Parameters!$B$38*Parameters!$E$25)+Parameters!$B$39) -> 68.685982 | AW17: =1000*(AR17+AS17+AT17)/(EXP(-Parameters!$B$42*A17)*((C17<0)*Parameters!$B$37*EXP(-Parameters!$B$38*AF17)+(C17>=0)*Parameters!$B$41)) -> 213.42944 | AX17: =1-W17/'6states,ExoDamages'!T17 -> 0.052502785 | AY17: =-Y17*W17*X17^(-Parameters!B$52)*Parameters!B$46*Parameters!B$45*N17 -> -1.9435326e-05 | AZ17: =1000*EXP(-(Parameters!$B$54)*'6states'!A17)*AQ17*Parameters!B$46*Parameters!B$45*N17 -> 1.7379704 | BA17: =SUM(AZ17:AZ$204)*EXP(Parameters!$B$54*A17) -> 249.05307 | BB17: =(C17+D17+E17)/W17 -> 0.20633833 | BF17: =SUM(AY17:AY215)/Y17 -> -0.0019618063 | BG17: =BF17/Parameters!$B$45 -> -3.2696772 | BH17: =1-BG16/BG17 -> 0.0030847251 | BK17: =-EXP(-Parameters!B$42*'6states'!A17)*(-Parameters!B$37/Parameters!B$38/Parameters!E$25*(EXP(-Parameters!B$38*Parameters!E$25*'6states'!AE17/('6states'!F17+'6states'!AE17))-EXP(-Parameters!B$38*Parameters!E$25))+Parameters!B$37*'6states'!F17/('6states'!F17+'6states'!AE17)*EXP(-Parameters!B$38*Parameters!E$25*'6states'!I17/('6states'!F17+'6states'!AE17))) -> -0.38247506 | BL17: =-J17*K17*EXP(-Parameters!B$42*'6states'!A17)*(-Parameters!B$37/Parameters!B$38/Parameters!E$25*(EXP(-Parameters!B$38*Parameters!E$25*'6states'!I17/('6states'!F17+'6states'!I17))-EXP(-Parameters!B$38*Parameters!E$25)) + Parameters!B$37*'6states'!F17/('6states'!F17+'6states'!I17)*EXP(-Parameters!B$38*Parameters!E$25*'6states'!I17/('6states'!F17+'6states'!I17))) -> -16.21268 | BM17: =I17/(F17+I17) -> 0.079470445 | BN17: =BK17-AU17 -> -1.0747104 | BS17: =EXP(-Parameters!$B$56*A17)*BF17*BL17 -> 0.011538155 | BT17: =-EXP((Parameters!$B$56)*F17)*SUM(BS17:BS25) -> -0.11762111 | BU17: =X17^-Parameters!B$52/(1-2*Parameters!B$5*'6states'!D17/'6states'!G17) -> 1.1596394 | BV17: =BU17/BU16 -> 0.98986772 | BW17: =$X17^-Parameters!$B$52/(1-2*Parameters!$B$5*'6states'!$E17/'6states'!$H17) -> 0.96783936 | BX17: =BW17/BW16 -> 1.0084964 | BY17: =($X17^-Parameters!$B$52*(1/(1+EXP(-C17)) + IF(C17<0,2*Parameters!$B$6*C17/F17,0)) + BQ17*(1/(1+EXP((C17-Parameters!$B$22)*Parameters!$B$21))))/(1-IF(C17>0,2*Parameters!$B$5*C17/F17,0)) -> 0.45418554 | BZ17: =BY17/BY16 -> 1.0084389 | CA17: =BY17-BY16 -> 0.0038007545 | CB17: =(1/$T17-1/Parameters!$B$13) * LN(Parameters!$B$18) / LN(P17) -> 0.23645704 | CC17: =(Parameters!$B$18*'6states'!T17^+Parameters!$B$19*Parameters!$B$25^'6states'!T17)^((1-'6states'!T17)/'6states'!T17)*Parameters!$B$18*Parameters!$B$26^('6states'!T17-1) -> 0.22155055 | CD17: =(LN(CC17)-LN(CC$4))/ LN(P17) -> 0.27880326 | CE17: =1-2^-CB17 -> 0.1511727 | CF17: =1-2^-CC17 -> 0.14235682
A18: =A17+Parameters!$B$65 -> 14 | B18: 2039 | C18: 0.0096183938 | D18: 0.061479512 | E18: 0.22234189 | F18: =MAX((1-Parameters!$B$4)^Parameters!B$65*F17 + C17*Parameters!B$65 - IF(C17>0,Parameters!$B$5,0)*C17^2/F17*Parameters!B$65, 0.0001) -> 0.35072724 | G18: =(1-Parameters!$B$4)^Parameters!B$65*G17+D17*Parameters!B$65-Parameters!$B$5*D17^2/G17*Parameters!B$65 -> 0.48879468 | H18: =(1-Parameters!$B$4)^Parameters!B$65*H17+E17*Parameters!B$65-Parameters!$B$5*E17^2/H17*Parameters!B$65 -> 3.7809003 | I18: =I17 *(1-Parameters!$B$4)-C17*(C17<0)*Parameters!B$65 -> 0.029459477 | J18: =J17*(1+Parameters!$B$51)^Parameters!B$65 -> 8.497614 | K18: =K17*(1+Parameters!$B$53)^Parameters!B$65 -> 11.944697 | L18: =J18*K18*EXP(-Parameters!$B$42*'6states'!A18)*(Parameters!$B$37/Parameters!$B$38*('6states'!F18+'6states'!I18)/Parameters!$E$25*(EXP(-Parameters!$B$38*Parameters!$E$25*'6states'!I18/('6states'!F18+'6states'!I18))-EXP(-Parameters!$B$38*Parameters!$E$25)) + Parameters!$B$39*'6states'!F18) -> 23.91478 | M18: =M17+L18*Parameters!B$65 -> 2724.6302 | N18: =M18*Parameters!$B$45 -> 1.6347781 | O18: =EXP(-Parameters!$B$46/2*N18^2) -> 0.97349887 | P18: =MAX((Parameters!$B$62 + Parameters!$B$31*'6states'!A18 - '6states'!M18 + Parameters!$B$47/Parameters!$B$45)/Parameters!B$62,1) -> 7.4033965 | Q18: =Parameters!B$61*EXP(-Parameters!B$60*A18) -> 0.34261525 | R18: =(1-Parameters!B$61)*P18^-Parameters!B$63 -> 0.40928601 | S18: =Parameters!B$61*EXP(-Parameters!B$60*A18)+(1-Parameters!B$61)*P18^-Parameters!B$63 -> 0.75190126 | T18: =1-S18/Parameters!$B$12 -> 0.62404937 | U18: =1/(1-T18) -> 2.6599237 | V18: =(Parameters!$B$19*(F18+Parameters!$B$20)^T18+Parameters!$B$18*G18^T18)^(1/T18) -> 0.39808697 | W18: =(Parameters!$B$10*H18^Parameters!$B$9+Parameters!$B$11*V18^Parameters!$B$9)^(Parameters!$B$7/Parameters!$B$9)*O18 -> 1.4105206 | X18: =W18 - D18 - E18 - LN(1+EXP(Parameters!$B$21*C18))/Parameters!$B$21 - IF(C18>0, 0,Parameters!$B$6*C18^2/F18) -> 1.1168998 | Y18: =EXP(-Parameters!$B$55*A18) -> 0.80945022 | Z18: =IF(X18>0,X18^(1-Parameters!$B$52)/(1-Parameters!$B$52)*Y18*Parameters!$B$65,-10+X18*1000) -> -2.224934 | AC18: =C18*$J18*$K18 -> 0.9762807 | AD18: =D18*$J18*$K18 -> 6.2402582 | AE18: =I18*J18*K18 -> 2.9901789 | AF18: =F18*J18*K18 -> 35.599316 | AG18: =G18*J18*K18 -> 49.613357 | AH18: =V18*J18*K18 -> 40.406395 | AI18: =AH18/AH$4*100 -> 99.443215 | AJ18: =W18*J18*K18 -> 143.16986 | AK18: =X18*J18*K18 -> 113.36692 | AL18: =LN(AJ18)-LN(AJ17) -> 0.019843743 | AM18: =LN(AK18)-LN(AK17) -> 0.017694855 | AN18: =AVERAGE(AL16:AL20) -> 0.019841614 | AO18: =AVERAGE(AM16:AM20) -> 0.018081263 | AQ18: =W18*K18*J18 -> 143.16986 | AR18: =Parameters!$B$7*W18*(W18/O18)^(-Parameters!$B$9/Parameters!$B$7)*Parameters!$B$11*(V18)^(Parameters!$B$9-T18)*((1-2*Parameters!$B$5*C18/F18)*Parameters!$B$19*(F18+Parameters!$B$20)^(T18-1)-(1-2*Parameters!$B$5*D18/G18)*(Parameters!$B$18)*(G18)^(T18-1)) -> 0.1572278 | AS18: =((C19-C17)/2-(F19-F17)/F18/2*C18)/(F18/2/Parameters!$B$5-C18)-((D19-D17)/D18-(G19-G17)/G18)/(G18/2/Parameters!$B$5/D18-1) -> 0.0279518 | AT18: =+Parameters!$B$5*C18^2/F18^2-Parameters!$B$5*D18^2/G18^2 -> -0.015067968 | AU18: =EXP(-Parameters!$B$42*'6states'!A18)*(Parameters!$B$37*EXP(-Parameters!$B$38*Parameters!$E$25*'6states'!I18/('6states'!F18+'6states'!I18))*(1/Parameters!$B$38/Parameters!$E$25+'6states'!I18/('6states'!F18+'6states'!I18))-Parameters!$B$37/Parameters!$B$38/Parameters!$E$25*EXP(-Parameters!$B$38*Parameters!$E$25)+Parameters!$B$39) -> 0.68659473 | AV18: =J18*K18*EXP(-Parameters!$B$42*'6states'!A18)*(Parameters!$B$37*EXP(-Parameters!$B$38*Parameters!$E$25*'6states'!I18/('6states'!F18+'6states'!I18))*(1/Parameters!$B$38/Parameters!$E$25+'6states'!I18/('6states'!F18+'6states'!I18))-Parameters!$B$37/Parameters!$B$38/Parameters!$E$25*EXP(-Parameters!$B$38*Parameters!$E$25)+Parameters!$B$39) -> 69.690345 | AW18: =1000*(AR18+AS18+AT18)/(EXP(-Parameters!$B$42*A18)*((C18<0)*Parameters!$B$37*EXP(-Parameters!$B$38*AF18)+(C18>=0)*Parameters!$B$41)) -> 214.86832 | AX18: =1-W18/'6states,ExoDamages'!T18 -> 0.054747333 | AY18: =-Y18*W18*X18^(-Parameters!B$52)*Parameters!B$46*Parameters!B$45*N18 -> -1.938905e-05 | AZ18: =1000*EXP(-(Parameters!$B$54)*'6states'!A18)*AQ18*Parameters!B$46*Parameters!B$45*N18 -> 1.7268134 | BA18: =SUM(AZ18:AZ$204)*EXP(Parameters!$B$54*A18) -> 255.10917 | BB18: =(C18+D18+E18)/W18 -> 0.20803651 | BF18: =SUM(AY18:AY216)/Y18 -> -0.0019676439 | BG18: =BF18/Parameters!$B$45 -> -3.2794065 | BH18: =1-BG17/BG18 -> 0.0029667638 | BK18: =-EXP(-Parameters!B$42*'6states'!A18)*(-Parameters!B$37/Parameters!B$38/Parameters!E$25*(EXP(-Parameters!B$38*Parameters!E$25*'6states'!I18/('6states'!F18+'6states'!I18))-EXP(-Parameters!B$38*Parameters!E$25))+Parameters!B$37*'6states'!F18/('6states'!F18+'6states'!I18)*EXP(-Parameters!B$38*Parameters!E$25*'6states'!I18/('6states'!F18+'6states'!I18))) -> -0.17641831 | BL18: =-J18*K18*EXP(-Parameters!B$42*'6states'!A18)*(-Parameters!B$37/Parameters!B$38/Parameters!E$25*(EXP(-Parameters!B$38*Parameters!E$25*'6states'!I18/('6states'!F18+'6states'!I18))-EXP(-Parameters!B$38*Parameters!E$25)) + Parameters!B$37*'6states'!F18/('6states'!F18+'6states'!I18)*EXP(-Parameters!B$38*Parameters!E$25*'6states'!I18/('6states'!F18+'6states'!I18))) -> -17.90671 | BM18: =I18/(F18+I18) -> 0.077486864 | BN18: =BK18-AU18 -> -0.86301304 | BS18: =EXP(-Parameters!$B$56*A18)*BF18*BL18 -> 0.011822593 | BT18: =-EXP((Parameters!$B$56)*F18)*SUM(BS18:BS26) -> -0.1201357 | BU18: =X18^-Parameters!B$52/(1-2*Parameters!B$5*'6states'!D18/'6states'!G18) -> 1.1508567 | BV18: =BU18/BU17 -> 0.99242639 | BW18: =$X18^-Parameters!$B$52/(1-2*Parameters!$B$5*'6states'!$E18/'6states'!$H18) -> 0.97616183 | BX18: =BW18/BW17 -> 1.008599 | BY18: =($X18^-Parameters!$B$52*(1/(1+EXP(-C18)) + IF(C18<0,2*Parameters!$B$6*C18/F18,0)) + BQ18*(1/(1+EXP((C18-Parameters!$B$22)*Parameters!$B$21))))/(1-IF(C18>0,2*Parameters!$B$5*C18/F18,0)) -> 0.45786019 | BZ18: =BY18/BY17 -> 1.0080907 | CA18: =BY18-BY17 -> 0.0036746569 | CB18: =(1/$T18-1/Parameters!$B$13) * LN(Parameters!$B$18) / LN(P18) -> 0.23657467 | CC18: =(Parameters!$B$18*'6states'!T18^+Parameters!$B$19*Parameters!$B$25^'6states'!T18)^((1-'6states'!T18)/'6states'!T18)*Parameters!$B$18*Parameters!$B$26^('6states'!T18-1) -> 0.22581965 | CD18: =(LN(CC18)-LN(CC$4))/ LN(P18) -> 0.27685889 | CE18: =1-2^-CB18 -> 0.15124191 | CF18: =1-2^-CC18 -> 0.14489093
A19: =A18+Parameters!$B$65 -> 15 | B19: 2040 | C19: 0.0095610947 | D19: 0.062031323 | E19: 0.22189868 | F19: =MAX((1-Parameters!$B$4)^Parameters!B$65*F18 + C18*Parameters!B$65 - IF(C18>0,Parameters!$B$5,0)*C18^2/F18*Parameters!B$65, 0.0001) -> 0.33802112 | G19: =(1-Parameters!$B$4)^Parameters!B$65*G18+D18*Parameters!B$65-Parameters!$B$5*D18^2/G18*Parameters!B$65 -> 0.51179625 | H19: =(1-Parameters!$B$4)^Parameters!B$65*H18+E18*Parameters!B$65-Parameters!$B$5*E18^2/H18*Parameters!B$65 -> 3.7523484 | I19: =I18 *(1-Parameters!$B$4)-C18*(C18<0)*Parameters!B$65 -> 0.027606475 | J19: =J18*(1+Parameters!$B$51)^Parameters!B$65 -> 8.522257 | K19: =K18*(1+Parameters!$B$53)^Parameters!B$65 -> 12.183591 | L19: =J19*K19*EXP(-Parameters!$B$42*'6states'!A19)*(Parameters!$B$37/Parameters!$B$38*('6states'!F19+'6states'!I19)/Parameters!$E$25*(EXP(-Parameters!$B$38*Parameters!$E$25*'6states'!I19/('6states'!F19+'6states'!I19))-EXP(-Parameters!$B$38*Parameters!$E$25)) + Parameters!$B$39*'6states'!F19) -> 23.357827 | M19: =M18+L19*Parameters!B$65 -> 2747.988 | N19: =M19*Parameters!$B$45 -> 1.6487928 | O19: =EXP(-Parameters!$B$46/2*N19^2) -> 0.97304874 | P19: =MAX((Parameters!$B$62 + Parameters!$B$31*'6states'!A19 - '6states'!M19 + Parameters!$B$47/Parameters!$B$45)/Parameters!B$62,1) -> 8.00024 | Q19: =Parameters!B$61*EXP(-Parameters!B$60*A19) -> 0.33348841 | R19: =(1-Parameters!B$61)*P19^-Parameters!B$63 -> 0.40612498 | S19: =Parameters!B$61*EXP(-Parameters!B$60*A19)+(1-Parameters!B$61)*P19^-Parameters!B$63 -> 0.73961339 | T19: =1-S19/Parameters!$B$12 -> 0.63019331 | U19: =1/(1-T19) -> 2.7041155 | V19: =(Parameters!$B$19*(F19+Parameters!$B$20)^T19+Parameters!$B$18*G19^T19)^(1/T19) -> 0.3953035 | W19: =(Parameters!$B$10*H19^Parameters!$B$9+Parameters!$B$11*V19^Parameters!$B$9)^(Parameters!$B$7/Parameters!$B$9)*O19 -> 1.4067404 | X19: =W19 - D19 - E19 - LN(1+EXP(Parameters!$B$21*C19))/Parameters!$B$21 - IF(C19>0, 0,Parameters!$B$6*C19^2/F19) -> 1.1130651 | Y19: =EXP(-Parameters!$B$55*A19) -> 0.79731934 | Z19: =IF(X19>0,X19^(1-Parameters!$B$52)/(1-Parameters!$B$52)*Y19*Parameters!$B$65,-10+X19*1000) -> -2.1942295 | AC19: =C19*$J19*$K19 -> 0.99274469 | AD19: =D19*$J19*$K19 -> 6.4408175 | AE19: =I19*J19*K19 -> 2.8664272 | AF19: =F19*J19*K19 -> 35.097306 | AG19: =G19*J19*K19 -> 53.140673 | AH19: =V19*J19*K19 -> 41.045033 | AI19: =AH19/AH$4*100 -> 101.01495 | AJ19: =W19*J19*K19 -> 146.06424 | AK19: =X19*J19*K19 -> 115.57144 | AL19: =LN(AJ19)-LN(AJ18) -> 0.020014776 | AM19: =LN(AK19)-LN(AK18) -> 0.019259238 | AN19: =AVERAGE(AL17:AL21) -> 0.019994628 | AO19: =AVERAGE(AM17:AM21) -> 0.018656287 | AQ19: =W19*K19*J19 -> 146.06424 | AR19: =Parameters!$B$7*W19*(W19/O19)^(-Parameters!$B$9/Parameters!$B$7)*Parameters!$B$11*(V19)^(Parameters!$B$9-T19)*((1-2*Parameters!$B$5*C19/F19)*Parameters!$B$19*(F19+Parameters!$B$20)^(T19-1)-(1-2*Parameters!$B$5*D19/G19)*(Parameters!$B$18)*(G19)^(T19-1)) -> 0.15998481 | AS19: =((C20-C18)/2-(F20-F18)/F19/2*C19)/(F19/2/Parameters!$B$5-C19)-((D20-D18)/D19-(G20-G18)/G19)/(G19/2/Parameters!$B$5/D19-1) -> 0.026528621 | AT19: =+Parameters!$B$5*C19^2/F19^2-Parameters!$B$5*D19^2/G19^2 -> -0.013890137 | AU19: =EXP(-Parameters!$B$42*'6states'!A19)*(Parameters!$B$37*EXP(-Parameters!$B$38*Parameters!$E$25*'6states'!I19/('6states'!F19+'6states'!I19))*(1/Parameters!$B$38/Parameters!$E$25+'6states'!I19/('6states'!F19+'6states'!I19))-Parameters!$B$37/Parameters!$B$38/Parameters!$E$25*EXP(-Parameters!$B$38*Parameters!$E$25)+Parameters!$B$39) -> 0.68107199 | AV19: =J19*K19*EXP(-Parameters!$B$42*'6states'!A19)*(Parameters!$B$37*EXP(-Parameters!$B$38*Parameters!$E$25*'6states'!I19/('6states'!F19+'6states'!I19))*(1/Parameters!$B$38/Parameters!$E$25+'6states'!I19/('6states'!F19+'6states'!I19))-Parameters!$B$37/Parameters!$B$38/Parameters!$E$25*EXP(-Parameters!$B$38*Parameters!$E$25)+Parameters!$B$39) -> 70.716861 | AW19: =1000*(AR19+AS19+AT19)/(EXP(-Parameters!$B$42*A19)*((C19<0)*Parameters!$B$37*EXP(-Parameters!$B$38*AF19)+(C19>=0)*Parameters!$B$41)) -> 220.23216 | AX19: =1-W19/'6states,ExoDamages'!T19 -> 0.056816651 | AY19: =-Y19*W19*X19^(-Parameters!B$52)*Parameters!B$46*Parameters!B$45*N19 -> -1.929998e-05 | AZ19: =1000*EXP(-(Parameters!$B$54)*'6states'!A19)*AQ19*Parameters!B$46*Parameters!B$45*N19 -> 1.7155416 | BA19: =SUM(AZ19:AZ$204)*EXP(Parameters!$B$54*A19) -> 261.29902 | BB19: =(C19+D19+E19)/W19 -> 0.20863203 | BF19: =SUM(AY19:AY217)/Y19 -> -0.001973263 | BG19: =BF19/Parameters!$B$45 -> -3.2887716 | BH19: =1-BG18/BG19 -> 0.0028476081 | BK19: =-EXP(-Parameters!B$42*'6states'!A19)*(-Parameters!B$37/Parameters!B$38/Parameters!E$25*(EXP(-Parameters!B$38*Parameters!E$25*'6states'!I19/('6states'!F19+'6states'!I19))-EXP(-Parameters!B$38*Parameters!E$25))+Parameters!B$37*'6states'!F19/('6states'!F19+'6states'!I19)*EXP(-Parameters!B$38*Parameters!E$25*'6states'!I19/('6states'!F19+'6states'!I19))) -> -0.19046903 | BL19: =-J19*K19*EXP(-Parameters!B$42*'6states'!A19)*(-Parameters!B$37/Parameters!B$38/Parameters!E$25*(EXP(-Parameters!B$38*Parameters!E$25*'6states'!I19/('6states'!F19+'6states'!I19))-EXP(-Parameters!B$38*Parameters!E$25)) + Parameters!B$37*'6states'!F19/('6states'!F19+'6states'!I19)*EXP(-Parameters!B$38*Parameters!E$25*'6states'!I19/('6states'!F19+'6states'!I19))) -> -19.776723 | BM19: =I19/(F19+I19) -> 0.075504355 | BN19: =BK19-AU19 -> -0.87154103 | BS19: =EXP(-Parameters!$B$56*A19)*BF19*BL19 -> 0.012111969 | BT19: =-EXP((Parameters!$B$56)*F19)*SUM(BS19:BS27) -> -0.12260897 | BU19: =X19^-Parameters!B$52/(1-2*Parameters!B$5*'6states'!D19/'6states'!G19) -> 1.1422492 | BV19: =BU19/BU18 -> 0.99252078 | BW19: =$X19^-Parameters!$B$52/(1-2*Parameters!$B$5*'6states'!$E19/'6states'!$H19) -> 0.98143724 | BX19: =BW19/BW18 -> 1.0054042 | BY19: =($X19^-Parameters!$B$52*(1/(1+EXP(-C19)) + IF(C19<0,2*Parameters!$B$6*C19/F19,0)) + BQ19*(1/(1+EXP((C19-Parameters!$B$22)*Parameters!$B$21))))/(1-IF(C19>0,2*Parameters!$B$5*C19/F19,0)) -> 0.46081775 | BZ19: =BY19/BY18 -> 1.0064595 | CA19: =BY19-BY18 -> 0.0029575529 | CB19: =(1/$T19-1/Parameters!$B$13) * LN(Parameters!$B$18) / LN(P19) -> 0.23670387 | CC19: =(Parameters!$B$18*'6states'!T19^+Parameters!$B$19*Parameters!$B$25^'6states'!T19)^((1-'6states'!T19)/'6states'!T19)*Parameters!$B$18*Parameters!$B$26^('6states'!T19-1) -> 0.22983631 | CD19: =(LN(CC19)-LN(CC$4))/ LN(P19) -> 0.27501471 | CE19: =1-2^-CB19 -> 0.15131791 | CF19: =1-2^-CC19 -> 0.14726836
A20: =A19+Parameters!$B$65 -> 16 | B20: 2041 | C20: 0.0092911972 | D20: 0.062055147 | E20: 0.22487875 | F20: =MAX((1-Parameters!$B$4)^Parameters!B$65*F19 + C19*Parameters!B$65 - IF(C19>0,Parameters!$B$5,0)*C19^2/F19*Parameters!B$65, 0.0001) -> 0.32605024 | G20: =(1-Parameters!$B$4)^Parameters!B$65*G19+D19*Parameters!B$65-Parameters!$B$5*D19^2/G19*Parameters!B$65 -> 0.53411719 | H20: =(1-Parameters!$B$4)^Parameters!B$65*H19+E19*Parameters!B$65-Parameters!$B$5*E19^2/H19*Parameters!B$65 -> 3.7251022 | I20: =I19 *(1-Parameters!$B$4)-C19*(C19<0)*Parameters!B$65 -> 0.025870028 | J20: =J19*(1+Parameters!$B$51)^Parameters!B$65 -> 8.5469716 | K20: =K19*(1+Parameters!$B$53)^Parameters!B$65 -> 12.427263 | L20: =J20*K20*EXP(-Parameters!$B$42*'6states'!A20)*(Parameters!$B$37/Parameters!$B$38*('6states'!F20+'6states'!I20)/Parameters!$E$25*(EXP(-Parameters!$B$38*Parameters!$E$25*'6states'!I20/('6states'!F20+'6states'!I20))-EXP(-Parameters!$B$38*Parameters!$E$25)) + Parameters!$B$39*'6states'!F20) -> 22.834426 | M20: =M19+L20*Parameters!B$65 -> 2770.8224 | N20: =M20*Parameters!$B$45 -> 1.6624935 | O20: =EXP(-Parameters!$B$46/2*N20^2) -> 0.9726052 | P20: =MAX((Parameters!$B$62 + Parameters!$B$31*'6states'!A20 - '6states'!M20 + Parameters!$B$47/Parameters!$B$45)/Parameters!B$62,1) -> 8.6075514 | Q20: =Parameters!B$61*EXP(-Parameters!B$60*A20) -> 0.32460469 | R20: =(1-Parameters!B$61)*P20^-Parameters!B$63 -> 0.40316428 | S20: =Parameters!B$61*EXP(-Parameters!B$60*A20)+(1-Parameters!B$61)*P20^-Parameters!B$63 -> 0.72776896 | T20: =1-S20/Parameters!$B$12 -> 0.63611552 | U20: =1/(1-T20) -> 2.7481249 | V20: =(Parameters!$B$19*(F20+Parameters!$B$20)^T20+Parameters!$B$18*G20^T20)^(1/T20) -> 0.39268648 | W20: =(Parameters!$B$10*H20^Parameters!$B$9+Parameters!$B$11*V20^Parameters!$B$9)^(Parameters!$B$7/Parameters!$B$9)*O20 -> 1.4031132 | X20: =W20 - D20 - E20 - LN(1+EXP(Parameters!$B$21*C20))/Parameters!$B$21 - IF(C20>0, 0,Parameters!$B$6*C20^2/F20) -> 1.1066889 | Y20: =EXP(-Parameters!$B$55*A20) -> 0.78537026 | Z20: =IF(X20>0,X20^(1-Parameters!$B$52)/(1-Parameters!$B$52)*Y20*Parameters!$B$65,-10+X20*1000) -> -2.1656958 | AC20: =C20*$J20*$K20 -> 0.98686883 | AD20: =D20*$J20*$K20 -> 6.5912163 | AE20: =I20*J20*K20 -> 2.7477971 | AF20: =F20*J20*K20 -> 34.631578 | AG20: =G20*J20*K20 -> 56.731506 | AH20: =V20*J20*K20 -> 41.709378 | AI20: =AH20/AH$4*100 -> 102.64995 | AJ20: =W20*J20*K20 -> 149.03232 | AK20: =X20*J20*K20 -> 117.54748 | AL20: =LN(AJ20)-LN(AJ19) -> 0.020116695 | AM20: =LN(AK20)-LN(AK19) -> 0.01695344 | AN20: =AVERAGE(AL18:AL22) -> 0.020121843 | AO20: =AVERAGE(AM18:AM22) -> 0.01923445 | AQ20: =W20*K20*J20 -> 149.03232 | AR20: =Parameters!$B$7*W20*(W20/O20)^(-Parameters!$B$9/Parameters!$B$7)*Parameters!$B$11*(V20)^(Parameters!$B$9-T20)*((1-2*Parameters!$B$5*C20/F20)*Parameters!$B$19*(F20+Parameters!$B$20)^(T20-1)-(1-2*Parameters!$B$5*D20/G20)*(Parameters!$B$18)*(G20)^(T20-1)) -> 0.16268843 | AS20: =((C21-C19)/2-(F21-F19)/F20/2*C20)/(F20/2/Parameters!$B$5-C20)-((D21-D19)/D20-(G21-G19)/G20)/(G20/2/Parameters!$B$5/D20-1) -> 0.018553575 | AT20: =+Parameters!$B$5*C20^2/F20^2-Parameters!$B$5*D20^2/G20^2 -> -0.012686372 | AU20: =EXP(-Parameters!$B$42*'6states'!A20)*(Parameters!$B$37*EXP(-Parameters!$B$38*Parameters!$E$25*'6states'!I20/('6states'!F20+'6states'!I20))*(1/Parameters!$B$38/Parameters!$E$25+'6states'!I20/('6states'!F20+'6states'!I20))-Parameters!$B$37/Parameters!$B$38/Parameters!$E$25*EXP(-Parameters!$B$38*Parameters!$E$25)+Parameters!$B$39) -> 0.6756765 | AV20: =J20*K20*EXP(-Parameters!$B$42*'6states'!A20)*(Parameters!$B$37*EXP(-Parameters!$B$38*Parameters!$E$25*'6states'!I20/('6states'!F20+'6states'!I20))*(1/Parameters!$B$38/Parameters!$E$25+'6states'!I20/('6states'!F20+'6states'!I20))-Parameters!$B$37/Parameters!$B$38/Parameters!$E$25*EXP(-Parameters!$B$38*Parameters!$E$25)+Parameters!$B$39) -> 71.767293 | AW20: =1000*(AR20+AS20+AT20)/(EXP(-Parameters!$B$42*A20)*((C20<0)*Parameters!$B$37*EXP(-Parameters!$B$38*AF20)+(C20>=0)*Parameters!$B$41)) -> 217.20386 | AX20: =1-W20/'6states,ExoDamages'!T20 -> 0.058796185 | AY20: =-Y20*W20*X20^(-Parameters!B$52)*Parameters!B$46*Parameters!B$45*N20 -> -1.9268145e-05 | AZ20: =1000*EXP(-(Parameters!$B$54)*'6states'!A20)*AQ20*Parameters!B$46*Parameters!B$45*N20 -> 1.704072 | BA20: =SUM(AZ20:AZ$204)*EXP(Parameters!$B$54*A20) -> 267.62531 | BB20: =(C20+D20+E20)/W20 -> 0.21111988 | BF20: =SUM(AY20:AY218)/Y20 -> -0.0019787109 | BG20: =BF20/Parameters!$B$45 -> -3.2978516 | BH20: =1-BG19/BG20 -> 0.0027533069 | BK20: =-EXP(-Parameters!B$42*'6states'!A20)*(-Parameters!B$37/Parameters!B$38/Parameters!E$25*(EXP(-Parameters!B$38*Parameters!E$25*'6states'!I20/('6states'!F20+'6states'!I20))-EXP(-Parameters!B$38*Parameters!E$25))+Parameters!B$37*'6states'!F20/('6states'!F20+'6states'!I20)*EXP(-Parameters!B$38*Parameters!E$25*'6states'!I20/('6states'!F20+'6states'!I20))) -> -0.20573486 | BL20: =-J20*K20*EXP(-Parameters!B$42*'6states'!A20)*(-Parameters!B$37/Parameters!B$38/Parameters!E$25*(EXP(-Parameters!B$38*Parameters!E$25*'6states'!I20/('6states'!F20+'6states'!I20))-EXP(-Parameters!B$38*Parameters!E$25)) + Parameters!B$37*'6states'!F20/('6states'!F20+'6states'!I20)*EXP(-Parameters!B$38*Parameters!E$25*'6states'!I20/('6states'!F20+'6states'!I20))) -> -21.852224 | BM20: =I20/(F20+I20) -> 0.073511049 | BN20: =BK20-AU20 -> -0.88141136 | BS20: =EXP(-Parameters!$B$56*A20)*BF20*BL20 -> 0.01241305 | BT20: =-EXP((Parameters!$B$56)*F20)*SUM(BS20:BS28) -> -0.12501181 | BU20: =X20^-Parameters!B$52/(1-2*Parameters!B$5*'6states'!D20/'6states'!G20) -> 1.1360851 | BV20: =BU20/BU19 -> 0.99460356 | BW20: =$X20^-Parameters!$B$52/(1-2*Parameters!$B$5*'6states'!$E20/'6states'!$H20) -> 0.99185153 | BX20: =BW20/BW19 -> 1.0106113 | BY20: =($X20^-Parameters!$B$52*(1/(1+EXP(-C20)) + IF(C20<0,2*Parameters!$B$6*C20/F20,0)) + BQ20*(1/(1+EXP((C20-Parameters!$B$22)*Parameters!$B$21))))/(1-IF(C20>0,2*Parameters!$B$5*C20/F20,0)) -> 0.46455077 | BZ20: =BY20/BY19 -> 1.0081009 | CA20: =BY20-BY19 -> 0.0037330227 | CB20: =(1/$T20-1/Parameters!$B$13) * LN(Parameters!$B$18) / LN(P20) -> 0.23683382 | CC20: =(Parameters!$B$18*'6states'!T20^+Parameters!$B$19*Parameters!$B$25^'6states'!T20)^((1-'6states'!T20)/'6states'!T20)*Parameters!$B$18*Parameters!$B$26^('6states'!T20-1) -> 0.23361957 | CD20: =(LN(CC20)-LN(CC$4))/ LN(P20) -> 0.27325143 | CE20: =1-2^-CB20 -> 0.15139436 | CF20: =1-2^-CC20 -> 0.1495016
A21: =A20+Parameters!$B$65 -> 17 | B21: 2042 | C21: 0.0092747922 | D21: 0.063544609 | E21: 0.22121289 | F21: =MAX((1-Parameters!$B$4)^Parameters!B$65*F20 + C20*Parameters!B$65 - IF(C20>0,Parameters!$B$5,0)*C20^2/F20*Parameters!B$65, 0.0001) -> 0.31456812 | G21: =(1-Parameters!$B$4)^Parameters!B$65*G20+D20*Parameters!B$65-Parameters!$B$5*D20^2/G20*Parameters!B$65 -> 0.55536664 | H21: =(1-Parameters!$B$4)^Parameters!B$65*H20+E20*Parameters!B$65-Parameters!$B$5*E20^2/H20*Parameters!B$65 -> 3.7020964 | I21: =I20 *(1-Parameters!$B$4)-C20*(C20<0)*Parameters!B$65 -> 0.024242803 | J21: =J20*(1+Parameters!$B$51)^Parameters!B$65 -> 8.5717578 | K21: =K20*(1+Parameters!$B$53)^Parameters!B$65 -> 12.675808 | L21: =J21*K21*EXP(-Parameters!$B$42*'6states'!A21)*(Parameters!$B$37/Parameters!$B$38*('6states'!F21+'6states'!I21)/Parameters!$E$25*(EXP(-Parameters!$B$38*Parameters!$E$25*'6states'!I21/('6states'!F21+'6states'!I21))-EXP(-Parameters!$B$38*Parameters!$E$25)) + Parameters!$B$39*'6states'!F21) -> 22.328374 | M21: =M20+L21*Parameters!B$65 -> 2793.1508 | N21: =M21*Parameters!$B$45 -> 1.6758905 | O21: =EXP(-Parameters!$B$46/2*N21^2) -> 0.97216813 | P21: =MAX((Parameters!$B$62 + Parameters!$B$31*'6states'!A21 - '6states'!M21 + Parameters!$B$47/Parameters!$B$45)/Parameters!B$62,1) -> 9.2249839 | Q21: =Parameters!B$61*EXP(-Parameters!B$60*A21) -> 0.31595762 | R21: =(1-Parameters!B$61)*P21^-Parameters!B$63 -> 0.40038098 | S21: =Parameters!B$61*EXP(-Parameters!B$60*A21)+(1-Parameters!B$61)*P21^-Parameters!B$63 -> 0.71633861 | T21: =1-S21/Parameters!$B$12 -> 0.6418307 | U21: =1/(1-T21) -> 2.7919757 | V21: =(Parameters!$B$19*(F21+Parameters!$B$20)^T21+Parameters!$B$18*G21^T21)^(1/T21) -> 0.38998204 | W21: =(Parameters!$B$10*H21^Parameters!$B$9+Parameters!$B$11*V21^Parameters!$B$9)^(Parameters!$B$7/Parameters!$B$9)*O21 -> 1.3997847 | X21: =W21 - D21 - E21 - LN(1+EXP(Parameters!$B$21*C21))/Parameters!$B$21 - IF(C21>0, 0,Parameters!$B$6*C21^2/F21) -> 1.1055522 | Y21: =EXP(-Parameters!$B$55*A21) -> 0.77360026 | Z21: =IF(X21>0,X21^(1-Parameters!$B$52)/(1-Parameters!$B$52)*Y21*Parameters!$B$65,-10+X21*1000) -> -2.1340069 | AC21: =C21*$J21*$K21 -> 1.0077429 | AD21: =D21*$J21*$K21 -> 6.9043734 | AE21: =I21*J21*K21 -> 2.6340766 | AF21: =F21*J21*K21 -> 34.179072 | AG21: =G21*J21*K21 -> 60.342784 | AH21: =V21*J21*K21 -> 42.373093 | AI21: =AH21/AH$4*100 -> 104.28341 | AJ21: =W21*J21*K21 -> 152.09215 | AK21: =X21*J21*K21 -> 120.12263 | AL21: =LN(AJ21)-LN(AJ20) -> 0.020323346 | AM21: =LN(AK21)-LN(AK20) -> 0.021670775 | AN21: =AVERAGE(AL19:AL23) -> 0.020223192 | AO21: =AVERAGE(AM19:AM23) -> 0.018840941 | AQ21: =W21*K21*J21 -> 152.09215 | AR21: =Parameters!$B$7*W21*(W21/O21)^(-Parameters!$B$9/Parameters!$B$7)*Parameters!$B$11*(V21)^(Parameters!$B$9-T21)*((1-2*Parameters!$B$5*C21/F21)*Parameters!$B$19*(F21+Parameters!$B$20)^(T21-1)-(1-2*Parameters!$B$5*D21/G21)*(Parameters!$B$18)*(G21)^(T21-1)) -> 0.16609724 | AS21: =((C22-C20)/2-(F22-F20)/F21/2*C21)/(F21/2/Parameters!$B$5-C21)-((D22-D20)/D21-(G22-G20)/G21)/(G21/2/Parameters!$B$5/D21-1) -> 0.012350606 | AT21: =+Parameters!$B$5*C21^2/F21^2-Parameters!$B$5*D21^2/G21^2 -> -0.012222436 | AU21: =EXP(-Parameters!$B$42*'6states'!A21)*(Parameters!$B$37*EXP(-Parameters!$B$38*Parameters!$E$25*'6states'!I21/('6states'!F21+'6states'!I21))*(1/Parameters!$B$38/Parameters!$E$25+'6states'!I21/('6states'!F21+'6states'!I21))-Parameters!$B$37/Parameters!$B$38/Parameters!$E$25*EXP(-Parameters!$B$38*Parameters!$E$25)+Parameters!$B$39) -> 0.67037621 | AV21: =J21*K21*EXP(-Parameters!$B$42*'6states'!A21)*(Parameters!$B$37*EXP(-Parameters!$B$38*Parameters!$E$25*'6states'!I21/('6states'!F21+'6states'!I21))*(1/Parameters!$B$38/Parameters!$E$25+'6states'!I21/('6states'!F21+'6states'!I21))-Parameters!$B$37/Parameters!$B$38/Parameters!$E$25*EXP(-Parameters!$B$38*Parameters!$E$25)+Parameters!$B$39) -> 72.83903 | AW21: =1000*(AR21+AS21+AT21)/(EXP(-Parameters!$B$42*A21)*((C21<0)*Parameters!$B$37*EXP(-Parameters!$B$38*AF21)+(C21>=0)*Parameters!$B$41)) -> 216.35385 | AX21: =1-W21/'6states,ExoDamages'!T21 -> 0.060566036 | AY21: =-Y21*W21*X21^(-Parameters!B$52)*Parameters!B$46*Parameters!B$45*N21 -> -1.9113437e-05 | AZ21: =1000*EXP(-(Parameters!$B$54)*'6states'!A21)*AQ21*Parameters!B$46*Parameters!B$45*N21 -> 1.6926073 | BA21: =SUM(AZ21:AZ$204)*EXP(Parameters!$B$54*A21) -> 274.09097 | BB21: =(C21+D21+E21)/W21 -> 0.21005537 | BF21: =SUM(AY21:AY219)/Y21 -> -0.0019839091 | BG21: =BF21/Parameters!$B$45 -> -3.3065152 | BH21: =1-BG20/BG21 -> 0.0026201553 | BK21: =-EXP(-Parameters!B$42*'6states'!A21)*(-Parameters!B$37/Parameters!B$38/Parameters!E$25*(EXP(-Parameters!B$38*Parameters!E$25*'6states'!I21/('6states'!F21+'6states'!I21))-EXP(-Parameters!B$38*Parameters!E$25))+Parameters!B$37*'6states'!F21/('6states'!F21+'6states'!I21)*EXP(-Parameters!B$38*Parameters!E$25*'6states'!I21/('6states'!F21+'6states'!I21))) -> -0.22188492 | BL21: =-J21*K21*EXP(-Parameters!B$42*'6states'!A21)*(-Parameters!B$37/Parameters!B$38/Parameters!E$25*(EXP(-Parameters!B$38*Parameters!E$25*'6states'!I21/('6states'!F21+'6states'!I21))-EXP(-Parameters!B$38*Parameters!E$25)) + Parameters!B$37*'6states'!F21/('6states'!F21+'6states'!I21)*EXP(-Parameters!B$38*Parameters!E$25*'6states'!I21/('6states'!F21+'6states'!I21))) -> -24.108676 | BM21: =I21/(F21+I21) -> 0.071552604 | BN21: =BK21-AU21 -> -0.89226113 | BS21: =EXP(-Parameters!$B$56*A21)*BF21*BL21 -> 0.012700495 | BT21: =-EXP((Parameters!$B$56)*F21)*SUM(BS21:BS29) -> -0.12730442 | BU21: =X21^-Parameters!B$52/(1-2*Parameters!B$5*'6states'!D21/'6states'!G21) -> 1.1324593 | BV21: =BU21/BU20 -> 0.99680849 | BW21: =$X21^-Parameters!$B$52/(1-2*Parameters!$B$5*'6states'!$E21/'6states'!$H21) -> 0.99184088 | BX21: =BW21/BW20 -> 0.99998926 | BY21: =($X21^-Parameters!$B$52*(1/(1+EXP(-C21)) + IF(C21<0,2*Parameters!$B$6*C21/F21,0)) + BQ21*(1/(1+EXP((C21-Parameters!$B$22)*Parameters!$B$21))))/(1-IF(C21>0,2*Parameters!$B$5*C21/F21,0)) -> 0.46616872 | BZ21: =BY21/BY20 -> 1.0034828 | CA21: =BY21-BY20 -> 0.0016179534 | CB21: =(1/$T21-1/Parameters!$B$13) * LN(Parameters!$B$18) / LN(P21) -> 0.23695489 | CC21: =(Parameters!$B$18*'6states'!T21^+Parameters!$B$19*Parameters!$B$25^'6states'!T21)^((1-'6states'!T21)/'6states'!T21)*Parameters!$B$18*Parameters!$B$26^('6states'!T21-1) -> 0.23718675 | CD21: =(LN(CC21)-LN(CC$4))/ LN(P21) -> 0.27155207 | CE21: =1-2^-CB21 -> 0.15146557 | CF21: =1-2^-CC21 -> 0.15160193
A22: =A21+Parameters!$B$65 -> 18 | B22: 2043 | C22: 0.0092026726 | D22: 0.064694498 | E22: 0.21911666 | F22: =MAX((1-Parameters!$B$4)^Parameters!B$65*F21 + C21*Parameters!B$65 - IF(C21>0,Parameters!$B$5,0)*C21^2/F21*Parameters!B$65, 0.0001) -> 0.30378311 | G22: =(1-Parameters!$B$4)^Parameters!B$65*G21+D21*Parameters!B$65-Parameters!$B$5*D21^2/G21*Parameters!B$65 -> 0.57670796 | H22: =(1-Parameters!$B$4)^Parameters!B$65*H21+E21*Parameters!B$65-Parameters!$B$5*E21^2/H21*Parameters!B$65 -> 3.6772292 | I22: =I21 *(1-Parameters!$B$4)-C21*(C21<0)*Parameters!B$65 -> 0.022717931 | J22: =J21*(1+Parameters!$B$51)^Parameters!B$65 -> 8.5966159 | K22: =K21*(1+Parameters!$B$53)^Parameters!B$65 -> 12.929325 | L22: =J22*K22*EXP(-Parameters!$B$42*'6states'!A22)*(Parameters!$B$37/Parameters!$B$38*('6states'!F22+'6states'!I22)/Parameters!$E$25*(EXP(-Parameters!$B$38*Parameters!$E$25*'6states'!I22/('6states'!F22+'6states'!I22))-EXP(-Parameters!$B$38*Parameters!$E$25)) + Parameters!$B$39*'6states'!F22) -> 21.856093 | M22: =M21+L22*Parameters!B$65 -> 2815.0069 | N22: =M22*Parameters!$B$45 -> 1.6890041 | O22: =EXP(-Parameters!$B$46/2*N22^2) -> 0.9717371 | P22: =MAX((Parameters!$B$62 + Parameters!$B$31*'6states'!A22 - '6states'!M22 + Parameters!$B$47/Parameters!$B$45)/Parameters!B$62,1) -> 9.8518621 | Q22: =Parameters!B$61*EXP(-Parameters!B$60*A22) -> 0.3075409 | R22: =(1-Parameters!B$61)*P22^-Parameters!B$63 -> 0.39775731 | S22: =Parameters!B$61*EXP(-Parameters!B$60*A22)+(1-Parameters!B$61)*P22^-Parameters!B$63 -> 0.70529822 | T22: =1-S22/Parameters!$B$12 -> 0.64735089 | U22: =1/(1-T22) -> 2.8356799 | V22: =(Parameters!$B$19*(F22+Parameters!$B$20)^T22+Parameters!$B$18*G22^T22)^(1/T22) -> 0.38768342 | W22: =(Parameters!$B$10*H22^Parameters!$B$9+Parameters!$B$11*V22^Parameters!$B$9)^(Parameters!$B$7/Parameters!$B$9)*O22 -> 1.3964463 | X22: =W22 - D22 - E22 - LN(1+EXP(Parameters!$B$21*C22))/Parameters!$B$21 - IF(C22>0, 0,Parameters!$B$6*C22^2/F22) -> 1.103228 | Y22: =EXP(-Parameters!$B$55*A22) -> 0.76200665 | Z22: =IF(X22>0,X22^(1-Parameters!$B$52)/(1-Parameters!$B$52)*Y22*Parameters!$B$65,-10+X22*1000) -> -2.1035743 | AC22: =C22*$J22*$K22 -> 1.0228627 | AD22: =D22*$J22*$K22 -> 7.1906924 | AE22: =I22*J22*K22 -> 2.5250625 | AF22: =F22*J22*K22 -> 33.765018 | AG22: =G22*J22*K22 -> 64.100189 | AH22: =V22*J22*K22 -> 43.090407 | AI22: =AH22/AH$4*100 -> 106.04877 | AJ22: =W22*J22*K22 -> 155.21282 | AK22: =X22*J22*K22 -> 122.62207 | AL22: =LN(AJ22)-LN(AJ21) -> 0.020310656 | AM22: =LN(AK22)-LN(AK21) -> 0.020593943 | AN22: =AVERAGE(AL20:AL24) -> 0.020345395 | AO22: =AVERAGE(AM20:AM24) -> 0.018939252 | AQ22: =W22*K22*J22 -> 155.21282 | AR22: =Parameters!$B$7*W22*(W22/O22)^(-Parameters!$B$9/Parameters!$B$7)*Parameters!$B$11*(V22)^(Parameters!$B$9-T22)*((1-2*Parameters!$B$5*C22/F22)*Parameters!$B$19*(F22+Parameters!$B$20)^(T22-1)-(1-2*Parameters!$B$5*D22/G22)*(Parameters!$B$18)*(G22)^(T22-1)) -> 0.16851426 | AS22: =((C23-C21)/2-(F23-F21)/F22/2*C22)/(F22/2/Parameters!$B$5-C22)-((D23-D21)/D22-(G23-G21)/G22)/(G22/2/Parameters!$B$5/D22-1) -> 0.022178419 | AT22: =+Parameters!$B$5*C22^2/F22^2-Parameters!$B$5*D22^2/G22^2 -> -0.011666419 | AU22: =EXP(-Parameters!$B$42*'6states'!A22)*(Parameters!$B$37*EXP(-Parameters!$B$38*Parameters!$E$25*'6states'!I22/('6states'!F22+'6states'!I22))*(1/Parameters!$B$38/Parameters!$E$25+'6states'!I22/('6states'!F22+'6states'!I22))-Parameters!$B$37/Parameters!$B$38/Parameters!$E$25*EXP(-Parameters!$B$38*Parameters!$E$25)+Parameters!$B$39) -> 0.66520678 | AV22: =J22*K22*EXP(-Parameters!$B$42*'6states'!A22)*(Parameters!$B$37*EXP(-Parameters!$B$38*Parameters!$E$25*'6states'!I22/('6states'!F22+'6states'!I22))*(1/Parameters!$B$38/Parameters!$E$25+'6states'!I22/('6states'!F22+'6states'!I22))-Parameters!$B$37/Parameters!$B$38/Parameters!$E$25*EXP(-Parameters!$B$38*Parameters!$E$25)+Parameters!$B$39) -> 73.936694 | AW22: =1000*(AR22+AS22+AT22)/(EXP(-Parameters!$B$42*A22)*((C22<0)*Parameters!$B$37*EXP(-Parameters!$B$38*AF22)+(C22>=0)*Parameters!$B$41)) -> 235.35688 | AX22: =1-W22/'6states,ExoDamages'!T22 -> 0.062355238 | AY22: =-Y22*W22*X22^(-Parameters!B$52)*Parameters!B$46*Parameters!B$45*N22 -> -1.8982914e-05 | AZ22: =1000*EXP(-(Parameters!$B$54)*'6states'!A22)*AQ22*Parameters!B$46*Parameters!B$45*N22 -> 1.680809 | BA22: =SUM(AZ22:AZ$204)*EXP(Parameters!$B$54*A22) -> 280.69862 | BB22: =(C22+D22+E22)/W22 -> 0.20982822 | BF22: =SUM(AY22:AY220)/Y22 -> -0.0019890104 | BG22: =BF22/Parameters!$B$45 -> -3.3150174 | BH22: =1-BG21/BG22 -> 0.00256475 | BK22: =-EXP(-Parameters!B$42*'6states'!A22)*(-Parameters!B$37/Parameters!B$38/Parameters!E$25*(EXP(-Parameters!B$38*Parameters!E$25*'6states'!I22/('6states'!F22+'6states'!I22))-EXP(-Parameters!B$38*Parameters!E$25))+Parameters!B$37*'6states'!F22/('6states'!F22+'6states'!I22)*EXP(-Parameters!B$38*Parameters!E$25*'6states'!I22/('6states'!F22+'6states'!I22))) -> -0.23945008 | BL22: =-J22*K22*EXP(-Parameters!B$42*'6states'!A22)*(-Parameters!B$37/Parameters!B$38/Parameters!E$25*(EXP(-Parameters!B$38*Parameters!E$25*'6states'!I22/('6states'!F22+'6states'!I22))-EXP(-Parameters!B$38*Parameters!E$25)) + Parameters!B$37*'6states'!F22/('6states'!F22+'6states'!I22)*EXP(-Parameters!B$38*Parameters!E$25*'6states'!I22/('6states'!F22+'6states'!I22))) -> -26.614502 | BM22: =I22/(F22+I22) -> 0.069579964 | BN22: =BK22-AU22 -> -0.90465685 | BS22: =EXP(-Parameters!$B$56*A22)*BF22*BL22 -> 0.013001874 | BT22: =-EXP((Parameters!$B$56)*F22)*SUM(BS22:BS30) -> -0.12949402 | BU22: =X22^-Parameters!B$52/(1-2*Parameters!B$5*'6states'!D22/'6states'!G22) -> 1.129121 | BV22: =BU22/BU21 -> 0.99705216 | BW22: =$X22^-Parameters!$B$52/(1-2*Parameters!$B$5*'6states'!$E22/'6states'!$H22) -> 0.99428792 | BX22: =BW22/BW21 -> 1.0024672 | BY22: =($X22^-Parameters!$B$52*(1/(1+EXP(-C22)) + IF(C22<0,2*Parameters!$B$6*C22/F22,0)) + BQ22*(1/(1+EXP((C22-Parameters!$B$22)*Parameters!$B$21))))/(1-IF(C22>0,2*Parameters!$B$5*C22/F22,0)) -> 0.46828375 | BZ22: =BY22/BY21 -> 1.004537 | CA22: =BY22-BY21 -> 0.0021150291 | CB22: =(1/$T22-1/Parameters!$B$13) * LN(Parameters!$B$18) / LN(P22) -> 0.23706362 | CC22: =(Parameters!$B$18*'6states'!T22^+Parameters!$B$19*Parameters!$B$25^'6states'!T22)^((1-'6states'!T22)/'6states'!T22)*Parameters!$B$18*Parameters!$B$26^('6states'!T22-1) -> 0.24055289 | CD22: =(LN(CC22)-LN(CC$4))/ LN(P22) -> 0.26990802 | CE22: =1-2^-CB22 -> 0.15152951 | CF22: =1-2^-CC22 -> 0.15357913
A23: =A22+Parameters!$B$65 -> 19 | B23: 2044 | C23: 0.0088441432 | D23: 0.063512532 | E23: 0.22502378 | F23: =MAX((1-Parameters!$B$4)^Parameters!B$65*F22 + C22*Parameters!B$65 - IF(C22>0,Parameters!$B$5,0)*C22^2/F22*Parameters!B$65, 0.0001) -> 0.29359905 | G23: =(1-Parameters!$B$4)^Parameters!B$65*G22+D22*Parameters!B$65-Parameters!$B$5*D22^2/G22*Parameters!B$65 -> 0.59787017 | H23: =(1-Parameters!$B$4)^Parameters!B$65*H22+E22*Parameters!B$65-Parameters!$B$5*E22^2/H22*Parameters!B$65 -> 3.6519916 | I23: =I22 *(1-Parameters!$B$4)-C22*(C22<0)*Parameters!B$65 -> 0.021288973 | J23: =J22*(1+Parameters!$B$51)^Parameters!B$65 -> 8.6215461 | K23: =K22*(1+Parameters!$B$53)^Parameters!B$65 -> 13.187911 | L23: =J23*K23*EXP(-Parameters!$B$42*'6states'!A23)*(Parameters!$B$37/Parameters!$B$38*('6states'!F23+'6states'!I23)/Parameters!$E$25*(EXP(-Parameters!$B$38*Parameters!$E$25*'6states'!I23/('6states'!F23+'6states'!I23))-EXP(-Parameters!$B$38*Parameters!$E$25)) + Parameters!$B$39*'6states'!F23) -> 21.412116 | M23: =M22+L23*Parameters!B$65 -> 2836.419 | N23: =M23*Parameters!$B$45 -> 1.7018514 | O23: =EXP(-Parameters!$B$46/2*N23^2) -> 0.97131175 | P23: =MAX((Parameters!$B$62 + Parameters!$B$31*'6states'!A23 - '6states'!M23 + Parameters!$B$47/Parameters!$B$45)/Parameters!B$62,1) -> 10.48762 | Q23: =Parameters!B$61*EXP(-Parameters!B$60*A23) -> 0.2993484 | R23: =(1-Parameters!B$61)*P23^-Parameters!B$63 -> 0.3952777 | S23: =Parameters!B$61*EXP(-Parameters!B$60*A23)+(1-Parameters!B$61)*P23^-Parameters!B$63 -> 0.69462609 | T23: =1-S23/Parameters!$B$12 -> 0.65268695 | U23: =1/(1-T23) -> 2.8792469 | V23: =(Parameters!$B$19*(F23+Parameters!$B$20)^T23+Parameters!$B$18*G23^T23)^(1/T23) -> 0.38566602 | W23: =(Parameters!$B$10*H23^Parameters!$B$9+Parameters!$B$11*V23^Parameters!$B$9)^(Parameters!$B$7/Parameters!$B$9)*O23 -> 1.3931713 | X23: =W23 - D23 - E23 - LN(1+EXP(Parameters!$B$21*C23))/Parameters!$B$21 - IF(C23>0, 0,Parameters!$B$6*C23^2/F23) -> 1.095564 | Y23: =EXP(-Parameters!$B$55*A23) -> 0.75058678 | Z23: =IF(X23>0,X23^(1-Parameters!$B$52)/(1-Parameters!$B$52)*Y23*Parameters!$B$65,-10+X23*1000) -> -2.0771107 | AC23: =C23*$J23*$K23 -> 1.0055807 | AD23: =D23*$J23*$K23 -> 7.2213865 | AE23: =I23*J23*K23 -> 2.4205602 | AF23: =F23*J23*K23 -> 33.382265 | AG23: =G23*J23*K23 -> 67.977948 | AH23: =V23*J23*K23 -> 43.850297 | AI23: =AH23/AH$4*100 -> 107.91892 | AJ23: =W23*J23*K23 -> 158.40384 | AK23: =X23*J23*K23 -> 124.56583 | AL23: =LN(AJ23)-LN(AJ22) -> 0.020350485 | AM23: =LN(AK23)-LN(AK22) -> 0.015727308 | AN23: =AVERAGE(AL21:AL25) -> 0.020463228 | AO23: =AVERAGE(AM21:AM25) -> 0.019971505 | AQ23: =W23*K23*J23 -> 158.40384 | AR23: =Parameters!$B$7*W23*(W23/O23)^(-Parameters!$B$9/Parameters!$B$7)*Parameters!$B$11*(V23)^(Parameters!$B$9-T23)*((1-2*Parameters!$B$5*C23/F23)*Parameters!$B$19*(F23+Parameters!$B$20)^(T23-1)-(1-2*Parameters!$B$5*D23/G23)*(Parameters!$B$18)*(G23)^(T23-1)) -> 0.17013099 | AS23: =((C24-C22)/2-(F24-F22)/F23/2*C23)/(F23/2/Parameters!$B$5-C23)-((D24-D22)/D23-(G24-G22)/G23)/(G23/2/Parameters!$B$5/D23-1) -> 0.020504029 | AT23: =+Parameters!$B$5*C23^2/F23^2-Parameters!$B$5*D23^2/G23^2 -> -0.010377684 | AU23: =EXP(-Parameters!$B$42*'6states'!A23)*(Parameters!$B$37*EXP(-Parameters!$B$38*Parameters!$E$25*'6states'!I23/('6states'!F23+'6states'!I23))*(1/Parameters!$B$38/Parameters!$E$25+'6states'!I23/('6states'!F23+'6states'!I23))-Parameters!$B$37/Parameters!$B$38/Parameters!$E$25*EXP(-Parameters!$B$38*Parameters!$E$25)+Parameters!$B$39) -> 0.66015827 | AV23: =J23*K23*EXP(-Parameters!$B$42*'6states'!A23)*(Parameters!$B$37*EXP(-Parameters!$B$38*Parameters!$E$25*'6states'!I23/('6states'!F23+'6states'!I23))*(1/Parameters!$B$38/Parameters!$E$25+'6states'!I23/('6states'!F23+'6states'!I23))-Parameters!$B$37/Parameters!$B$38/Parameters!$E$25*EXP(-Parameters!$B$38*Parameters!$E$25)+Parameters!$B$39) -> 75.060117 | AW23: =1000*(AR23+AS23+AT23)/(EXP(-Parameters!$B$42*A23)*((C23<0)*Parameters!$B$37*EXP(-Parameters!$B$38*AF23)+(C23>=0)*Parameters!$B$41)) -> 239.35695 | AX23: =1-W23/'6states,ExoDamages'!T23 -> 0.064094843 | AY23: =-Y23*W23*X23^(-Parameters!B$52)*Parameters!B$46*Parameters!B$45*N23 -> -1.8974197e-05 | AZ23: =1000*EXP(-(Parameters!$B$54)*'6states'!A23)*AQ23*Parameters!B$46*Parameters!B$45*N23 -> 1.6687976 | BA23: =SUM(AZ23:AZ$204)*EXP(Parameters!$B$54*A23) -> 287.45156 | BB23: =(C23+D23+E23)/W23 -> 0.21345577 | BF23: =SUM(AY23:AY221)/Y23 -> -0.0019939816 | BG23: =BF23/Parameters!$B$45 -> -3.3233027 | BH23: =1-BG22/BG23 -> 0.0024931 | BK23: =-EXP(-Parameters!B$42*'6states'!A23)*(-Parameters!B$37/Parameters!B$38/Parameters!E$25*(EXP(-Parameters!B$38*Parameters!E$25*'6states'!I23/('6states'!F23+'6states'!I23))-EXP(-Parameters!B$38*Parameters!E$25))+Parameters!B$37*'6states'!F23/('6states'!F23+'6states'!I23)*EXP(-Parameters!B$38*Parameters!E$25*'6states'!I23/('6states'!F23+'6states'!I23))) -> -0.25839605 | BL23: =-J23*K23*EXP(-Parameters!B$42*'6states'!A23)*(-Parameters!B$37/Parameters!B$38/Parameters!E$25*(EXP(-Parameters!B$38*Parameters!E$25*'6states'!I23/('6states'!F23+'6states'!I23))-EXP(-Parameters!B$38*Parameters!E$25)) + Parameters!B$37*'6states'!F23/('6states'!F23+'6states'!I23)*EXP(-Parameters!B$38*Parameters!E$25*'6states'!I23/('6states'!F23+'6states'!I23))) -> -29.379678 | BM23: =I23/(F23+I23) -> 0.067608076 | BN23: =BK23-AU23 -> -0.91855432 | BS23: =EXP(-Parameters!$B$56*A23)*BF23*BL23 -> 0.013308949 | BT23: =-EXP((Parameters!$B$56)*F23)*SUM(BS23:BS31) -> -0.13154974 | BU23: =X23^-Parameters!B$52/(1-2*Parameters!B$5*'6states'!D23/'6states'!G23) -> 1.1225814 | BV23: =BU23/BU22 -> 0.9942082 | BW23: =$X23^-Parameters!$B$52/(1-2*Parameters!$B$5*'6states'!$E23/'6states'!$H23) -> 1.0083355 | BX23: =BW23/BW22 -> 1.0141282 | BY23: =($X23^-Parameters!$B$52*(1/(1+EXP(-C23)) + IF(C23<0,2*Parameters!$B$6*C23/F23,0)) + BQ23*(1/(1+EXP((C23-Parameters!$B$22)*Parameters!$B$21))))/(1-IF(C23>0,2*Parameters!$B$5*C23/F23,0)) -> 0.47245587 | BZ23: =BY23/BY22 -> 1.0089094 | CA23: =BY23-BY22 -> 0.0041721197 | CB23: =(1/$T23-1/Parameters!$B$13) * LN(Parameters!$B$18) / LN(P23) -> 0.23715728 | CC23: =(Parameters!$B$18*'6states'!T23^+Parameters!$B$19*Parameters!$B$25^'6states'!T23)^((1-'6states'!T23)/'6states'!T23)*Parameters!$B$18*Parameters!$B$26^('6states'!T23-1) -> 0.24373169 | CD23: =(LN(CC23)-LN(CC$4))/ LN(P23) -> 0.26831211 | CE23: =1-2^-CB23 -> 0.1515846 | CF23: =1-2^-CC23 -> 0.15544206
A24: =A23+Parameters!$B$65 -> 20 | B24: 2045 | C24: 0.0086478926 | D24: 0.064193394 | E24: 0.22486592 | F24: =MAX((1-Parameters!$B$4)^Parameters!B$65*F23 + C23*Parameters!B$65 - IF(C23>0,Parameters!$B$5,0)*C23^2/F23*Parameters!B$65, 0.0001) -> 0.2837094 | G24: =(1-Parameters!$B$4)^Parameters!B$65*G23+D23*Parameters!B$65-Parameters!$B$5*D23^2/G23*Parameters!B$65 -> 0.61702965 | H24: =(1-Parameters!$B$4)^Parameters!B$65*H23+E23*Parameters!B$65-Parameters!$B$5*E23^2/H23*Parameters!B$65 -> 3.6334398 | I24: =I23 *(1-Parameters!$B$4)-C23*(C23<0)*Parameters!B$65 -> 0.019949897 | J24: =J23*(1+Parameters!$B$51)^Parameters!B$65 -> 8.6465486 | K24: =K23*(1+Parameters!$B$53)^Parameters!B$65 -> 13.451669 | L24: =J24*K24*EXP(-Parameters!$B$42*'6states'!A24)*(Parameters!$B$37/Parameters!$B$38*('6states'!F24+'6states'!I24)/Parameters!$E$25*(EXP(-Parameters!$B$38*Parameters!$E$25*'6states'!I24/('6states'!F24+'6states'!I24))-EXP(-Parameters!$B$38*Parameters!$E$25)) + Parameters!$B$39*'6states'!F24) -> 20.974583 | M24: =M23+L24*Parameters!B$65 -> 2857.3936 | N24: =M24*Parameters!$B$45 -> 1.7144362 | O24: =EXP(-Parameters!$B$46/2*N24^2) -> 0.97089216 | P24: =MAX((Parameters!$B$62 + Parameters!$B$31*'6states'!A24 - '6states'!M24 + Parameters!$B$47/Parameters!$B$45)/Parameters!B$62,1) -> 11.132128 | Q24: =Parameters!B$61*EXP(-Parameters!B$60*A24) -> 0.29137413 | R24: =(1-Parameters!B$61)*P24^-Parameters!B$63 -> 0.39292728 | S24: =Parameters!B$61*EXP(-Parameters!B$60*A24)+(1-Parameters!B$61)*P24^-Parameters!B$63 -> 0.68430141 | T24: =1-S24/Parameters!$B$12 -> 0.6578493 | U24: =1/(1-T24) -> 2.9226887 | V24: =(Parameters!$B$19*(F24+Parameters!$B$20)^T24+Parameters!$B$18*G24^T24)^(1/T24) -> 0.38324384 | W24: =(Parameters!$B$10*H24^Parameters!$B$9+Parameters!$B$11*V24^Parameters!$B$9)^(Parameters!$B$7/Parameters!$B$9)*O24 -> 1.3902868 | X24: =W24 - D24 - E24 - LN(1+EXP(Parameters!$B$21*C24))/Parameters!$B$21 - IF(C24>0, 0,Parameters!$B$6*C24^2/F24) -> 1.0923395 | Y24: =EXP(-Parameters!$B$55*A24) -> 0.73933806 | Z24: =IF(X24>0,X24^(1-Parameters!$B$52)/(1-Parameters!$B$52)*Y24*Parameters!$B$65,-10+X24*1000) -> -2.0480938 | AC24: =C24*$J24*$K24 -> 1.0058408 | AD24: =D24*$J24*$K24 -> 7.4663665 | AE24: =I24*J24*K24 -> 2.3203827 | AF24: =F24*J24*K24 -> 32.998385 | AG24: =G24*J24*K24 -> 71.767034 | AH24: =V24*J24*K24 -> 44.575287 | AI24: =AH24/AH$4*100 -> 109.70317 | AJ24: =W24*J24*K24 -> 161.70497 | AK24: =X24*J24*K24 -> 127.05056 | AL24: =LN(AJ24)-LN(AJ23) -> 0.020625795 | AM24: =LN(AK24)-LN(AK23) -> 0.019750793 | AN24: =AVERAGE(AL22:AL26) -> 0.020532699 | AO24: =AVERAGE(AM22:AM26) -> 0.019675115 | AQ24: =W24*K24*J24 -> 161.70497 | AR24: =Parameters!$B$7*W24*(W24/O24)^(-Parameters!$B$9/Parameters!$B$7)*Parameters!$B$11*(V24)^(Parameters!$B$9-T24)*((1-2*Parameters!$B$5*C24/F24)*Parameters!$B$19*(F24+Parameters!$B$20)^(T24-1)-(1-2*Parameters!$B$5*D24/G24)*(Parameters!$B$18)*(G24)^(T24-1)) -> 0.17351428 | AS24: =((C25-C23)/2-(F25-F23)/F24/2*C24)/(F24/2/Parameters!$B$5-C24)-((D25-D23)/D24-(G25-G23)/G24)/(G24/2/Parameters!$B$5/D24-1) -> 0.0065594622 | AT24: =+Parameters!$B$5*C24^2/F24^2-Parameters!$B$5*D24^2/G24^2 -> -0.0098943994 | AU24: =EXP(-Parameters!$B$42*'6states'!A24)*(Parameters!$B$37*EXP(-Parameters!$B$38*Parameters!$E$25*'6states'!I24/('6states'!F24+'6states'!I24))*(1/Parameters!$B$38/Parameters!$E$25+'6states'!I24/('6states'!F24+'6states'!I24))-Parameters!$B$37/Parameters!$B$38/Parameters!$E$25*EXP(-Parameters!$B$38*Parameters!$E$25)+Parameters!$B$39) -> 0.65517887 | AV24: =J24*K24*EXP(-Parameters!$B$42*'6states'!A24)*(Parameters!$B$37*EXP(-Parameters!$B$38*Parameters!$E$25*'6states'!I24/('6states'!F24+'6states'!I24))*(1/Parameters!$B$38/Parameters!$E$25+'6states'!I24/('6states'!F24+'6states'!I24))-Parameters!$B$37/Parameters!$B$38/Parameters!$E$25*EXP(-Parameters!$B$38*Parameters!$E$25)+Parameters!$B$39) -> 76.20419 | AW24: =1000*(AR24+AS24+AT24)/(EXP(-Parameters!$B$42*A24)*((C24<0)*Parameters!$B$37*EXP(-Parameters!$B$38*AF24)+(C24>=0)*Parameters!$B$41)) -> 228.24585 | AX24: =1-W24/'6states,ExoDamages'!T24 -> 0.065584902 | AY24: =-Y24*W24*X24^(-Parameters!B$52)*Parameters!B$46*Parameters!B$45*N24 -> -1.8863978e-05 | AZ24: =1000*EXP(-(Parameters!$B$54)*'6states'!A24)*AQ24*Parameters!B$46*Parameters!B$45*N24 -> 1.65698 | BA24: =SUM(AZ24:AZ$204)*EXP(Parameters!$B$54*A24) -> 294.353 | BB24: =(C24+D24+E24)/W24 -> 0.21413367 | BF24: =SUM(AY24:AY222)/Y24 -> -0.0019986554 | BG24: =BF24/Parameters!$B$45 -> -3.3310924 | BH24: =1-BG23/BG24 -> 0.002338488 | BK24: =-EXP(-Parameters!B$42*'6states'!A24)*(-Parameters!B$37/Parameters!B$38/Parameters!E$25*(EXP(-Parameters!B$38*Parameters!E$25*'6states'!I24/('6states'!F24+'6states'!I24))-EXP(-Parameters!B$38*Parameters!E$25))+Parameters!B$37*'6states'!F24/('6states'!F24+'6states'!I24)*EXP(-Parameters!B$38*Parameters!E$25*'6states'!I24/('6states'!F24+'6states'!I24))) -> -0.2780843 | BL24: =-J24*K24*EXP(-Parameters!B$42*'6states'!A24)*(-Parameters!B$37/Parameters!B$38/Parameters!E$25*(EXP(-Parameters!B$38*Parameters!E$25*'6states'!I24/('6states'!F24+'6states'!I24))-EXP(-Parameters!B$38*Parameters!E$25)) + Parameters!B$37*'6states'!F24/('6states'!F24+'6states'!I24)*EXP(-Parameters!B$38*Parameters!E$25*'6states'!I24/('6states'!F24+'6states'!I24))) -> -32.344127 | BM24: =I24/(F24+I24) -> 0.065698292 | BN24: =BK24-AU24 -> -0.93326317 | BS24: =EXP(-Parameters!$B$56*A24)*BF24*BL24 -> 0.013584197 | BT24: =-EXP((Parameters!$B$56)*F24)*SUM(BS24:BS32) -> -0.1334308 | BU24: =X24^-Parameters!B$52/(1-2*Parameters!B$5*'6states'!D24/'6states'!G24) -> 1.1208092 | BV24: =BU24/BU23 -> 0.99842131 | BW24: =$X24^-Parameters!$B$52/(1-2*Parameters!$B$5*'6states'!$E24/'6states'!$H24) -> 1.0129825 | BX24: =BW24/BW23 -> 1.0046086 | BY24: =($X24^-Parameters!$B$52*(1/(1+EXP(-C24)) + IF(C24<0,2*Parameters!$B$6*C24/F24,0)) + BQ24*(1/(1+EXP((C24-Parameters!$B$22)*Parameters!$B$21))))/(1-IF(C24>0,2*Parameters!$B$5*C24/F24,0)) -> 0.47465529 | BZ24: =BY24/BY23 -> 1.0046553 | CA24: =BY24-BY23 -> 0.0021994139 | CB24: =(1/$T24-1/Parameters!$B$13) * LN(Parameters!$B$18) / LN(P24) -> 0.23723148 | CC24: =(Parameters!$B$18*'6states'!T24^+Parameters!$B$19*Parameters!$B$25^'6states'!T24)^((1-'6states'!T24)/'6states'!T24)*Parameters!$B$18*Parameters!$B$26^('6states'!T24-1) -> 0.24673603 | CD24: =(LN(CC24)-LN(CC$4))/ LN(P24) -> 0.26675556 | CE24: =1-2^-CB24 -> 0.15162823 | CF24: =1-2^-CC24 -> 0.15719898
A25: =A24+Parameters!$B$65 -> 21 | B25: 2046 | C25: 0.0085440831 | D25: 0.066114813 | E25: 0.22091094 | F25: =MAX((1-Parameters!$B$4)^Parameters!B$65*F24 + C24*Parameters!B$65 - IF(C24>0,Parameters!$B$5,0)*C24^2/F24*Parameters!B$65, 0.0001) -> 0.27424837 | G25: =(1-Parameters!$B$4)^Parameters!B$65*G24+D24*Parameters!B$65-Parameters!$B$5*D24^2/G24*Parameters!B$65 -> 0.63573344 | H25: =(1-Parameters!$B$4)^Parameters!B$65*H24+E24*Parameters!B$65-Parameters!$B$5*E24^2/H24*Parameters!B$65 -> 3.6158459 | I25: =I24 *(1-Parameters!$B$4)-C24*(C24<0)*Parameters!B$65 -> 0.018695048 | J25: =J24*(1+Parameters!$B$51)^Parameters!B$65 -> 8.6716236 | K25: =K24*(1+Parameters!$B$53)^Parameters!B$65 -> 13.720703 | L25: =J25*K25*EXP(-Parameters!$B$42*'6states'!A25)*(Parameters!$B$37/Parameters!$B$38*('6states'!F25+'6states'!I25)/Parameters!$E$25*(EXP(-Parameters!$B$38*Parameters!$E$25*'6states'!I25/('6states'!F25+'6states'!I25))-EXP(-Parameters!$B$38*Parameters!$E$25)) + Parameters!$B$39*'6states'!F25) -> 20.554362 | M25: =M24+L25*Parameters!B$65 -> 2877.948 | N25: =M25*Parameters!$B$45 -> 1.7267688 | O25: =EXP(-Parameters!$B$46/2*N25^2) -> 0.97047815 | P25: =MAX((Parameters!$B$62 + Parameters!$B$31*'6states'!A25 - '6states'!M25 + Parameters!$B$47/Parameters!$B$45)/Parameters!B$62,1) -> 11.785041 | Q25: =Parameters!B$61*EXP(-Parameters!B$60*A25) -> 0.28361228 | R25: =(1-Parameters!B$61)*P25^-Parameters!B$63 -> 0.39069414 | S25: =Parameters!B$61*EXP(-Parameters!B$60*A25)+(1-Parameters!B$61)*P25^-Parameters!B$63 -> 0.67430642 | T25: =1-S25/Parameters!$B$12 -> 0.66284679 | U25: =1/(1-T25) -> 2.9660106 | V25: =(Parameters!$B$19*(F25+Parameters!$B$20)^T25+Parameters!$B$18*G25^T25)^(1/T25) -> 0.38094089 | W25: =(Parameters!$B$10*H25^Parameters!$B$9+Parameters!$B$11*V25^Parameters!$B$9)^(Parameters!$B$7/Parameters!$B$9)*O25 -> 1.3875193 | X25: =W25 - D25 - E25 - LN(1+EXP(Parameters!$B$21*C25))/Parameters!$B$21 - IF(C25>0, 0,Parameters!$B$6*C25^2/F25) -> 1.091702 | Y25: =EXP(-Parameters!$B$55*A25) -> 0.72825793 | Z25: =IF(X25>0,X25^(1-Parameters!$B$52)/(1-Parameters!$B$52)*Y25*Parameters!$B$65,-10+X25*1000) -> -2.0178122 | AC25: =C25*$J25*$K25 -> 1.0165816 | AD25: =D25*$J25*$K25 -> 7.8663912 | AE25: =I25*J25*K25 -> 2.2243512 | AF25: =F25*J25*K25 -> 32.630282 | AG25: =G25*J25*K25 -> 75.640054 | AH25: =V25*J25*K25 -> 45.324639 | AI25: =AH25/AH$4*100 -> 111.54739 | AJ25: =W25*J25*K25 -> 165.08811 | AK25: =X25*J25*K25 -> 129.89155 | AL25: =LN(AJ25)-LN(AJ24) -> 0.020705857 | AM25: =LN(AK25)-LN(AK24) -> 0.022114703 | AN25: =AVERAGE(AL23:AL27) -> 0.02061693 | AO25: =AVERAGE(AM23:AM27) -> 0.019343033 | AQ25: =W25*K25*J25 -> 165.08811 | AR25: =Parameters!$B$7*W25*(W25/O25)^(-Parameters!$B$9/Parameters!$B$7)*Parameters!$B$11*(V25)^(Parameters!$B$9-T25)*((1-2*Parameters!$B$5*C25/F25)*Parameters!$B$19*(F25+Parameters!$B$20)^(T25-1)-(1-2*Parameters!$B$5*D25/G25)*(Parameters!$B$18)*(G25)^(T25-1)) -> 0.17697983 | AS25: =((C26-C24)/2-(F26-F24)/F25/2*C25)/(F25/2/Parameters!$B$5-C25)-((D26-D24)/D25-(G26-G24)/G25)/(G25/2/Parameters!$B$5/D25-1) -> 0.0062271784 | AT25: =+Parameters!$B$5*C25^2/F25^2-Parameters!$B$5*D25^2/G25^2 -> -0.0098449149 | AU25: =EXP(-Parameters!$B$42*'6states'!A25)*(Parameters!$B$37*EXP(-Parameters!$B$38*Parameters!$E$25*'6states'!I25/('6states'!F25+'6states'!I25))*(1/Parameters!$B$38/Parameters!$E$25+'6states'!I25/('6states'!F25+'6states'!I25))-Parameters!$B$37/Parameters!$B$38/Parameters!$E$25*EXP(-Parameters!$B$38*Parameters!$E$25)+Parameters!$B$39) -> 0.65029138 | AV25: =J25*K25*EXP(-Parameters!$B$42*'6states'!A25)*(Parameters!$B$37*EXP(-Parameters!$B$38*Parameters!$E$25*'6states'!I25/('6states'!F25+'6states'!I25))*(1/Parameters!$B$38/Parameters!$E$25+'6states'!I25/('6states'!F25+'6states'!I25))-Parameters!$B$37/Parameters!$B$38/Parameters!$E$25*EXP(-Parameters!$B$38*Parameters!$E$25)+Parameters!$B$39) -> 77.372169 | AW25: =1000*(AR25+AS25+AT25)/(EXP(-Parameters!$B$42*A25)*((C25<0)*Parameters!$B$37*EXP(-Parameters!$B$38*AF25)+(C25>=0)*Parameters!$B$41)) -> 234.8514 | AX25: =1-W25/'6states,ExoDamages'!T25 -> 0.066980939 | AY25: =-Y25*W25*X25^(-Parameters!B$52)*Parameters!B$46*Parameters!B$45*N25 -> -1.8692405e-05 | AZ25: =1000*EXP(-(Parameters!$B$54)*'6states'!A25)*AQ25*Parameters!B$46*Parameters!B$45*N25 -> 1.645049 | BA25: =SUM(AZ25:AZ$204)*EXP(Parameters!$B$54*A25) -> 301.40538 | BB25: =(C25+D25+E25)/W25 -> 0.21302034 | BF25: =SUM(AY25:AY223)/Y25 -> -0.0020031613 | BG25: =BF25/Parameters!$B$45 -> -3.3386021 | BH25: =1-BG24/BG25 -> 0.0022493566 | BK25: =-EXP(-Parameters!B$42*'6states'!A25)*(-Parameters!B$37/Parameters!B$38/Parameters!E$25*(EXP(-Parameters!B$38*Parameters!E$25*'6states'!I25/('6states'!F25+'6states'!I25))-EXP(-Parameters!B$38*Parameters!E$25))+Parameters!B$37*'6states'!F25/('6states'!F25+'6states'!I25)*EXP(-Parameters!B$38*Parameters!E$25*'6states'!I25/('6states'!F25+'6states'!I25))) -> -0.29888671 | BL25: =-J25*K25*EXP(-Parameters!B$42*'6states'!A25)*(-Parameters!B$37/Parameters!B$38/Parameters!E$25*(EXP(-Parameters!B$38*Parameters!E$25*'6states'!I25/('6states'!F25+'6states'!I25))-EXP(-Parameters!B$38*Parameters!E$25)) + Parameters!B$37*'6states'!F25/('6states'!F25+'6states'!I25)*EXP(-Parameters!B$38*Parameters!E$25*'6states'!I25/('6states'!F25+'6states'!I25))) -> -35.56177 | BM25: =I25/(F25+I25) -> 0.06381795 | BN25: =BK25-AU25 -> -0.94917809 | BS25: =EXP(-Parameters!$B$56*A25)*BF25*BL25 -> 0.013846019 | BT25: =-EXP((Parameters!$B$56)*F25)*SUM(BS25:BS33) -> -0.13516084 | BU25: =X25^-Parameters!B$52/(1-2*Parameters!B$5*'6states'!D25/'6states'!G25) -> 1.1215838 | BV25: =BU25/BU24 -> 1.0006911 | BW25: =$X25^-Parameters!$B$52/(1-2*Parameters!$B$5*'6states'!$E25/'6states'!$H25) -> 1.0119502 | BX25: =BW25/BW24 -> 0.99898093 | BY25: =($X25^-Parameters!$B$52*(1/(1+EXP(-C25)) + IF(C25<0,2*Parameters!$B$6*C25/F25,0)) + BQ25*(1/(1+EXP((C25-Parameters!$B$22)*Parameters!$B$21))))/(1-IF(C25>0,2*Parameters!$B$5*C25/F25,0)) -> 0.4756868 | BZ25: =BY25/BY24 -> 1.0021732 | CA25: =BY25-BY24 -> 0.001031512 | CB25: =(1/$T25-1/Parameters!$B$13) * LN(Parameters!$B$18) / LN(P25) -> 0.2372849 | CC25: =(Parameters!$B$18*'6states'!T25^+Parameters!$B$19*Parameters!$B$25^'6states'!T25)^((1-'6states'!T25)/'6states'!T25)*Parameters!$B$18*Parameters!$B$26^('6states'!T25-1) -> 0.24957736 | CD25: =(LN(CC25)-LN(CC$4))/ LN(P25) -> 0.26523376 | CE25: =1-2^-CB25 -> 0.15165964 | CF25: =1-2^-CC25 -> 0.15885721
A26: =A25+Parameters!$B$65 -> 22 | B26: 2047 | C26: 0.0083630234 | D26: 0.066856269 | E26: 0.2202629 | F26: =MAX((1-Parameters!$B$4)^Parameters!B$65*F25 + C25*Parameters!B$65 - IF(C25>0,Parameters!$B$5,0)*C25^2/F25*Parameters!B$65, 0.0001) -> 0.26527604 | G26: =(1-Parameters!$B$4)^Parameters!B$65*G25+D25*Parameters!B$65-Parameters!$B$5*D25^2/G25*Parameters!B$65 -> 0.65498483 | H26: =(1-Parameters!$B$4)^Parameters!B$65*H25+E25*Parameters!B$65-Parameters!$B$5*E25^2/H25*Parameters!B$65 -> 3.5958236 | I26: =I25 *(1-Parameters!$B$4)-C25*(C25<0)*Parameters!B$65 -> 0.01751913 | J26: =J25*(1+Parameters!$B$51)^Parameters!B$65 -> 8.6967713 | K26: =K25*(1+Parameters!$B$53)^Parameters!B$65 -> 13.995117 | L26: =J26*K26*EXP(-Parameters!$B$42*'6states'!A26)*(Parameters!$B$37/Parameters!$B$38*('6states'!F26+'6states'!I26)/Parameters!$E$25*(EXP(-Parameters!$B$38*Parameters!$E$25*'6states'!I26/('6states'!F26+'6states'!I26))-EXP(-Parameters!$B$38*Parameters!$E$25)) + Parameters!$B$39*'6states'!F26) -> 20.157158 | M26: =M25+L26*Parameters!B$65 -> 2898.1051 | N26: =M26*Parameters!$B$45 -> 1.7388631 | O26: =EXP(-Parameters!$B$46/2*N26^2) -> 0.97006943 | P26: =MAX((Parameters!$B$62 + Parameters!$B$31*'6states'!A26 - '6states'!M26 + Parameters!$B$47/Parameters!$B$45)/Parameters!B$62,1) -> 12.445898 | Q26: =Parameters!B$61*EXP(-Parameters!B$60*A26) -> 0.2760572 | R26: =(1-Parameters!B$61)*P26^-Parameters!B$63 -> 0.38856831 | S26: =Parameters!B$61*EXP(-Parameters!B$60*A26)+(1-Parameters!B$61)*P26^-Parameters!B$63 -> 0.66462551 | T26: =1-S26/Parameters!$B$12 -> 0.66768724 | U26: =1/(1-T26) -> 3.0092134 | V26: =(Parameters!$B$19*(F26+Parameters!$B$20)^T26+Parameters!$B$18*G26^T26)^(1/T26) -> 0.37907145 | W26: =(Parameters!$B$10*H26^Parameters!$B$9+Parameters!$B$11*V26^Parameters!$B$9)^(Parameters!$B$7/Parameters!$B$9)*O26 -> 1.3847087 | X26: =W26 - D26 - E26 - LN(1+EXP(Parameters!$B$21*C26))/Parameters!$B$21 - IF(C26>0, 0,Parameters!$B$6*C26^2/F26) -> 1.0889657 | Y26: =EXP(-Parameters!$B$55*A26) -> 0.71734384 | Z26: =IF(X26>0,X26^(1-Parameters!$B$52)/(1-Parameters!$B$52)*Y26*Parameters!$B$65,-10+X26*1000) -> -1.9893186 | AC26: =C26*$J26*$K26 -> 1.0178831 | AD26: =D26*$J26*$K26 -> 8.1372322 | AE26: =I26*J26*K26 -> 2.1322941 | AF26: =F26*J26*K26 -> 32.287365 | AG26: =G26*J26*K26 -> 79.71973 | AH26: =V26*J26*K26 -> 46.137669 | AI26: =AH26/AH$4*100 -> 113.54832 | AJ26: =W26*J26*K26 -> 168.53612 | AK26: =X26*J26*K26 -> 132.54056 | AL26: =LN(AJ26)-LN(AJ25) -> 0.020670702 | AM26: =LN(AK26)-LN(AK25) -> 0.020188827 | AN26: =AVERAGE(AL24:AL28) -> 0.020718599 | AO26: =AVERAGE(AM24:AM28) -> 0.020031918 | AQ26: =W26*K26*J26 -> 168.53612 | AR26: =Parameters!$B$7*W26*(W26/O26)^(-Parameters!$B$9/Parameters!$B$7)*Parameters!$B$11*(V26)^(Parameters!$B$9-T26)*((1-2*Parameters!$B$5*C26/F26)*Parameters!$B$19*(F26+Parameters!$B$20)^(T26-1)-(1-2*Parameters!$B$5*D26/G26)*(Parameters!$B$18)*(G26)^(T26-1)) -> 0.17916024 | AS26: =((C27-C25)/2-(F27-F25)/F26/2*C26)/(F26/2/Parameters!$B$5-C26)-((D27-D25)/D26-(G27-G25)/G26)/(G26/2/Parameters!$B$5/D26-1) -> 0.012322778 | AT26: =+Parameters!$B$5*C26^2/F26^2-Parameters!$B$5*D26^2/G26^2 -> -0.0094250257 | AU26: =EXP(-Parameters!$B$42*'6states'!A26)*(Parameters!$B$37*EXP(-Parameters!$B$38*Parameters!$E$25*'6states'!I26/('6states'!F26+'6states'!I26))*(1/Parameters!$B$38/Parameters!$E$25+'6states'!I26/('6states'!F26+'6states'!I26))-Parameters!$B$37/Parameters!$B$38/Parameters!$E$25*EXP(-Parameters!$B$38*Parameters!$E$25)+Parameters!$B$39) -> 0.64550877 | AV26: =J26*K26*EXP(-Parameters!$B$42*'6states'!A26)*(Parameters!$B$37*EXP(-Parameters!$B$38*Parameters!$E$25*'6states'!I26/('6states'!F26+'6states'!I26))*(1/Parameters!$B$38/Parameters!$E$25+'6states'!I26/('6states'!F26+'6states'!I26))-Parameters!$B$37/Parameters!$B$38/Parameters!$E$25*EXP(-Parameters!$B$38*Parameters!$E$25)+Parameters!$B$39) -> 78.566377 | AW26: =1000*(AR26+AS26+AT26)/(EXP(-Parameters!$B$42*A26)*((C26<0)*Parameters!$B$37*EXP(-Parameters!$B$38*AF26)+(C26>=0)*Parameters!$B$41)) -> 249.1103 | AX26: =1-W26/'6states,ExoDamages'!T26 -> 0.068418957 | AY26: =-Y26*W26*X26^(-Parameters!B$52)*Parameters!B$46*Parameters!B$45*N26 -> -1.8566468e-05 | AZ26: =1000*EXP(-(Parameters!$B$54)*'6states'!A26)*AQ26*Parameters!B$46*Parameters!B$45*N26 -> 1.6328394 | BA26: =SUM(AZ26:AZ$204)*EXP(Parameters!$B$54*A26) -> 308.61183 | BB26: =(C26+D26+E26)/W26 -> 0.21338944 | BF26: =SUM(AY26:AY224)/Y26 -> -0.0020075807 | BG26: =BF26/Parameters!$B$45 -> -3.3459679 | BH26: =1-BG25/BG26 -> 0.0022013835 | BK26: =-EXP(-Parameters!B$42*'6states'!A26)*(-Parameters!B$37/Parameters!B$38/Parameters!E$25*(EXP(-Parameters!B$38*Parameters!E$25*'6states'!I26/('6states'!F26+'6states'!I26))-EXP(-Parameters!B$38*Parameters!E$25))+Parameters!B$37*'6states'!F26/('6states'!F26+'6states'!I26)*EXP(-Parameters!B$38*Parameters!E$25*'6states'!I26/('6states'!F26+'6states'!I26))) -> -0.32107161 | BL26: =-J26*K26*EXP(-Parameters!B$42*'6states'!A26)*(-Parameters!B$37/Parameters!B$38/Parameters!E$25*(EXP(-Parameters!B$38*Parameters!E$25*'6states'!I26/('6states'!F26+'6states'!I26))-EXP(-Parameters!B$38*Parameters!E$25)) + Parameters!B$37*'6states'!F26/('6states'!F26+'6states'!I26)*EXP(-Parameters!B$38*Parameters!E$25*'6states'!I26/('6states'!F26+'6states'!I26))) -> -39.078373 | BM26: =I26/(F26+I26) -> 0.06194989 | BS26: =EXP(-Parameters!$B$56*A26)*BF26*BL26 -> 0.01410458 | BT26: =-EXP((Parameters!$B$56)*F26)*SUM(BS26:BS34) -> -0.13672809 | BU26: =X26^-Parameters!B$52/(1-2*Parameters!B$5*'6states'!D26/'6states'!G26) -> 1.1199468 | BV26: =BU26/BU25 -> 0.9985405 | BW26: =$X26^-Parameters!$B$52/(1-2*Parameters!$B$5*'6states'!$E26/'6states'!$H26) -> 1.0157547 | BX26: =BW26/BW25 -> 1.0037596 | BY26: =($X26^-Parameters!$B$52*(1/(1+EXP(-C26)) + IF(C26<0,2*Parameters!$B$6*C26/F26,0)) + BQ26*(1/(1+EXP((C26-Parameters!$B$22)*Parameters!$B$21))))/(1-IF(C26>0,2*Parameters!$B$5*C26/F26,0)) -> 0.47763627 | BZ26: =BY26/BY25 -> 1.0040982 | CA26: =BY26-BY25 -> 0.001949472 | CB26: =(1/$T26-1/Parameters!$B$13) * LN(Parameters!$B$18) / LN(P26) -> 0.23731773 | CC26: =(Parameters!$B$18*'6states'!T26^+Parameters!$B$19*Parameters!$B$25^'6states'!T26)^((1-'6states'!T26)/'6states'!T26)*Parameters!$B$18*Parameters!$B$26^('6states'!T26-1) -> 0.25226604 | CD26: =(LN(CC26)-LN(CC$4))/ LN(P26) -> 0.26374416 | CE26: =1-2^-CB26 -> 0.15167895 | CF26: =1-2^-CC26 -> 0.16042334
A27: =A26+Parameters!$B$65 -> 23 | B27: 2048 | C27: 0.0081353854 | D27: 0.066942392 | E27: 0.22175836 | F27: =MAX((1-Parameters!$B$4)^Parameters!B$65*F26 + C26*Parameters!B$65 - IF(C26>0,Parameters!$B$5,0)*C26^2/F26*Parameters!B$65, 0.0001) -> 0.25668955 | G27: =(1-Parameters!$B$4)^Parameters!B$65*G26+D26*Parameters!B$65-Parameters!$B$5*D26^2/G26*Parameters!B$65 -> 0.67381833 | H27: =(1-Parameters!$B$4)^Parameters!B$65*H26+E26*Parameters!B$65-Parameters!$B$5*E26^2/H26*Parameters!B$65 -> 3.5764169 | I27: =I26 *(1-Parameters!$B$4)-C26*(C26<0)*Parameters!B$65 -> 0.016417176 | J27: =J26*(1+Parameters!$B$51)^Parameters!B$65 -> 8.7219919 | K27: =K26*(1+Parameters!$B$53)^Parameters!B$65 -> 14.275019 | L27: =J27*K27*EXP(-Parameters!$B$42*'6states'!A27)*(Parameters!$B$37/Parameters!$B$38*('6states'!F27+'6states'!I27)/Parameters!$E$25*(EXP(-Parameters!$B$38*Parameters!$E$25*'6states'!I27/('6states'!F27+'6states'!I27))-EXP(-Parameters!$B$38*Parameters!$E$25)) + Parameters!$B$39*'6states'!F27) -> 19.776009 | M27: =M26+L27*Parameters!B$65 -> 2917.8811 | N27: =M27*Parameters!$B$45 -> 1.7507287 | O27: =EXP(-Parameters!$B$46/2*N27^2) -> 0.96966584 | P27: =MAX((Parameters!$B$62 + Parameters!$B$31*'6states'!A27 - '6states'!M27 + Parameters!$B$47/Parameters!$B$45)/Parameters!B$62,1) -> 13.114378 | Q27: =Parameters!B$61*EXP(-Parameters!B$60*A27) -> 0.26870338 | R27: =(1-Parameters!B$61)*P27^-Parameters!B$63 -> 0.38654071 | S27: =Parameters!B$61*EXP(-Parameters!B$60*A27)+(1-Parameters!B$61)*P27^-Parameters!B$63 -> 0.65524409 | T27: =1-S27/Parameters!$B$12 -> 0.67237796 | U27: =1/(1-T27) -> 3.0522977 | V27: =(Parameters!$B$19*(F27+Parameters!$B$20)^T27+Parameters!$B$18*G27^T27)^(1/T27) -> 0.37731996 | W27: =(Parameters!$B$10*H27^Parameters!$B$9+Parameters!$B$11*V27^Parameters!$B$9)^(Parameters!$B$7/Parameters!$B$9)*O27 -> 1.3819881 | X27: =W27 - D27 - E27 - LN(1+EXP(Parameters!$B$21*C27))/Parameters!$B$21 - IF(C27>0, 0,Parameters!$B$6*C27^2/F27) -> 1.0848736 | Y27: =EXP(-Parameters!$B$55*A27) -> 0.70659332 | Z27: =IF(X27>0,X27^(1-Parameters!$B$52)/(1-Parameters!$B$52)*Y27*Parameters!$B$65,-10+X27*1000) -> -1.9620894 | AC27: =C27*$J27*$K27 -> 1.0129092 | AD27: =D27*$J27*$K27 -> 8.3347696 | AE27: =I27*J27*K27 -> 2.0440468 | AF27: =F27*J27*K27 -> 31.959543 | AG27: =G27*J27*K27 -> 83.894831 | AH27: =V27*J27*K27 -> 46.978826 | AI27: =AH27/AH$4*100 -> 115.61847 | AJ27: =W27*J27*K27 -> 172.06665 | AK27: =X27*J27*K27 -> 135.07392 | AL27: =LN(AJ27)-LN(AJ26) -> 0.020731811 | AM27: =LN(AK27)-LN(AK26) -> 0.018933534 | AN27: =AVERAGE(AL25:AL29) -> 0.020788714 | AO27: =AVERAGE(AM25:AM29) -> 0.020512316 | AQ27: =W27*K27*J27 -> 172.06665 | AR27: =Parameters!$B$7*W27*(W27/O27)^(-Parameters!$B$9/Parameters!$B$7)*Parameters!$B$11*(V27)^(Parameters!$B$9-T27)*((1-2*Parameters!$B$5*C27/F27)*Parameters!$B$19*(F27+Parameters!$B$20)^(T27-1)-(1-2*Parameters!$B$5*D27/G27)*(Parameters!$B$18)*(G27)^(T27-1)) -> 0.18109554 | AS27: =((C28-C26)/2-(F28-F26)/F27/2*C27)/(F27/2/Parameters!$B$5-C27)-((D28-D26)/D27-(G28-G26)/G27)/(G27/2/Parameters!$B$5/D27-1) -> 0.013191471 | AT27: =+Parameters!$B$5*C27^2/F27^2-Parameters!$B$5*D27^2/G27^2 -> -0.0088655152 | AU27: =EXP(-Parameters!$B$42*'6states'!A27)*(Parameters!$B$37*EXP(-Parameters!$B$38*Parameters!$E$25*'6states'!I27/('6states'!F27+'6states'!I27))*(1/Parameters!$B$38/Parameters!$E$25+'6states'!I27/('6states'!F27+'6states'!I27))-Parameters!$B$37/Parameters!$B$38/Parameters!$E$25*EXP(-Parameters!$B$38*Parameters!$E$25)+Parameters!$B$39) -> 0.64081188 | AV27: =J27*K27*EXP(-Parameters!$B$42*'6states'!A27)*(Parameters!$B$37*EXP(-Parameters!$B$38*Parameters!$E$25*'6states'!I27/('6states'!F27+'6states'!I27))*(1/Parameters!$B$38/Parameters!$E$25+'6states'!I27/('6states'!F27+'6states'!I27))-Parameters!$B$37/Parameters!$B$38/Parameters!$E$25*EXP(-Parameters!$B$38*Parameters!$E$25)+Parameters!$B$39) -> 79.785309 | AW27: =1000*(AR27+AS27+AT27)/(EXP(-Parameters!$B$42*A27)*((C27<0)*Parameters!$B$37*EXP(-Parameters!$B$38*AF27)+(C27>=0)*Parameters!$B$41)) -> 256.26244 | AX27: =1-W27/'6states,ExoDamages'!T27 -> 0.069808636 | AY27: =-Y27*W27*X27^(-Parameters!B$52)*Parameters!B$46*Parameters!B$45*N27 -> -1.8470479e-05 | AZ27: =1000*EXP(-(Parameters!$B$54)*'6states'!A27)*AQ27*Parameters!B$46*Parameters!B$45*N27 -> 1.6205294 | BA27: =SUM(AZ27:AZ$204)*EXP(Parameters!$B$54*A27) -> 315.97588 | BB27: =(C27+D27+E27)/W27 -> 0.21478921 | BF27: =SUM(AY27:AY225)/Y27 -> -0.0020118492 | BG27: =BF27/Parameters!$B$45 -> -3.353082 | BH27: =1-BG26/BG27 -> 0.0021216645 | BK27: =-EXP(-Parameters!B$42*'6states'!A27)*(-Parameters!B$37/Parameters!B$38/Parameters!E$25*(EXP(-Parameters!B$38*Parameters!E$25*'6states'!I27/('6states'!F27+'6states'!I27))-EXP(-Parameters!B$38*Parameters!E$25))+Parameters!B$37*'6states'!F27/('6states'!F27+'6states'!I27)*EXP(-Parameters!B$38*Parameters!E$25*'6states'!I27/('6states'!F27+'6states'!I27))) -> -0.34443736 | BL27: =-J27*K27*EXP(-Parameters!B$42*'6states'!A27)*(-Parameters!B$37/Parameters!B$38/Parameters!E$25*(EXP(-Parameters!B$38*Parameters!E$25*'6states'!I27/('6states'!F27+'6states'!I27))-EXP(-Parameters!B$38*Parameters!E$25)) + Parameters!B$37*'6states'!F27/('6states'!F27+'6states'!I27)*EXP(-Parameters!B$38*Parameters!E$25*'6states'!I27/('6states'!F27+'6states'!I27))) -> -42.884725 | BM27: =I27/(F27+I27) -> 0.060112677 | BS27: =EXP(-Parameters!$B$56*A27)*BF27*BL27 -> 0.014347418 | BT27: =-EXP((Parameters!$B$56)*F27)*SUM(BS27:BS35) -> -0.13811922 | BU27: =X27^-Parameters!B$52/(1-2*Parameters!B$5*'6states'!D27/'6states'!G27) -> 1.1179971 | BV27: =BU27/BU26 -> 0.99825906 | BW27: =$X27^-Parameters!$B$52/(1-2*Parameters!$B$5*'6states'!$E27/'6states'!$H27) -> 1.02268 | BX27: =BW27/BW26 -> 1.0068178 | BY27: =($X27^-Parameters!$B$52*(1/(1+EXP(-C27)) + IF(C27<0,2*Parameters!$B$6*C27/F27,0)) + BQ27*(1/(1+EXP((C27-Parameters!$B$22)*Parameters!$B$21))))/(1-IF(C27>0,2*Parameters!$B$5*C27/F27,0)) -> 0.48018761 | BZ27: =BY27/BY26 -> 1.0053416 | CA27: =BY27-BY26 -> 0.0025513418 | CB27: =(1/$T27-1/Parameters!$B$13) * LN(Parameters!$B$18) / LN(P27) -> 0.23732979 | CC27: =(Parameters!$B$18*'6states'!T27^+Parameters!$B$19*Parameters!$B$25^'6states'!T27)^((1-'6states'!T27)/'6states'!T27)*Parameters!$B$18*Parameters!$B$26^('6states'!T27-1) -> 0.25481171 | CD27: =(LN(CC27)-LN(CC$4))/ LN(P27) -> 0.26228403 | CE27: =1-2^-CB27 -> 0.15168604 | CF27: =1-2^-CC27 -> 0.16190349
A28: =A27+Parameters!$B$65 -> 24 | B28: 2049 | C28: 0.0079131783 | D28: 0.067039967 | E28: 0.22314395 | F28: =MAX((1-Parameters!$B$4)^Parameters!B$65*F27 + C27*Parameters!B$65 - IF(C27>0,Parameters!$B$5,0)*C27^2/F27*Parameters!B$65, 0.0001) -> 0.24842132 | G28: =(1-Parameters!$B$4)^Parameters!B$65*G27+D27*Parameters!B$65-Parameters!$B$5*D27^2/G27*Parameters!B$65 -> 0.69172697 | H28: =(1-Parameters!$B$4)^Parameters!B$65*H27+E27*Parameters!B$65-Parameters!$B$5*E27^2/H27*Parameters!B$65 -> 3.5594684 | I28: =I27 *(1-Parameters!$B$4)-C27*(C27<0)*Parameters!B$65 -> 0.015384536 | J28: =J27*(1+Parameters!$B$51)^Parameters!B$65 -> 8.7472857 | K28: =K27*(1+Parameters!$B$53)^Parameters!B$65 -> 14.56052 | L28: =J28*K28*EXP(-Parameters!$B$42*'6states'!A28)*(Parameters!$B$37/Parameters!$B$38*('6states'!F28+'6states'!I28)/Parameters!$E$25*(EXP(-Parameters!$B$38*Parameters!$E$25*'6states'!I28/('6states'!F28+'6states'!I28))-EXP(-Parameters!$B$38*Parameters!$E$25)) + Parameters!$B$39*'6states'!F28) -> 19.406352 | M28: =M27+L28*Parameters!B$65 -> 2937.2875 | N28: =M28*Parameters!$B$45 -> 1.7623725 | O28: =EXP(-Parameters!$B$46/2*N28^2) -> 0.96926729 | P28: =MAX((Parameters!$B$62 + Parameters!$B$31*'6states'!A28 - '6states'!M28 + Parameters!$B$47/Parameters!$B$45)/Parameters!B$62,1) -> 13.790251 | Q28: =Parameters!B$61*EXP(-Parameters!B$60*A28) -> 0.26154546 | R28: =(1-Parameters!B$61)*P28^-Parameters!B$63 -> 0.38460311 | S28: =Parameters!B$61*EXP(-Parameters!B$60*A28)+(1-Parameters!B$61)*P28^-Parameters!B$63 -> 0.64614856 | T28: =1-S28/Parameters!$B$12 -> 0.67692572 | U28: =1/(1-T28) -> 3.0952634 | V28: =(Parameters!$B$19*(F28+Parameters!$B$20)^T28+Parameters!$B$18*G28^T28)^(1/T28) -> 0.3755181 | W28: =(Parameters!$B$10*H28^Parameters!$B$9+Parameters!$B$11*V28^Parameters!$B$9)^(Parameters!$B$7/Parameters!$B$9)*O28 -> 1.3794482 | X28: =W28 - D28 - E28 - LN(1+EXP(Parameters!$B$21*C28))/Parameters!$B$21 - IF(C28>0, 0,Parameters!$B$6*C28^2/F28) -> 1.0810543 | Y28: =EXP(-Parameters!$B$55*A28) -> 0.69600391 | Z28: =IF(X28>0,X28^(1-Parameters!$B$52)/(1-Parameters!$B$52)*Y28*Parameters!$B$65,-10+X28*1000) -> -1.9350715 | AC28: =C28*$J28*$K28 -> 1.0078621 | AD28: =D28*$J28*$K28 -> 8.538547 | AE28: =I28*J28*K28 -> 1.9594518 | AF28: =F28*J28*K28 -> 31.640188 | AG28: =G28*J28*K28 -> 88.101822 | AH28: =V28*J28*K28 -> 47.827871 | AI28: =AH28/AH$4*100 -> 117.70803 | AJ28: =W28*J28*K28 -> 175.69345 | AK28: =X28*J28*K28 -> 137.68851 | AL28: =LN(AJ28)-LN(AJ27) -> 0.020858832 | AM28: =LN(AK28)-LN(AK27) -> 0.019171731 | AN28: =AVERAGE(AL26:AL30) -> 0.020836996 | AO28: =AVERAGE(AM26:AM30) -> 0.020171018 | AQ28: =W28*K28*J28 -> 175.69345 | AR28: =Parameters!$B$7*W28*(W28/O28)^(-Parameters!$B$9/Parameters!$B$7)*Parameters!$B$11*(V28)^(Parameters!$B$9-T28)*((1-2*Parameters!$B$5*C28/F28)*Parameters!$B$19*(F28+Parameters!$B$20)^(T28-1)-(1-2*Parameters!$B$5*D28/G28)*(Parameters!$B$18)*(G28)^(T28-1)) -> 0.18342822 | AS28: =((C29-C27)/2-(F29-F27)/F28/2*C28)/(F28/2/Parameters!$B$5-C28)-((D29-D27)/D28-(G29-G27)/G28)/(G28/2/Parameters!$B$5/D28-1) -> 0.0057421171 | AT28: =+Parameters!$B$5*C28^2/F28^2-Parameters!$B$5*D28^2/G28^2 -> -0.0083781983 | AU28: =EXP(-Parameters!$B$42*'6states'!A28)*(Parameters!$B$37*EXP(-Parameters!$B$38*Parameters!$E$25*'6states'!I28/('6states'!F28+'6states'!I28))*(1/Parameters!$B$38/Parameters!$E$25+'6states'!I28/('6states'!F28+'6states'!I28))-Parameters!$B$37/Parameters!$B$38/Parameters!$E$25*EXP(-Parameters!$B$38*Parameters!$E$25)+Parameters!$B$39) -> 0.63618587 | AV28: =J28*K28*EXP(-Parameters!$B$42*'6states'!A28)*(Parameters!$B$37*EXP(-Parameters!$B$38*Parameters!$E$25*'6states'!I28/('6states'!F28+'6states'!I28))*(1/Parameters!$B$38/Parameters!$E$25+'6states'!I28/('6states'!F28+'6states'!I28))-Parameters!$B$37/Parameters!$B$38/Parameters!$E$25*EXP(-Parameters!$B$38*Parameters!$E$25)+Parameters!$B$39) -> 81.027829 | AW28: =1000*(AR28+AS28+AT28)/(EXP(-Parameters!$B$42*A28)*((C28<0)*Parameters!$B$37*EXP(-Parameters!$B$38*AF28)+(C28>=0)*Parameters!$B$41)) -> 252.3756 | AX28: =1-W28/'6states,ExoDamages'!T28 -> 0.071088483 | AY28: =-Y28*W28*X28^(-Parameters!B$52)*Parameters!B$46*Parameters!B$45*N28 -> -1.8368256e-05 | AZ28: =1000*EXP(-(Parameters!$B$54)*'6states'!A28)*AQ28*Parameters!B$46*Parameters!B$45*N28 -> 1.6082402 | BA28: =SUM(AZ28:AZ$204)*EXP(Parameters!$B$54*A28) -> 323.50081 | BB28: =(C28+D28+E28)/W28 -> 0.2160988 | BF28: =SUM(AY28:AY226)/Y28 -> -0.0020159207 | BG28: =BF28/Parameters!$B$45 -> -3.3598679 | BH28: =1-BG27/BG28 -> 0.0020196961 | BK28: =-EXP(-Parameters!B$42*'6states'!A28)*(-Parameters!B$37/Parameters!B$38/Parameters!E$25*(EXP(-Parameters!B$38*Parameters!E$25*'6states'!I28/('6states'!F28+'6states'!I28))-EXP(-Parameters!B$38*Parameters!E$25))+Parameters!B$37*'6states'!F28/('6states'!F28+'6states'!I28)*EXP(-Parameters!B$38*Parameters!E$25*'6states'!I28/('6states'!F28+'6states'!I28))) -> -0.36882198 | BL28: =-J28*K28*EXP(-Parameters!B$42*'6states'!A28)*(-Parameters!B$37/Parameters!B$38/Parameters!E$25*(EXP(-Parameters!B$38*Parameters!E$25*'6states'!I28/('6states'!F28+'6states'!I28))-EXP(-Parameters!B$38*Parameters!E$25)) + Parameters!B$37*'6states'!F28/('6states'!F28+'6states'!I28)*EXP(-Parameters!B$38*Parameters!E$25*'6states'!I28/('6states'!F28+'6states'!I28))) -> -46.97502 | BM28: =I28/(F28+I28) -> 0.058317643 | BS28: =EXP(-Parameters!$B$56*A28)*BF28*BL28 -> 0.014566029 | BT28: =-EXP((Parameters!$B$56)*F28)*SUM(BS28:BS36) -> -0.1393432 | BU28: =X28^-Parameters!B$52/(1-2*Parameters!B$5*'6states'!D28/'6states'!G28) -> 1.1165577 | BV28: =BU28/BU27 -> 0.99871253 | BW28: =$X28^-Parameters!$B$52/(1-2*Parameters!$B$5*'6states'!$E28/'6states'!$H28) -> 1.029169 | BX28: =BW28/BW27 -> 1.0063451 | BY28: =($X28^-Parameters!$B$52*(1/(1+EXP(-C28)) + IF(C28<0,2*Parameters!$B$6*C28/F28,0)) + BQ28*(1/(1+EXP((C28-Parameters!$B$22)*Parameters!$B$21))))/(1-IF(C28>0,2*Parameters!$B$5*C28/F28,0)) -> 0.48259114 | BZ28: =BY28/BY27 -> 1.0050054 | CA28: =BY28-BY27 -> 0.0024035299 | CB28: =(1/$T28-1/Parameters!$B$13) * LN(Parameters!$B$18) / LN(P28) -> 0.23732085 | CC28: =(Parameters!$B$18*'6states'!T28^+Parameters!$B$19*Parameters!$B$25^'6states'!T28)^((1-'6states'!T28)/'6states'!T28)*Parameters!$B$18*Parameters!$B$26^('6states'!T28-1) -> 0.2572233 | CD28: =(LN(CC28)-LN(CC$4))/ LN(P28) -> 0.26085079 | CE28: =1-2^-CB28 -> 0.15168078 | CF28: =1-2^-CC28 -> 0.16330327
A29: =A28+Parameters!$B$65 -> 25 | B29: 2050 | C29: 0.0078169328 | D29: 0.068965892 | E29: 0.21952222 | F29: =MAX((1-Parameters!$B$4)^Parameters!B$65*F28 + C28*Parameters!B$65 - IF(C28>0,Parameters!$B$5,0)*C28^2/F28*Parameters!B$65, 0.0001) -> 0.24045674 | G29: =(1-Parameters!$B$4)^Parameters!B$65*G28+D28*Parameters!B$65-Parameters!$B$5*D28^2/G28*Parameters!B$65 -> 0.70876001 | H29: =(1-Parameters!$B$4)^Parameters!B$65*H28+E28*Parameters!B$65-Parameters!$B$5*E28^2/H28*Parameters!B$65 -> 3.5447328 | I29: =I28 *(1-Parameters!$B$4)-C28*(C28<0)*Parameters!B$65 -> 0.014416849 | J29: =J28*(1+Parameters!$B$51)^Parameters!B$65 -> 8.7726528 | K29: =K28*(1+Parameters!$B$53)^Parameters!B$65 -> 14.85173 | L29: =J29*K29*EXP(-Parameters!$B$42*'6states'!A29)*(Parameters!$B$37/Parameters!$B$38*('6states'!F29+'6states'!I29)/Parameters!$E$25*(EXP(-Parameters!$B$38*Parameters!$E$25*'6states'!I29/('6states'!F29+'6states'!I29))-EXP(-Parameters!$B$38*Parameters!$E$25)) + Parameters!$B$39*'6states'!F29) -> 19.047677 | M29: =M28+L29*Parameters!B$65 -> 2956.3352 | N29: =M29*Parameters!$B$45 -> 1.7738011 | O29: =EXP(-Parameters!$B$46/2*N29^2) -> 0.96887369 | P29: =MAX((Parameters!$B$62 + Parameters!$B$31*'6states'!A29 - '6states'!M29 + Parameters!$B$47/Parameters!$B$45)/Parameters!B$62,1) -> 14.473297 | Q29: =Parameters!B$61*EXP(-Parameters!B$60*A29) -> 0.25457821 | R29: =(1-Parameters!B$61)*P29^-Parameters!B$63 -> 0.38274829 | S29: =Parameters!B$61*EXP(-Parameters!B$60*A29)+(1-Parameters!B$61)*P29^-Parameters!B$63 -> 0.6373265 | T29: =1-S29/Parameters!$B$12 -> 0.68133675 | U29: =1/(1-T29) -> 3.138109 | V29: =(Parameters!$B$19*(F29+Parameters!$B$20)^T29+Parameters!$B$18*G29^T29)^(1/T29) -> 0.37367825 | W29: =(Parameters!$B$10*H29^Parameters!$B$9+Parameters!$B$11*V29^Parameters!$B$9)^(Parameters!$B$7/Parameters!$B$9)*O29 -> 1.3770747 | X29: =W29 - D29 - E29 - LN(1+EXP(Parameters!$B$21*C29))/Parameters!$B$21 - IF(C29>0, 0,Parameters!$B$6*C29^2/F29) -> 1.0804646 | Y29: =EXP(-Parameters!$B$55*A29) -> 0.6855732 | Z29: =IF(X29>0,X29^(1-Parameters!$B$52)/(1-Parameters!$B$52)*Y29*Parameters!$B$65,-10+X29*1000) -> -1.9064354 | AC29: =C29*$J29*$K29 -> 1.0184609 | AD29: =D29*$J29*$K29 -> 8.9855019 | AE29: =I29*J29*K29 -> 1.8783578 | AF29: =F29*J29*K29 -> 31.328885 | AG29: =G29*J29*K29 -> 92.343683 | AH29: =V29*J29*K29 -> 48.686192 | AI29: =AH29/AH$4*100 -> 119.82042 | AJ29: =W29*J29*K29 -> 179.41778 | AK29: =X29*J29*K29 -> 140.77273 | AL29: =LN(AJ29)-LN(AJ28) -> 0.02097637 | AM29: =LN(AK29)-LN(AK28) -> 0.022152785 | AN29: =AVERAGE(AL27:AL31) -> 0.020905046 | AO29: =AVERAGE(AM27:AM31) -> 0.019587451 | AQ29: =W29*K29*J29 -> 179.41778 | AR29: =Parameters!$B$7*W29*(W29/O29)^(-Parameters!$B$9/Parameters!$B$7)*Parameters!$B$11*(V29)^(Parameters!$B$9-T29)*((1-2*Parameters!$B$5*C29/F29)*Parameters!$B$19*(F29+Parameters!$B$20)^(T29-1)-(1-2*Parameters!$B$5*D29/G29)*(Parameters!$B$18)*(G29)^(T29-1)) -> 0.18629004 | AS29: =((C30-C28)/2-(F30-F28)/F29/2*C29)/(F29/2/Parameters!$B$5-C29)-((D30-D28)/D29-(G30-G28)/G29)/(G29/2/Parameters!$B$5/D29-1) -> 0.0030417602 | AT29: =+Parameters!$B$5*C29^2/F29^2-Parameters!$B$5*D29^2/G29^2 -> -0.008411448 | AU29: =EXP(-Parameters!$B$42*'6states'!A29)*(Parameters!$B$37*EXP(-Parameters!$B$38*Parameters!$E$25*'6states'!I29/('6states'!F29+'6states'!I29))*(1/Parameters!$B$38/Parameters!$E$25+'6states'!I29/('6states'!F29+'6states'!I29))-Parameters!$B$37/Parameters!$B$38/Parameters!$E$25*EXP(-Parameters!$B$38*Parameters!$E$25)+Parameters!$B$39) -> 0.63162596 | AV29: =J29*K29*EXP(-Parameters!$B$42*'6states'!A29)*(Parameters!$B$37*EXP(-Parameters!$B$38*Parameters!$E$25*'6states'!I29/('6states'!F29+'6states'!I29))*(1/Parameters!$B$38/Parameters!$E$25+'6states'!I29/('6states'!F29+'6states'!I29))-Parameters!$B$37/Parameters!$B$38/Parameters!$E$25*EXP(-Parameters!$B$38*Parameters!$E$25)+Parameters!$B$39) -> 82.293958 | AW29: =1000*(AR29+AS29+AT29)/(EXP(-Parameters!$B$42*A29)*((C29<0)*Parameters!$B$37*EXP(-Parameters!$B$38*AF29)+(C29>=0)*Parameters!$B$41)) -> 255.0928 | AX29: =1-W29/'6states,ExoDamages'!T29 -> 0.072267285 | AY29: =-Y29*W29*X29^(-Parameters!B$52)*Parameters!B$46*Parameters!B$45*N29 -> -1.8192372e-05 | AZ29: =1000*EXP(-(Parameters!$B$54)*'6states'!A29)*AQ29*Parameters!B$46*Parameters!B$45*N29 -> 1.5959685 | BA29: =SUM(AZ29:AZ$204)*EXP(Parameters!$B$54*A29) -> 331.18969 | BB29: =(C29+D29+E29)/W29 -> 0.21516991 | BF29: =SUM(AY29:AY227)/Y29 -> -0.0020197996 | BG29: =BF29/Parameters!$B$45 -> -3.3663326 | BH29: =1-BG28/BG29 -> 0.0019204065 | BK29: =-EXP(-Parameters!B$42*'6states'!A29)*(-Parameters!B$37/Parameters!B$38/Parameters!E$25*(EXP(-Parameters!B$38*Parameters!E$25*'6states'!I29/('6states'!F29+'6states'!I29))-EXP(-Parameters!B$38*Parameters!E$25))+Parameters!B$37*'6states'!F29/('6states'!F29+'6states'!I29)*EXP(-Parameters!B$38*Parameters!E$25*'6states'!I29/('6states'!F29+'6states'!I29))) -> -0.39420603 | BL29: =-J29*K29*EXP(-Parameters!B$42*'6states'!A29)*(-Parameters!B$37/Parameters!B$38/Parameters!E$25*(EXP(-Parameters!B$38*Parameters!E$25*'6states'!I29/('6states'!F29+'6states'!I29))-EXP(-Parameters!B$38*Parameters!E$25)) + Parameters!B$37*'6states'!F29/('6states'!F29+'6states'!I29)*EXP(-Parameters!B$38*Parameters!E$25*'6states'!I29/('6states'!F29+'6states'!I29))) -> -51.360737 | BM29: =I29/(F29+I29) -> 0.056564703 | BS29: =EXP(-Parameters!$B$56*A29)*BF29*BL29 -> 0.014759284 | BT29: =-EXP((Parameters!$B$56)*F29)*SUM(BS29:BS37) -> -0.1404089 | BU29: =X29^-Parameters!B$52/(1-2*Parameters!B$5*'6states'!D29/'6states'!G29) -> 1.1184576 | BV29: =BU29/BU28 -> 1.0017016 | BW29: =$X29^-Parameters!$B$52/(1-2*Parameters!$B$5*'6states'!$E29/'6states'!$H29) -> 1.028138 | BX29: =BW29/BW28 -> 0.99899819 | BY29: =($X29^-Parameters!$B$52*(1/(1+EXP(-C29)) + IF(C29<0,2*Parameters!$B$6*C29/F29,0)) + BQ29*(1/(1+EXP((C29-Parameters!$B$22)*Parameters!$B$21))))/(1-IF(C29>0,2*Parameters!$B$5*C29/F29,0)) -> 0.48360005 | BZ29: =BY29/BY28 -> 1.0020906 | CA29: =BY29-BY28 -> 0.0010089121 | CB29: =(1/$T29-1/Parameters!$B$13) * LN(Parameters!$B$18) / LN(P29) -> 0.23729107 | CC29: =(Parameters!$B$18*'6states'!T29^+Parameters!$B$19*Parameters!$B$25^'6states'!T29)^((1-'6states'!T29)/'6states'!T29)*Parameters!$B$18*Parameters!$B$26^('6states'!T29-1) -> 0.25950906 | CD29: =(LN(CC29)-LN(CC$4))/ LN(P29) -> 0.25944249 | CE29: =1-2^-CB29 -> 0.15166327 | CF29: =1-2^-CC29 -> 0.16462786
A30: =A29+Parameters!$B$65 -> 26 | B30: 2051 | C30: 0.0076891444 | D30: 0.069905356 | E30: 0.21876147 | F30: =MAX((1-Parameters!$B$4)^Parameters!B$65*F29 + C29*Parameters!B$65 - IF(C29>0,Parameters!$B$5,0)*C29^2/F29*Parameters!B$65, 0.0001) -> 0.23289482 | G30: =(1-Parameters!$B$4)^Parameters!B$65*G29+D29*Parameters!B$65-Parameters!$B$5*D29^2/G29*Parameters!B$65 -> 0.72643417 | H30: =(1-Parameters!$B$4)^Parameters!B$65*H29+E29*Parameters!B$65-Parameters!$B$5*E29^2/H29*Parameters!B$65 -> 3.5276965 | I30: =I29 *(1-Parameters!$B$4)-C29*(C29<0)*Parameters!B$65 -> 0.013510029 | J30: =J29*(1+Parameters!$B$51)^Parameters!B$65 -> 8.7980935 | K30: =K29*(1+Parameters!$B$53)^Parameters!B$65 -> 15.148764 | L30: =J30*K30*EXP(-Parameters!$B$42*'6states'!A30)*(Parameters!$B$37/Parameters!$B$38*('6states'!F30+'6states'!I30)/Parameters!$E$25*(EXP(-Parameters!$B$38*Parameters!$E$25*'6states'!I30/('6states'!F30+'6states'!I30))-EXP(-Parameters!$B$38*Parameters!$E$25)) + Parameters!$B$39*'6states'!F30) -> 18.708929 | M30: =M29+L30*Parameters!B$65 -> 2975.0441 | N30: =M30*Parameters!$B$45 -> 1.7850264 | O30: =EXP(-Parameters!$B$46/2*N30^2) -> 0.96848478 | P30: =MAX((Parameters!$B$62 + Parameters!$B$31*'6states'!A30 - '6states'!M30 + Parameters!$B$47/Parameters!$B$45)/Parameters!B$62,1) -> 15.163118 | Q30: =Parameters!B$61*EXP(-Parameters!B$60*A30) -> 0.24779656 | R30: =(1-Parameters!B$61)*P30^-Parameters!B$63 -> 0.38097033 | S30: =Parameters!B$61*EXP(-Parameters!B$60*A30)+(1-Parameters!B$61)*P30^-Parameters!B$63 -> 0.62876689 | T30: =1-S30/Parameters!$B$12 -> 0.68561655 | U30: =1/(1-T30) -> 3.1808291 | V30: =(Parameters!$B$19*(F30+Parameters!$B$20)^T30+Parameters!$B$18*G30^T30)^(1/T30) -> 0.37226284 | W30: =(Parameters!$B$10*H30^Parameters!$B$9+Parameters!$B$11*V30^Parameters!$B$9)^(Parameters!$B$7/Parameters!$B$9)*O30 -> 1.3746653 | X30: =W30 - D30 - E30 - LN(1+EXP(Parameters!$B$21*C30))/Parameters!$B$21 - IF(C30>0, 0,Parameters!$B$6*C30^2/F30) -> 1.0779929 | Y30: =EXP(-Parameters!$B$55*A30) -> 0.67529881 | Z30: =IF(X30>0,X30^(1-Parameters!$B$52)/(1-Parameters!$B$52)*Y30*Parameters!$B$65,-10+X30*1000) -> -1.8793704 | AC30: =C30*$J30*$K30 -> 1.0248111 | AD30: =D30*$J30*$K30 -> 9.3170031 | AE30: =I30*J30*K30 -> 1.80062 | AF30: =F30*J30*K30 -> 31.040279 | AG30: =G30*J30*K30 -> 96.819326 | AH30: =V30*J30*K30 -> 49.615283 | AI30: =AH30/AH$4*100 -> 122.10699 | AJ30: =W30*J30*K30 -> 183.21574 | AK30: =X30*J30*K30 -> 143.67516 | AL30: =LN(AJ30)-LN(AJ29) -> 0.020947268 | AM30: =LN(AK30)-LN(AK29) -> 0.020408212 | AN30: =AVERAGE(AL28:AL32) -> 0.021006891 | AO30: =AVERAGE(AM28:AM32) -> 0.020056365 | AQ30: =W30*K30*J30 -> 183.21574 | AR30: =Parameters!$B$7*W30*(W30/O30)^(-Parameters!$B$9/Parameters!$B$7)*Parameters!$B$11*(V30)^(Parameters!$B$9-T30)*((1-2*Parameters!$B$5*C30/F30)*Parameters!$B$19*(F30+Parameters!$B$20)^(T30-1)-(1-2*Parameters!$B$5*D30/G30)*(Parameters!$B$18)*(G30)^(T30-1)) -> 0.187833 | AS30: =((C31-C29)/2-(F31-F29)/F30/2*C30)/(F30/2/Parameters!$B$5-C30)-((D31-D29)/D30-(G31-G29)/G30)/(G30/2/Parameters!$B$5/D30-1) -> 0.012567781 | AT30: =+Parameters!$B$5*C30^2/F30^2-Parameters!$B$5*D30^2/G30^2 -> -0.0081703459 | AU30: =EXP(-Parameters!$B$42*'6states'!A30)*(Parameters!$B$37*EXP(-Parameters!$B$38*Parameters!$E$25*'6states'!I30/('6states'!F30+'6states'!I30))*(1/Parameters!$B$38/Parameters!$E$25+'6states'!I30/('6states'!F30+'6states'!I30))-Parameters!$B$37/Parameters!$B$38/Parameters!$E$25*EXP(-Parameters!$B$38*Parameters!$E$25)+Parameters!$B$39) -> 0.62715406 | AV30: =J30*K30*EXP(-Parameters!$B$42*'6states'!A30)*(Parameters!$B$37*EXP(-Parameters!$B$38*Parameters!$E$25*'6states'!I30/('6states'!F30+'6states'!I30))*(1/Parameters!$B$38/Parameters!$E$25+'6states'!I30/('6states'!F30+'6states'!I30))-Parameters!$B$37/Parameters!$B$38/Parameters!$E$25*EXP(-Parameters!$B$38*Parameters!$E$25)+Parameters!$B$39) -> 83.587247 | AW30: =1000*(AR30+AS30+AT30)/(EXP(-Parameters!$B$42*A30)*((C30<0)*Parameters!$B$37*EXP(-Parameters!$B$38*AF30)+(C30>=0)*Parameters!$B$41)) -> 273.7637 | AX30: =1-W30/'6states,ExoDamages'!T30 -> 0.073447677 | AY30: =-Y30*W30*X30^(-Parameters!B$52)*Parameters!B$46*Parameters!B$45*N30 -> -1.8057326e-05 | AZ30: =1000*EXP(-(Parameters!$B$54)*'6states'!A30)*AQ30*Parameters!B$46*Parameters!B$45*N30 -> 1.5834983 | BA30: =SUM(AZ30:AZ$204)*EXP(Parameters!$B$54*A30) -> 339.04565 | BB30: =(C30+D30+E30)/W30 -> 0.21558408 | BF30: =SUM(AY30:AY228)/Y30 -> -0.0020235902 | BG30: =BF30/Parameters!$B$45 -> -3.3726504 | BH30: =1-BG29/BG30 -> 0.0018732388 | BK30: =-EXP(-Parameters!B$42*'6states'!A30)*(-Parameters!B$37/Parameters!B$38/Parameters!E$25*(EXP(-Parameters!B$38*Parameters!E$25*'6states'!I30/('6states'!F30+'6states'!I30))-EXP(-Parameters!B$38*Parameters!E$25))+Parameters!B$37*'6states'!F30/('6states'!F30+'6states'!I30)*EXP(-Parameters!B$38*Parameters!E$25*'6states'!I30/('6states'!F30+'6states'!I30))) -> -0.42102622 | BL30: =-J30*K30*EXP(-Parameters!B$42*'6states'!A30)*(-Parameters!B$37/Parameters!B$38/Parameters!E$25*(EXP(-Parameters!B$38*Parameters!E$25*'6states'!I30/('6states'!F30+'6states'!I30))-EXP(-Parameters!B$38*Parameters!E$25)) + Parameters!B$37*'6states'!F30/('6states'!F30+'6states'!I30)*EXP(-Parameters!B$38*Parameters!E$25*'6states'!I30/('6states'!F30+'6states'!I30))) -> -56.114478 | BM30: =I30/(F30+I30) -> 0.054828584 | BS30: =EXP(-Parameters!$B$56*A30)*BF30*BL30 -> 0.014943361 | BT30: =-EXP((Parameters!$B$56)*F30)*SUM(BS30:BS38) -> -0.14136317 | BU30: =X30^-Parameters!B$52/(1-2*Parameters!B$5*'6states'!D30/'6states'!G30) -> 1.1189363 | BV30: =BU30/BU29 -> 1.000428 | BW30: =$X30^-Parameters!$B$52/(1-2*Parameters!$B$5*'6states'!$E30/'6states'!$H30) -> 1.0315181 | BX30: =BW30/BW29 -> 1.0032876 | BY30: =($X30^-Parameters!$B$52*(1/(1+EXP(-C30)) + IF(C30<0,2*Parameters!$B$6*C30/F30,0)) + BQ30*(1/(1+EXP((C30-Parameters!$B$22)*Parameters!$B$21))))/(1-IF(C30>0,2*Parameters!$B$5*C30/F30,0)) -> 0.48559315 | BZ30: =BY30/BY29 -> 1.0041214 | CA30: =BY30-BY29 -> 0.0019930932 | CB30: =(1/$T30-1/Parameters!$B$13) * LN(Parameters!$B$18) / LN(P30) -> 0.23724172 | CC30: =(Parameters!$B$18*'6states'!T30^+Parameters!$B$19*Parameters!$B$25^'6states'!T30)^((1-'6states'!T30)/'6states'!T30)*Parameters!$B$18*Parameters!$B$26^('6states'!T30-1) -> 0.26167649 | CD30: =(LN(CC30)-LN(CC$4))/ LN(P30) -> 0.25805865 | CE30: =1-2^-CB30 -> 0.15163425 | CF30: =1-2^-CC30 -> 0.16588193
A31: =A30+Parameters!$B$65 -> 27 | B31: 2052 | C31: 0.0074664937 | D31: 0.06884833 | E31: 0.22353748 | F31: =MAX((1-Parameters!$B$4)^Parameters!B$65*F30 + C30*Parameters!B$65 - IF(C30>0,Parameters!$B$5,0)*C30^2/F30*Parameters!B$65, 0.0001) -> 0.22568102 | G31: =(1-Parameters!$B$4)^Parameters!B$65*G30+D30*Parameters!B$65-Parameters!$B$5*D30^2/G30*Parameters!B$65 -> 0.74391977 | H31: =(1-Parameters!$B$4)^Parameters!B$65*H30+E30*Parameters!B$65-Parameters!$B$5*E30^2/H30*Parameters!B$65 -> 3.5109999 | I31: =I30 *(1-Parameters!$B$4)-C30*(C30<0)*Parameters!B$65 -> 0.012660248 | J31: =J30*(1+Parameters!$B$51)^Parameters!B$65 -> 8.823608 | K31: =K30*(1+Parameters!$B$53)^Parameters!B$65 -> 15.45174 | L31: =J31*K31*EXP(-Parameters!$B$42*'6states'!A31)*(Parameters!$B$37/Parameters!$B$38*('6states'!F31+'6states'!I31)/Parameters!$E$25*(EXP(-Parameters!$B$38*Parameters!$E$25*'6states'!I31/('6states'!F31+'6states'!I31))-EXP(-Parameters!$B$38*Parameters!$E$25)) + Parameters!$B$39*'6states'!F31) -> 18.386563 | M31: =M30+L31*Parameters!B$65 -> 2993.4306 | N31: =M31*Parameters!$B$45 -> 1.7960584 | O31: =EXP(-Parameters!$B$46/2*N31^2) -> 0.96810033 | P31: =MAX((Parameters!$B$62 + Parameters!$B$31*'6states'!A31 - '6states'!M31 + Parameters!$B$47/Parameters!$B$45)/Parameters!B$62,1) -> 15.859387 | Q31: =Parameters!B$61*EXP(-Parameters!B$60*A31) -> 0.24119557 | R31: =(1-Parameters!B$61)*P31^-Parameters!B$63 -> 0.37926378 | S31: =Parameters!B$61*EXP(-Parameters!B$60*A31)+(1-Parameters!B$61)*P31^-Parameters!B$63 -> 0.62045935 | T31: =1-S31/Parameters!$B$12 -> 0.68977033 | U31: =1/(1-T31) -> 3.2234183 | V31: =(Parameters!$B$19*(F31+Parameters!$B$20)^T31+Parameters!$B$18*G31^T31)^(1/T31) -> 0.3710294 | W31: =(Parameters!$B$10*H31^Parameters!$B$9+Parameters!$B$11*V31^Parameters!$B$9)^(Parameters!$B$7/Parameters!$B$9)*O31 -> 1.3723476 | X31: =W31 - D31 - E31 - LN(1+EXP(Parameters!$B$21*C31))/Parameters!$B$21 - IF(C31>0, 0,Parameters!$B$6*C31^2/F31) -> 1.072158 | Y31: =EXP(-Parameters!$B$55*A31) -> 0.6651784 | Z31: =IF(X31>0,X31^(1-Parameters!$B$52)/(1-Parameters!$B$52)*Y31*Parameters!$B$65,-10+X31*1000) -> -1.8547249 | AC31: =C31*$J31*$K31 -> 1.0179824 | AD31: =D31*$J31*$K31 -> 9.3867878 | AE31: =I31*J31*K31 -> 1.7260994 | AF31: =F31*J31*K31 -> 30.769372 | AG31: =G31*J31*K31 -> 101.42609 | AH31: =V31*J31*K31 -> 50.586183 | AI31: =AH31/AH$4*100 -> 124.49645 | AJ31: =W31*J31*K31 -> 187.106 | AK31: =X31*J31*K31 -> 146.17813 | AL31: =LN(AJ31)-LN(AJ30) -> 0.021010949 | AM31: =LN(AK31)-LN(AK30) -> 0.017270992 | AN31: =AVERAGE(AL29:AL33) -> 0.02108928 | AO31: =AVERAGE(AM29:AM33) -> 0.019910526 | AQ31: =W31*K31*J31 -> 187.106 | AR31: =Parameters!$B$7*W31*(W31/O31)^(-Parameters!$B$9/Parameters!$B$7)*Parameters!$B$11*(V31)^(Parameters!$B$9-T31)*((1-2*Parameters!$B$5*C31/F31)*Parameters!$B$19*(F31+Parameters!$B$20)^(T31-1)-(1-2*Parameters!$B$5*D31/G31)*(Parameters!$B$18)*(G31)^(T31-1)) -> 0.18880852 | AS31: =((C32-C30)/2-(F32-F30)/F31/2*C31)/(F31/2/Parameters!$B$5-C31)-((D32-D30)/D31-(G32-G30)/G31)/(G31/2/Parameters!$B$5/D31-1) -> 0.010329235 | AT31: =+Parameters!$B$5*C31^2/F31^2-Parameters!$B$5*D31^2/G31^2 -> -0.0074705735 | AU31: =EXP(-Parameters!$B$42*'6states'!A31)*(Parameters!$B$37*EXP(-Parameters!$B$38*Parameters!$E$25*'6states'!I31/('6states'!F31+'6states'!I31))*(1/Parameters!$B$38/Parameters!$E$25+'6states'!I31/('6states'!F31+'6states'!I31))-Parameters!$B$37/Parameters!$B$38/Parameters!$E$25*EXP(-Parameters!$B$38*Parameters!$E$25)+Parameters!$B$39) -> 0.62275782 | AV31: =J31*K31*EXP(-Parameters!$B$42*'6states'!A31)*(Parameters!$B$37*EXP(-Parameters!$B$38*Parameters!$E$25*'6states'!I31/('6states'!F31+'6states'!I31))*(1/Parameters!$B$38/Parameters!$E$25+'6states'!I31/('6states'!F31+'6states'!I31))-Parameters!$B$37/Parameters!$B$38/Parameters!$E$25*EXP(-Parameters!$B$38*Parameters!$E$25)+Parameters!$B$39) -> 84.90686 | AW31: =1000*(AR31+AS31+AT31)/(EXP(-Parameters!$B$42*A31)*((C31<0)*Parameters!$B$37*EXP(-Parameters!$B$38*AF31)+(C31>=0)*Parameters!$B$41)) -> 275.70486 | AX31: =1-W31/'6states,ExoDamages'!T31 -> 0.074578174 | AY31: =-Y31*W31*X31^(-Parameters!B$52)*Parameters!B$46*Parameters!B$45*N31 -> -1.799785e-05 | AZ31: =1000*EXP(-(Parameters!$B$54)*'6states'!A31)*AQ31*Parameters!B$46*Parameters!B$45*N31 -> 1.5709942 | BA31: =SUM(AZ31:AZ$204)*EXP(Parameters!$B$54*A31) -> 347.07241 | BB31: =(C31+D31+E31)/W31 -> 0.21849589 | BF31: =SUM(AY31:AY229)/Y31 -> -0.0020272317 | BG31: =BF31/Parameters!$B$45 -> -3.3787195 | BH31: =1-BG30/BG31 -> 0.001796285 | BK31: =-EXP(-Parameters!B$42*'6states'!A31)*(-Parameters!B$37/Parameters!B$38/Parameters!E$25*(EXP(-Parameters!B$38*Parameters!E$25*'6states'!I31/('6states'!F31+'6states'!I31))-EXP(-Parameters!B$38*Parameters!E$25))+Parameters!B$37*'6states'!F31/('6states'!F31+'6states'!I31)*EXP(-Parameters!B$38*Parameters!E$25*'6states'!I31/('6states'!F31+'6states'!I31))) -> -0.44916536 | BL31: =-J31*K31*EXP(-Parameters!B$42*'6states'!A31)*(-Parameters!B$37/Parameters!B$38/Parameters!E$25*(EXP(-Parameters!B$38*Parameters!E$25*'6states'!I31/('6states'!F31+'6states'!I31))-EXP(-Parameters!B$38*Parameters!E$25)) + Parameters!B$37*'6states'!F31/('6states'!F31+'6states'!I31)*EXP(-Parameters!B$38*Parameters!E$25*'6states'!I31/('6states'!F31+'6states'!I31))) -> -61.239248 | BM31: =I31/(F31+I31) -> 0.053118154 | BS31: =EXP(-Parameters!$B$56*A31)*BF31*BL31 -> 0.015111552 | BT31: =-EXP((Parameters!$B$56)*F31)*SUM(BS31:BS39) -> -0.14223154 | BU31: =X31^-Parameters!B$52/(1-2*Parameters!B$5*'6states'!D31/'6states'!G31) -> 1.116977 | BV31: =BU31/BU30 -> 0.99824896 | BW31: =$X31^-Parameters!$B$52/(1-2*Parameters!$B$5*'6states'!$E31/'6states'!$H31) -> 1.0430456 | BX31: =BW31/BW30 -> 1.0111753 | BY31: =($X31^-Parameters!$B$52*(1/(1+EXP(-C31)) + IF(C31<0,2*Parameters!$B$6*C31/F31,0)) + BQ31*(1/(1+EXP((C31-Parameters!$B$22)*Parameters!$B$21))))/(1-IF(C31>0,2*Parameters!$B$5*C31/F31,0)) -> 0.48918195 | BZ31: =BY31/BY30 -> 1.0073906 | CA31: =BY31-BY30 -> 0.0035888037 | CB31: =(1/$T31-1/Parameters!$B$13) * LN(Parameters!$B$18) / LN(P31) -> 0.23717378 | CC31: =(Parameters!$B$18*'6states'!T31^+Parameters!$B$19*Parameters!$B$25^'6states'!T31)^((1-'6states'!T31)/'6states'!T31)*Parameters!$B$18*Parameters!$B$26^('6states'!T31-1) -> 0.2637326 | CD31: =(LN(CC31)-LN(CC$4))/ LN(P31) -> 0.25669857 | CE31: =1-2^-CB31 -> 0.1515943 | CF31: =1-2^-CC31 -> 0.16706986
A32: =A31+Parameters!$B$65 -> 28 | B32: 2053 | C32: 0.0073955989 | D32: 0.070097231 | E32: 0.22187573 | F32: =MAX((1-Parameters!$B$4)^Parameters!B$65*F31 + C31*Parameters!B$65 - IF(C31>0,Parameters!$B$5,0)*C31^2/F31*Parameters!B$65, 0.0001) -> 0.21870516 | G32: =(1-Parameters!$B$4)^Parameters!B$65*G31+D31*Parameters!B$65-Parameters!$B$5*D31^2/G31*Parameters!B$65 -> 0.75960377 | H32: =(1-Parameters!$B$4)^Parameters!B$65*H31+E31*Parameters!B$65-Parameters!$B$5*E31^2/H31*Parameters!B$65 -> 3.4994634 | I32: =I31 *(1-Parameters!$B$4)-C31*(C31<0)*Parameters!B$65 -> 0.011863919 | J32: =J31*(1+Parameters!$B$51)^Parameters!B$65 -> 8.8491964 | K32: =K31*(1+Parameters!$B$53)^Parameters!B$65 -> 15.760775 | L32: =J32*K32*EXP(-Parameters!$B$42*'6states'!A32)*(Parameters!$B$37/Parameters!$B$38*('6states'!F32+'6states'!I32)/Parameters!$E$25*(EXP(-Parameters!$B$38*Parameters!$E$25*'6states'!I32/('6states'!F32+'6states'!I32))-EXP(-Parameters!$B$38*Parameters!$E$25)) + Parameters!$B$39*'6states'!F32) -> 18.071988 | M32: =M31+L32*Parameters!B$65 -> 3011.5026 | N32: =M32*Parameters!$B$45 -> 1.8069016 | O32: =EXP(-Parameters!$B$46/2*N32^2) -> 0.9677203 | P32: =MAX((Parameters!$B$62 + Parameters!$B$31*'6states'!A32 - '6states'!M32 + Parameters!$B$47/Parameters!$B$45)/Parameters!B$62,1) -> 16.561947 | Q32: =Parameters!B$61*EXP(-Parameters!B$60*A32) -> 0.23477042 | R32: =(1-Parameters!B$61)*P32^-Parameters!B$63 -> 0.37762337 | S32: =Parameters!B$61*EXP(-Parameters!B$60*A32)+(1-Parameters!B$61)*P32^-Parameters!B$63 -> 0.61239379 | T32: =1-S32/Parameters!$B$12 -> 0.6938031 | U32: =1/(1-T32) -> 3.2658724 | V32: =(Parameters!$B$19*(F32+Parameters!$B$20)^T32+Parameters!$B$18*G32^T32)^(1/T32) -> 0.36950301 | W32: =(Parameters!$B$10*H32^Parameters!$B$9+Parameters!$B$11*V32^Parameters!$B$9)^(Parameters!$B$7/Parameters!$B$9)*O32 -> 1.370349 | X32: =W32 - D32 - E32 - LN(1+EXP(Parameters!$B$21*C32))/Parameters!$B$21 - IF(C32>0, 0,Parameters!$B$6*C32^2/F32) -> 1.0706363 | Y32: =EXP(-Parameters!$B$55*A32) -> 0.65520966 | Z32: =IF(X32>0,X32^(1-Parameters!$B$52)/(1-Parameters!$B$52)*Y32*Parameters!$B$65,-10+X32*1000) -> -1.8278374 | AC32: =C32*$J32*$K32 -> 1.0314656 | AD32: =D32*$J32*$K32 -> 9.7764742 | AE32: =I32*J32*K32 -> 1.654663 | AF32: =F32*J32*K32 -> 30.50285 | AG32: =G32*J32*K32 -> 105.94208 | AH32: =V32*J32*K32 -> 51.534656 | AI32: =AH32/AH$4*100 -> 126.83071 | AJ32: =W32*J32*K32 -> 191.12283 | AK32: =X32*J32*K32 -> 149.32185 | AL32: =LN(AJ32)-LN(AJ31) -> 0.021241038 | AM32: =LN(AK32)-LN(AK31) -> 0.021278105 | AN32: =AVERAGE(AL30:AL34) -> 0.021183606 | AO32: =AVERAGE(AM30:AM34) -> 0.019634884 | AQ32: =W32*K32*J32 -> 191.12283 | AR32: =Parameters!$B$7*W32*(W32/O32)^(-Parameters!$B$9/Parameters!$B$7)*Parameters!$B$11*(V32)^(Parameters!$B$9-T32)*((1-2*Parameters!$B$5*C32/F32)*Parameters!$B$19*(F32+Parameters!$B$20)^(T32-1)-(1-2*Parameters!$B$5*D32/G32)*(Parameters!$B$18)*(G32)^(T32-1)) -> 0.19121282 | AS32: =((C33-C31)/2-(F33-F31)/F32/2*C32)/(F32/2/Parameters!$B$5-C32)-((D33-D31)/D32-(G33-G31)/G32)/(G32/2/Parameters!$B$5/D32-1) -> 0.0080717427 | AT32: =+Parameters!$B$5*C32^2/F32^2-Parameters!$B$5*D32^2/G32^2 -> -0.0073723601 | AU32: =EXP(-Parameters!$B$42*'6states'!A32)*(Parameters!$B$37*EXP(-Parameters!$B$38*Parameters!$E$25*'6states'!I32/('6states'!F32+'6states'!I32))*(1/Parameters!$B$38/Parameters!$E$25+'6states'!I32/('6states'!F32+'6states'!I32))-Parameters!$B$37/Parameters!$B$38/Parameters!$E$25*EXP(-Parameters!$B$38*Parameters!$E$25)+Parameters!$B$39) -> 0.61840917 | AV32: =J32*K32*EXP(-Parameters!$B$42*'6states'!A32)*(Parameters!$B$37*EXP(-Parameters!$B$38*Parameters!$E$25*'6states'!I32/('6states'!F32+'6states'!I32))*(1/Parameters!$B$38/Parameters!$E$25+'6states'!I32/('6states'!F32+'6states'!I32))-Parameters!$B$37/Parameters!$B$38/Parameters!$E$25*EXP(-Parameters!$B$38*Parameters!$E$25)+Parameters!$B$39) -> 86.249644 | AW32: =1000*(AR32+AS32+AT32)/(EXP(-Parameters!$B$42*A32)*((C32<0)*Parameters!$B$37*EXP(-Parameters!$B$38*AF32)+(C32>=0)*Parameters!$B$41)) -> 278.83173 | AX32: =1-W32/'6states,ExoDamages'!T32 -> 0.07550466 | AY32: =-Y32*W32*X32^(-Parameters!B$52)*Parameters!B$46*Parameters!B$45*N32 -> -1.7843359e-05 | AZ32: =1000*EXP(-(Parameters!$B$54)*'6states'!A32)*AQ32*Parameters!B$46*Parameters!B$45*N32 -> 1.5587259 | BA32: =SUM(AZ32:AZ$204)*EXP(Parameters!$B$54*A32) -> 355.27339 | BB32: =(C32+D32+E32)/W32 -> 0.21846155 | BF32: =SUM(AY32:AY230)/Y32 -> -0.0020306064 | BG32: =BF32/Parameters!$B$45 -> -3.3843439 | BH32: =1-BG31/BG32 -> 0.001661888 | BK32: =-EXP(-Parameters!B$42*'6states'!A32)*(-Parameters!B$37/Parameters!B$38/Parameters!E$25*(EXP(-Parameters!B$38*Parameters!E$25*'6states'!I32/('6states'!F32+'6states'!I32))-EXP(-Parameters!B$38*Parameters!E$25))+Parameters!B$37*'6states'!F32/('6states'!F32+'6states'!I32)*EXP(-Parameters!B$38*Parameters!E$25*'6states'!I32/('6states'!F32+'6states'!I32))) -> -0.47819648 | BL32: =-J32*K32*EXP(-Parameters!B$42*'6states'!A32)*(-Parameters!B$37/Parameters!B$38/Parameters!E$25*(EXP(-Parameters!B$38*Parameters!E$25*'6states'!I32/('6states'!F32+'6states'!I32))-EXP(-Parameters!B$38*Parameters!E$25)) + Parameters!B$37*'6states'!F32/('6states'!F32+'6states'!I32)*EXP(-Parameters!B$38*Parameters!E$25*'6states'!I32/('6states'!F32+'6states'!I32))) -> -66.694154 | BM32: =I32/(F32+I32) -> 0.051454943 | BS32: =EXP(-Parameters!$B$56*A32)*BF32*BL32 -> 0.015248052 | BT32: =-EXP((Parameters!$B$56)*F32)*SUM(BS32:BS40) -> -0.13283674 | BU32: =X32^-Parameters!B$52/(1-2*Parameters!B$5*'6states'!D32/'6states'!G32) -> 1.1183886 | BV32: =BU32/BU31 -> 1.0012638 | BW32: =$X32^-Parameters!$B$52/(1-2*Parameters!$B$5*'6states'!$E32/'6states'!$H32) -> 1.0444133 | BX32: =BW32/BW31 -> 1.0013112 | BY32: =($X32^-Parameters!$B$52*(1/(1+EXP(-C32)) + IF(C32<0,2*Parameters!$B$6*C32/F32,0)) + BQ32*(1/(1+EXP((C32-Parameters!$B$22)*Parameters!$B$21))))/(1-IF(C32>0,2*Parameters!$B$5*C32/F32,0)) -> 0.49087214 | BZ32: =BY32/BY31 -> 1.0034551 | CA32: =BY32-BY31 -> 0.001690186 | CB32: =(1/$T32-1/Parameters!$B$13) * LN(Parameters!$B$18) / LN(P32) -> 0.23708761 | CC32: =(Parameters!$B$18*'6states'!T32^+Parameters!$B$19*Parameters!$B$25^'6states'!T32)^((1-'6states'!T32)/'6states'!T32)*Parameters!$B$18*Parameters!$B$26^('6states'!T32-1) -> 0.26568401 | CD32: =(LN(CC32)-LN(CC$4))/ LN(P32) -> 0.25536091 | CE32: =1-2^-CB32 -> 0.15154363 | CF32: =1-2^-CC32 -> 0.16819573
A33: =A32+Parameters!$B$65 -> 29 | B33: 2054 | C33: 0.0072330551 | D33: 0.069601686 | E33: 0.22510936 | F33: =MAX((1-Parameters!$B$4)^Parameters!B$65*F32 + C32*Parameters!B$65 - IF(C32>0,Parameters!$B$5,0)*C32^2/F32*Parameters!B$65, 0.0001) -> 0.21209411 | G33: =(1-Parameters!$B$4)^Parameters!B$65*G32+D32*Parameters!B$65-Parameters!$B$5*D32^2/G32*Parameters!B$65 -> 0.77545326 | H33: =(1-Parameters!$B$4)^Parameters!B$65*H32+E32*Parameters!B$65-Parameters!$B$5*E32^2/H32*Parameters!B$65 -> 3.4871553 | I33: =I32 *(1-Parameters!$B$4)-C32*(C32<0)*Parameters!B$65 -> 0.011117678 | J33: =J32*(1+Parameters!$B$51)^Parameters!B$65 -> 8.8748591 | K33: =K32*(1+Parameters!$B$53)^Parameters!B$65 -> 16.07599 | L33: =J33*K33*EXP(-Parameters!$B$42*'6states'!A33)*(Parameters!$B$37/Parameters!$B$38*('6states'!F33+'6states'!I33)/Parameters!$E$25*(EXP(-Parameters!$B$38*Parameters!$E$25*'6states'!I33/('6states'!F33+'6states'!I33))-EXP(-Parameters!$B$38*Parameters!$E$25)) + Parameters!$B$39*'6states'!F33) -> 17.77682 | M33: =M32+L33*Parameters!B$65 -> 3029.2795 | N33: =M33*Parameters!$B$45 -> 1.8175677 | O33: =EXP(-Parameters!$B$46/2*N33^2) -> 0.96734439 | P33: =MAX((Parameters!$B$62 + Parameters!$B$31*'6states'!A33 - '6states'!M33 + Parameters!$B$47/Parameters!$B$45)/Parameters!B$62,1) -> 17.270411 | Q33: =Parameters!B$61*EXP(-Parameters!B$60*A33) -> 0.22851643 | R33: =(1-Parameters!B$61)*P33^-Parameters!B$63 -> 0.37604493 | S33: =Parameters!B$61*EXP(-Parameters!B$60*A33)+(1-Parameters!B$61)*P33^-Parameters!B$63 -> 0.60456136 | T33: =1-S33/Parameters!$B$12 -> 0.69771932 | U33: =1/(1-T33) -> 3.3081837 | V33: =(Parameters!$B$19*(F33+Parameters!$B$20)^T33+Parameters!$B$18*G33^T33)^(1/T33) -> 0.36827401 | W33: =(Parameters!$B$10*H33^Parameters!$B$9+Parameters!$B$11*V33^Parameters!$B$9)^(Parameters!$B$7/Parameters!$B$9)*O33 -> 1.368394 | X33: =W33 - D33 - E33 - LN(1+EXP(Parameters!$B$21*C33))/Parameters!$B$21 - IF(C33>0, 0,Parameters!$B$6*C33^2/F33) -> 1.0660895 | Y33: =EXP(-Parameters!$B$55*A33) -> 0.64539032 | Z33: =IF(X33>0,X33^(1-Parameters!$B$52)/(1-Parameters!$B$52)*Y33*Parameters!$B$65,-10+X33*1000) -> -1.8031283 | AC33: =C33*$J33*$K33 -> 1.0319555 | AD33: =D33*$J33*$K33 -> 9.930222 | AE33: =I33*J33*K33 -> 1.586183 | AF33: =F33*J33*K33 -> 30.259923 | AG33: =G33*J33*K33 -> 110.63558 | AH33: =V33*J33*K33 -> 52.542443 | AI33: =AH33/AH$4*100 -> 129.31095 | AJ33: =W33*J33*K33 -> 195.23171 | AK33: =X33*J33*K33 -> 152.10127 | AL33: =LN(AJ33)-LN(AJ32) -> 0.021270773 | AM33: =LN(AK33)-LN(AK32) -> 0.018442538 | AN33: =AVERAGE(AL31:AL35) -> 0.02129582 | AO33: =AVERAGE(AM31:AM35) -> 0.019985846 | AQ33: =W33*K33*J33 -> 195.23171 | AR33: =Parameters!$B$7*W33*(W33/O33)^(-Parameters!$B$9/Parameters!$B$7)*Parameters!$B$11*(V33)^(Parameters!$B$9-T33)*((1-2*Parameters!$B$5*C33/F33)*Parameters!$B$19*(F33+Parameters!$B$20)^(T33-1)-(1-2*Parameters!$B$5*D33/G33)*(Parameters!$B$18)*(G33)^(T33-1)) -> 0.19275542 | AS33: =((C34-C32)/2-(F34-F32)/F33/2*C33)/(F33/2/Parameters!$B$5-C33)-((D34-D32)/D33-(G34-G32)/G33)/(G33/2/Parameters!$B$5/D33-1) -> 0.0081503271 | AT33: =+Parameters!$B$5*C33^2/F33^2-Parameters!$B$5*D33^2/G33^2 -> -0.0068931458 | AU33: =EXP(-Parameters!$B$42*'6states'!A33)*(Parameters!$B$37*EXP(-Parameters!$B$38*Parameters!$E$25*'6states'!I33/('6states'!F33+'6states'!I33))*(1/Parameters!$B$38/Parameters!$E$25+'6states'!I33/('6states'!F33+'6states'!I33))-Parameters!$B$37/Parameters!$B$38/Parameters!$E$25*EXP(-Parameters!$B$38*Parameters!$E$25)+Parameters!$B$39) -> 0.61413854 | AV33: =J33*K33*EXP(-Parameters!$B$42*'6states'!A33)*(Parameters!$B$37*EXP(-Parameters!$B$38*Parameters!$E$25*'6states'!I33/('6states'!F33+'6states'!I33))*(1/Parameters!$B$38/Parameters!$E$25+'6states'!I33/('6states'!F33+'6states'!I33))-Parameters!$B$37/Parameters!$B$38/Parameters!$E$25*EXP(-Parameters!$B$38*Parameters!$E$25)+Parameters!$B$39) -> 87.620465 | AW33: =1000*(AR33+AS33+AT33)/(EXP(-Parameters!$B$42*A33)*((C33<0)*Parameters!$B$37*EXP(-Parameters!$B$38*AF33)+(C33>=0)*Parameters!$B$41)) -> 284.71641 | AX33: =1-W33/'6states,ExoDamages'!T33 -> 0.076412125 | AY33: =-Y33*W33*X33^(-Parameters!B$52)*Parameters!B$46*Parameters!B$45*N33 -> -1.7756202e-05 | AZ33: =1000*EXP(-(Parameters!$B$54)*'6states'!A33)*AQ33*Parameters!B$46*Parameters!B$45*N33 -> 1.5463931 | BA33: =SUM(AZ33:AZ$204)*EXP(Parameters!$B$54*A33) -> 363.65134 | BB33: =(C33+D33+E33)/W33 -> 0.22065582 | BF33: =SUM(AY33:AY231)/Y33 -> -0.0020338538 | BG33: =BF33/Parameters!$B$45 -> -3.3897563 | BH33: =1-BG32/BG33 -> 0.0015966892 | BK33: =-EXP(-Parameters!B$42*'6states'!A33)*(-Parameters!B$37/Parameters!B$38/Parameters!E$25*(EXP(-Parameters!B$38*Parameters!E$25*'6states'!I33/('6states'!F33+'6states'!I33))-EXP(-Parameters!B$38*Parameters!E$25))+Parameters!B$37*'6states'!F33/('6states'!F33+'6states'!I33)*EXP(-Parameters!B$38*Parameters!E$25*'6states'!I33/('6states'!F33+'6states'!I33))) -> -0.50874629 | BL33: =-J33*K33*EXP(-Parameters!B$42*'6states'!A33)*(-Parameters!B$37/Parameters!B$38/Parameters!E$25*(EXP(-Parameters!B$38*Parameters!E$25*'6states'!I33/('6states'!F33+'6states'!I33))-EXP(-Parameters!B$38*Parameters!E$25)) + Parameters!B$37*'6states'!F33/('6states'!F33+'6states'!I33)*EXP(-Parameters!B$38*Parameters!E$25*'6states'!I33/('6states'!F33+'6states'!I33))) -> -72.583926 | BM33: =I33/(F33+I33) -> 0.049807754 | BS33: =EXP(-Parameters!$B$56*A33)*BF33*BL33 -> 0.015373971 | BT33: =-EXP((Parameters!$B$56)*F33)*SUM(BS33:BS41) -> -0.12358256 | BU33: =X33^-Parameters!B$52/(1-2*Parameters!B$5*'6states'!D33/'6states'!G33) -> 1.117909 | BV33: =BU33/BU32 -> 0.99957122 | BW33: =$X33^-Parameters!$B$52/(1-2*Parameters!$B$5*'6states'!$E33/'6states'!$H33) -> 1.053208 | BX33: =BW33/BW32 -> 1.0084207 | BY33: =($X33^-Parameters!$B$52*(1/(1+EXP(-C33)) + IF(C33<0,2*Parameters!$B$6*C33/F33,0)) + BQ33*(1/(1+EXP((C33-Parameters!$B$22)*Parameters!$B$21))))/(1-IF(C33>0,2*Parameters!$B$5*C33/F33,0)) -> 0.49396536 | BZ33: =BY33/BY32 -> 1.0063015 | CA33: =BY33-BY32 -> 0.0030932281 | CB33: =(1/$T33-1/Parameters!$B$13) * LN(Parameters!$B$18) / LN(P33) -> 0.23698463 | CC33: =(Parameters!$B$18*'6states'!T33^+Parameters!$B$19*Parameters!$B$25^'6states'!T33)^((1-'6states'!T33)/'6states'!T33)*Parameters!$B$18*Parameters!$B$26^('6states'!T33-1) -> 0.26753674 | CD33: =(LN(CC33)-LN(CC$4))/ LN(P33) -> 0.25404569 | CE33: =1-2^-CB33 -> 0.15148306 | CF33: =1-2^-CC33 -> 0.16926326
