Workbook
Name ControlVars1to20: '6states'!$B$4:$D$24

Sheet Parameters
A2: Production and capital accumulation
A3: δ | B3: 0.04 | C3: decay rate of capital | M3: MAC
A4: δ+g_L+g | B4: =B3+B54+B52 -> 0.0629 | C4: decay rate of capital per unit of effective labour | L4: emissions | M4: Model | N4: MedianIPCC | O4: P25_IPCC | P4: P75_IPCC | Q4: MedianIPCC | R4: P25_IPCC | S4: P75_IPCC
A5: χ | B5: 1 | C5: investment adjustment cost | L5: -2.5 | M5: =_xlfn.XLOOKUP($L5,'6states'!$K$4:$K$104,'6states'!AS$4:AS$104,,-1) -> #N/A | N5: 830.6485 | O5: 534.3041 | P5: 1319.8 | Q5: 0.0282474 | R5: 0.0203494 | S5: 0.0396778
A6: χ_s | B6: 5 | C6: investment adjustment cost for negative investments | L6: 2.5 | M6: =_xlfn.XLOOKUP($L6,'6states'!$K$4:$K$104,'6states'!AS$4:AS$104,,-1) -> 954.8116 | N6: 606.6119 | O6: 387.1183 | P6: 1117.905 | Q6: 0.0266951 | R6: 0.0180696 | S6: 0.0408597
A7: α | B7: 0.3 | C7: share of capital income in national income | L7: 7.5 | M7: =_xlfn.XLOOKUP($L7,'6states'!$K$4:$K$104,'6states'!AS$4:AS$104,,-1) -> 491.5692 | N7: 417.0838 | O7: 242.3764 | P7: 684.3727 | Q7: 0.0196925 | R7: 0.0123111 | S7: 0.0283897
A8: σ_f | B8: 0.2 | C8: elasticity of substitution between energy and final capital | L8: 12.5 | M8: =_xlfn.XLOOKUP($L8,'6states'!$K$4:$K$101,'6states'!AS$4:AS$101,,-1) -> 352.25735 | N8: 369.451 | O8: 259.5315 | P8: 657.7192 | Q8: 0.0201464 | R8: 0.0142053 | S8: 0.0303724
A9: ε_f | B9: =1-1/B8 -> -4 | C9: 1-1/sigma | L9: 17.5 | M9: =_xlfn.XLOOKUP($L9,'6states'!$K$4:$K$101,'6states'!AS$4:AS$101,,-1) -> 287.34689 | N9: 279.1021 | O9: 194.9201 | P9: 471.1751 | Q9: 0.0194575 | R9: 0.0137847 | S9: 0.0288798
A10: φ_f | B10: =1-B11 -> 0.99994397 | C10: share parameter of final-good capital | L10: 22.5 | M10: =_xlfn.XLOOKUP($L10,'6states'!$K$4:$K$101,'6states'!AS$4:AS$101,,-1) -> 256.26342 | N10: 201.3134 | O10: 145.1962 | P10: 330 | Q10: 0.0183307 | R10: 0.0123982 | S10: 0.0285
A11: φ_E | B11: =1/(1+(B18*B16^B13+B19*B14^B13)^(B9/B13-1)*B18*B16^(B13-1)) -> 5.603267e-05 | C11: share parameter of energy capital, using Y_k_f=Y_k_c | L11: 27.5 | M11: =_xlfn.XLOOKUP($L11,'6states'!$K$4:$K$101,'6states'!AS$4:AS$101,,-1) -> 207.72092 | N11: 158.2803 | O11: 107.6669 | P11: 245.52 | Q11: 0.0160009 | R11: 0.0110032 | S11: 0.0237186
A12: σ[0] | B12: 2 | C12: elasticity of substitution between clean and dirty capital in energy sector (initially 2) | L12: 32.5 | M12: =_xlfn.XLOOKUP($L12,'6states'!$K$4:$K$101,'6states'!AS$4:AS$101,,-1) -> 193.43569 | N12: 112.6412 | O12: 81.44473 | P12: 177.918 | Q12: 0.0121626 | R12: 0.008787 | S12: 0.0173682
A13: ε[0] | B13: =1-1/B12 -> 0.5 | C13: 1-1/sigma | L13: 37.5 | M13: =_xlfn.XLOOKUP($L13,'6states'!$K$4:$K$101,'6states'!AS$4:AS$101,,-1) -> 184.39915 | N13: 89.53163 | O13: 58.81897 | P13: 159.2609 | Q13: 0.0082251 | R13: 0.0056994 | S13: 0.0138741
A14: θ_d | B14: 0.1841 | C14: ratio of dirty capital over final capital (k_d+xi)/k_f | L14: 42.5 | M14: =_xlfn.XLOOKUP($L14,'6states'!$K$4:$K$101,'6states'!AS$4:AS$101,,-1) -> 175.71981 | N14: 74.8676 | O14: 47.31793 | P14: 131.6824 | Q14: 0.006194 | R14: 0.0038782 | S14: 0.0092856
A15: k_c/(k_c+k_d+ξ) | B15: 0.16 | C15: ratio of renewable over all energy from IEA (should be 0.16) | L15: 47.5 | M15: =_xlfn.XLOOKUP($L15,'6states'!$K$4:$K$101,'6states'!AS$4:AS$101,,-1) -> 175.71981 | N15: 32.49194 | O15: 10.02872 | P15: 64.102 | Q15: 0.0027149 | R15: 0.0007531 | S15: 0.0051001
A16: θ_c | B16: =B14*B15/(1-B15) -> 0.035066667 | C16: ratio of renewable capital over final capital k_c/k_f | L16: 52.5 | M16: =_xlfn.XLOOKUP($L16,'6states'!$K$4:$K$101,'6states'!AS$4:AS$101,,-1) -> 175.71981 | N16: 1.7695 | O16: 0 | P16: 12.83052 | Q16: 0 | R16: 0 | S16: 0.0005013
A17: k_c/(k_d+ξ) | B17: =B16/B14 -> 0.19047619 | C17: ratio of renewable over clean energy | L17: 57.5 | M17: =_xlfn.XLOOKUP($L17,'6states'!$K$4:$K$101,'6states'!AS$4:AS$101,,-1) -> 171.50605 | N17: 2.24156 | O17: 0 | P17: 11.00962 | Q17: 0 | R17: 0 | S17: 1e-05
A18: φ_c | B18: =1-B19 -> 0.30383243 | C18: share parameter of clean capital | D18: =B18^(1/B13) -> 0.092314148
A19: φ_d | B19: =1/((B17)^(1-B13)+1) -> 0.69616757 | C19: share parameter of dirty capital | D19: =B18^(1/0.77) -> 0.21286109 | L19: Squared Error | M19: =SUMXMY2(M6:M16,N6:N16)/11/1000 -> 19.008207
A20: ξ | B20: 0.01 | C20: shift in the MAC curve (0.01) | L20: combined error | M20: =M19+#REF! -> #REF!
A21: varespilon | B21: 400 | C21: parameter in softplus function
A22: vareps2 | B22: 0 | C22: shift in softplus of stranding (0.004)
A24: Initial states
A25: k_d[0] | B25: =B27*B14-B20 -> 0.790835 | C25: initial dirty capital (ss in constantT&epsilon sheet) | D25: K_d[0] | E25: =B25*B$28*B$29 -> 58.418283 | F25: k_d[0] theory | G25: =B14*G27 -> 0.80194854 | H25: steady state capital return | I25: =(B57-B5*I26^2)/(1-2*B5*I26) -> 0.084904031
A26: k_c[0] | B26: =B27*B16 -> 0.15254 | C26: initial clean capital (ss in constantT&epsilon sheet) | D26: K_c[0] | E26: =B26*B$28*B$29 -> 11.267995 | F26: k_c[0] theory | G26: =B16*G27 -> 0.1527521 | H26: steady state i/k | I26: =(1-SQRT(1-4*B5*(B4)))/2/B5 -> 0.067449425
A27: k_f[0] | B27: 4.35 | C27: initial final capital (ss in constantT&epsilon sheet) | D27: K_f[0] | E27: =B27*B$28*B$29 -> 321.33066 | F27: k_f[0] theory | G27: =(B7*B10*(B10+B11*(B18*B16^B13+B19*B14^B13)^(B9/B13))^(B7/B9-1)*EXP(-B47/2*B48^2) / I25) ^ (1/(1-B7)) -> 4.3560486 | H27: steady state i/k, approximation | I27: =B4+B5*B4^2 -> 0.06685641
A28: L[0] | B28: 8.16 | C28: initial Labour | D28: K[0]=(k_f[0]+k_d[0]+k_c[0])*A[0]L[0] | E28: =(B25+B26+B27)*B28*B29 -> 391.01694 | F28: total capital
A29: A[0] | B29: =B30*EXP(B47/2*B48^2)/B28/(Parameters!$B$10*B27^Parameters!$B$9+B11*E30^Parameters!$B$9)^(Parameters!$B$7/Parameters!$B$9) -> 9.0525879 | C29: tfp (targeting Y0) | D29: k_ramsey | E29: =((Parameters!B3+Parameters!B51+Parameters!B53*Parameters!B54)/Parameters!B7)^(1/(Parameters!B7-1)) -> 6.8509746 | F29: k steady state in Ramsey model (without energy)k=((sigma+delta+etag)/alpha)^(1/alpha-1)
A30: Y[0] | B30: 110.98 | C30: initial GDP (trillion $, MERs) | D30: E[0] | E30: =(B18*B26^B13+B19*(B25+B20)^B13)^(1/B13) -> 0.55006251
A31: P_BAU | B31: 53.2 | C31: initial business as usual emissions | D31: k_c/(k_c+k_d) | E31: =B26/(B26+B25) -> 0.16169604 | F31: Slightly higher than in theory, due to effect of z
D32: Y_E*E/Y | E32: =B7*B11*E30^(B9-1)/(B10*B27^B9+B11*E30^B9) * E30 -> 0.05393028 | F32: share of energy capital in GDP
D33: Y_kf*kf/Y | E33: =B7*B10*B27^(B9-1)/(B10*B27^B9+B11*E30^B9) * B27 -> 0.24606972 | F33: share of final capital income in GDP
A35: Stranding costs
A36: A[0]L[0]ψ/(σ+g_ψ) | B36: =Parameters!B29*Parameters!B28*Parameters!B42/(Parameters!B3+B43) -> 1345.4134 | C36: cumulative stranded emissions per unit of stranded capital k_s at time zero
A37: Intercept | B37: 6.886 | C37: highest carbon intensity in GtCO2/T$, that is kg per $ (sum of a and c from calibration)
A38: ψ_1 | B38: =B37-B40 -> 6.119009
A39: ψ_2 | B39: 0.729 | C39: degrowth rate of psi as a function of cumulative stranded emissions (calibrated parameter per Billion $ multiplied by 1000)
A40: ψ_3 | B40: =(B31-B37/B39*(1-EXP(-B39*E25)))/(E25-(1-EXP(-B39*E25))/B39) -> 0.76699101
A41: ψ_min | B41: =B38*EXP(-B39*E25)+B40 -> 0.76699101 | C41: lowest emissions intensity of capital at start
A42: \bar{ψ} | B42: =B31/B28/B29/B25 -> 0.9106738 | C42: mean emissions intensity at start
A43: g_ψ | B43: 0.01 | C43: autonomous decrease in carbon intensity
A45: Damages
A46: ζ | B46: 0.0006 | C46: TCRE
A47: γ | B47: 0.0201 | C47: total damage for 1°C/2 (0.0154 before)
A48: T[0] | B48: 1.38 | C48: initial temperature
A50: Discount rate
A51: ρ | B51: =0.011 -> 0.011 | C51: pure time preference rate
A52: g_L | B52: 0.0029 | C52: labour growth
A53: η | B53: 1.35 | C53: elasticity of marginal utility of consumption
A54: g | B54: 0.02 | C54: productivity growth
A55: r | B55: =B51-B52+B53*B54 -> 0.0351
A56: r-g | B56: =B51-B52+(B53-1)*B54 -> 0.0151
A57: r+δ+g_L | B57: =B55+B3+B52 -> 0.078
A58: β | B58: =EXP(-B56) -> 0.98501343 | C58: discount factor
A60: Technical change | F60: =1-EXP(-0.015*150) -> 0.89460078
A61: g_σ | B61: 0.027 | C61: growth rate of exogenous TC (0.027)
A62: ω | B62: 0.5 | C62: share of exogenous TC
A63: M[0] | B63: 50 | C63: initial cumulative abatement
A64: ρ | B64: 0.1 | C64: elasticity of endogenous TC
A71: time step | B71: 1
B74: cells to optimize in ExoDamages | C74: $B$4:$D$18,$B$20:$D$20,$B$22:$D$22,$B$24:$D$24,$B$29:$D$29,$B$34:$D$34,$B$44:$D$44,$B$54:$D$54,$B$64:$D$64,$B$74:$D$74,$B$84:$D$84,$B$94:$D$94 | M74: 2 reasons for high total abatement costs: 1) this model abates fast, therefore GDP is lower than in IPCC models for a given level of abatement 2) abatement costs reduce the return on all types of capital and lead to lower kf

Sheet 6states
A1: 6 states: k_f, k_d, k_c, k_s, T, time
I2: =8.6*12 -> 103.2
A3: Period | B3: i_d[t] | C3: i_c[t] | D3: i_f[t] | E3: k_d[t] | F3: k_c[t] | G3: k_f[t] | H3: k_s[t] | I3: L[t] | J3: A[t] | K3: P[t] | L3: S[t] | M3: T[t] | N3: Ω[t] | O3: M[t]/M[0] | P3: ω*exp(g_σ)*t | Q3: ω*M[t]^-ρ | R3: TC[t] | S3: ε[t] | T3: σ[t] | U3: E[t]/(A[t]*L[t]) | V3: y[t] | W3: c[t] | X3: β^t | Y3: β^t * u(c[t]) | Z3: W | AA3: FD id/kd | AB3: FD ic/kc | AC3: FD if/kf | AD3: Discounted sum of FDs | AE3: SD id/kd | AF3: SD ic/kc | AG3: SD if/kf | AH3: Discounted sum of SDs | AJ3: W w/ penalty | AM3: K_s[t] | AN3: K_d[t] | AO3: E[t] | AP3: Y[t] | AQ3: Mgl damage[t] (utils) | AR3: Mgl damage[t] ($) | AS3: SCC[t] | AT3: s[t] | AU3: elasticity wrt M for LT clean productivity | AV3: E_kc at initial capital ratios | AW3: LR elasticity wrt M for initial clean productivity | AX3: Learning rate | AY3: Learning rate at initial k_j
A4: 0 | B4: -0.028124507 | C4: 0.036740613 | D4: 0.25584329 | E4: =Parameters!B25 -> 0.790835 | F4: =Parameters!B26 -> 0.15254 | G4: =Parameters!B27 -> 4.35 | H4: 0 | I4: =Parameters!B28 -> 8.16 | J4: =Parameters!B29 -> 9.0525879 | K4: =I4*J4*EXP(-Parameters!$B$43*'6states'!A4)*(Parameters!$B$38/Parameters!$B$39*('6states'!E4+'6states'!H4)/Parameters!$E$25*(EXP(-Parameters!$B$39*Parameters!$E$25*'6states'!H4/('6states'!E4+'6states'!H4))-EXP(-Parameters!$B$39*Parameters!$E$25)) + Parameters!$B$40*'6states'!E4) -> 53.2 | L4: =M4/Parameters!$B$46 -> 2300 | M4: =Parameters!B48 -> 1.38 | N4: =EXP(-Parameters!$B$47/2*M4^2) -> 0.98104277 | O4: =MAX((Parameters!$B$63 + Parameters!$B$31*'6states'!A4 - '6states'!L4 + Parameters!$B$48/Parameters!$B$46)/Parameters!B$63,1) -> 1 | P4: =Parameters!B$62*EXP(-Parameters!B$61*A4) -> 0.5 | Q4: =(1-Parameters!B$62)*O4^-Parameters!B$64 -> 0.5 | R4: =Parameters!B$62*EXP(-Parameters!B$61*A4)+(1-Parameters!B$62)*O4^-Parameters!B$64 -> 1 | S4: =1-R4/Parameters!$B$12 -> 0.5 | T4: =1/(1-S4) -> 2 | U4: =(Parameters!$B$19*(E4+Parameters!$B$20)^S4+Parameters!$B$18*F4^S4)^(1/S4) -> 0.55006251 | V4: =(Parameters!$B$10*G4^Parameters!$B$9+Parameters!$B$11*U4^Parameters!$B$9)^(Parameters!$B$7/Parameters!$B$9)*N4 -> 1.502387 | W4: =V4 - C4 - D4 - LN(1+EXP(Parameters!$B$21*B4))/Parameters!$B$21 - IF(B4>0, 0,Parameters!$B$6*B4^2/E4) -> 1.2048021 | X4: =EXP(-Parameters!$B$56*A4) -> 1 | Y4: =IF(W4>0,W4^(1-Parameters!$B$53)/(1-Parameters!$B$53)*X4*Parameters!$B$71,-10+W4*1000) -> -2.6767725 | Z4: =SUM(Y4:Y204)*Parameters!$B$71 -> -186.87944 | AJ4: =Z4-AK7*SUM(AD5:AD204)-AK8*SUM(AH5:AH204) -> -186.88602 | AM4: =H4*I4*J4 -> 0 | AN4: =E4*I4*J4 -> 58.418283 | AO4: =U4*I4*J4 -> 40.632632 | AP4: =V4*J4*I4 -> 110.98 | AR4: =1000*EXP(-(Parameters!$B$55)*'6states'!A4)*AP4*Parameters!B$47*Parameters!B$46*M4 -> 1.8470179 | AS4: =SUM(AR4:AR$204)*EXP(Parameters!$B$55*A4) -> 171.50605 | AT4: =((B4>0)*B4+C4+D4)/V4 -> 0.19474603 | AV4: =(Parameters!$B$18*'6states'!S4^+Parameters!$B$19*Parameters!$B$25^'6states'!S4)^((1-'6states'!S4)/'6states'!S4)*Parameters!$B$18*Parameters!$B$26^('6states'!S4-1) -> 0.12973347
A5: =A4+Parameters!$B$71 -> 1 | B5: -0.01049962 | C5: 0.040543532 | D5: 0.25057863 | E5: =MAX((1-Parameters!$B$4)^Parameters!B$71*E4 + B4*Parameters!B$71 - IF(B4>0,Parameters!$B$5,0)*B4^2/E4*Parameters!B$71, 0.0001) -> 0.71296697 | F5: =(1-Parameters!$B$4)^Parameters!B$71*F4+C4*Parameters!B$71-Parameters!$B$5*C4^2/F4*Parameters!B$71 -> 0.17083654 | G5: =(1-Parameters!$B$4)^Parameters!B$71*G4+D4*Parameters!B$71-Parameters!$B$5*D4^2/G4*Parameters!B$71 -> 4.317181 | H5: =MAX(H4 * (1-Parameters!$B$4) ^ Parameters!B$71 + (LN(1+EXP(Parameters!$B$21*(-B4+0.004)))/Parameters!$B$21 -0.004) * Parameters!B$71,0) -> 0.028124513 | I5: =I4*(1+Parameters!$B$52)^Parameters!B$71 -> 8.183664 | J5: =J4*(1+Parameters!$B$54)^Parameters!B$71 -> 9.2336396 | K5: =I5*J5*EXP(-Parameters!$B$43*'6states'!A5)*(Parameters!$B$38/Parameters!$B$39*('6states'!E5+'6states'!H5)/Parameters!$E$25*(EXP(-Parameters!$B$39*Parameters!$E$25*'6states'!H5/('6states'!E5+'6states'!H5))-EXP(-Parameters!$B$39*Parameters!$E$25)) + Parameters!$B$40*'6states'!E5) -> 42.493298 | L5: =L4+K5*Parameters!B$71 -> 2342.4933 | M5: =L5*Parameters!$B$46 -> 1.405496 | N5: =EXP(-Parameters!$B$47/2*M5^2) -> 0.98034281 | O5: =MAX((Parameters!$B$63 + Parameters!$B$31*'6states'!A5 - '6states'!L5 + Parameters!$B$48/Parameters!$B$46)/Parameters!B$63,1) -> 1.214134 | P5: =Parameters!B$62*EXP(-Parameters!B$61*A5) -> 0.48668062 | Q5: =(1-Parameters!B$62)*O5^-Parameters!B$64 -> 0.49039196 | R5: =Parameters!B$62*EXP(-Parameters!B$61*A5)+(1-Parameters!B$62)*O5^-Parameters!B$64 -> 0.97707258 | S5: =1-R5/Parameters!$B$12 -> 0.51146371 | T5: =1/(1-S5) -> 2.0469308 | U5: =(Parameters!$B$19*(E5+Parameters!$B$20)^S5+Parameters!$B$18*F5^S5)^(1/S5) -> 0.51585261 | V5: =(Parameters!$B$10*G5^Parameters!$B$9+Parameters!$B$11*U5^Parameters!$B$9)^(Parameters!$B$7/Parameters!$B$9)*N5 -> 1.4928952 | W5: =V5 - C5 - D5 - LN(1+EXP(Parameters!$B$21*B5))/Parameters!$B$21 - IF(B5>0, 0,Parameters!$B$6*B5^2/E5) -> 1.2009627 | X5: =EXP(-Parameters!$B$56*A5) -> 0.98501343 | Y5: =IF(W5>0,W5^(1-Parameters!$B$53)/(1-Parameters!$B$53)*X5*Parameters!$B$71,-10+W5*1000) -> -2.639604 | AB5: =C5/F5-C4/F4 -> -0.0035353471 | AC5: =D5/G5-D4/G4 -> -0.0007723626 | AD5: =X5*(AA5^2+AB5^2+AC5^2) -> 1.2898971e-05 | AH5: =X5*(AE5^2+AF5^2+AG5^2) -> 0 | AM5: =H5*I5*J5 -> 2.1252289 | AN5: =E5*I5*J5 -> 53.875352 | AO5: =U5*I5*J5 -> 38.980405 | AP5: =V5*J5*I5 -> 112.81063 | AQ5: =-X5*V5*W5^(-Parameters!B$53)*Parameters!B$47*Parameters!B$46*M5 -> -1.9466305e-05 | AR5: =1000*EXP(-(Parameters!$B$55)*'6states'!A5)*AP5*Parameters!B$47*Parameters!B$46*M5 -> 1.846219 | AS5: =SUM(AR5:AR$204)*EXP(Parameters!$B$55*A5) -> 175.71981 | AT5: =((B5>0)*B5+C5+D5)/V5 -> 0.19500508 | AU5: =(1/$S5-1/Parameters!$B$13) * LN(Parameters!$B$18) / LN(O5) -> 0.27522157 | AV5: =(Parameters!$B$18*'6states'!S5^+Parameters!$B$19*Parameters!$B$25^'6states'!S5)^((1-'6states'!S5)/'6states'!S5)*Parameters!$B$18*Parameters!$B$26^('6states'!S5-1) -> 0.13931298 | AW5: =(LN(AV5)-LN(AV$4))/ LN(O5) -> 0.36716267 | AX5: =1-2^-AU5 -> 0.1736766 | AY5: =1-2^-AV5 -> 0.092048576 | AZ5: =(1/$S5-1/Parameters!$B$13) * LN(Parameters!$B$18) / A5 -> 0.053401545
A6: =A5+Parameters!$B$71 -> 2 | B6: -0.0066558129 | C6: 0.044251293 | D6: 0.24474072 | E6: =MAX((1-Parameters!$B$4)^Parameters!B$71*E5 + B5*Parameters!B$71 - IF(B5>0,Parameters!$B$5,0)*B5^2/E5*Parameters!B$71, 0.0001) -> 0.65762173 | F6: =(1-Parameters!$B$4)^Parameters!B$71*F5+C5*Parameters!B$71-Parameters!$B$5*C5^2/F5*Parameters!B$71 -> 0.19101252 | G6: =(1-Parameters!$B$4)^Parameters!B$71*G5+D5*Parameters!B$71-Parameters!$B$5*D5^2/G5*Parameters!B$71 -> 4.2816648 | H6: =MAX(H5 * (1-Parameters!$B$4) ^ Parameters!B$71 + (LN(1+EXP(Parameters!$B$21*(-B5+0.004)))/Parameters!$B$21 -0.004) * Parameters!B$71,0) -> 0.03686266 | I6: =I5*(1+Parameters!$B$52)^Parameters!B$71 -> 8.2073966 | J6: =J5*(1+Parameters!$B$54)^Parameters!B$71 -> 9.4183124 | K6: =I6*J6*EXP(-Parameters!$B$43*'6states'!A6)*(Parameters!$B$38/Parameters!$B$39*('6states'!E6+'6states'!H6)/Parameters!$E$25*(EXP(-Parameters!$B$39*Parameters!$E$25*'6states'!H6/('6states'!E6+'6states'!H6))-EXP(-Parameters!$B$39*Parameters!$E$25)) + Parameters!$B$40*'6states'!E6) -> 39.005797 | L6: =L5+K6*Parameters!B$71 -> 2381.4991 | M6: =L6*Parameters!$B$46 -> 1.4288995 | N6: =EXP(-Parameters!$B$47/2*M6^2) -> 0.97968947 | O6: =MAX((Parameters!$B$63 + Parameters!$B$31*'6states'!A6 - '6states'!L6 + Parameters!$B$48/Parameters!$B$46)/Parameters!B$63,1) -> 1.4980181 | P6: =Parameters!B$62*EXP(-Parameters!B$61*A6) -> 0.47371605 | Q6: =(1-Parameters!B$62)*O6^-Parameters!B$64 -> 0.48019573 | R6: =Parameters!B$62*EXP(-Parameters!B$61*A6)+(1-Parameters!B$62)*O6^-Parameters!B$64 -> 0.95391179 | S6: =1-R6/Parameters!$B$12 -> 0.52304411 | T6: =1/(1-S6) -> 2.0966299 | U6: =(Parameters!$B$19*(E6+Parameters!$B$20)^S6+Parameters!$B$18*F6^S6)^(1/S6) -> 0.49379805 | V6: =(Parameters!$B$10*G6^Parameters!$B$9+Parameters!$B$11*U6^Parameters!$B$9)^(Parameters!$B$7/Parameters!$B$9)*N6 -> 1.4846062 | W6: =V6 - C6 - D6 - LN(1+EXP(Parameters!$B$21*B6))/Parameters!$B$21 - IF(B6>0, 0,Parameters!$B$6*B6^2/E6) -> 1.1951087 | X6: =EXP(-Parameters!$B$56*A6) -> 0.97025146 | Y6: =IF(W6>0,W6^(1-Parameters!$B$53)/(1-Parameters!$B$53)*X6*Parameters!$B$71,-10+W6*1000) -> -2.6044958 | AB6: =C6/F6-C5/F5 -> -0.0056565586 | AC6: =D6/G6-D5/G5 -> -0.00088201029 | AD6: =X6*(AA6^2+AB6^2+AC6^2) -> 3.1799602e-05 | AF6: =C6/F6-2*C5/F5+C4/F4 -> -0.0021212115 | AG6: =D6/G6-2*D5/G5+D4/G4 -> -0.0001096477 | AH6: =X6*(AE6^2+AF6^2+AG6^2) -> 4.3773487e-06 | AJ6: Penalty weights | AM6: =H6*I6*J6 -> 2.8494772 | AN6: =E6*I6*J6 -> 50.834045 | AO6: =U6*I6*J6 -> 38.170503 | AP6: =V6*J6*I6 -> 114.7598 | AQ6: =-X6*V6*W6^(-Parameters!B$53)*Parameters!B$47*Parameters!B$46*M6 -> -1.9513921e-05 | AR6: =1000*EXP(-(Parameters!$B$55)*'6states'!A6)*AP6*Parameters!B$47*Parameters!B$46*M6 -> 1.8435346 | AS6: =SUM(AR6:AR$204)*EXP(Parameters!$B$55*A6) -> 180.01661 | AT6: =((B6>0)*B6+C6+D6)/V6 -> 0.19465903 | AU6: =(1/$S6-1/Parameters!$B$13) * LN(Parameters!$B$18) / LN(O6) -> 0.2597347 | AV6: =(Parameters!$B$18*'6states'!S6^+Parameters!$B$19*Parameters!$B$25^'6states'!S6)^((1-'6states'!S6)/'6states'!S6)*Parameters!$B$18*Parameters!$B$26^('6states'!S6-1) -> 0.14895626 | AW6: =(LN(AV6)-LN(AV$4))/ LN(O6) -> 0.3418855 | AX6: =1-2^-AU6 -> 0.1647585 | AY6: =1-2^-AV6 -> 0.098097277 | AZ6: =(1/$S6-1/Parameters!$B$13) * LN(Parameters!$B$18) / A6 -> 0.052484977
A7: =A6+Parameters!$B$71 -> 3 | B7: -0.0048907717 | C7: 0.047731894 | D7: 0.23983585 | E7: =MAX((1-Parameters!$B$4)^Parameters!B$71*E6 + B6*Parameters!B$71 - IF(B6>0,Parameters!$B$5,0)*B6^2/E6*Parameters!B$71, 0.0001) -> 0.60960151 | F7: =(1-Parameters!$B$4)^Parameters!B$71*F6+C6*Parameters!B$71-Parameters!$B$5*C6^2/F6*Parameters!B$71 -> 0.21299757 | G7: =(1-Parameters!$B$4)^Parameters!B$71*G6+D6*Parameters!B$71-Parameters!$B$5*D6^2/G6*Parameters!B$71 -> 4.2430994 | H7: =MAX(H6 * (1-Parameters!$B$4) ^ Parameters!B$71 + (LN(1+EXP(Parameters!$B$21*(-B6+0.004)))/Parameters!$B$21 -0.004) * Parameters!B$71,0) -> 0.041234789 | I7: =I6*(1+Parameters!$B$52)^Parameters!B$71 -> 8.2311981 | J7: =J6*(1+Parameters!$B$54)^Parameters!B$71 -> 9.6066786 | K7: =I7*J7*EXP(-Parameters!$B$43*'6states'!A7)*(Parameters!$B$38/Parameters!$B$39*('6states'!E7+'6states'!H7)/Parameters!$E$25*(EXP(-Parameters!$B$39*Parameters!$E$25*'6states'!H7/('6states'!E7+'6states'!H7))-EXP(-Parameters!$B$39*Parameters!$E$25)) + Parameters!$B$40*'6states'!E7) -> 36.36244 | L7: =L6+K7*Parameters!B$71 -> 2417.8615 | M7: =L7*Parameters!$B$46 -> 1.4507169 | N7: =EXP(-Parameters!$B$47/2*M7^2) -> 0.97907109 | O7: =MAX((Parameters!$B$63 + Parameters!$B$31*'6states'!A7 - '6states'!L7 + Parameters!$B$48/Parameters!$B$46)/Parameters!B$63,1) -> 1.8347693 | P7: =Parameters!B$62*EXP(-Parameters!B$61*A7) -> 0.46109685 | Q7: =(1-Parameters!B$62)*O7^-Parameters!B$64 -> 0.47055659 | R7: =Parameters!B$62*EXP(-Parameters!B$61*A7)+(1-Parameters!B$62)*O7^-Parameters!B$64 -> 0.93165343 | S7: =1-R7/Parameters!$B$12 -> 0.53417328 | T7: =1/(1-S7) -> 2.146721 | U7: =(Parameters!$B$19*(E7+Parameters!$B$20)^S7+Parameters!$B$18*F7^S7)^(1/S7) -> 0.47527918 | V7: =(Parameters!$B$10*G7^Parameters!$B$9+Parameters!$B$11*U7^Parameters!$B$9)^(Parameters!$B$7/Parameters!$B$9)*N7 -> 1.4763946 | W7: =V7 - C7 - D7 - LN(1+EXP(Parameters!$B$21*B7))/Parameters!$B$21 - IF(B7>0, 0,Parameters!$B$6*B7^2/E7) -> 1.1883001 | X7: =EXP(-Parameters!$B$56*A7) -> 0.95571073 | Y7: =IF(W7>0,W7^(1-Parameters!$B$53)/(1-Parameters!$B$53)*X7*Parameters!$B$71,-10+W7*1000) -> -2.5705986 | AB7: =C7/F7-C6/F6 -> -0.0075710139 | AC7: =D7/G7-D6/G6 -> -0.00063643632 | AD7: =X7*(AA7^2+AB7^2+AC7^2) -> 5.5168691e-05 | AF7: =C7/F7-2*C6/F6+C5/F5 -> -0.0019144553 | AG7: =D7/G7-2*D6/G6+D5/G5 -> 0.00024557397 | AH7: =X7*(AE7^2+AF7^2+AG7^2) -> 3.5604483e-06 | AJ7: FD | AK7: 1 | AM7: =H7*I7*J7 -> 3.2606193 | AN7: =E7*I7*J7 -> 48.203919 | AO7: =U7*I7*J7 -> 37.582451 | AP7: =V7*J7*I7 -> 116.74513 | AQ7: =-X7*V7*W7^(-Parameters!B$53)*Parameters!B$47*Parameters!B$46*M7 -> -1.9557288e-05 | AR7: =1000*EXP(-(Parameters!$B$55)*'6states'!A7)*AP7*Parameters!B$47*Parameters!B$46*M7 -> 1.8383896 | AS7: =SUM(AR7:AR$204)*EXP(Parameters!$B$55*A7) -> 184.39915 | AT7: =((B7>0)*B7+C7+D7)/V7 -> 0.19477702 | AU7: =(1/$S7-1/Parameters!$B$13) * LN(Parameters!$B$18) / LN(O7) -> 0.2511409 | AV7: =(Parameters!$B$18*'6states'!S7^+Parameters!$B$19*Parameters!$B$25^'6states'!S7)^((1-'6states'!S7)/'6states'!S7)*Parameters!$B$18*Parameters!$B$26^('6states'!S7-1) -> 0.15814998 | AW7: =(LN(AV7)-LN(AV$4))/ LN(O7) -> 0.32633984 | AX7: =1-2^-AU7 -> 0.15976831 | AY7: =1-2^-AV7 -> 0.10382647 | AZ7: =(1/$S7-1/Parameters!$B$13) * LN(Parameters!$B$18) / A7 -> 0.050807373
A8: =A7+Parameters!$B$71 -> 4 | B8: -0.0039105241 | C8: 0.050910123 | D8: 0.2355976 | E8: =MAX((1-Parameters!$B$4)^Parameters!B$71*E7 + B7*Parameters!B$71 - IF(B7>0,Parameters!$B$5,0)*B7^2/E7*Parameters!B$71, 0.0001) -> 0.5663668 | F8: =(1-Parameters!$B$4)^Parameters!B$71*F7+C7*Parameters!B$71-Parameters!$B$5*C7^2/F7*Parameters!B$71 -> 0.23663539 | G8: =(1-Parameters!$B$4)^Parameters!B$71*G7+D7*Parameters!B$71-Parameters!$B$5*D7^2/G7*Parameters!B$71 -> 4.2024879 | H8: =MAX(H7 * (1-Parameters!$B$4) ^ Parameters!B$71 + (LN(1+EXP(Parameters!$B$21*(-B7+0.004)))/Parameters!$B$21 -0.004) * Parameters!B$71,0) -> 0.043602253 | I8: =I7*(1+Parameters!$B$52)^Parameters!B$71 -> 8.2550686 | J8: =J7*(1+Parameters!$B$54)^Parameters!B$71 -> 9.7988122 | K8: =I8*J8*EXP(-Parameters!$B$43*'6states'!A8)*(Parameters!$B$38/Parameters!$B$39*('6states'!E8+'6states'!H8)/Parameters!$E$25*(EXP(-Parameters!$B$39*Parameters!$E$25*'6states'!H8/('6states'!E8+'6states'!H8))-EXP(-Parameters!$B$39*Parameters!$E$25)) + Parameters!$B$40*'6states'!E8) -> 34.085065 | L8: =L7+K8*Parameters!B$71 -> 2451.9466 | M8: =L8*Parameters!$B$46 -> 1.471168 | N8: =EXP(-Parameters!$B$47/2*M8^2) -> 0.97848329 | O8: =MAX((Parameters!$B$63 + Parameters!$B$31*'6states'!A8 - '6states'!L8 + Parameters!$B$48/Parameters!$B$46)/Parameters!B$63,1) -> 2.217068 | P8: =Parameters!B$62*EXP(-Parameters!B$61*A8) -> 0.4488138 | Q8: =(1-Parameters!B$62)*O8^-Parameters!B$64 -> 0.46173426 | R8: =Parameters!B$62*EXP(-Parameters!B$61*A8)+(1-Parameters!B$62)*O8^-Parameters!B$64 -> 0.91054806 | S8: =1-R8/Parameters!$B$12 -> 0.54472597 | T8: =1/(1-S8) -> 2.1964793 | U8: =(Parameters!$B$19*(E8+Parameters!$B$20)^S8+Parameters!$B$18*F8^S8)^(1/S8) -> 0.45890198 | V8: =(Parameters!$B$10*G8^Parameters!$B$9+Parameters!$B$11*U8^Parameters!$B$9)^(Parameters!$B$7/Parameters!$B$9)*N8 -> 1.4681993 | W8: =V8 - C8 - D8 - LN(1+EXP(Parameters!$B$21*B8))/Parameters!$B$21 - IF(B8>0, 0,Parameters!$B$6*B8^2/E8) -> 1.1810816 | X8: =EXP(-Parameters!$B$56*A8) -> 0.9413879 | Y8: =IF(W8>0,W8^(1-Parameters!$B$53)/(1-Parameters!$B$53)*X8*Parameters!$B$71,-10+W8*1000) -> -2.5374799 | AB8: =C8/F8-C7/F7 -> -0.0089543301 | AC8: =D8/G8-D7/G7 -> -0.00046228191 | AD8: =X8*(AA8^2+AB8^2+AC8^2) -> 7.5681686e-05 | AF8: =C8/F8-2*C7/F7+C6/F6 -> -0.0013833161 | AG8: =D8/G8-2*D7/G7+D6/G6 -> 0.00017415442 | AH8: =X8*(AE8^2+AF8^2+AG8^2) -> 1.8299577e-06 | AJ8: SD | AK8: 0.3 | AM8: =H8*I8*J8 -> 3.5269804 | AN8: =E8*I8*J8 -> 45.813335 | AO8: =U8*I8*J8 -> 37.12052 | AP8: =V8*J8*I8 -> 118.76245 | AQ8: =-X8*V8*W8^(-Parameters!B$53)*Parameters!B$47*Parameters!B$46*M8 -> -1.9587785e-05 | AR8: =1000*EXP(-(Parameters!$B$55)*'6states'!A8)*AP8*Parameters!B$47*Parameters!B$46*M8 -> 1.8311072 | AS8: =SUM(AR8:AR$204)*EXP(Parameters!$B$55*A8) -> 188.87099 | AT8: =((B8>0)*B8+C8+D8)/V8 -> 0.19514225 | AU8: =(1/$S8-1/Parameters!$B$13) * LN(Parameters!$B$18) / LN(O8) -> 0.2457032 | AV8: =(Parameters!$B$18*'6states'!S8^+Parameters!$B$19*Parameters!$B$25^'6states'!S8)^((1-'6states'!S8)/'6states'!S8)*Parameters!$B$18*Parameters!$B$26^('6states'!S8-1) -> 0.16676645 | AW8: =(LN(AV8)-LN(AV$4))/ LN(O8) -> 0.31539412 | AX8: =1-2^-AU8 -> 0.1565954 | AY8: =1-2^-AV8 -> 0.1091629 | AZ8: =(1/$S8-1/Parameters!$B$13) * LN(Parameters!$B$18) / A8 -> 0.048906338
A9: =A8+Parameters!$B$71 -> 5 | B9: -0.0030479352 | C9: 0.05370798 | D9: 0.23249509 | E9: =MAX((1-Parameters!$B$4)^Parameters!B$71*E8 + B8*Parameters!B$71 - IF(B8>0,Parameters!$B$5,0)*B8^2/E8*Parameters!B$71, 0.0001) -> 0.52683181 | F9: =(1-Parameters!$B$4)^Parameters!B$71*F8+C8*Parameters!B$71-Parameters!$B$5*C8^2/F8*Parameters!B$71 -> 0.26170826 | G9: =(1-Parameters!$B$4)^Parameters!B$71*G8+D8*Parameters!B$71-Parameters!$B$5*D8^2/G8*Parameters!B$71 -> 4.160541 | H9: =MAX(H8 * (1-Parameters!$B$4) ^ Parameters!B$71 + (LN(1+EXP(Parameters!$B$21*(-B8+0.004)))/Parameters!$B$21 -0.004) * Parameters!B$71,0) -> 0.044873644 | I9: =I8*(1+Parameters!$B$52)^Parameters!B$71 -> 8.2790082 | J9: =J8*(1+Parameters!$B$54)^Parameters!B$71 -> 9.9947885 | K9: =I9*J9*EXP(-Parameters!$B$43*'6states'!A9)*(Parameters!$B$38/Parameters!$B$39*('6states'!E9+'6states'!H9)/Parameters!$E$25*(EXP(-Parameters!$B$39*Parameters!$E$25*'6states'!H9/('6states'!E9+'6states'!H9))-EXP(-Parameters!$B$39*Parameters!$E$25)) + Parameters!$B$40*'6states'!E9) -> 32.033807 | L9: =L8+K9*Parameters!B$71 -> 2483.9804 | M9: =L9*Parameters!$B$46 -> 1.4903882 | N9: =EXP(-Parameters!$B$47/2*M9^2) -> 0.97792369 | O9: =MAX((Parameters!$B$63 + Parameters!$B$31*'6states'!A9 - '6states'!L9 + Parameters!$B$48/Parameters!$B$46)/Parameters!B$63,1) -> 2.6403918 | P9: =Parameters!B$62*EXP(-Parameters!B$61*A9) -> 0.43685796 | Q9: =(1-Parameters!B$62)*O9^-Parameters!B$64 -> 0.45373592 | R9: =Parameters!B$62*EXP(-Parameters!B$61*A9)+(1-Parameters!B$62)*O9^-Parameters!B$64 -> 0.89059388 | S9: =1-R9/Parameters!$B$12 -> 0.55470306 | T9: =1/(1-S9) -> 2.2456925 | U9: =(Parameters!$B$19*(E9+Parameters!$B$20)^S9+Parameters!$B$18*F9^S9)^(1/S9) -> 0.44408215 | V9: =(Parameters!$B$10*G9^Parameters!$B$9+Parameters!$B$11*U9^Parameters!$B$9)^(Parameters!$B$7/Parameters!$B$9)*N9 -> 1.4600313 | W9: =V9 - C9 - D9 - LN(1+EXP(Parameters!$B$21*B9))/Parameters!$B$21 - IF(B9>0, 0,Parameters!$B$6*B9^2/E9) -> 1.1730929 | X9: =EXP(-Parameters!$B$56*A9) -> 0.92727973 | Y9: =IF(W9>0,W9^(1-Parameters!$B$53)/(1-Parameters!$B$53)*X9*Parameters!$B$71,-10+W9*1000) -> -2.505396 | AA9: =B9/E9-B8/E8 -> 0.0011191738 | AB9: =C9/F9-C8/F8 -> -0.0099208224 | AC9: =D9/G9-D8/G8 -> -0.00018048308 | AD9: =X9*(AA9^2+AB9^2+AC9^2) -> 9.2457059e-05 | AE9: =B9/E9-2*B8/E8+B7/E7 -> 8.5276029e-07 | AF9: =C9/F9-2*C8/F8+C7/F7 -> -0.0009664923 | AG9: =D9/G9-2*D8/G8+D7/G7 -> 0.00028179882 | AH9: =X9*(AE9^2+AF9^2+AG9^2) -> 9.3981532e-07 | AM9: =H9*I9*J9 -> 3.7131566 | AN9: =E9*I9*J9 -> 43.593718 | AO9: =U9*I9*J9 -> 36.746438 | AP9: =V9*J9*I9 -> 120.81312 | AQ9: =-X9*V9*W9^(-Parameters!B$53)*Parameters!B$47*Parameters!B$46*M9 -> -1.9616473e-05 | AR9: =1000*EXP(-(Parameters!$B$55)*'6states'!A9)*AP9*Parameters!B$47*Parameters!B$46*M9 -> 1.8219738 | AS9: =SUM(AR9:AR$204)*EXP(Parameters!$B$55*A9) -> 193.43569 | AT9: =((B9>0)*B9+C9+D9)/V9 -> 0.1960253 | AU9: =(1/$S9-1/Parameters!$B$13) * LN(Parameters!$B$18) / LN(O9) -> 0.24199578 | AV9: =(Parameters!$B$18*'6states'!S9^+Parameters!$B$19*Parameters!$B$25^'6states'!S9)^((1-'6states'!S9)/'6states'!S9)*Parameters!$B$18*Parameters!$B$26^('6states'!S9-1) -> 0.17479565 | AW9: =(LN(AV9)-LN(AV$4))/ LN(O9) -> 0.30706264 | AX9: =1-2^-AU9 -> 0.15442524 | AY9: =1-2^-AV9 -> 0.11410701 | AZ9: =(1/$S9-1/Parameters!$B$13) * LN(Parameters!$B$18) / A9 -> 0.046992063
A10: =A9+Parameters!$B$71 -> 6 | B10: -0.001397365 | C10: 0.056014686 | D10: 0.23090231 | E10: =MAX((1-Parameters!$B$4)^Parameters!B$71*E9 + B9*Parameters!B$71 - IF(B9>0,Parameters!$B$5,0)*B9^2/E9*Parameters!B$71, 0.0001) -> 0.49064615 | F10: =(1-Parameters!$B$4)^Parameters!B$71*F9+C9*Parameters!B$71-Parameters!$B$5*C9^2/F9*Parameters!B$71 -> 0.28793279 | G10: =(1-Parameters!$B$4)^Parameters!B$71*G9+D9*Parameters!B$71-Parameters!$B$5*D9^2/G9*Parameters!B$71 -> 4.118346 | H10: =MAX(H9 * (1-Parameters!$B$4) ^ Parameters!B$71 + (LN(1+EXP(Parameters!$B$21*(-B9+0.004)))/Parameters!$B$21 -0.004) * Parameters!B$71,0) -> 0.045243886 | I10: =I9*(1+Parameters!$B$52)^Parameters!B$71 -> 8.3030174 | J10: =J9*(1+Parameters!$B$54)^Parameters!B$71 -> 10.194684 | K10: =I10*J10*EXP(-Parameters!$B$43*'6states'!A10)*(Parameters!$B$38/Parameters!$B$39*('6states'!E10+'6states'!H10)/Parameters!$E$25*(EXP(-Parameters!$B$39*Parameters!$E$25*'6states'!H10/('6states'!E10+'6states'!H10))-EXP(-Parameters!$B$39*Parameters!$E$25)) + Parameters!$B$40*'6states'!E10) -> 30.167742 | L10: =L9+K10*Parameters!B$71 -> 2514.1482 | M10: =L10*Parameters!$B$46 -> 1.5084889 | N10: =EXP(-Parameters!$B$47/2*M10^2) -> 0.97739035 | O10: =MAX((Parameters!$B$63 + Parameters!$B$31*'6states'!A10 - '6states'!L10 + Parameters!$B$48/Parameters!$B$46)/Parameters!B$63,1) -> 3.101037 | P10: =Parameters!B$62*EXP(-Parameters!B$61*A10) -> 0.4252206 | Q10: =(1-Parameters!B$62)*O10^-Parameters!B$64 -> 0.44649779 | R10: =Parameters!B$62*EXP(-Parameters!B$61*A10)+(1-Parameters!B$62)*O10^-Parameters!B$64 -> 0.87171839 | S10: =1-R10/Parameters!$B$12 -> 0.56414081 | T10: =1/(1-S10) -> 2.2943189 | U10: =(Parameters!$B$19*(E10+Parameters!$B$20)^S10+Parameters!$B$18*F10^S10)^(1/S10) -> 0.43065414 | V10: =(Parameters!$B$10*G10^Parameters!$B$9+Parameters!$B$11*U10^Parameters!$B$9)^(Parameters!$B$7/Parameters!$B$9)*N10 -> 1.4520046 | W10: =V10 - C10 - D10 - LN(1+EXP(Parameters!$B$21*B10))/Parameters!$B$21 - IF(B10>0, 0,Parameters!$B$6*B10^2/E10) -> 1.1639371 | X10: =EXP(-Parameters!$B$56*A10) -> 0.91338299 | Y10: =IF(W10>0,W10^(1-Parameters!$B$53)/(1-Parameters!$B$53)*X10*Parameters!$B$71,-10+W10*1000) -> -2.4746258 | AA10: =B10/E10-B9/E9 -> 0.002937395 | AB10: =C10/F10-C9/F9 -> -0.010679972 | AC10: =D10/G10-D9/G9 -> 0.00018578212 | AD10: =X10*(AA10^2+AB10^2+AC10^2) -> 0.00011209457 | AE10: =B10/E10-2*B9/E9+B8/E8 -> 0.0018182211 | AF10: =C10/F10-2*C9/F9+C8/F8 -> -0.00075914961 | AG10: =D10/G10-2*D9/G9+D8/G8 -> 0.00036626521 | AH10: =X10*(AE10^2+AF10^2+AG10^2) -> 3.6684991e-06 | AM10: =H10*I10*J10 -> 3.8297429 | AN10: =E10*I10*J10 -> 41.531548 | AO10: =U10*I10*J10 -> 36.453426 | AP10: =V10*J10*I10 -> 122.90731 | AQ10: =-X10*V10*W10^(-Parameters!B$53)*Parameters!B$47*Parameters!B$46*M10 -> -1.9656468e-05 | AR10: =1000*EXP(-(Parameters!$B$55)*'6states'!A10)*AP10*Parameters!B$47*Parameters!B$46*M10 -> 1.8113598 | AS10: =SUM(AR10:AR$204)*EXP(Parameters!$B$55*A10) -> 198.09677 | AT10: =((B10>0)*B10+C10+D10)/V10 -> 0.19760061 | AU10: =(1/$S10-1/Parameters!$B$13) * LN(Parameters!$B$18) / LN(O10) -> 0.23935638 | AV10: =(Parameters!$B$18*'6states'!S10^+Parameters!$B$19*Parameters!$B$25^'6states'!S10)^((1-'6states'!S10)/'6states'!S10)*Parameters!$B$18*Parameters!$B$26^('6states'!S10-1) -> 0.18226504 | AW10: =(LN(AV10)-LN(AV$4))/ LN(O10) -> 0.30040545 | AX10: =1-2^-AU10 -> 0.15287685 | AY10: =1-2^-AV10 -> 0.11868177 | AZ10: =(1/$S10-1/Parameters!$B$13) * LN(Parameters!$B$18) / A10 -> 0.045148061
A11: =A10+Parameters!$B$71 -> 7 | B11: -0.0035797568 | C11: 0.057714133 | D11: 0.23026833 | E11: =MAX((1-Parameters!$B$4)^Parameters!B$71*E10 + B10*Parameters!B$71 - IF(B10>0,Parameters!$B$5,0)*B10^2/E10*Parameters!B$71, 0.0001) -> 0.45838714 | F11: =(1-Parameters!$B$4)^Parameters!B$71*F10+C10*Parameters!B$71-Parameters!$B$5*C10^2/F10*Parameters!B$71 -> 0.31493936 | G11: =(1-Parameters!$B$4)^Parameters!B$71*G10+D10*Parameters!B$71-Parameters!$B$5*D10^2/G10*Parameters!B$71 -> 4.0772584 | H11: =MAX(H10 * (1-Parameters!$B$4) ^ Parameters!B$71 + (LN(1+EXP(Parameters!$B$21*(-B10+0.004)))/Parameters!$B$21 -0.004) * Parameters!B$71,0) -> 0.044068548 | I11: =I10*(1+Parameters!$B$52)^Parameters!B$71 -> 8.3270961 | J11: =J10*(1+Parameters!$B$54)^Parameters!B$71 -> 10.398578 | K11: =I11*J11*EXP(-Parameters!$B$43*'6states'!A11)*(Parameters!$B$38/Parameters!$B$39*('6states'!E11+'6states'!H11)/Parameters!$E$25*(EXP(-Parameters!$B$39*Parameters!$E$25*'6states'!H11/('6states'!E11+'6states'!H11))-EXP(-Parameters!$B$39*Parameters!$E$25)) + Parameters!$B$40*'6states'!E11) -> 28.524176 | L11: =L10+K11*Parameters!B$71 -> 2542.6723 | M11: =L11*Parameters!$B$46 -> 1.5256034 | N11: =EXP(-Parameters!$B$47/2*M11^2) -> 0.97688042 | O11: =MAX((Parameters!$B$63 + Parameters!$B$31*'6states'!A11 - '6states'!L11 + Parameters!$B$48/Parameters!$B$46)/Parameters!B$63,1) -> 3.5945535 | P11: =Parameters!B$62*EXP(-Parameters!B$61*A11) -> 0.41389325 | Q11: =(1-Parameters!B$62)*O11^-Parameters!B$64 -> 0.43995222 | R11: =Parameters!B$62*EXP(-Parameters!B$61*A11)+(1-Parameters!B$62)*O11^-Parameters!B$64 -> 0.85384547 | S11: =1-R11/Parameters!$B$12 -> 0.57307727 | T11: =1/(1-S11) -> 2.3423442 | U11: =(Parameters!$B$19*(E11+Parameters!$B$20)^S11+Parameters!$B$18*F11^S11)^(1/S11) -> 0.41903474 | V11: =(Parameters!$B$10*G11^Parameters!$B$9+Parameters!$B$11*U11^Parameters!$B$9)^(Parameters!$B$7/Parameters!$B$9)*N11 -> 1.4444336 | W11: =V11 - C11 - D11 - LN(1+EXP(Parameters!$B$21*B11))/Parameters!$B$21 - IF(B11>0, 0,Parameters!$B$6*B11^2/E11) -> 1.1557759 | X11: =EXP(-Parameters!$B$56*A11) -> 0.89969452 | Y11: =IF(W11>0,W11^(1-Parameters!$B$53)/(1-Parameters!$B$53)*X11*Parameters!$B$71,-10+W11*1000) -> -2.4435502 | AA11: =B11/E11-B10/E10 -> -0.0049614519 | AB11: =C11/F11-C10/F10 -> -0.011286087 | AC11: =D11/G11-D10/G10 -> 0.000409507 | AD11: =X11*(AA11^2+AB11^2+AC11^2) -> 0.00013689704 | AE11: =B11/E11-2*B10/E10+B9/E9 -> -0.0078988469 | AF11: =C11/F11-2*C10/F10+C9/F9 -> -0.00060611539 | AG11: =D11/G11-2*D10/G10+D9/G9 -> 0.00022372487 | AH11: =X11*(AE11^2+AF11^2+AG11^2) -> 5.6509102e-05 | AM11: =H11*I11*J11 -> 3.8158937 | AN11: =E11*I11*J11 -> 39.691723 | AO11: =U11*I11*J11 -> 36.284201 | AP11: =V11*J11*I11 -> 125.07344 | AQ11: =-X11*V11*W11^(-Parameters!B$53)*Parameters!B$47*Parameters!B$46*M11 -> -1.9665374e-05 | AR11: =1000*EXP(-(Parameters!$B$55)*'6states'!A11)*AP11*Parameters!B$47*Parameters!B$46*M11 -> 1.799898 | AS11: =SUM(AR11:AR$204)*EXP(Parameters!$B$55*A11) -> 202.85758 | AT11: =((B11>0)*B11+C11+D11)/V11 -> 0.19937398 | AU11: =(1/$S11-1/Parameters!$B$13) * LN(Parameters!$B$18) / LN(O11) -> 0.23746494 | AV11: =(Parameters!$B$18*'6states'!S11^+Parameters!$B$19*Parameters!$B$25^'6states'!S11)^((1-'6states'!S11)/'6states'!S11)*Parameters!$B$18*Parameters!$B$26^('6states'!S11-1) -> 0.18920883 | AW11: =(LN(AV11)-LN(AV$4))/ LN(O11) -> 0.29495342 | AX11: =1-2^-AU11 -> 0.15176551 | AY11: =1-2^-AV11 -> 0.12291342 | AZ11: =(1/$S11-1/Parameters!$B$13) * LN(Parameters!$B$18) / A11 -> 0.043402478
A12: =A11+Parameters!$B$71 -> 8 | B12: -0.00065021139 | C12: 0.058701307 | D12: 0.22970673 | E12: =MAX((1-Parameters!$B$4)^Parameters!B$71*E11 + B11*Parameters!B$71 - IF(B11>0,Parameters!$B$5,0)*B11^2/E11*Parameters!B$71, 0.0001) -> 0.42597484 | F12: =(1-Parameters!$B$4)^Parameters!B$71*F11+C11*Parameters!B$71-Parameters!$B$5*C11^2/F11*Parameters!B$71 -> 0.34226742 | G12: =(1-Parameters!$B$4)^Parameters!B$71*G11+D11*Parameters!B$71-Parameters!$B$5*D11^2/G11*Parameters!B$71 -> 4.0380625 | H12: =MAX(H11 * (1-Parameters!$B$4) ^ Parameters!B$71 + (LN(1+EXP(Parameters!$B$21*(-B11+0.004)))/Parameters!$B$21 -0.004) * Parameters!B$71,0) -> 0.044994136 | I12: =I11*(1+Parameters!$B$52)^Parameters!B$71 -> 8.3512447 | J12: =J11*(1+Parameters!$B$54)^Parameters!B$71 -> 10.606549 | K12: =I12*J12*EXP(-Parameters!$B$43*'6states'!A12)*(Parameters!$B$38/Parameters!$B$39*('6states'!E12+'6states'!H12)/Parameters!$E$25*(EXP(-Parameters!$B$39*Parameters!$E$25*'6states'!H12/('6states'!E12+'6states'!H12))-EXP(-Parameters!$B$39*Parameters!$E$25)) + Parameters!$B$40*'6states'!E12) -> 26.80968 | L12: =L11+K12*Parameters!B$71 -> 2569.482 | M12: =L12*Parameters!$B$46 -> 1.5416892 | N12: =EXP(-Parameters!$B$47/2*M12^2) -> 0.97639614 | O12: =MAX((Parameters!$B$63 + Parameters!$B$31*'6states'!A12 - '6states'!L12 + Parameters!$B$48/Parameters!$B$46)/Parameters!B$63,1) -> 4.1223599 | P12: =Parameters!B$62*EXP(-Parameters!B$61*A12) -> 0.40286765 | Q12: =(1-Parameters!B$62)*O12^-Parameters!B$64 -> 0.43396571 | R12: =Parameters!B$62*EXP(-Parameters!B$61*A12)+(1-Parameters!B$62)*O12^-Parameters!B$64 -> 0.83683336 | S12: =1-R12/Parameters!$B$12 -> 0.58158332 | T12: =1/(1-S12) -> 2.3899621 | U12: =(Parameters!$B$19*(E12+Parameters!$B$20)^S12+Parameters!$B$18*F12^S12)^(1/S12) -> 0.40650392 | V12: =(Parameters!$B$10*G12^Parameters!$B$9+Parameters!$B$11*U12^Parameters!$B$9)^(Parameters!$B$7/Parameters!$B$9)*N12 -> 1.436471 | W12: =V12 - C12 - D12 - LN(1+EXP(Parameters!$B$21*B12))/Parameters!$B$21 - IF(B12>0, 0,Parameters!$B$6*B12^2/E12) -> 1.1466291 | X12: =EXP(-Parameters!$B$56*A12) -> 0.88621118 | Y12: =IF(W12>0,W12^(1-Parameters!$B$53)/(1-Parameters!$B$53)*X12*Parameters!$B$71,-10+W12*1000) -> -2.4136325 | AA12: =B12/E12-B11/E11 -> 0.0062830536 | AB12: =C12/F12-C11/F11 -> -0.011747605 | AC12: =D12/G12-D11/G11 -> 0.00040911705 | AD12: =X12*(AA12^2+AB12^2+AC12^2) -> 0.00015743573 | AE12: =B12/E12-2*B11/E11+B10/E10 -> 0.011244505 | AF12: =C12/F12-2*C11/F11+C10/F10 -> -0.00046151742 | AG12: =D12/G12-2*D11/G11+D10/G10 -> -3.8994925e-07 | AH12: =X12*(AE12^2+AF12^2+AG12^2) -> 0.00011224033 | AM12: =H12*I12*J12 -> 3.9854856 | AN12: =E12*I12*J12 -> 37.731952 | AO12: =U12*I12*J12 -> 36.007259 | AP12: =V12*J12*I12 -> 127.23957 | AQ12: =-X12*V12*W12^(-Parameters!B$53)*Parameters!B$47*Parameters!B$46*M12 -> -1.9676924e-05 | AR12: =1000*EXP(-(Parameters!$B$55)*'6states'!A12)*AP12*Parameters!B$47*Parameters!B$46*M12 -> 1.7865552 | AS12: =SUM(AR12:AR$204)*EXP(Parameters!$B$55*A12) -> 207.72092 | AT12: =((B12>0)*B12+C12+D12)/V12 -> 0.2007754 | AU12: =(1/$S12-1/Parameters!$B$13) * LN(Parameters!$B$18) / LN(O12) -> 0.23596037 | AV12: =(Parameters!$B$18*'6states'!S12^+Parameters!$B$19*Parameters!$B$25^'6states'!S12)^((1-'6states'!S12)/'6states'!S12)*Parameters!$B$18*Parameters!$B$26^('6states'!S12-1) -> 0.19568911 | AW12: =(LN(AV12)-LN(AV$4))/ LN(O12) -> 0.29019885 | AX12: =1-2^-AU12 -> 0.15088043 | AY12: =1-2^-AV12 -> 0.12684427 | AZ12: =(1/$S12-1/Parameters!$B$13) * LN(Parameters!$B$18) / A12 -> 0.041777544
A13: =A12+Parameters!$B$71 -> 9 | B13: 0.014940549 | C13: 0.05910464 | D13: 0.22364574 | E13: =MAX((1-Parameters!$B$4)^Parameters!B$71*E12 + B12*Parameters!B$71 - IF(B12>0,Parameters!$B$5,0)*B12^2/E12*Parameters!B$71, 0.0001) -> 0.39853081 | F13: =(1-Parameters!$B$4)^Parameters!B$71*F12+C12*Parameters!B$71-Parameters!$B$5*C12^2/F12*Parameters!B$71 -> 0.36937241 | G13: =(1-Parameters!$B$4)^Parameters!B$71*G12+D12*Parameters!B$71-Parameters!$B$5*D12^2/G12*Parameters!B$71 -> 4.0007082 | H13: =MAX(H12 * (1-Parameters!$B$4) ^ Parameters!B$71 + (LN(1+EXP(Parameters!$B$21*(-B12+0.004)))/Parameters!$B$21 -0.004) * Parameters!B$71,0) -> 0.043175894 | I13: =I12*(1+Parameters!$B$52)^Parameters!B$71 -> 8.3754633 | J13: =J12*(1+Parameters!$B$54)^Parameters!B$71 -> 10.81868 | K13: =I13*J13*EXP(-Parameters!$B$43*'6states'!A13)*(Parameters!$B$38/Parameters!$B$39*('6states'!E13+'6states'!H13)/Parameters!$E$25*(EXP(-Parameters!$B$39*Parameters!$E$25*'6states'!H13/('6states'!E13+'6states'!H13))-EXP(-Parameters!$B$39*Parameters!$E$25)) + Parameters!$B$40*'6states'!E13) -> 25.395104 | L13: =L12+K13*Parameters!B$71 -> 2594.8771 | M13: =L13*Parameters!$B$46 -> 1.5569263 | N13: =EXP(-Parameters!$B$47/2*M13^2) -> 0.97593295 | O13: =MAX((Parameters!$B$63 + Parameters!$B$31*'6states'!A13 - '6states'!L13 + Parameters!$B$48/Parameters!$B$46)/Parameters!B$63,1) -> 4.6784578 | P13: =Parameters!B$62*EXP(-Parameters!B$61*A13) -> 0.39213576 | Q13: =(1-Parameters!B$62)*O13^-Parameters!B$64 -> 0.42850879 | R13: =Parameters!B$62*EXP(-Parameters!B$61*A13)+(1-Parameters!B$62)*O13^-Parameters!B$64 -> 0.82064454 | S13: =1-R13/Parameters!$B$12 -> 0.58967773 | T13: =1/(1-S13) -> 2.4371088 | U13: =(Parameters!$B$19*(E13+Parameters!$B$20)^S13+Parameters!$B$18*F13^S13)^(1/S13) -> 0.39646223 | V13: =(Parameters!$B$10*G13^Parameters!$B$9+Parameters!$B$11*U13^Parameters!$B$9)^(Parameters!$B$7/Parameters!$B$9)*N13 -> 1.4293618 | W13: =V13 - C13 - D13 - LN(1+EXP(Parameters!$B$21*B13))/Parameters!$B$21 - IF(B13>0, 0,Parameters!$B$6*B13^2/E13) -> 1.1316645 | X13: =EXP(-Parameters!$B$56*A13) -> 0.87292992 | Y13: =IF(W13>0,W13^(1-Parameters!$B$53)/(1-Parameters!$B$53)*X13*Parameters!$B$71,-10+W13*1000) -> -2.3884169 | AA13: =B13/E13-B12/E12 -> 0.039015476 | AB13: =C13/F13-C12/F12 -> -0.01149346 | AC13: =D13/G13-D12/G12 -> -0.00098384512 | AD13: =X13*(AA13^2+AB13^2+AC13^2) -> 0.0014449391 | AE13: =B13/E13-2*B12/E12+B11/E11 -> 0.032732423 | AF13: =C13/F13-2*C12/F12+C11/F11 -> 0.00025414496 | AG13: =D13/G13-2*D12/G12+D11/G11 -> -0.0013929622 | AH13: =X13*(AE13^2+AF13^2+AG13^2) -> 0.00093701733 | AM13: =H13*I13*J13 -> 3.9122309 | AN13: =E13*I13*J13 -> 36.111459 | AO13: =U13*I13*J13 -> 35.924022 | AP13: =V13*J13*I13 -> 129.51656 | AQ13: =-X13*V13*W13^(-Parameters!B$53)*Parameters!B$47*Parameters!B$46*M13 -> -1.982522e-05 | AR13: =1000*EXP(-(Parameters!$B$55)*'6states'!A13)*AP13*Parameters!B$47*Parameters!B$46*M13 -> 1.7731563 | AS13: =SUM(AR13:AR$204)*EXP(Parameters!$B$55*A13) -> 212.69114 | AT13: =((B13>0)*B13+C13+D13)/V13 -> 0.20826843 | AU13: =(1/$S13-1/Parameters!$B$13) * LN(Parameters!$B$18) / LN(O13) -> 0.23483145 | AV13: =(Parameters!$B$18*'6states'!S13^+Parameters!$B$19*Parameters!$B$25^'6states'!S13)^((1-'6states'!S13)/'6states'!S13)*Parameters!$B$18*Parameters!$B$26^('6states'!S13-1) -> 0.20172899 | AW13: =(LN(AV13)-LN(AV$4))/ LN(O13) -> 0.28609987 | AX13: =1-2^-AU13 -> 0.15021573 | AY13: =1-2^-AV13 -> 0.13049212 | AZ13: =(1/$S13-1/Parameters!$B$13) * LN(Parameters!$B$18) / A13 -> 0.040259726
A14: =A13+Parameters!$B$71 -> 10 | B14: 0.024351969 | C14: 0.059466325 | D14: 0.22088997 | E14: =MAX((1-Parameters!$B$4)^Parameters!B$71*E13 + B13*Parameters!B$71 - IF(B13>0,Parameters!$B$5,0)*B13^2/E13*Parameters!B$71, 0.0001) -> 0.38784366 | F14: =(1-Parameters!$B$4)^Parameters!B$71*F13+C13*Parameters!B$71-Parameters!$B$5*C13^2/F13*Parameters!B$71 -> 0.39578598 | G14: =(1-Parameters!$B$4)^Parameters!B$71*G13+D13*Parameters!B$71-Parameters!$B$5*D13^2/G13*Parameters!B$71 -> 3.9602072 | H14: =MAX(H13 * (1-Parameters!$B$4) ^ Parameters!B$71 + (LN(1+EXP(Parameters!$B$21*(-B13+0.004)))/Parameters!$B$21 -0.004) * Parameters!B$71,0) -> 0.036491366 | I14: =I13*(1+Parameters!$B$52)^Parameters!B$71 -> 8.3997522 | J14: =J13*(1+Parameters!$B$54)^Parameters!B$71 -> 11.035054 | K14: =I14*J14*EXP(-Parameters!$B$43*'6states'!A14)*(Parameters!$B$38/Parameters!$B$39*('6states'!E14+'6states'!H14)/Parameters!$E$25*(EXP(-Parameters!$B$39*Parameters!$E$25*'6states'!H14/('6states'!E14+'6states'!H14))-EXP(-Parameters!$B$39*Parameters!$E$25)) + Parameters!$B$40*'6states'!E14) -> 25.080584 | L14: =L13+K14*Parameters!B$71 -> 2619.9577 | M14: =L14*Parameters!$B$46 -> 1.5719746 | N14: =EXP(-Parameters!$B$47/2*M14^2) -> 0.97547124 | O14: =MAX((Parameters!$B$63 + Parameters!$B$31*'6states'!A14 - '6states'!L14 + Parameters!$B$48/Parameters!$B$46)/Parameters!B$63,1) -> 5.2408461 | P14: =Parameters!B$62*EXP(-Parameters!B$61*A14) -> 0.38168975 | Q14: =(1-Parameters!B$62)*O14^-Parameters!B$64 -> 0.4236721 | R14: =Parameters!B$62*EXP(-Parameters!B$61*A14)+(1-Parameters!B$62)*O14^-Parameters!B$64 -> 0.80536185 | S14: =1-R14/Parameters!$B$12 -> 0.59731908 | T14: =1/(1-S14) -> 2.4833558 | U14: =(Parameters!$B$19*(E14+Parameters!$B$20)^S14+Parameters!$B$18*F14^S14)^(1/S14) -> 0.39721802 | V14: =(Parameters!$B$10*G14^Parameters!$B$9+Parameters!$B$11*U14^Parameters!$B$9)^(Parameters!$B$7/Parameters!$B$9)*N14 -> 1.4262004 | W14: =V14 - C14 - D14 - LN(1+EXP(Parameters!$B$21*B14))/Parameters!$B$21 - IF(B14>0, 0,Parameters!$B$6*B14^2/E14) -> 1.121492 | X14: =EXP(-Parameters!$B$56*A14) -> 0.8598477 | Y14: =IF(W14>0,W14^(1-Parameters!$B$53)/(1-Parameters!$B$53)*X14*Parameters!$B$71,-10+W14*1000) -> -2.3600697 | AA14: =B14/E14-B13/E13 -> 0.025299038 | AB14: =C14/F14-C13/F13 -> -0.0097649924 | AC14: =D14/G14-D13/G13 -> -0.00012415986 | AD14: =X14*(AA14^2+AB14^2+AC14^2) -> 0.00063234215 | AE14: =B14/E14-2*B13/E13+B12/E12 -> -0.013716439 | AF14: =C14/F14-2*C13/F13+C12/F12 -> 0.0017284674 | AG14: =D14/G14-2*D13/G13+D12/G12 -> 0.00085968526 | AH14: =X14*(AE14^2+AF14^2+AG14^2) -> 0.0001649767 | AM14: =H14*I14*J14 -> 3.3824475 | AN14: =E14*I14*J14 -> 35.949896 | AO14: =U14*I14*J14 -> 36.818821 | AP14: =V14*J14*I14 -> 132.19697 | AQ14: =-X14*V14*W14^(-Parameters!B$53)*Parameters!B$47*Parameters!B$46*M14 -> -1.9914531e-05 | AR14: =1000*EXP(-(Parameters!$B$55)*'6states'!A14)*AP14*Parameters!B$47*Parameters!B$46*M14 -> 1.7643184 | AS14: =SUM(AR14:AR$204)*EXP(Parameters!$B$55*A14) -> 217.77042 | AT14: =(B14+C14+D14)/V14 -> 0.21365039 | AU14: =(1/$S14-1/Parameters!$B$13) * LN(Parameters!$B$18) / LN(O14) -> 0.23434089 | AV14: =(Parameters!$B$18*'6states'!S14^+Parameters!$B$19*Parameters!$B$25^'6states'!S14)^((1-'6states'!S14)/'6states'!S14)*Parameters!$B$18*Parameters!$B$26^('6states'!S14-1) -> 0.20730973 | AW14: =(LN(AV14)-LN(AV$4))/ LN(O14) -> 0.28296812 | AX14: =1-2^-AU14 -> 0.14992673 | AY14: =1-2^-AV14 -> 0.13384911 | AZ14: =(1/$S14-1/Parameters!$B$13) * LN(Parameters!$B$18) / A14 -> 0.03881817
A15: =A14+Parameters!$B$71 -> 11 | B15: 0.0277171 | C15: 0.060311935 | D15: 0.22097238 | E15: =MAX((1-Parameters!$B$4)^Parameters!B$71*E14 + B14*Parameters!B$71 - IF(B14>0,Parameters!$B$5,0)*B14^2/E14*Parameters!B$71, 0.0001) -> 0.38627125 | F15: =(1-Parameters!$B$4)^Parameters!B$71*F14+C14*Parameters!B$71-Parameters!$B$5*C14^2/F14*Parameters!B$71 -> 0.42142263 | G15: =(1-Parameters!$B$4)^Parameters!B$71*G14+D14*Parameters!B$71-Parameters!$B$5*D14^2/G14*Parameters!B$71 -> 3.9196795 | H15: =MAX(H14 * (1-Parameters!$B$4) ^ Parameters!B$71 + (LN(1+EXP(Parameters!$B$21*(-B14+0.004)))/Parameters!$B$21 -0.004) * Parameters!B$71,0) -> 0.030196788 | I15: =I14*(1+Parameters!$B$52)^Parameters!B$71 -> 8.4241114 | J15: =J14*(1+Parameters!$B$54)^Parameters!B$71 -> 11.255755 | K15: =I15*J15*EXP(-Parameters!$B$43*'6states'!A15)*(Parameters!$B$38/Parameters!$B$39*('6states'!E15+'6states'!H15)/Parameters!$E$25*(EXP(-Parameters!$B$39*Parameters!$E$25*'6states'!H15/('6states'!E15+'6states'!H15))-EXP(-Parameters!$B$39*Parameters!$E$25)) + Parameters!$B$40*'6states'!E15) -> 25.397481 | L15: =L14+K15*Parameters!B$71 -> 2645.3552 | M15: =L15*Parameters!$B$46 -> 1.5872131 | N15: =EXP(-Parameters!$B$47/2*M15^2) -> 0.97499941 | O15: =MAX((Parameters!$B$63 + Parameters!$B$31*'6states'!A15 - '6states'!L15 + Parameters!$B$48/Parameters!$B$46)/Parameters!B$63,1) -> 5.7968965 | P15: =Parameters!B$62*EXP(-Parameters!B$61*A15) -> 0.37152201 | Q15: =(1-Parameters!B$62)*O15^-Parameters!B$64 -> 0.41942127 | R15: =Parameters!B$62*EXP(-Parameters!B$61*A15)+(1-Parameters!B$62)*O15^-Parameters!B$64 -> 0.79094327 | S15: =1-R15/Parameters!$B$12 -> 0.60452836 | T15: =1/(1-S15) -> 2.5286263 | U15: =(Parameters!$B$19*(E15+Parameters!$B$20)^S15+Parameters!$B$18*F15^S15)^(1/S15) -> 0.40384827 | V15: =(Parameters!$B$10*G15^Parameters!$B$9+Parameters!$B$11*U15^Parameters!$B$9)^(Parameters!$B$7/Parameters!$B$9)*N15 -> 1.425062 | W15: =V15 - C15 - D15 - LN(1+EXP(Parameters!$B$21*B15))/Parameters!$B$21 - IF(B15>0, 0,Parameters!$B$6*B15^2/E15) -> 1.1160606 | X15: =EXP(-Parameters!$B$56*A15) -> 0.84696153 | Y15: =IF(W15>0,W15^(1-Parameters!$B$53)/(1-Parameters!$B$53)*X15*Parameters!$B$71,-10+W15*1000) -> -2.3286538 | AA15: =B15/E15-B14/E14 -> 0.0089674291 | AB15: =C15/F15-C14/F14 -> -0.0071336042 | AC15: =D15/G15-D14/G14 -> 0.00059773625 | AD15: =X15*(AA15^2+AB15^2+AC15^2) -> 0.00011151128 | AE15: =B15/E15-2*B14/E14+B13/E13 -> -0.016331609 | AF15: =C15/F15-2*C14/F14+C13/F13 -> 0.0026313882 | AG15: =D15/G15-2*D14/G14+D13/G13 -> 0.00072189611 | AH15: =X15*(AE15^2+AF15^2+AG15^2) -> 0.00023220872 | AM15: =H15*I15*J15 -> 2.8632514 | AN15: =E15*I15*J15 -> 36.626138 | AO15: =U15*I15*J15 -> 38.292786 | AP15: =V15*J15*I15 -> 135.124 | AQ15: =-X15*V15*W15^(-Parameters!B$53)*Parameters!B$47*Parameters!B$46*M15 -> -1.9920559e-05 | AR15: =1000*EXP(-(Parameters!$B$55)*'6states'!A15)*AP15*Parameters!B$47*Parameters!B$46*M15 -> 1.7580611 | AS15: =SUM(AR15:AR$204)*EXP(Parameters!$B$55*A15) -> 222.95417 | AT15: =(B15+C15+D15)/V15 -> 0.21683366 | AU15: =(1/$S15-1/Parameters!$B$13) * LN(Parameters!$B$18) / LN(O15) -> 0.23442796 | AV15: =(Parameters!$B$18*'6states'!S15^+Parameters!$B$19*Parameters!$B$25^'6states'!S15)^((1-'6states'!S15)/'6states'!S15)*Parameters!$B$18*Parameters!$B$26^('6states'!S15-1) -> 0.21246127 | AW15: =(LN(AV15)-LN(AV$4))/ LN(O15) -> 0.28069838 | AX15: =1-2^-AU15 -> 0.14997803 | AY15: =1-2^-AV15 -> 0.13693643 | AZ15: =(1/$S15-1/Parameters!$B$13) * LN(Parameters!$B$18) / A15 -> 0.037451416
A16: =A15+Parameters!$B$71 -> 12 | B16: 0.025652145 | C16: 0.061999034 | D16: 0.22351418 | E16: =MAX((1-Parameters!$B$4)^Parameters!B$71*E15 + B15*Parameters!B$71 - IF(B15>0,Parameters!$B$5,0)*B15^2/E15*Parameters!B$71, 0.0001) -> 0.38770303 | F16: =(1-Parameters!$B$4)^Parameters!B$71*F15+C15*Parameters!B$71-Parameters!$B$5*C15^2/F15*Parameters!B$71 -> 0.44659553 | G16: =(1-Parameters!$B$4)^Parameters!B$71*G15+D15*Parameters!B$71-Parameters!$B$5*D15^2/G15*Parameters!B$71 -> 3.8816467 | H16: =MAX(H15 * (1-Parameters!$B$4) ^ Parameters!B$71 + (LN(1+EXP(Parameters!$B$21*(-B15+0.004)))/Parameters!$B$21 -0.004) * Parameters!B$71,0) -> 0.024297599 | I16: =I15*(1+Parameters!$B$52)^Parameters!B$71 -> 8.4485414 | J16: =J15*(1+Parameters!$B$54)^Parameters!B$71 -> 11.48087 | K16: =I16*J16*EXP(-Parameters!$B$43*'6states'!A16)*(Parameters!$B$38/Parameters!$B$39*('6states'!E16+'6states'!H16)/Parameters!$E$25*(EXP(-Parameters!$B$39*Parameters!$E$25*'6states'!H16/('6states'!E16+'6states'!H16))-EXP(-Parameters!$B$39*Parameters!$E$25)) + Parameters!$B$40*'6states'!E16) -> 25.995005 | L16: =L15+K16*Parameters!B$71 -> 2671.3502 | M16: =L16*Parameters!$B$46 -> 1.6028101 | N16: =EXP(-Parameters!$B$47/2*M16^2) -> 0.97451199 | O16: =MAX((Parameters!$B$63 + Parameters!$B$31*'6states'!A16 - '6states'!L16 + Parameters!$B$48/Parameters!$B$46)/Parameters!B$63,1) -> 6.3409964 | P16: =Parameters!B$62*EXP(-Parameters!B$61*A16) -> 0.36162512 | Q16: =(1-Parameters!B$62)*O16^-Parameters!B$64 -> 0.41567533 | R16: =Parameters!B$62*EXP(-Parameters!B$61*A16)+(1-Parameters!B$62)*O16^-Parameters!B$64 -> 0.77730045 | S16: =1-R16/Parameters!$B$12 -> 0.61134977 | T16: =1/(1-S16) -> 2.5730076 | U16: =(Parameters!$B$19*(E16+Parameters!$B$20)^S16+Parameters!$B$18*F16^S16)^(1/S16) -> 0.41232483 | V16: =(Parameters!$B$10*G16^Parameters!$B$9+Parameters!$B$11*U16^Parameters!$B$9)^(Parameters!$B$7/Parameters!$B$9)*N16 -> 1.4243407 | W16: =V16 - C16 - D16 - LN(1+EXP(Parameters!$B$21*B16))/Parameters!$B$21 - IF(B16>0, 0,Parameters!$B$6*B16^2/E16) -> 1.1131753 | X16: =EXP(-Parameters!$B$56*A16) -> 0.83426849 | Y16: =IF(W16>0,W16^(1-Parameters!$B$53)/(1-Parameters!$B$53)*X16*Parameters!$B$71,-10+W16*1000) -> -2.2958343 | AA16: =B16/E16-B15/E15 -> -0.0055911186 | AB16: =C16/F16-C15/F15 -> -0.0042891691 | AC16: =D16/G16-D15/G15 -> 0.0012071944 | AD16: =X16*(AA16^2+AB16^2+AC16^2) -> 4.2643548e-05 | AE16: =B16/E16-2*B15/E15+B14/E14 -> -0.014558548 | AF16: =C16/F16-2*C15/F15+C14/F14 -> 0.0028444351 | AG16: =D16/G16-2*D15/G15+D14/G14 -> 0.00060945813 | AH16: =X16*(AE16^2+AF16^2+AG16^2) -> 0.00018388409 | AM16: =H16*I16*J16 -> 2.3567847 | AN16: =E16*I16*J16 -> 37.605879 | AO16: =U16*I16*J16 -> 39.994109 | AP16: =V16*J16*I16 -> 138.15622 | AQ16: =-X16*V16*W16^(-Parameters!B$53)*Parameters!B$47*Parameters!B$46*M16 -> -1.9874138e-05 | AR16: =1000*EXP(-(Parameters!$B$55)*'6states'!A16)*AP16*Parameters!B$47*Parameters!B$46*M16 -> 1.7525684 | AS16: =SUM(AR16:AR$204)*EXP(Parameters!$B$55*A16) -> 228.23991 | AT16: =(B16+C16+D16)/V16 -> 0.21846272 | AU16: =(1/$S16-1/Parameters!$B$13) * LN(Parameters!$B$18) / LN(O16) -> 0.23494581 | AV16: =(Parameters!$B$18*'6states'!S16^+Parameters!$B$19*Parameters!$B$25^'6states'!S16)^((1-'6states'!S16)/'6states'!S16)*Parameters!$B$18*Parameters!$B$26^('6states'!S16-1) -> 0.2172296 | AW16: =(LN(AV16)-LN(AV$4))/ LN(O16) -> 0.27908108 | AX16: =1-2^-AU16 -> 0.15028308 | AY16: =1-2^-AV16 -> 0.13978428 | AZ16: =(1/$S16-1/Parameters!$B$13) * LN(Parameters!$B$18) / A16 -> 0.036162778
A17: =A16+Parameters!$B$71 -> 13 | B17: 0.016234739 | C17: 0.064698149 | D17: 0.22825968 | E17: =MAX((1-Parameters!$B$4)^Parameters!B$71*E16 + B16*Parameters!B$71 - IF(B16>0,Parameters!$B$5,0)*B16^2/E16*Parameters!B$71, 0.0001) -> 0.3872714 | F17: =(1-Parameters!$B$4)^Parameters!B$71*F16+C16*Parameters!B$71-Parameters!$B$5*C16^2/F16*Parameters!B$71 -> 0.47189663 | G17: =(1-Parameters!$B$4)^Parameters!B$71*G16+D16*Parameters!B$71-Parameters!$B$5*D16^2/G16*Parameters!B$71 -> 3.8481348 | H17: =MAX(H16 * (1-Parameters!$B$4) ^ Parameters!B$71 + (LN(1+EXP(Parameters!$B$21*(-B16+0.004)))/Parameters!$B$21 -0.004) * Parameters!B$71,0) -> 0.018769714 | I17: =I16*(1+Parameters!$B$52)^Parameters!B$71 -> 8.4730421 | J17: =J16*(1+Parameters!$B$54)^Parameters!B$71 -> 11.710488 | K17: =I17*J17*EXP(-Parameters!$B$43*'6states'!A17)*(Parameters!$B$38/Parameters!$B$39*('6states'!E17+'6states'!H17)/Parameters!$E$25*(EXP(-Parameters!$B$39*Parameters!$E$25*'6states'!H17/('6states'!E17+'6states'!H17))-EXP(-Parameters!$B$39*Parameters!$E$25)) + Parameters!$B$40*'6states'!E17) -> 26.589699 | L17: =L16+K17*Parameters!B$71 -> 2697.9399 | M17: =L17*Parameters!$B$46 -> 1.6187639 | N17: =EXP(-Parameters!$B$47/2*M17^2) -> 0.97400876 | O17: =MAX((Parameters!$B$63 + Parameters!$B$31*'6states'!A17 - '6states'!L17 + Parameters!$B$48/Parameters!$B$46)/Parameters!B$63,1) -> 6.8732024 | P17: =Parameters!B$62*EXP(-Parameters!B$61*A17) -> 0.35199188 | Q17: =(1-Parameters!B$62)*O17^-Parameters!B$64 -> 0.41233869 | R17: =Parameters!B$62*EXP(-Parameters!B$61*A17)+(1-Parameters!B$62)*O17^-Parameters!B$64 -> 0.76433057 | S17: =1-R17/Parameters!$B$12 -> 0.61783471 | T17: =1/(1-S17) -> 2.6166689 | U17: =(Parameters!$B$19*(E17+Parameters!$B$20)^S17+Parameters!$B$18*F17^S17)^(1/S17) -> 0.41942474 | V17: =(Parameters!$B$10*G17^Parameters!$B$9+Parameters!$B$11*U17^Parameters!$B$9)^(Parameters!$B$7/Parameters!$B$9)*N17 -> 1.4231437 | W17: =V17 - C17 - D17 - LN(1+EXP(Parameters!$B$21*B17))/Parameters!$B$21 - IF(B17>0, 0,Parameters!$B$6*B17^2/E17) -> 1.1139474 | X17: =EXP(-Parameters!$B$56*A17) -> 0.82176567 | Y17: =IF(W17>0,W17^(1-Parameters!$B$53)/(1-Parameters!$B$53)*X17*Parameters!$B$71,-10+W17*1000) -> -2.260879 | AA17: =B17/E17-B16/E16 -> -0.024243585 | AB17: =C17/F17-C16/F16 -> -0.0017235429 | AC17: =D17/G17-D16/G16 -> 0.0017346572 | AD17: =X17*(AA17^2+AB17^2+AC17^2) -> 0.00048790779 | AE17: =B17/E17-2*B16/E16+B15/E15 -> -0.018652466 | AF17: =C17/F17-2*C16/F16+C15/F15 -> 0.0025656261 | AG17: =D17/G17-2*D16/G16+D15/G15 -> 0.00052746279 | AH17: =X17*(AE17^2+AF17^2+AG17^2) -> 0.00029154205 | AM17: =H17*I17*J17 -> 1.8623958 | AN17: =E17*I17*J17 -> 38.426406 | AO17: =U17*I17*J17 -> 41.616772 | AP17: =V17*J17*I17 -> 141.20924 | AQ17: =-X17*V17*W17^(-Parameters!B$53)*Parameters!B$47*Parameters!B$46*M17 -> -1.9736052e-05 | AR17: =1000*EXP(-(Parameters!$B$55)*'6states'!A17)*AP17*Parameters!B$47*Parameters!B$46*M17 -> 1.7467283 | AS17: =SUM(AR17:AR$204)*EXP(Parameters!$B$55*A17) -> 233.62744 | AT17: =(B17+C17+D17)/V17 -> 0.21726026 | AU17: =(1/$S17-1/Parameters!$B$13) * LN(Parameters!$B$18) / LN(O17) -> 0.23573317 | AV17: =(Parameters!$B$18*'6states'!S17^+Parameters!$B$19*Parameters!$B$25^'6states'!S17)^((1-'6states'!S17)/'6states'!S17)*Parameters!$B$18*Parameters!$B$26^('6states'!S17-1) -> 0.22166368 | AW17: =(LN(AV17)-LN(AV$4))/ LN(O17) -> 0.27789521 | AX17: =1-2^-AU17 -> 0.1507467 | AY17: =1-2^-AV17 -> 0.14242407 | AZ17: =(1/$S17-1/Parameters!$B$13) * LN(Parameters!$B$18) / A17 -> 0.034954336
A18: =A17+Parameters!$B$71 -> 14 | B18: -0.00038015281 | C18: 0.068013288 | D18: 0.2331651 | E18: =MAX((1-Parameters!$B$4)^Parameters!B$71*E17 + B17*Parameters!B$71 - IF(B17>0,Parameters!$B$5,0)*B17^2/E17*Parameters!B$71, 0.0001) -> 0.37846619 | F18: =(1-Parameters!$B$4)^Parameters!B$71*F17+C17*Parameters!B$71-Parameters!$B$5*C17^2/F17*Parameters!B$71 -> 0.49804221 | G18: =(1-Parameters!$B$4)^Parameters!B$71*G17+D17*Parameters!B$71-Parameters!$B$5*D17^2/G17*Parameters!B$71 -> 3.8208072 | H18: =MAX(H17 * (1-Parameters!$B$4) ^ Parameters!B$71 + (LN(1+EXP(Parameters!$B$21*(-B17+0.004)))/Parameters!$B$21 -0.004) * Parameters!B$71,0) -> 0.013607759 | I18: =I17*(1+Parameters!$B$52)^Parameters!B$71 -> 8.497614 | J18: =J17*(1+Parameters!$B$54)^Parameters!B$71 -> 11.944697 | K18: =I18*J18*EXP(-Parameters!$B$43*'6states'!A18)*(Parameters!$B$38/Parameters!$B$39*('6states'!E18+'6states'!H18)/Parameters!$E$25*(EXP(-Parameters!$B$39*Parameters!$E$25*'6states'!H18/('6states'!E18+'6states'!H18))-EXP(-Parameters!$B$39*Parameters!$E$25)) + Parameters!$B$40*'6states'!E18) -> 26.748415 | L18: =L17+K18*Parameters!B$71 -> 2724.6883 | M18: =L18*Parameters!$B$46 -> 1.634813 | N18: =EXP(-Parameters!$B$47/2*M18^2) -> 0.97349775 | O18: =MAX((Parameters!$B$63 + Parameters!$B$31*'6states'!A18 - '6states'!L18 + Parameters!$B$48/Parameters!$B$46)/Parameters!B$63,1) -> 7.4022341 | P18: =Parameters!B$62*EXP(-Parameters!B$61*A18) -> 0.34261525 | Q18: =(1-Parameters!B$62)*O18^-Parameters!B$64 -> 0.40929244 | R18: =Parameters!B$62*EXP(-Parameters!B$61*A18)+(1-Parameters!B$62)*O18^-Parameters!B$64 -> 0.75190769 | S18: =1-R18/Parameters!$B$12 -> 0.62404615 | T18: =1/(1-S18) -> 2.659901 | U18: =(Parameters!$B$19*(E18+Parameters!$B$20)^S18+Parameters!$B$18*F18^S18)^(1/S18) -> 0.42067358 | V18: =(Parameters!$B$10*G18^Parameters!$B$9+Parameters!$B$11*U18^Parameters!$B$9)^(Parameters!$B$7/Parameters!$B$9)*N18 -> 1.4205644 | W18: =V18 - C18 - D18 - LN(1+EXP(Parameters!$B$21*B18))/Parameters!$B$21 - IF(B18>0, 0,Parameters!$B$6*B18^2/E18) -> 1.1178341 | X18: =EXP(-Parameters!$B$56*A18) -> 0.80945022 | Y18: =IF(W18>0,W18^(1-Parameters!$B$53)/(1-Parameters!$B$53)*X18*Parameters!$B$71,-10+W18*1000) -> -2.224283 | AA18: =B18/E18-B17/E17 -> -0.042925288 | AB18: =C18/F18-C17/F17 -> -0.00054108154 | AC18: =D18/G18-D17/G17 -> 0.0017081238 | AD18: =X18*(AA18^2+AB18^2+AC18^2) -> 0.0014940758 | AE18: =B18/E18-2*B17/E17+B16/E16 -> -0.018681703 | AF18: =C18/F18-2*C17/F17+C16/F16 -> 0.0011824614 | AG18: =D18/G18-2*D17/G17+D16/G16 -> -2.6533396e-05 | AH18: =X18*(AE18^2+AF18^2+AG18^2) -> 0.00028363537 | AM18: =H18*I18*J18 -> 1.381207 | AN18: =E18*I18*J18 -> 38.414859 | AO18: =U18*I18*J18 -> 42.698968 | AP18: =V18*J18*I18 -> 144.18931 | AQ18: =-X18*V18*W18^(-Parameters!B$53)*Parameters!B$47*Parameters!B$46*M18 -> -1.9505498e-05 | AR18: =1000*EXP(-(Parameters!$B$55)*'6states'!A18)*AP18*Parameters!B$47*Parameters!B$46*M18 -> 1.7391464 | AS18: =SUM(AR18:AR$204)*EXP(Parameters!$B$55*A18) -> 239.11817 | AT18: =(B18+C18+D18)/V18 -> 0.21174558 | AU18: =(1/$S18-1/Parameters!$B$13) * LN(Parameters!$B$18) / LN(O18) -> 0.23658832 | AV18: =(Parameters!$B$18*'6states'!S18^+Parameters!$B$19*Parameters!$B$25^'6states'!S18)^((1-'6states'!S18)/'6states'!S18)*Parameters!$B$18*Parameters!$B$26^('6states'!S18-1) -> 0.22581752 | AW18: =(LN(AV18)-LN(AV$4))/ LN(O18) -> 0.2768759 | AX18: =1-2^-AU18 -> 0.15124994 | AY18: =1-2^-AV18 -> 0.14488967 | AZ18: =(1/$S18-1/Parameters!$B$13) * LN(Parameters!$B$18) / A18 -> 0.033828444
A19: =A18+Parameters!$B$71 -> 15 | B19: -0.0028169629 | C19: 0.071161642 | D19: 0.23022042 | E19: =MAX((1-Parameters!$B$4)^Parameters!B$71*E18 + B18*Parameters!B$71 - IF(B18>0,Parameters!$B$5,0)*B18^2/E18*Parameters!B$71, 0.0001) -> 0.35428052 | F19: =(1-Parameters!$B$4)^Parameters!B$71*F18+C18*Parameters!B$71-Parameters!$B$5*C18^2/F18*Parameters!B$71 -> 0.52544066 | G19: =(1-Parameters!$B$4)^Parameters!B$71*G18+D18*Parameters!B$71-Parameters!$B$5*D18^2/G18*Parameters!B$71 -> 3.7994146 | H19: =MAX(H18 * (1-Parameters!$B$4) ^ Parameters!B$71 + (LN(1+EXP(Parameters!$B$21*(-B18+0.004)))/Parameters!$B$21 -0.004) * Parameters!B$71,0) -> 0.013531782 | I19: =I18*(1+Parameters!$B$52)^Parameters!B$71 -> 8.522257 | J19: =J18*(1+Parameters!$B$54)^Parameters!B$71 -> 12.183591 | K19: =I19*J19*EXP(-Parameters!$B$43*'6states'!A19)*(Parameters!$B$38/Parameters!$B$39*('6states'!E19+'6states'!H19)/Parameters!$E$25*(EXP(-Parameters!$B$39*Parameters!$E$25*'6states'!H19/('6states'!E19+'6states'!H19))-EXP(-Parameters!$B$39*Parameters!$E$25)) + Parameters!$B$40*'6states'!E19) -> 25.269947 | L19: =L18+K19*Parameters!B$71 -> 2749.9582 | M19: =L19*Parameters!$B$46 -> 1.6499749 | N19: =EXP(-Parameters!$B$47/2*M19^2) -> 0.97301061 | O19: =MAX((Parameters!$B$63 + Parameters!$B$31*'6states'!A19 - '6states'!L19 + Parameters!$B$48/Parameters!$B$46)/Parameters!B$63,1) -> 7.9608352 | P19: =Parameters!B$62*EXP(-Parameters!B$61*A19) -> 0.33348841 | Q19: =(1-Parameters!B$62)*O19^-Parameters!B$64 -> 0.40632556 | R19: =Parameters!B$62*EXP(-Parameters!B$61*A19)+(1-Parameters!B$62)*O19^-Parameters!B$64 -> 0.73981396 | S19: =1-R19/Parameters!$B$12 -> 0.63009302 | T19: =1/(1-S19) -> 2.7033823 | U19: =(Parameters!$B$19*(E19+Parameters!$B$20)^S19+Parameters!$B$18*F19^S19)^(1/S19) -> 0.41092963 | V19: =(Parameters!$B$10*G19^Parameters!$B$9+Parameters!$B$11*U19^Parameters!$B$9)^(Parameters!$B$7/Parameters!$B$9)*N19 -> 1.415319 | W19: =V19 - C19 - D19 - LN(1+EXP(Parameters!$B$21*B19))/Parameters!$B$21 - IF(B19>0, 0,Parameters!$B$6*B19^2/E19) -> 1.1131232 | X19: =EXP(-Parameters!$B$56*A19) -> 0.79731934 | Y19: =IF(W19>0,W19^(1-Parameters!$B$53)/(1-Parameters!$B$53)*X19*Parameters!$B$71,-10+W19*1000) -> -2.1941895 | AA19: =B19/E19-B18/E18 -> -0.0069467651 | AB19: =C19/F19-C18/F18 -> -0.001128984 | AC19: =D19/G19-D18/G18 -> -0.00043143187 | AD19: =X19*(AA19^2+AB19^2+AC19^2) -> 3.9641349e-05 | AE19: =B19/E19-2*B18/E18+B17/E17 -> 0.035978523 | AF19: =C19/F19-2*C18/F18+C17/F17 -> -0.00058790244 | AG19: =D19/G19-2*D18/G18+D17/G17 -> -0.0021395556 | AH19: =X19*(AE19^2+AF19^2+AG19^2) -> 0.0010360188 | AM19: =H19*I19*J19 -> 1.4050279 | AN19: =E19*I19*J19 -> 36.785547 | AO19: =U19*I19*J19 -> 42.667521 | AP19: =V19*J19*I19 -> 146.95497 | AQ19: =-X19*V19*W19^(-Parameters!B$53)*Parameters!B$47*Parameters!B$46*M19 -> -1.943023e-05 | AR19: =1000*EXP(-(Parameters!$B$55)*'6states'!A19)*AP19*Parameters!B$47*Parameters!B$46*M19 -> 1.7272409 | AS19: =SUM(AR19:AR$204)*EXP(Parameters!$B$55*A19) -> 244.71589 | AT19: =(B19+C19+D19)/V19 -> 0.21095252 | AU19: =(1/$S19-1/Parameters!$B$13) * LN(Parameters!$B$18) / LN(O19) -> 0.23712221 | AV19: =(Parameters!$B$18*'6states'!S19^+Parameters!$B$19*Parameters!$B$25^'6states'!S19)^((1-'6states'!S19)/'6states'!S19)*Parameters!$B$18*Parameters!$B$26^('6states'!S19-1) -> 0.22977149 | AW19: =(LN(AV19)-LN(AV$4))/ LN(O19) -> 0.27553331 | AX19: =1-2^-AU19 -> 0.15156397 | AY19: =1-2^-AV19 -> 0.14723005 | AZ19: =(1/$S19-1/Parameters!$B$13) * LN(Parameters!$B$18) / A19 -> 0.032794538
A20: =A19+Parameters!$B$71 -> 16 | B20: 1.7296603e-05 | C20: 0.073944619 | D20: 0.2254563 | E20: =MAX((1-Parameters!$B$4)^Parameters!B$71*E19 + B19*Parameters!B$71 - IF(B19>0,Parameters!$B$5,0)*B19^2/E19*Parameters!B$71, 0.0001) -> 0.32917931 | F20: =(1-Parameters!$B$4)^Parameters!B$71*F19+C19*Parameters!B$71-Parameters!$B$5*C19^2/F19*Parameters!B$71 -> 0.5539145 | G20: =(1-Parameters!$B$4)^Parameters!B$71*G19+D19*Parameters!B$71-Parameters!$B$5*D19^2/G19*Parameters!B$71 -> 3.7767019 | H20: =MAX(H19 * (1-Parameters!$B$4) ^ Parameters!B$71 + (LN(1+EXP(Parameters!$B$21*(-B19+0.004)))/Parameters!$B$21 -0.004) * Parameters!B$71,0) -> 0.01565604 | I20: =I19*(1+Parameters!$B$52)^Parameters!B$71 -> 8.5469716 | J20: =J19*(1+Parameters!$B$54)^Parameters!B$71 -> 12.427263 | K20: =I20*J20*EXP(-Parameters!$B$43*'6states'!A20)*(Parameters!$B$38/Parameters!$B$39*('6states'!E20+'6states'!H20)/Parameters!$E$25*(EXP(-Parameters!$B$39*Parameters!$E$25*'6states'!H20/('6states'!E20+'6states'!H20))-EXP(-Parameters!$B$39*Parameters!$E$25)) + Parameters!$B$40*'6states'!E20) -> 23.5006 | L20: =L19+K20*Parameters!B$71 -> 2773.4588 | M20: =L20*Parameters!$B$46 -> 1.6640753 | N20: =EXP(-Parameters!$B$47/2*M20^2) -> 0.97255376 | O20: =MAX((Parameters!$B$63 + Parameters!$B$31*'6states'!A20 - '6states'!L20 + Parameters!$B$48/Parameters!$B$46)/Parameters!B$63,1) -> 8.5548232 | P20: =Parameters!B$62*EXP(-Parameters!B$61*A20) -> 0.32460469 | Q20: =(1-Parameters!B$62)*O20^-Parameters!B$64 -> 0.40341208 | R20: =Parameters!B$62*EXP(-Parameters!B$61*A20)+(1-Parameters!B$62)*O20^-Parameters!B$64 -> 0.72801677 | S20: =1-R20/Parameters!$B$12 -> 0.63599162 | T20: =1/(1-S20) -> 2.7471895 | U20: =(Parameters!$B$19*(E20+Parameters!$B$20)^S20+Parameters!$B$18*F20^S20)^(1/S20) -> 0.40035607 | V20: =(Parameters!$B$10*G20^Parameters!$B$9+Parameters!$B$11*U20^Parameters!$B$9)^(Parameters!$B$7/Parameters!$B$9)*N20 -> 1.4095729 | W20: =V20 - C20 - D20 - LN(1+EXP(Parameters!$B$21*B20))/Parameters!$B$21 - IF(B20>0, 0,Parameters!$B$6*B20^2/E20) -> 1.1084304 | X20: =EXP(-Parameters!$B$56*A20) -> 0.78537026 | Y20: =IF(W20>0,W20^(1-Parameters!$B$53)/(1-Parameters!$B$53)*X20*Parameters!$B$71,-10+W20*1000) -> -2.1645043 | AA20: =B20/E20-B19/E19 -> 0.0080037662 | AB20: =C20/F20-C19/F19 -> -0.0019376649 | AC20: =D20/G20-D19/G19 -> -0.00089704762 | AD20: =X20*(AA20^2+AB20^2+AC20^2) -> 5.3891724e-05 | AE20: =B20/E20-2*B19/E19+B18/E18 -> 0.014950531 | AF20: =C20/F20-2*C19/F19+C18/F18 -> -0.00080868091 | AG20: =D20/G20-2*D19/G19+D18/G18 -> -0.00046561575 | AH20: =X20*(AE20^2+AF20^2+AG20^2) -> 0.00017622856 | AM20: =H20*I20*J20 -> 1.6629136 | AN20: =E20*I20*J20 -> 34.963933 | AO20: =U20*I20*J20 -> 42.524006 | AP20: =V20*J20*I20 -> 149.71844 | AQ20: =-X20*V20*W20^(-Parameters!B$53)*Parameters!B$47*Parameters!B$46*M20 -> -1.9334186e-05 | AR20: =1000*EXP(-(Parameters!$B$55)*'6states'!A20)*AP20*Parameters!B$47*Parameters!B$46*M20 -> 1.7135461 | AS20: =SUM(AR20:AR$204)*EXP(Parameters!$B$55*A20) -> 250.42927 | AT20: =(B20+C20+D20)/V20 -> 0.21241769 | AU20: =(1/$S20-1/Parameters!$B$13) * LN(Parameters!$B$18) / LN(O20) -> 0.23734182 | AV20: =(Parameters!$B$18*'6states'!S20^+Parameters!$B$19*Parameters!$B$25^'6states'!S20)^((1-'6states'!S20)/'6states'!S20)*Parameters!$B$18*Parameters!$B$26^('6states'!S20-1) -> 0.23354131 | AW20: =(LN(AV20)-LN(AV$4))/ LN(O20) -> 0.27387758 | AX20: =1-2^-AU20 -> 0.15169311 | AY20: =1-2^-AV20 -> 0.14945546 | AZ20: =(1/$S20-1/Parameters!$B$13) * LN(Parameters!$B$18) / A20 -> 0.031840818
A21: =A20+Parameters!$B$71 -> 17 | B21: -0.00039375361 | C21: 0.076452757 | D21: 0.22252777 | E21: =MAX((1-Parameters!$B$4)^Parameters!B$71*E20 + B20*Parameters!B$71 - IF(B20>0,Parameters!$B$5,0)*B20^2/E20*Parameters!B$71, 0.0001) -> 0.30849123 | F21: =(1-Parameters!$B$4)^Parameters!B$71*F20+C20*Parameters!B$71-Parameters!$B$5*C20^2/F20*Parameters!B$71 -> 0.58314669 | G21: =(1-Parameters!$B$4)^Parameters!B$71*G20+D20*Parameters!B$71-Parameters!$B$5*D20^2/G20*Parameters!B$71 -> 3.7511447 | H21: =MAX(H20 * (1-Parameters!$B$4) ^ Parameters!B$71 + (LN(1+EXP(Parameters!$B$21*(-B20+0.004)))/Parameters!$B$21 -0.004) * Parameters!B$71,0) -> 0.015116645 | I21: =I20*(1+Parameters!$B$52)^Parameters!B$71 -> 8.5717578 | J21: =J20*(1+Parameters!$B$54)^Parameters!B$71 -> 12.675808 | K21: =I21*J21*EXP(-Parameters!$B$43*'6states'!A21)*(Parameters!$B$38/Parameters!$B$39*('6states'!E21+'6states'!H21)/Parameters!$E$25*(EXP(-Parameters!$B$39*Parameters!$E$25*'6states'!H21/('6states'!E21+'6states'!H21))-EXP(-Parameters!$B$39*Parameters!$E$25)) + Parameters!$B$40*'6states'!E21) -> 22.272458 | L21: =L20+K21*Parameters!B$71 -> 2795.7313 | M21: =L21*Parameters!$B$46 -> 1.6774388 | N21: =EXP(-Parameters!$B$47/2*M21^2) -> 0.9721174 | O21: =MAX((Parameters!$B$63 + Parameters!$B$31*'6states'!A21 - '6states'!L21 + Parameters!$B$48/Parameters!$B$46)/Parameters!B$63,1) -> 9.173374 | P21: =Parameters!B$62*EXP(-Parameters!B$61*A21) -> 0.31595762 | Q21: =(1-Parameters!B$62)*O21^-Parameters!B$64 -> 0.40060567 | R21: =Parameters!B$62*EXP(-Parameters!B$61*A21)+(1-Parameters!B$62)*O21^-Parameters!B$64 -> 0.71656329 | S21: =1-R21/Parameters!$B$12 -> 0.64171835 | T21: =1/(1-S21) -> 2.7911003 | U21: =(Parameters!$B$19*(E21+Parameters!$B$20)^S21+Parameters!$B$18*F21^S21)^(1/S21) -> 0.39282197 | V21: =(Parameters!$B$10*G21^Parameters!$B$9+Parameters!$B$11*U21^Parameters!$B$9)^(Parameters!$B$7/Parameters!$B$9)*N21 -> 1.4044646 | W21: =V21 - C21 - D21 - LN(1+EXP(Parameters!$B$21*B21))/Parameters!$B$21 - IF(B21>0, 0,Parameters!$B$6*B21^2/E21) -> 1.1039378 | X21: =EXP(-Parameters!$B$56*A21) -> 0.77360026 | Y21: =IF(W21>0,W21^(1-Parameters!$B$53)/(1-Parameters!$B$53)*X21*Parameters!$B$71,-10+W21*1000) -> -2.1350987 | AA21: =B21/E21-B20/E20 -> -0.0013289297 | AB21: =C21/F21-C20/F20 -> -0.0023908262 | AC21: =D21/G21-D20/G20 -> -0.00037397809 | AD21: =X21*(AA21^2+AB21^2+AC21^2) -> 5.896353e-06 | AE21: =B21/E21-2*B20/E20+B19/E19 -> -0.0093326959 | AF21: =C21/F21-2*C20/F20+C19/F19 -> -0.00045316126 | AG21: =D21/G21-2*D20/G20+D19/G19 -> 0.00052306954 | AH21: =X21*(AE21^2+AF21^2+AG21^2) -> 6.7750495e-05 | AM21: =H21*I21*J21 -> 1.6424833 | AN21: =E21*I21*J21 -> 33.518793 | AO21: =U21*I21*J21 -> 42.681663 | AP21: =V21*J21*I21 -> 152.60064 | AQ21: =-X21*V21*W21^(-Parameters!B$53)*Parameters!B$47*Parameters!B$46*M21 -> -1.9232962e-05 | AR21: =1000*EXP(-(Parameters!$B$55)*'6states'!A21)*AP21*Parameters!B$47*Parameters!B$46*M21 -> 1.6998352 | AS21: =SUM(AR21:AR$204)*EXP(Parameters!$B$55*A21) -> 256.26342 | AT21: =(B21+C21+D21)/V21 -> 0.2125983 | AU21: =(1/$S21-1/Parameters!$B$13) * LN(Parameters!$B$18) / LN(O21) -> 0.2374081 | AV21: =(Parameters!$B$18*'6states'!S21^+Parameters!$B$19*Parameters!$B$25^'6states'!S21)^((1-'6states'!S21)/'6states'!S21)*Parameters!$B$18*Parameters!$B$26^('6states'!S21-1) -> 0.23711743 | AW21: =(LN(AV21)-LN(AV$4))/ LN(O21) -> 0.27210758 | AX21: =1-2^-AU21 -> 0.15173209 | AY21: =1-2^-AV21 -> 0.15156116 | AZ21: =(1/$S21-1/Parameters!$B$13) * LN(Parameters!$B$18) / A21 -> 0.030951106
A22: =A21+Parameters!$B$71 -> 18 | B22: -5.8173735e-05 | C22: 0.078534877 | D22: 0.22047662 | E22: =MAX((1-Parameters!$B$4)^Parameters!B$71*E21 + B21*Parameters!B$71 - IF(B21>0,Parameters!$B$5,0)*B21^2/E21*Parameters!B$71, 0.0001) -> 0.28869337 | F22: =(1-Parameters!$B$4)^Parameters!B$71*F21+C21*Parameters!B$71-Parameters!$B$5*C21^2/F21*Parameters!B$71 -> 0.61289627 | G22: =(1-Parameters!$B$4)^Parameters!B$71*G21+D21*Parameters!B$71-Parameters!$B$5*D21^2/G21*Parameters!B$71 -> 3.7245245 | H22: =MAX(H21 * (1-Parameters!$B$4) ^ Parameters!B$71 + (LN(1+EXP(Parameters!$B$21*(-B21+0.004)))/Parameters!$B$21 -0.004) * Parameters!B$71,0) -> 0.014957354 | I22: =I21*(1+Parameters!$B$52)^Parameters!B$71 -> 8.5966159 | J22: =J21*(1+Parameters!$B$54)^Parameters!B$71 -> 12.929325 | K22: =I22*J22*EXP(-Parameters!$B$43*'6states'!A22)*(Parameters!$B$38/Parameters!$B$39*('6states'!E22+'6states'!H22)/Parameters!$E$25*(EXP(-Parameters!$B$39*Parameters!$E$25*'6states'!H22/('6states'!E22+'6states'!H22))-EXP(-Parameters!$B$39*Parameters!$E$25)) + Parameters!$B$40*'6states'!E22) -> 21.054012 | L22: =L21+K22*Parameters!B$71 -> 2816.7853 | M22: =L22*Parameters!$B$46 -> 1.6900712 | N22: =EXP(-Parameters!$B$47/2*M22^2) -> 0.97170189 | O22: =MAX((Parameters!$B$63 + Parameters!$B$31*'6states'!A22 - '6states'!L22 + Parameters!$B$48/Parameters!$B$46)/Parameters!B$63,1) -> 9.8162938 | P22: =Parameters!B$62*EXP(-Parameters!B$61*A22) -> 0.3075409 | Q22: =(1-Parameters!B$62)*O22^-Parameters!B$64 -> 0.3979012 | R22: =Parameters!B$62*EXP(-Parameters!B$61*A22)+(1-Parameters!B$62)*O22^-Parameters!B$64 -> 0.7054421 | S22: =1-R22/Parameters!$B$12 -> 0.64727895 | T22: =1/(1-S22) -> 2.8351015 | U22: =(Parameters!$B$19*(E22+Parameters!$B$20)^S22+Parameters!$B$18*F22^S22)^(1/S22) -> 0.38572234 | V22: =(Parameters!$B$10*G22^Parameters!$B$9+Parameters!$B$11*U22^Parameters!$B$9)^(Parameters!$B$7/Parameters!$B$9)*N22 -> 1.3993612 | W22: =V22 - C22 - D22 - LN(1+EXP(Parameters!$B$21*B22))/Parameters!$B$21 - IF(B22>0, 0,Parameters!$B$6*B22^2/E22) -> 1.0986457 | X22: =EXP(-Parameters!$B$56*A22) -> 0.76200665 | Y22: =IF(W22>0,W22^(1-Parameters!$B$53)/(1-Parameters!$B$53)*X22*Parameters!$B$71,-10+W22*1000) -> -2.106641 | AA22: =B22/E22-B21/E21 -> 0.0010748781 | AB22: =C22/F22-C21/F21 -> -0.0029665105 | AC22: =D22/G22-D21/G21 -> -0.00012672233 | AD22: =X22*(AA22^2+AB22^2+AC22^2) -> 7.5984299e-06 | AE22: =B22/E22-2*B21/E21+B20/E20 -> 0.0024038079 | AF22: =C22/F22-2*C21/F21+C20/F20 -> -0.0005756843 | AG22: =D22/G22-2*D21/G21+D20/G20 -> 0.00024725575 | AH22: =X22*(AE22^2+AF22^2+AG22^2) -> 4.7022212e-06 | AM22: =H22*I22*J22 -> 1.6624865 | AN22: =E22*I22*J22 -> 32.087817 | AO22: =U22*I22*J22 -> 42.872436 | AP22: =V22*J22*I22 -> 155.53681 | AQ22: =-X22*V22*W22^(-Parameters!B$53)*Parameters!B$47*Parameters!B$46*M22 -> -1.9141812e-05 | AR22: =1000*EXP(-(Parameters!$B$55)*'6states'!A22)*AP22*Parameters!B$47*Parameters!B$46*M22 -> 1.6853816 | AS22: =SUM(AR22:AR$204)*EXP(Parameters!$B$55*A22) -> 262.22061 | AT22: =(B22+C22+D22)/V22 -> 0.21363556 | AU22: =(1/$S22-1/Parameters!$B$13) * LN(Parameters!$B$18) / LN(O22) -> 0.23734946 | AV22: =(Parameters!$B$18*'6states'!S22^+Parameters!$B$19*Parameters!$B$25^'6states'!S22)^((1-'6states'!S22)/'6states'!S22)*Parameters!$B$18*Parameters!$B$26^('6states'!S22-1) -> 0.24050953 | AW22: =(LN(AV22)-LN(AV$4))/ LN(O22) -> 0.27025649 | AX22: =1-2^-AU22 -> 0.15169761 | AY22: =1-2^-AV22 -> 0.15355369 | AZ22: =(1/$S22-1/Parameters!$B$13) * LN(Parameters!$B$18) / A22 -> 0.030117585
A23: =A22+Parameters!$B$71 -> 19 | B23: 0.00061081688 | C23: 0.080191488 | D23: 0.21857375 | E23: =MAX((1-Parameters!$B$4)^Parameters!B$71*E22 + B22*Parameters!B$71 - IF(B22>0,Parameters!$B$5,0)*B22^2/E22*Parameters!B$71, 0.0001) -> 0.27047639 | F23: =(1-Parameters!$B$4)^Parameters!B$71*F22+C22*Parameters!B$71-Parameters!$B$5*C22^2/F22*Parameters!B$71 -> 0.64281673 | G23: =(1-Parameters!$B$4)^Parameters!B$71*G22+D22*Parameters!B$71-Parameters!$B$5*D22^2/G22*Parameters!B$71 -> 3.6976772 | H23: =MAX(H22 * (1-Parameters!$B$4) ^ Parameters!B$71 + (LN(1+EXP(Parameters!$B$21*(-B22+0.004)))/Parameters!$B$21 -0.004) * Parameters!B$71,0) -> 0.014524784 | I23: =I22*(1+Parameters!$B$52)^Parameters!B$71 -> 8.6215461 | J23: =J22*(1+Parameters!$B$54)^Parameters!B$71 -> 13.187911 | K23: =I23*J23*EXP(-Parameters!$B$43*'6states'!A23)*(Parameters!$B$38/Parameters!$B$39*('6states'!E23+'6states'!H23)/Parameters!$E$25*(EXP(-Parameters!$B$39*Parameters!$E$25*'6states'!H23/('6states'!E23+'6states'!H23))-EXP(-Parameters!$B$39*Parameters!$E$25)) + Parameters!$B$40*'6states'!E23) -> 19.945294 | L23: =L22+K23*Parameters!B$71 -> 2836.7306 | M23: =L23*Parameters!$B$46 -> 1.7020384 | N23: =EXP(-Parameters!$B$47/2*M23^2) -> 0.97130554 | O23: =MAX((Parameters!$B$63 + Parameters!$B$31*'6states'!A23 - '6states'!L23 + Parameters!$B$48/Parameters!$B$46)/Parameters!B$63,1) -> 10.481388 | P23: =Parameters!B$62*EXP(-Parameters!B$61*A23) -> 0.2993484 | Q23: =(1-Parameters!B$62)*O23^-Parameters!B$64 -> 0.39530119 | R23: =Parameters!B$62*EXP(-Parameters!B$61*A23)+(1-Parameters!B$62)*O23^-Parameters!B$64 -> 0.69464959 | S23: =1-R23/Parameters!$B$12 -> 0.65267521 | T23: =1/(1-S23) -> 2.8791495 | U23: =(Parameters!$B$19*(E23+Parameters!$B$20)^S23+Parameters!$B$18*F23^S23)^(1/S23) -> 0.37953033 | V23: =(Parameters!$B$10*G23^Parameters!$B$9+Parameters!$B$11*U23^Parameters!$B$9)^(Parameters!$B$7/Parameters!$B$9)*N23 -> 1.3945162 | W23: =V23 - C23 - D23 - LN(1+EXP(Parameters!$B$21*B23))/Parameters!$B$21 - IF(B23>0, 0,Parameters!$B$6*B23^2/E23) -> 1.0936941 | X23: =EXP(-Parameters!$B$56*A23) -> 0.75058678 | Y23: =IF(W23>0,W23^(1-Parameters!$B$53)/(1-Parameters!$B$53)*X23*Parameters!$B$71,-10+W23*1000) -> -2.078353 | AA23: =B23/E23-B22/E22 -> 0.0024598072 | AB23: =C23/F23-C22/F22 -> -0.0033871483 | AC23: =D23/G23-D22/G22 -> -8.4813984e-05 | AD23: =X23*(AA23^2+AB23^2+AC23^2) -> 1.3158251e-05 | AE23: =B23/E23-2*B22/E22+B21/E21 -> 0.0013849291 | AF23: =C23/F23-2*C22/F22+C21/F21 -> -0.00042063789 | AG23: =D23/G23-2*D22/G22+D21/G21 -> 4.1908348e-05 | AH23: =X23*(AE23^2+AF23^2+AG23^2) -> 1.5737711e-06 | AM23: =H23*I23*J23 -> 1.6514706 | AN23: =E23*I23*J23 -> 30.753215 | AO23: =U23*I23*J23 -> 43.152668 | AP23: =V23*J23*I23 -> 158.55675 | AQ23: =-X23*V23*W23^(-Parameters!B$53)*Parameters!B$47*Parameters!B$46*M23 -> -1.9038456e-05 | AR23: =1000*EXP(-(Parameters!$B$55)*'6states'!A23)*AP23*Parameters!B$47*Parameters!B$46*M23 -> 1.670592 | AS23: =SUM(AR23:AR$204)*EXP(Parameters!$B$55*A23) -> 268.30455 | AT23: =(B23+C23+D23)/V23 -> 0.21468095 | AU23: =(1/$S23-1/Parameters!$B$13) * LN(Parameters!$B$18) / LN(O23) -> 0.2372033 | AV23: =(Parameters!$B$18*'6states'!S23^+Parameters!$B$19*Parameters!$B$25^'6states'!S23)^((1-'6states'!S23)/'6states'!S23)*Parameters!$B$18*Parameters!$B$26^('6states'!S23-1) -> 0.24372477 | AW23: =(LN(AV23)-LN(AV$4))/ LN(O23) -> 0.26836791 | AX23: =1-2^-AU23 -> 0.15161166 | AY23: =1-2^-AV23 -> 0.15543801 | AZ23: =(1/$S23-1/Parameters!$B$13) * LN(Parameters!$B$18) / A23 -> 0.029333322
A24: =A23+Parameters!$B$71 -> 20 | B24: 0.0010705855 | C24: 0.081541131 | D24: 0.21716615 | E24: =MAX((1-Parameters!$B$4)^Parameters!B$71*E23 + B23*Parameters!B$71 - IF(B23>0,Parameters!$B$5,0)*B23^2/E23*Parameters!B$71, 0.0001) -> 0.25407286 | F24: =(1-Parameters!$B$4)^Parameters!B$71*F23+C23*Parameters!B$71-Parameters!$B$5*C23^2/F23*Parameters!B$71 -> 0.67257114 | G24: =(1-Parameters!$B$4)^Parameters!B$71*G23+D23*Parameters!B$71-Parameters!$B$5*D23^2/G23*Parameters!B$71 -> 3.670747 | H24: =MAX(H23 * (1-Parameters!$B$4) ^ Parameters!B$71 + (LN(1+EXP(Parameters!$B$21*(-B23+0.004)))/Parameters!$B$21 -0.004) * Parameters!B$71,0) -> 0.013573716 | I24: =I23*(1+Parameters!$B$52)^Parameters!B$71 -> 8.6465486 | J24: =J23*(1+Parameters!$B$54)^Parameters!B$71 -> 13.451669 | K24: =I24*J24*EXP(-Parameters!$B$43*'6states'!A24)*(Parameters!$B$38/Parameters!$B$39*('6states'!E24+'6states'!H24)/Parameters!$E$25*(EXP(-Parameters!$B$39*Parameters!$E$25*'6states'!H24/('6states'!E24+'6states'!H24))-EXP(-Parameters!$B$39*Parameters!$E$25)) + Parameters!$B$40*'6states'!E24) -> 18.97945 | L24: =L23+K24*Parameters!B$71 -> 2855.7101 | M24: =L24*Parameters!$B$46 -> 1.713426 | N24: =EXP(-Parameters!$B$47/2*M24^2) -> 0.97092595 | O24: =MAX((Parameters!$B$63 + Parameters!$B$31*'6states'!A24 - '6states'!L24 + Parameters!$B$48/Parameters!$B$46)/Parameters!B$63,1) -> 11.165799 | P24: =Parameters!B$62*EXP(-Parameters!B$61*A24) -> 0.29137413 | Q24: =(1-Parameters!B$62)*O24^-Parameters!B$64 -> 0.39280863 | R24: =Parameters!B$62*EXP(-Parameters!B$61*A24)+(1-Parameters!B$62)*O24^-Parameters!B$64 -> 0.68418276 | S24: =1-R24/Parameters!$B$12 -> 0.65790862 | T24: =1/(1-S24) -> 2.9231956 | U24: =(Parameters!$B$19*(E24+Parameters!$B$20)^S24+Parameters!$B$18*F24^S24)^(1/S24) -> 0.37439966 | V24: =(Parameters!$B$10*G24^Parameters!$B$9+Parameters!$B$11*U24^Parameters!$B$9)^(Parameters!$B$7/Parameters!$B$9)*N24 -> 1.3900285 | W24: =V24 - C24 - D24 - LN(1+EXP(Parameters!$B$21*B24))/Parameters!$B$21 - IF(B24>0, 0,Parameters!$B$6*B24^2/E24) -> 1.0889962 | X24: =EXP(-Parameters!$B$56*A24) -> 0.73933806 | Y24: =IF(W24>0,W24^(1-Parameters!$B$53)/(1-Parameters!$B$53)*X24*Parameters!$B$71,-10+W24*1000) -> -2.0502924 | AA24: =B24/E24-B23/E23 -> 0.0019553946 | AB24: =C24/F24-C23/F23 -> -0.0035122314 | AC24: =D24/G24-D23/G23 -> 5.0202601e-05 | AD24: =X24*(AA24^2+AB24^2+AC24^2) -> 1.1949076e-05 | AE24: =B24/E24-2*B23/E23+B22/E22 -> -0.00050441263 | AF24: =C24/F24-2*C23/F23+C22/F22 -> -0.00012508302 | AG24: =D24/G24-2*D23/G23+D22/G22 -> 0.00013501659 | AH24: =X24*(AE24^2+AF24^2+AG24^2) -> 2.1315659e-07 | AM24: =H24*I24*J24 -> 1.5787659 | AN24: =E24*I24*J24 -> 29.551344 | AO24: =U24*I24*J24 -> 43.546616 | AP24: =V24*J24*I24 -> 161.67492 | AQ24: =-X24*V24*W24^(-Parameters!B$53)*Parameters!B$47*Parameters!B$46*M24 -> -1.8927527e-05 | AR24: =1000*EXP(-(Parameters!$B$55)*'6states'!A24)*AP24*Parameters!B$47*Parameters!B$46*M24 -> 1.655696 | AS24: =SUM(AR24:AR$204)*EXP(Parameters!$B$55*A24) -> 274.51837 | AT24: =(B24+C24+D24)/V24 -> 0.21566311 | AU24: =(1/$S24-1/Parameters!$B$13) * LN(Parameters!$B$18) / LN(O24) -> 0.23700222 | AV24: =(Parameters!$B$18*'6states'!S24^+Parameters!$B$19*Parameters!$B$25^'6states'!S24)^((1-'6states'!S24)/'6states'!S24)*Parameters!$B$18*Parameters!$B$26^('6states'!S24-1) -> 0.24677015 | AW24: =(LN(AV24)-LN(AV$4))/ LN(O24) -> 0.26647898 | AX24: =1-2^-AU24 -> 0.1514934 | AY24: =1-2^-AV24 -> 0.15721891 | AZ24: =(1/$S24-1/Parameters!$B$13) * LN(Parameters!$B$18) / A24 -> 0.028592605
A25: =A24+Parameters!$B$71 -> 21 | B25: =B24+(B26-B24)/2 -> 0.0015070986 | C25: =C24+(C26-C24)/2 -> 0.082618814 | D25: =D24+(D26-D24)/2 -> 0.21635004 | E25: =MAX((1-Parameters!$B$4)^Parameters!B$71*E24 + B24*Parameters!B$71 - IF(B24>0,Parameters!$B$5,0)*B24^2/E24*Parameters!B$71, 0.0001) -> 0.23915775 | F25: =(1-Parameters!$B$4)^Parameters!B$71*F24+C24*Parameters!B$71-Parameters!$B$5*C24^2/F24*Parameters!B$71 -> 0.70192167 | G25: =(1-Parameters!$B$4)^Parameters!B$71*G24+D24*Parameters!B$71-Parameters!$B$5*D24^2/G24*Parameters!B$71 -> 3.6441753 | H25: =MAX(H24 * (1-Parameters!$B$4) ^ Parameters!B$71 + (LN(1+EXP(Parameters!$B$21*(-B24+0.004)))/Parameters!$B$21 -0.004) * Parameters!B$71,0) -> 0.012324067 | I25: =I24*(1+Parameters!$B$52)^Parameters!B$71 -> 8.6716236 | J25: =J24*(1+Parameters!$B$54)^Parameters!B$71 -> 13.720703 | K25: =I25*J25*EXP(-Parameters!$B$43*'6states'!A25)*(Parameters!$B$38/Parameters!$B$39*('6states'!E25+'6states'!H25)/Parameters!$E$25*(EXP(-Parameters!$B$39*Parameters!$E$25*'6states'!H25/('6states'!E25+'6states'!H25))-EXP(-Parameters!$B$39*Parameters!$E$25)) + Parameters!$B$40*'6states'!E25) -> 18.123215 | L25: =L24+K25*Parameters!B$71 -> 2873.8333 | M25: =L25*Parameters!$B$46 -> 1.7243 | N25: =EXP(-Parameters!$B$47/2*M25^2) -> 0.97056125 | O25: =MAX((Parameters!$B$63 + Parameters!$B$31*'6states'!A25 - '6states'!L25 + Parameters!$B$48/Parameters!$B$46)/Parameters!B$63,1) -> 11.867335 | P25: =Parameters!B$62*EXP(-Parameters!B$61*A25) -> 0.28361228 | Q25: =(1-Parameters!B$62)*O25^-Parameters!B$64 -> 0.39042236 | R25: =Parameters!B$62*EXP(-Parameters!B$61*A25)+(1-Parameters!B$62)*O25^-Parameters!B$64 -> 0.67403464 | S25: =1-R25/Parameters!$B$12 -> 0.66298268 | T25: =1/(1-S25) -> 2.9672065 | U25: =(Parameters!$B$19*(E25+Parameters!$B$20)^S25+Parameters!$B$18*F25^S25)^(1/S25) -> 0.37007934 | V25: =(Parameters!$B$10*G25^Parameters!$B$9+Parameters!$B$11*U25^Parameters!$B$9)^(Parameters!$B$7/Parameters!$B$9)*N25 -> 1.3858618 | W25: =V25 - C25 - D25 - LN(1+EXP(Parameters!$B$21*B25))/Parameters!$B$21 - IF(B25>0, 0,Parameters!$B$6*B25^2/E25) -> 1.0842946 | X25: =EXP(-Parameters!$B$56*A25) -> 0.72825793 | Y25: =IF(W25>0,W25^(1-Parameters!$B$53)/(1-Parameters!$B$53)*X25*Parameters!$B$71,-10+W25*1000) -> -2.0226262 | AA25: =B25/E25-B24/E24 -> 0.0020879977 | AB25: =C25/F25-C24/F24 -> -0.0035341741 | AC25: =D25/G25-D24/G24 -> 0.000207428 | AD25: =X25*(AA25^2+AB25^2+AC25^2) -> 1.2302568e-05 | AE25: =B25/E25-2*B24/E24+B23/E23 -> 0.00013260313 | AF25: =C25/F25-2*C24/F24+C23/F23 -> -2.1942744e-05 | AG25: =D25/G25-2*D24/G24+D23/G23 -> 0.0001572254 | AH25: =X25*(AE25^2+AF25^2+AG25^2) -> 3.1158443e-08 | AM25: =H25*I25*J25 -> 1.466327 | AN25: =E25*I25*J25 -> 28.455173 | AO25: =U25*I25*J25 -> 44.032325 | AP25: =V25*J25*I25 -> 164.8909 | AQ25: =-X25*V25*W25^(-Parameters!B$53)*Parameters!B$47*Parameters!B$46*M25 -> -1.8815528e-05 | AR25: =1000*EXP(-(Parameters!$B$55)*'6states'!A25)*AP25*Parameters!B$47*Parameters!B$46*M25 -> 1.6407347 | AS25: =SUM(AR25:AR$204)*EXP(Parameters!$B$55*A25) -> 280.86489 | AT25: =(B25+C25+D25)/V25 -> 0.21681524 | AU25: =(1/$S25-1/Parameters!$B$13) * LN(Parameters!$B$18) / LN(O25) -> 0.23676634 | AV25: =(Parameters!$B$18*'6states'!S25^+Parameters!$B$19*Parameters!$B$25^'6states'!S25)^((1-'6states'!S25)/'6states'!S25)*Parameters!$B$18*Parameters!$B$26^('6states'!S25-1) -> 0.24965369 | AW25: =(LN(AV25)-LN(AV$4))/ LN(O25) -> 0.26461129 | AX25: =1-2^-AU25 -> 0.15135466 | AY25: =1-2^-AV25 -> 0.15890171 | AZ25: =(1/$S25-1/Parameters!$B$13) * LN(Parameters!$B$18) / A25 -> 0.027890958
A26: =A25+Parameters!$B$71 -> 22 | B26: 0.0019436117 | C26: 0.083696498 | D26: 0.21553393 | E26: =MAX((1-Parameters!$B$4)^Parameters!B$71*E25 + B25*Parameters!B$71 - IF(B25>0,Parameters!$B$5,0)*B25^2/E25*Parameters!B$71, 0.0001) -> 0.22561233 | F26: =(1-Parameters!$B$4)^Parameters!B$71*F25+C25*Parameters!B$71-Parameters!$B$5*C25^2/F25*Parameters!B$71 -> 0.73066507 | G26: =(1-Parameters!$B$4)^Parameters!B$71*G25+D25*Parameters!B$71-Parameters!$B$5*D25^2/G25*Parameters!B$71 -> 3.6184623 | H26: =MAX(H25 * (1-Parameters!$B$4) ^ Parameters!B$71 + (LN(1+EXP(Parameters!$B$21*(-B25+0.004)))/Parameters!$B$21 -0.004) * Parameters!B$71,0) -> 0.01082685 | I26: =I25*(1+Parameters!$B$52)^Parameters!B$71 -> 8.6967713 | J26: =J25*(1+Parameters!$B$54)^Parameters!B$71 -> 13.995117 | K26: =I26*J26*EXP(-Parameters!$B$43*'6states'!A26)*(Parameters!$B$38/Parameters!$B$39*('6states'!E26+'6states'!H26)/Parameters!$E$25*(EXP(-Parameters!$B$39*Parameters!$E$25*'6states'!H26/('6states'!E26+'6states'!H26))-EXP(-Parameters!$B$39*Parameters!$E$25)) + Parameters!$B$40*'6states'!E26) -> 17.374241 | L26: =L25+K26*Parameters!B$71 -> 2891.2075 | M26: =L26*Parameters!$B$46 -> 1.7347245 | N26: =EXP(-Parameters!$B$47/2*M26^2) -> 0.97020959 | O26: =MAX((Parameters!$B$63 + Parameters!$B$31*'6states'!A26 - '6states'!L26 + Parameters!$B$48/Parameters!$B$46)/Parameters!B$63,1) -> 12.58385 | P26: =Parameters!B$62*EXP(-Parameters!B$61*A26) -> 0.2760572 | Q26: =(1-Parameters!B$62)*O26^-Parameters!B$64 -> 0.38814022 | R26: =Parameters!B$62*EXP(-Parameters!B$61*A26)+(1-Parameters!B$62)*O26^-Parameters!B$64 -> 0.66419743 | S26: =1-R26/Parameters!$B$12 -> 0.66790129 | T26: =1/(1-S26) -> 3.0111529 | U26: =(Parameters!$B$19*(E26+Parameters!$B$20)^S26+Parameters!$B$18*F26^S26)^(1/S26) -> 0.36647996 | V26: =(Parameters!$B$10*G26^Parameters!$B$9+Parameters!$B$11*U26^Parameters!$B$9)^(Parameters!$B$7/Parameters!$B$9)*N26 -> 1.3820333 | W26: =V26 - C26 - D26 - LN(1+EXP(Parameters!$B$21*B26))/Parameters!$B$21 - IF(B26>0, 0,Parameters!$B$6*B26^2/E26) -> 1.0799138 | X26: =EXP(-Parameters!$B$56*A26) -> 0.71734384 | Y26: =IF(W26>0,W26^(1-Parameters!$B$53)/(1-Parameters!$B$53)*X26*Parameters!$B$71,-10+W26*1000) -> -1.9951389 | AA26: =B26/E26-B25/E25 -> 0.0023131369 | AB26: =C26/F26-C25/F25 -> -0.0031553744 | AC26: =D26/G26-D25/G25 -> 0.00019633716 | AD26: =X26*(AA26^2+AB26^2+AC26^2) -> 1.1008027e-05 | AE26: =B26/E26-2*B25/E25+B24/E24 -> 0.00022513917 | AF26: =C26/F26-2*C25/F25+C24/F24 -> 0.00037879966 | AG26: =D26/G26-2*D25/G25+D24/G24 -> -1.1090845e-05 | AH26: =X26*(AE26^2+AF26^2+AG26^2) -> 1.3937979e-07 | AM26: =H26*I26*J26 -> 1.3177612 | AN26: =E26*I26*J26 -> 27.459802 | AO26: =U26*I26*J26 -> 44.60513 | AP26: =V26*J26*I26 -> 168.21049 | AQ26: =-X26*V26*W26^(-Parameters!B$53)*Parameters!B$47*Parameters!B$46*M26 -> -1.8695987e-05 | AR26: =1000*EXP(-(Parameters!$B$55)*'6states'!A26)*AP26*Parameters!B$47*Parameters!B$46*M26 -> 1.6258059 | AS26: =SUM(AR26:AR$204)*EXP(Parameters!$B$55*A26) -> 287.34689 | AT26: =(B26+C26+D26)/V26 -> 0.21792098 | AU26: =(1/$S26-1/Parameters!$B$13) * LN(Parameters!$B$18) / LN(O26) -> 0.23651052 | AV26: =(Parameters!$B$18*'6states'!S26^+Parameters!$B$19*Parameters!$B$25^'6states'!S26)^((1-'6states'!S26)/'6states'!S26)*Parameters!$B$18*Parameters!$B$26^('6states'!S26-1) -> 0.25238349 | AW26: =(LN(AV26)-LN(AV$4))/ LN(O26) -> 0.26277993 | AX26: =1-2^-AU26 -> 0.15120416 | AY26: =1-2^-AV26 -> 0.16049169 | AZ26: =(1/$S26-1/Parameters!$B$13) * LN(Parameters!$B$18) / A26 -> 0.027224664
A27: =A26+Parameters!$B$71 -> 23 | B27: =B26+(B28-B26)/2 -> 0.0017437737 | C27: =C26+(C28-C26)/2 -> 0.084537067 | D27: =D26+(D28-D26)/2 -> 0.21534567 | E27: =MAX((1-Parameters!$B$4)^Parameters!B$71*E26 + B26*Parameters!B$71 - IF(B26>0,Parameters!$B$5,0)*B26^2/E26*Parameters!B$71, 0.0001) -> 0.21334818 | F27: =(1-Parameters!$B$4)^Parameters!B$71*F26+C26*Parameters!B$71-Parameters!$B$5*C26^2/F26*Parameters!B$71 -> 0.75881543 | G27: =(1-Parameters!$B$4)^Parameters!B$71*G26+D26*Parameters!B$71-Parameters!$B$5*D26^2/G26*Parameters!B$71 -> 3.5935566 | H27: =MAX(H26 * (1-Parameters!$B$4) ^ Parameters!B$71 + (LN(1+EXP(Parameters!$B$21*(-B26+0.004)))/Parameters!$B$21 -0.004) * Parameters!B$71,0) -> 0.0091126351 | I27: =I26*(1+Parameters!$B$52)^Parameters!B$71 -> 8.7219919 | J27: =J26*(1+Parameters!$B$54)^Parameters!B$71 -> 14.275019 | K27: =I27*J27*EXP(-Parameters!$B$43*'6states'!A27)*(Parameters!$B$38/Parameters!$B$39*('6states'!E27+'6states'!H27)/Parameters!$E$25*(EXP(-Parameters!$B$39*Parameters!$E$25*'6states'!H27/('6states'!E27+'6states'!H27))-EXP(-Parameters!$B$39*Parameters!$E$25)) + Parameters!$B$40*'6states'!E27) -> 16.740167 | L27: =L26+K27*Parameters!B$71 -> 2907.9477 | M27: =L27*Parameters!$B$46 -> 1.7447686 | N27: =EXP(-Parameters!$B$47/2*M27^2) -> 0.96986889 | O27: =MAX((Parameters!$B$63 + Parameters!$B$31*'6states'!A27 - '6states'!L27 + Parameters!$B$48/Parameters!$B$46)/Parameters!B$63,1) -> 13.313046 | P27: =Parameters!B$62*EXP(-Parameters!B$61*A27) -> 0.26870338 | Q27: =(1-Parameters!B$62)*O27^-Parameters!B$64 -> 0.38595997 | R27: =Parameters!B$62*EXP(-Parameters!B$61*A27)+(1-Parameters!B$62)*O27^-Parameters!B$64 -> 0.65466335 | S27: =1-R27/Parameters!$B$12 -> 0.67266833 | T27: =1/(1-S27) -> 3.0550053 | U27: =(Parameters!$B$19*(E27+Parameters!$B$20)^S27+Parameters!$B$18*F27^S27)^(1/S27) -> 0.36358362 | V27: =(Parameters!$B$10*G27^Parameters!$B$9+Parameters!$B$11*U27^Parameters!$B$9)^(Parameters!$B$7/Parameters!$B$9)*N27 -> 1.3785404 | W27: =V27 - C27 - D27 - LN(1+EXP(Parameters!$B$21*B27))/Parameters!$B$21 - IF(B27>0, 0,Parameters!$B$6*B27^2/E27) -> 1.0759038 | X27: =EXP(-Parameters!$B$56*A27) -> 0.70659332 | Y27: =IF(W27>0,W27^(1-Parameters!$B$53)/(1-Parameters!$B$53)*X27*Parameters!$B$71,-10+W27*1000) -> -1.9677992 | AA27: =B27/E27-B26/E26 -> -0.00044145894 | AB27: =C27/F27-C26/F26 -> -0.0031417523 | AC27: =D27/G27-D26/G26 -> 0.00036043459 | AD27: =X27*(AA27^2+AB27^2+AC27^2) -> 7.2040062e-06 | AE27: =B27/E27-2*B26/E26+B25/E25 -> -0.0027545958 | AF27: =C27/F27-2*C26/F26+C25/F25 -> 1.3622136e-05 | AG27: =D27/G27-2*D26/G26+D25/G25 -> 0.00016409743 | AH27: =X27*(AE27^2+AF27^2+AG27^2) -> 5.3806456e-06 | AM27: =H27*I27*J27 -> 1.1345832 | AN27: =E27*I27*J27 -> 26.563257 | AO27: =U27*I27*J27 -> 45.268561 | AP27: =V27*J27*I27 -> 171.63738 | AQ27: =-X27*V27*W27^(-Parameters!B$53)*Parameters!B$47*Parameters!B$46*M27 -> -1.8568636e-05 | AR27: =1000*EXP(-(Parameters!$B$55)*'6states'!A27)*AP27*Parameters!B$47*Parameters!B$46*M27 -> 1.6109835 | AS27: =SUM(AR27:AR$204)*EXP(Parameters!$B$55*A27) -> 293.96706 | AT27: =(B27+C27+D27)/V27 -> 0.21880136 | AU27: =(1/$S27-1/Parameters!$B$13) * LN(Parameters!$B$18) / LN(O27) -> 0.23624682 | AV27: =(Parameters!$B$18*'6states'!S27^+Parameters!$B$19*Parameters!$B$25^'6states'!S27)^((1-'6states'!S27)/'6states'!S27)*Parameters!$B$18*Parameters!$B$26^('6states'!S27-1) -> 0.25496735 | AW27: =(LN(AV27)-LN(AV$4))/ LN(O27) -> 0.26099657 | AX27: =1-2^-AU27 -> 0.15104901 | AY27: =1-2^-AV27 -> 0.1619939 | AZ27: =(1/$S27-1/Parameters!$B$13) * LN(Parameters!$B$18) / A27 -> 0.02659055
A28: =A27+Parameters!$B$71 -> 24 | B28: 0.0015439357 | C28: 0.085377636 | D28: 0.21515741 | E28: =MAX((1-Parameters!$B$4)^Parameters!B$71*E27 + B27*Parameters!B$71 - IF(B27>0,Parameters!$B$5,0)*B27^2/E27*Parameters!B$71, 0.0001) -> 0.2016581 | F28: =(1-Parameters!$B$4)^Parameters!B$71*F27+C27*Parameters!B$71-Parameters!$B$5*C27^2/F27*Parameters!B$71 -> 0.78620502 | G28: =(1-Parameters!$B$4)^Parameters!B$71*G27+D27*Parameters!B$71-Parameters!$B$5*D27^2/G27*Parameters!B$71 -> 3.5699629 | H28: =MAX(H27 * (1-Parameters!$B$4) ^ Parameters!B$71 + (LN(1+EXP(Parameters!$B$21*(-B27+0.004)))/Parameters!$B$21 -0.004) * Parameters!B$71,0) -> 0.0076467632 | I28: =I27*(1+Parameters!$B$52)^Parameters!B$71 -> 8.7472857 | J28: =J27*(1+Parameters!$B$54)^Parameters!B$71 -> 14.56052 | K28: =I28*J28*EXP(-Parameters!$B$43*'6states'!A28)*(Parameters!$B$38/Parameters!$B$39*('6states'!E28+'6states'!H28)/Parameters!$E$25*(EXP(-Parameters!$B$39*Parameters!$E$25*'6states'!H28/('6states'!E28+'6states'!H28))-EXP(-Parameters!$B$39*Parameters!$E$25)) + Parameters!$B$40*'6states'!E28) -> 16.131972 | L28: =L27+K28*Parameters!B$71 -> 2924.0796 | M28: =L28*Parameters!$B$46 -> 1.7544478 | N28: =EXP(-Parameters!$B$47/2*M28^2) -> 0.96953881 | O28: =MAX((Parameters!$B$63 + Parameters!$B$31*'6states'!A28 - '6states'!L28 + Parameters!$B$48/Parameters!$B$46)/Parameters!B$63,1) -> 14.054407 | P28: =Parameters!B$62*EXP(-Parameters!B$61*A28) -> 0.26154546 | Q28: =(1-Parameters!B$62)*O28^-Parameters!B$64 -> 0.38387405 | R28: =Parameters!B$62*EXP(-Parameters!B$61*A28)+(1-Parameters!B$62)*O28^-Parameters!B$64 -> 0.6454195 | S28: =1-R28/Parameters!$B$12 -> 0.67729025 | T28: =1/(1-S28) -> 3.0987598 | U28: =(Parameters!$B$19*(E28+Parameters!$B$20)^S28+Parameters!$B$18*F28^S28)^(1/S28) -> 0.36081159 | V28: =(Parameters!$B$10*G28^Parameters!$B$9+Parameters!$B$11*U28^Parameters!$B$9)^(Parameters!$B$7/Parameters!$B$9)*N28 -> 1.3751971 | W28: =V28 - C28 - D28 - LN(1+EXP(Parameters!$B$21*B28))/Parameters!$B$21 - IF(B28>0, 0,Parameters!$B$6*B28^2/E28) -> 1.0720399 | X28: =EXP(-Parameters!$B$56*A28) -> 0.69600391 | Y28: =IF(W28>0,W28^(1-Parameters!$B$53)/(1-Parameters!$B$53)*X28*Parameters!$B$71,-10+W28*1000) -> -1.9407509 | AA28: =B28/E28-B27/E27 -> -0.00051716569 | AB28: =C28/F28-C27/F27 -> -0.0028120053 | AC28: =D28/G28-D27/G27 -> 0.0003433097 | AD28: =X28*(AA28^2+AB28^2+AC28^2) -> 5.7717485e-06 | AE28: =B28/E28-2*B27/E27+B26/E26 -> -7.5706753e-05 | AF28: =C28/F28-2*C27/F27+C26/F26 -> 0.00032974704 | AG28: =D28/G28-2*D27/G27+D26/G26 -> -1.7124887e-05 | AH28: =X28*(AE28^2+AF28^2+AG28^2) -> 7.9871936e-08 | AM28: =H28*I28*J28 -> 0.97393017 | AN28: =E28*I28*J28 -> 25.684189 | AO28: =U28*I28*J28 -> 45.954777 | AP28: =V28*J28*I28 -> 175.15202 | AQ28: =-X28*V28*W28^(-Parameters!B$53)*Parameters!B$47*Parameters!B$46*M28 -> -1.8436548e-05 | AR28: =1000*EXP(-(Parameters!$B$55)*'6states'!A28)*AP28*Parameters!B$47*Parameters!B$46*M28 -> 1.5960747 | AS28: =SUM(AR28:AR$204)*EXP(Parameters!$B$55*A28) -> 300.72793 | AT28: =(B28+C28+D28)/V28 -> 0.21966231 | AU28: =(1/$S28-1/Parameters!$B$13) * LN(Parameters!$B$18) / LN(O28) -> 0.23597546 | AV28: =(Parameters!$B$18*'6states'!S28^+Parameters!$B$19*Parameters!$B$25^'6states'!S28)^((1-'6states'!S28)/'6states'!S28)*Parameters!$B$18*Parameters!$B$26^('6states'!S28-1) -> 0.25741419 | AW28: =(LN(AV28)-LN(AV$4))/ LN(O28) -> 0.25925878 | AX28: =1-2^-AU28 -> 0.15088931 | AY28: =1-2^-AV28 -> 0.16341397 | AZ28: =(1/$S28-1/Parameters!$B$13) * LN(Parameters!$B$18) / A28 -> 0.025986168
A29: =A28+Parameters!$B$71 -> 25 | B29: =B28+(B30-B28)/2 -> 0.0013257326 | C29: =C28+(C30-C28)/2 -> 0.086032154 | D29: =D28+(D30-D28)/2 -> 0.21496035 | E29: =MAX((1-Parameters!$B$4)^Parameters!B$71*E28 + B28*Parameters!B$71 - IF(B28>0,Parameters!$B$5,0)*B28^2/E28*Parameters!B$71, 0.0001) -> 0.19050592 | F29: =(1-Parameters!$B$4)^Parameters!B$71*F28+C28*Parameters!B$71-Parameters!$B$5*C28^2/F28*Parameters!B$71 -> 0.81285881 | G29: =(1-Parameters!$B$4)^Parameters!B$71*G28+D28*Parameters!B$71-Parameters!$B$5*D28^2/G28*Parameters!B$71 -> 3.5476024 | H29: =MAX(H28 * (1-Parameters!$B$4) ^ Parameters!B$71 + (LN(1+EXP(Parameters!$B$21*(-B28+0.004)))/Parameters!$B$21 -0.004) * Parameters!B$71,0) -> 0.0064168925 | I29: =I28*(1+Parameters!$B$52)^Parameters!B$71 -> 8.7726528 | J29: =J28*(1+Parameters!$B$54)^Parameters!B$71 -> 14.85173 | K29: =I29*J29*EXP(-Parameters!$B$43*'6states'!A29)*(Parameters!$B$38/Parameters!$B$39*('6states'!E29+'6states'!H29)/Parameters!$E$25*(EXP(-Parameters!$B$39*Parameters!$E$25*'6states'!H29/('6states'!E29+'6states'!H29))-EXP(-Parameters!$B$39*Parameters!$E$25)) + Parameters!$B$40*'6states'!E29) -> 15.543035 | L29: =L28+K29*Parameters!B$71 -> 2939.6227 | M29: =L29*Parameters!$B$46 -> 1.7637736 | N29: =EXP(-Parameters!$B$47/2*M29^2) -> 0.96921916 | O29: =MAX((Parameters!$B$63 + Parameters!$B$31*'6states'!A29 - '6states'!L29 + Parameters!$B$48/Parameters!$B$46)/Parameters!B$63,1) -> 14.807546 | P29: =Parameters!B$62*EXP(-Parameters!B$61*A29) -> 0.25457821 | Q29: =(1-Parameters!B$62)*O29^-Parameters!B$64 -> 0.38187541 | R29: =Parameters!B$62*EXP(-Parameters!B$61*A29)+(1-Parameters!B$62)*O29^-Parameters!B$64 -> 0.63645362 | S29: =1-R29/Parameters!$B$12 -> 0.68177319 | T29: =1/(1-S29) -> 3.1424128 | U29: =(Parameters!$B$19*(E29+Parameters!$B$20)^S29+Parameters!$B$18*F29^S29)^(1/S29) -> 0.35816261 | V29: =(Parameters!$B$10*G29^Parameters!$B$9+Parameters!$B$11*U29^Parameters!$B$9)^(Parameters!$B$7/Parameters!$B$9)*N29 -> 1.3719985 | W29: =V29 - C29 - D29 - LN(1+EXP(Parameters!$B$21*B29))/Parameters!$B$21 - IF(B29>0, 0,Parameters!$B$6*B29^2/E29) -> 1.0685234 | X29: =EXP(-Parameters!$B$56*A29) -> 0.6855732 | Y29: =IF(W29>0,W29^(1-Parameters!$B$53)/(1-Parameters!$B$53)*X29*Parameters!$B$71,-10+W29*1000) -> -1.9138653 | AA29: =B29/E29-B28/E28 -> -0.00069719486 | AB29: =C29/F29-C28/F28 -> -0.0027556319 | AC29: =D29/G29-D28/G28 -> 0.00032432733 | AD29: =X29*(AA29^2+AB29^2+AC29^2) -> 5.6112632e-06 | AE29: =B29/E29-2*B28/E28+B27/E27 -> -0.00018002917 | AF29: =C29/F29-2*C28/F28+C27/F27 -> 5.6373362e-05 | AG29: =D29/G29-2*D28/G28+D27/G27 -> -1.8982365e-05 | AH29: =X29*(AE29^2+AF29^2+AG29^2) -> 2.4645527e-08 | AM29: =H29*I29*J29 -> 0.83605096 | AN29: =E29*I29*J29 -> 24.82084 | AO29: =U29*I29*J29 -> 46.664673 | AP29: =V29*J29*I29 -> 178.75641 | AQ29: =-X29*V29*W29^(-Parameters!B$53)*Parameters!B$47*Parameters!B$46*M29 -> -1.8295285e-05 | AR29: =1000*EXP(-(Parameters!$B$55)*'6states'!A29)*AP29*Parameters!B$47*Parameters!B$46*M29 -> 1.5810964 | AS29: =SUM(AR29:AR$204)*EXP(Parameters!$B$55*A29) -> 307.63255 | AT29: =(B29+C29+D29)/V29 -> 0.22034881 | AU29: =(1/$S29-1/Parameters!$B$13) * LN(Parameters!$B$18) / LN(O29) -> 0.23569617 | AV29: =(Parameters!$B$18*'6states'!S29^+Parameters!$B$19*Parameters!$B$25^'6states'!S29)^((1-'6states'!S29)/'6states'!S29)*Parameters!$B$18*Parameters!$B$26^('6states'!S29-1) -> 0.25973236 | AW29: =(LN(AV29)-LN(AV$4))/ LN(O29) -> 0.25756377 | AX29: =1-2^-AU29 -> 0.15072492 | AY29: =1-2^-AV29 -> 0.16475715 | AZ29: =(1/$S29-1/Parameters!$B$13) * LN(Parameters!$B$18) / A29 -> 0.025409338
A30: =A29+Parameters!$B$71 -> 26 | B30: 0.0011075295 | C30: 0.086686673 | D30: 0.21476329 | E30: =MAX((1-Parameters!$B$4)^Parameters!B$71*E29 + B29*Parameters!B$71 - IF(B29>0,Parameters!$B$5,0)*B29^2/E29*Parameters!B$71, 0.0001) -> 0.17983961 | F30: =(1-Parameters!$B$4)^Parameters!B$71*F29+C29*Parameters!B$71-Parameters!$B$5*C29^2/F29*Parameters!B$71 -> 0.83865659 | G30: =(1-Parameters!$B$4)^Parameters!B$71*G29+D29*Parameters!B$71-Parameters!$B$5*D29^2/G29*Parameters!B$71 -> 3.5263934 | H30: =MAX(H29 * (1-Parameters!$B$4) ^ Parameters!B$71 + (LN(1+EXP(Parameters!$B$21*(-B29+0.004)))/Parameters!$B$21 -0.004) * Parameters!B$71,0) -> 0.0054250052 | I30: =I29*(1+Parameters!$B$52)^Parameters!B$71 -> 8.7980935 | J30: =J29*(1+Parameters!$B$54)^Parameters!B$71 -> 15.148764 | K30: =I30*J30*EXP(-Parameters!$B$43*'6states'!A30)*(Parameters!$B$38/Parameters!$B$39*('6states'!E30+'6states'!H30)/Parameters!$E$25*(EXP(-Parameters!$B$39*Parameters!$E$25*'6states'!H30/('6states'!E30+'6states'!H30))-EXP(-Parameters!$B$39*Parameters!$E$25)) + Parameters!$B$40*'6states'!E30) -> 14.961124 | L30: =L29+K30*Parameters!B$71 -> 2954.5838 | M30: =L30*Parameters!$B$46 -> 1.7727503 | N30: =EXP(-Parameters!$B$47/2*M30^2) -> 0.96890998 | O30: =MAX((Parameters!$B$63 + Parameters!$B$31*'6states'!A30 - '6states'!L30 + Parameters!$B$48/Parameters!$B$46)/Parameters!B$63,1) -> 15.572324 | P30: =Parameters!B$62*EXP(-Parameters!B$61*A30) -> 0.24779656 | Q30: =(1-Parameters!B$62)*O30^-Parameters!B$64 -> 0.37995719 | R30: =Parameters!B$62*EXP(-Parameters!B$61*A30)+(1-Parameters!B$62)*O30^-Parameters!B$64 -> 0.62775375 | S30: =1-R30/Parameters!$B$12 -> 0.68612313 | T30: =1/(1-S30) -> 3.1859627 | U30: =(Parameters!$B$19*(E30+Parameters!$B$20)^S30+Parameters!$B$18*F30^S30)^(1/S30) -> 0.35558501 | V30: =(Parameters!$B$10*G30^Parameters!$B$9+Parameters!$B$11*U30^Parameters!$B$9)^(Parameters!$B$7/Parameters!$B$9)*N30 -> 1.368919 | W30: =V30 - C30 - D30 - LN(1+EXP(Parameters!$B$21*B30))/Parameters!$B$21 - IF(B30>0, 0,Parameters!$B$6*B30^2/E30) -> 1.0651215 | X30: =EXP(-Parameters!$B$56*A30) -> 0.67529881 | Y30: =IF(W30>0,W30^(1-Parameters!$B$53)/(1-Parameters!$B$53)*X30*Parameters!$B$71,-10+W30*1000) -> -1.8872882 | AA30: =B30/E30-B29/E29 -> -0.00080058073 | AB30: =C30/F30-C29/F29 -> -0.0024752593 | AC30: =D30/G30-D29/G29 -> 0.0003085472 | AD30: =X30*(AA30^2+AB30^2+AC30^2) -> 4.6346023e-06 | AE30: =B30/E30-2*B29/E29+B28/E28 -> -0.00010338587 | AF30: =C30/F30-2*C29/F29+C28/F28 -> 0.00028037263 | AG30: =D30/G30-2*D29/G29+D28/G28 -> -1.5780133e-05 | AH30: =X30*(AE30^2+AF30^2+AG30^2) -> 6.0470621e-08 | AM30: =H30*I30*J30 -> 0.72304602 | AN30: =E30*I30*J30 -> 23.969067 | AO30: =U30*I30*J30 -> 47.392458 | AP30: =V30*J30*I30 -> 182.44986 | AQ30: =-X30*V30*W30^(-Parameters!B$53)*Parameters!B$47*Parameters!B$46*M30 -> -1.8150129e-05 | AR30: =1000*EXP(-(Parameters!$B$55)*'6states'!A30)*AP30*Parameters!B$47*Parameters!B$46*M30 -> 1.5660343 | AS30: =SUM(AR30:AR$204)*EXP(Parameters!$B$55*A30) -> 314.68401 | AT30: =(B30+C30+D30)/V30 -> 0.22101928 | AU30: =(1/$S30-1/Parameters!$B$13) * LN(Parameters!$B$18) / LN(O30) -> 0.23540791 | AV30: =(Parameters!$B$18*'6states'!S30^+Parameters!$B$19*Parameters!$B$25^'6states'!S30)^((1-'6states'!S30)/'6states'!S30)*Parameters!$B$18*Parameters!$B$26^('6states'!S30-1) -> 0.26192975 | AW30: =(LN(AV30)-LN(AV$4))/ LN(O30) -> 0.25590802 | AX30: =1-2^-AU30 -> 0.15055521 | AY30: =1-2^-AV30 -> 0.16602835 | AZ30: =(1/$S30-1/Parameters!$B$13) * LN(Parameters!$B$18) / A30 -> 0.024858126
A31: =A30+Parameters!$B$71 -> 27 | B31: =B30+(B32-B30)/2 -> 0.0010966744 | C31: =C30+(C32-C30)/2 -> 0.087206922 | D31: =D30+(D32-D30)/2 -> 0.21458409 | E31: =MAX((1-Parameters!$B$4)^Parameters!B$71*E30 + B30*Parameters!B$71 - IF(B30>0,Parameters!$B$5,0)*B30^2/E30*Parameters!B$71, 0.0001) -> 0.16962841 | F31: =(1-Parameters!$B$4)^Parameters!B$71*F30+C30*Parameters!B$71-Parameters!$B$5*C30^2/F30*Parameters!B$71 -> 0.8636315 | G31: =(1-Parameters!$B$4)^Parameters!B$71*G30+D30*Parameters!B$71-Parameters!$B$5*D30^2/G30*Parameters!B$71 -> 3.5062671 | H31: =MAX(H30 * (1-Parameters!$B$4) ^ Parameters!B$71 + (LN(1+EXP(Parameters!$B$21*(-B30+0.004)))/Parameters!$B$21 -0.004) * Parameters!B$71,0) -> 0.004659754 | I31: =I30*(1+Parameters!$B$52)^Parameters!B$71 -> 8.823608 | J31: =J30*(1+Parameters!$B$54)^Parameters!B$71 -> 15.45174 | K31: =I31*J31*EXP(-Parameters!$B$43*'6states'!A31)*(Parameters!$B$38/Parameters!$B$39*('6states'!E31+'6states'!H31)/Parameters!$E$25*(EXP(-Parameters!$B$39*Parameters!$E$25*'6states'!H31/('6states'!E31+'6states'!H31))-EXP(-Parameters!$B$39*Parameters!$E$25)) + Parameters!$B$40*'6states'!E31) -> 14.375804 | L31: =L30+K31*Parameters!B$71 -> 2968.9596 | M31: =L31*Parameters!$B$46 -> 1.7813758 | N31: =EXP(-Parameters!$B$47/2*M31^2) -> 0.96861151 | O31: =MAX((Parameters!$B$63 + Parameters!$B$31*'6states'!A31 - '6states'!L31 + Parameters!$B$48/Parameters!$B$46)/Parameters!B$63,1) -> 16.348808 | P31: =Parameters!B$62*EXP(-Parameters!B$61*A31) -> 0.24119557 | Q31: =(1-Parameters!B$62)*O31^-Parameters!B$64 -> 0.37811281 | R31: =Parameters!B$62*EXP(-Parameters!B$61*A31)+(1-Parameters!B$62)*O31^-Parameters!B$64 -> 0.61930838 | S31: =1-R31/Parameters!$B$12 -> 0.69034581 | T31: =1/(1-S31) -> 3.2294089 | U31: =(Parameters!$B$19*(E31+Parameters!$B$20)^S31+Parameters!$B$18*F31^S31)^(1/S31) -> 0.35307824 | V31: =(Parameters!$B$10*G31^Parameters!$B$9+Parameters!$B$11*U31^Parameters!$B$9)^(Parameters!$B$7/Parameters!$B$9)*N31 -> 1.3659545 | W31: =V31 - C31 - D31 - LN(1+EXP(Parameters!$B$21*B31))/Parameters!$B$21 - IF(B31>0, 0,Parameters!$B$6*B31^2/E31) -> 1.0618226 | X31: =EXP(-Parameters!$B$56*A31) -> 0.6651784 | Y31: =IF(W31>0,W31^(1-Parameters!$B$53)/(1-Parameters!$B$53)*X31*Parameters!$B$71,-10+W31*1000) -> -1.8610237 | AA31: =B31/E31-B30/E30 -> 0.00030672875 | AB31: =C31/F31-C30/F30 -> -0.0023867248 | AC31: =D31/G31-D30/G30 -> 0.00029847307 | AD31: =X31*(AA31^2+AB31^2+AC31^2) -> 3.910999e-06 | AE31: =B31/E31-2*B30/E30+B29/E29 -> 0.0011073095 | AF31: =C31/F31-2*C30/F30+C29/F29 -> 8.8534447e-05 | AG31: =D31/G31-2*D30/G30+D29/G29 -> -1.0074135e-05 | AH31: =X31*(AE31^2+AF31^2+AG31^2) -> 8.2087946e-07 | AM31: =H31*I31*J31 -> 0.6353113 | AN31: =E31*I31*J31 -> 23.127153 | AO31: =U31*I31*J31 -> 48.13872 | AP31: =V31*J31*I31 -> 186.23436 | AQ31: =-X31*V31*W31^(-Parameters!B$53)*Parameters!B$47*Parameters!B$46*M31 -> -1.8001432e-05 | AR31: =1000*EXP(-(Parameters!$B$55)*'6states'!A31)*AP31*Parameters!B$47*Parameters!B$46*M31 -> 1.5508928 | AS31: =SUM(AR31:AR$204)*EXP(Parameters!$B$55*A31) -> 321.88555 | AT31: =(B31+C31+D31)/V31 -> 0.22174069 | AU31: =(1/$S31-1/Parameters!$B$13) * LN(Parameters!$B$18) / LN(O31) -> 0.23510918 | AV31: =(Parameters!$B$18*'6states'!S31^+Parameters!$B$19*Parameters!$B$25^'6states'!S31)^((1-'6states'!S31)/'6states'!S31)*Parameters!$B$18*Parameters!$B$26^('6states'!S31-1) -> 0.26401377 | AW31: =(LN(AV31)-LN(AV$4))/ LN(O31) -> 0.25428768 | AX31: =1-2^-AU31 -> 0.1503793 | AY31: =1-2^-AV31 -> 0.16723218 | AZ31: =(1/$S31-1/Parameters!$B$13) * LN(Parameters!$B$18) / A31 -> 0.024330796
A32: =A31+Parameters!$B$71 -> 28 | B32: 0.0010858194 | C32: 0.087727172 | D32: 0.21440489 | E32: =MAX((1-Parameters!$B$4)^Parameters!B$71*E31 + B31*Parameters!B$71 - IF(B31>0,Parameters!$B$5,0)*B31^2/E31*Parameters!B$71, 0.0001) -> 0.16004836 | F32: =(1-Parameters!$B$4)^Parameters!B$71*F31+C31*Parameters!B$71-Parameters!$B$5*C31^2/F31*Parameters!B$71 -> 0.88771011 | G32: =(1-Parameters!$B$4)^Parameters!B$71*G31+D31*Parameters!B$71-Parameters!$B$5*D31^2/G31*Parameters!B$71 -> 3.4871744 | H32: =MAX(H31 * (1-Parameters!$B$4) ^ Parameters!B$71 + (LN(1+EXP(Parameters!$B$21*(-B31+0.004)))/Parameters!$B$21 -0.004) * Parameters!B$71,0) -> 0.0039508998 | I32: =I31*(1+Parameters!$B$52)^Parameters!B$71 -> 8.8491964 | J32: =J31*(1+Parameters!$B$54)^Parameters!B$71 -> 15.760775 | K32: =I32*J32*EXP(-Parameters!$B$43*'6states'!A32)*(Parameters!$B$38/Parameters!$B$39*('6states'!E32+'6states'!H32)/Parameters!$E$25*(EXP(-Parameters!$B$39*Parameters!$E$25*'6states'!H32/('6states'!E32+'6states'!H32))-EXP(-Parameters!$B$39*Parameters!$E$25)) + Parameters!$B$40*'6states'!E32) -> 13.82993 | L32: =L31+K32*Parameters!B$71 -> 2982.7895 | M32: =L32*Parameters!$B$46 -> 1.7896737 | N32: =EXP(-Parameters!$B$47/2*M32^2) -> 0.9683231 | O32: =MAX((Parameters!$B$63 + Parameters!$B$31*'6states'!A32 - '6states'!L32 + Parameters!$B$48/Parameters!$B$46)/Parameters!B$63,1) -> 17.136209 | P32: =Parameters!B$62*EXP(-Parameters!B$61*A32) -> 0.23477042 | Q32: =(1-Parameters!B$62)*O32^-Parameters!B$64 -> 0.3763384 | R32: =Parameters!B$62*EXP(-Parameters!B$61*A32)+(1-Parameters!B$62)*O32^-Parameters!B$64 -> 0.61110881 | S32: =1-R32/Parameters!$B$12 -> 0.69444559 | T32: =1/(1-S32) -> 3.2727396 | U32: =(Parameters!$B$19*(E32+Parameters!$B$20)^S32+Parameters!$B$18*F32^S32)^(1/S32) -> 0.35079417 | V32: =(Parameters!$B$10*G32^Parameters!$B$9+Parameters!$B$11*U32^Parameters!$B$9)^(Parameters!$B$7/Parameters!$B$9)*N32 -> 1.363164 | W32: =V32 - C32 - D32 - LN(1+EXP(Parameters!$B$21*B32))/Parameters!$B$21 - IF(B32>0, 0,Parameters!$B$6*B32^2/E32) -> 1.0586977 | X32: =EXP(-Parameters!$B$56*A32) -> 0.65520966 | Y32: =IF(W32>0,W32^(1-Parameters!$B$53)/(1-Parameters!$B$53)*X32*Parameters!$B$71,-10+W32*1000) -> -1.8350253 | AA32: =B32/E32-B31/E31 -> 0.00031916246 | AB32: =C32/F32-C31/F31 -> -0.0021528829 | AC32: =D32/G32-D31/G31 -> 0.00028368994 | AD32: =X32*(AA32^2+AB32^2+AC32^2) -> 3.1563085e-06 | AE32: =B32/E32-2*B31/E31+B30/E30 -> 1.2433707e-05 | AF32: =C32/F32-2*C31/F31+C30/F30 -> 0.00023384189 | AG32: =D32/G32-2*D31/G31+D30/G30 -> -1.4783127e-05 | AH32: =X32*(AE32^2+AF32^2+AG32^2) -> 3.6072679e-08 | AM32: =H32*I32*J32 -> 0.55103274 | AN32: =E32*I32*J32 -> 22.321976 | AO32: =U32*I32*J32 -> 48.925329 | AP32: =V32*J32*I32 -> 190.12074 | AQ32: =-X32*V32*W32^(-Parameters!B$53)*Parameters!B$47*Parameters!B$46*M32 -> -1.7848735e-05 | AR32: =1000*EXP(-(Parameters!$B$55)*'6states'!A32)*AP32*Parameters!B$47*Parameters!B$46*M32 -> 1.5357696 | AS32: =SUM(AR32:AR$204)*EXP(Parameters!$B$55*A32) -> 329.24048 | AT32: =(B32+C32+D32)/V32 -> 0.22243683 | AU32: =(1/$S32-1/Parameters!$B$13) * LN(Parameters!$B$18) / LN(O32) -> 0.23480238 | AV32: =(Parameters!$B$18*'6states'!S32^+Parameters!$B$19*Parameters!$B$25^'6states'!S32)^((1-'6states'!S32)/'6states'!S32)*Parameters!$B$18*Parameters!$B$26^('6states'!S32-1) -> 0.26599082 | AW32: =(LN(AV32)-LN(AV$4))/ LN(O32) -> 0.25270354 | AX32: =1-2^-AU32 -> 0.1501986 | AY32: =1-2^-AV32 -> 0.16837261 | AZ32: =(1/$S32-1/Parameters!$B$13) * LN(Parameters!$B$18) / A32 -> 0.02382568
A33: =A32+Parameters!$B$71 -> 29 | B33: =B32+(B34-B32)/2 -> 0.0010994217 | C33: =C32+(C34-C32)/2 -> 0.087940165 | D33: =D32+(D34-D32)/2 -> 0.21461632 | E33: =MAX((1-Parameters!$B$4)^Parameters!B$71*E32 + B32*Parameters!B$71 - IF(B32>0,Parameters!$B$5,0)*B32^2/E32*Parameters!B$71, 0.0001) -> 0.15105977 | F33: =(1-Parameters!$B$4)^Parameters!B$71*F32+C32*Parameters!B$71-Parameters!$B$5*C32^2/F32*Parameters!B$71 -> 0.91093076 | G33: =(1-Parameters!$B$4)^Parameters!B$71*G32+D32*Parameters!B$71-Parameters!$B$5*D32^2/G32*Parameters!B$71 -> 3.4690536 | H33: =MAX(H32 * (1-Parameters!$B$4) ^ Parameters!B$71 + (LN(1+EXP(Parameters!$B$21*(-B32+0.004)))/Parameters!$B$21 -0.004) * Parameters!B$71,0) -> 0.0032949037 | I33: =I32*(1+Parameters!$B$52)^Parameters!B$71 -> 8.8748591 | J33: =J32*(1+Parameters!$B$54)^Parameters!B$71 -> 16.07599 | K33: =I33*J33*EXP(-Parameters!$B$43*'6states'!A33)*(Parameters!$B$38/Parameters!$B$39*('6states'!E33+'6states'!H33)/Parameters!$E$25*(EXP(-Parameters!$B$39*Parameters!$E$25*'6states'!H33/('6states'!E33+'6states'!H33))-EXP(-Parameters!$B$39*Parameters!$E$25)) + Parameters!$B$40*'6states'!E33) -> 13.322873 | L33: =L32+K33*Parameters!B$71 -> 2996.1124 | M33: =L33*Parameters!$B$46 -> 1.7976674 | N33: =EXP(-Parameters!$B$47/2*M33^2) -> 0.96804407 | O33: =MAX((Parameters!$B$63 + Parameters!$B$31*'6states'!A33 - '6states'!L33 + Parameters!$B$48/Parameters!$B$46)/Parameters!B$63,1) -> 17.933752 | P33: =Parameters!B$62*EXP(-Parameters!B$61*A33) -> 0.22851643 | Q33: =(1-Parameters!B$62)*O33^-Parameters!B$64 -> 0.37463029 | R33: =Parameters!B$62*EXP(-Parameters!B$61*A33)+(1-Parameters!B$62)*O33^-Parameters!B$64 -> 0.60314672 | S33: =1-R33/Parameters!$B$12 -> 0.69842664 | T33: =1/(1-S33) -> 3.3159428 | U33: =(Parameters!$B$19*(E33+Parameters!$B$20)^S33+Parameters!$B$18*F33^S33)^(1/S33) -> 0.34872723 | V33: =(Parameters!$B$10*G33^Parameters!$B$9+Parameters!$B$11*U33^Parameters!$B$9)^(Parameters!$B$7/Parameters!$B$9)*N33 -> 1.3605418 | W33: =V33 - C33 - D33 - LN(1+EXP(Parameters!$B$21*B33))/Parameters!$B$21 - IF(B33>0, 0,Parameters!$B$6*B33^2/E33) -> 1.0556428 | X33: =EXP(-Parameters!$B$56*A33) -> 0.64539032 | Y33: =IF(W33>0,W33^(1-Parameters!$B$53)/(1-Parameters!$B$53)*X33*Parameters!$B$71,-10+W33*1000) -> -1.8093537 | AA33: =B33/E33-B32/E32 -> 0.00049373714 | AB33: =C33/F33-C32/F32 -> -0.0022853181 | AC33: =D33/G33-D32/G32 -> 0.00038211097 | AD33: =X33*(AA33^2+AB33^2+AC33^2) -> 3.6222299e-06 | AE33: =B33/E33-2*B32/E32+B31/E31 -> 0.00017457469 | AF33: =C33/F33-2*C32/F32+C31/F31 -> -0.00013243517 | AG33: =D33/G33-2*D32/G32+D31/G31 -> 9.8421033e-05 | AH33: =X33*(AE33^2+AF33^2+AG33^2) -> 3.7240374e-08 | AM33: =H33*I33*J33 -> 0.47009098 | AN33: =E33*I33*J33 -> 21.552022 | AO33: =U33*I33*J33 -> 49.753663 | AP33: =V33*J33*I33 -> 194.11142 | AQ33: =-X33*V33*W33^(-Parameters!B$53)*Parameters!B$47*Parameters!B$46*M33 -> -1.7694695e-05 | AR33: =1000*EXP(-(Parameters!$B$55)*'6states'!A33)*AP33*Parameters!B$47*Parameters!B$46*M33 -> 1.5206854 | AS33: =SUM(AR33:AR$204)*EXP(Parameters!$B$55*A33) -> 336.75197 | AT33: =(B33+C33+D33)/V33 -> 0.22318749 | AU33: =(1/$S33-1/Parameters!$B$13) * LN(Parameters!$B$18) / LN(O33) -> 0.23448946 | AV33: =(Parameters!$B$18*'6states'!S33^+Parameters!$B$19*Parameters!$B$25^'6states'!S33)^((1-'6states'!S33)/'6states'!S33)*Parameters!$B$18*Parameters!$B$26^('6states'!S33-1) -> 0.26786693 | AW33: =(LN(AV33)-LN(AV$4))/ LN(O33) -> 0.25115604 | AX33: =1-2^-AU33 -> 0.15001426 | AY33: =1-2^-AV33 -> 0.16945337 | AZ33: =(1/$S33-1/Parameters!$B$13) * LN(Parameters!$B$18) / A33 -> 0.023341279
A34: =A33+Parameters!$B$71 -> 30 | B34: 0.0011130241 | C34: 0.088153158 | D34: 0.21482774 | E34: =MAX((1-Parameters!$B$4)^Parameters!B$71*E33 + B33*Parameters!B$71 - IF(B33>0,Parameters!$B$5,0)*B33^2/E33*Parameters!B$71, 0.0001) -> 0.14264953 | F34: =(1-Parameters!$B$4)^Parameters!B$71*F33+C33*Parameters!B$71-Parameters!$B$5*C33^2/F33*Parameters!B$71 -> 0.93308374 | G34: =(1-Parameters!$B$4)^Parameters!B$71*G33+D33*Parameters!B$71-Parameters!$B$5*D33^2/G33*Parameters!B$71 -> 3.452189 | H34: =MAX(H33 * (1-Parameters!$B$4) ^ Parameters!B$71 + (LN(1+EXP(Parameters!$B$21*(-B33+0.004)))/Parameters!$B$21 -0.004) * Parameters!B$71,0) -> 0.0026698065 | I34: =I33*(1+Parameters!$B$52)^Parameters!B$71 -> 8.9005962 | J34: =J33*(1+Parameters!$B$54)^Parameters!B$71 -> 16.39751 | K34: =I34*J34*EXP(-Parameters!$B$43*'6states'!A34)*(Parameters!$B$38/Parameters!$B$39*('6states'!E34+'6states'!H34)/Parameters!$E$25*(EXP(-Parameters!$B$39*Parameters!$E$25*'6states'!H34/('6states'!E34+'6states'!H34))-EXP(-Parameters!$B$39*Parameters!$E$25)) + Parameters!$B$40*'6states'!E34) -> 12.861964 | L34: =L33+K34*Parameters!B$71 -> 3008.9744 | M34: =L34*Parameters!$B$46 -> 1.8053846 | N34: =EXP(-Parameters!$B$47/2*M34^2) -> 0.9677736 | O34: =MAX((Parameters!$B$63 + Parameters!$B$31*'6states'!A34 - '6states'!L34 + Parameters!$B$48/Parameters!$B$46)/Parameters!B$63,1) -> 18.740512 | P34: =Parameters!B$62*EXP(-Parameters!B$61*A34) -> 0.22242903 | Q34: =(1-Parameters!B$62)*O34^-Parameters!B$64 -> 0.37298542 | R34: =Parameters!B$62*EXP(-Parameters!B$61*A34)+(1-Parameters!B$62)*O34^-Parameters!B$64 -> 0.59541446 | S34: =1-R34/Parameters!$B$12 -> 0.70229277 | T34: =1/(1-S34) -> 3.3590048 | U34: =(Parameters!$B$19*(E34+Parameters!$B$20)^S34+Parameters!$B$18*F34^S34)^(1/S34) -> 0.34683664 | V34: =(Parameters!$B$10*G34^Parameters!$B$9+Parameters!$B$11*U34^Parameters!$B$9)^(Parameters!$B$7/Parameters!$B$9)*N34 -> 1.3580932 | W34: =V34 - C34 - D34 - LN(1+EXP(Parameters!$B$21*B34))/Parameters!$B$21 - IF(B34>0, 0,Parameters!$B$6*B34^2/E34) -> 1.0527615 | X34: =EXP(-Parameters!$B$56*A34) -> 0.63571813 | Y34: =IF(W34>0,W34^(1-Parameters!$B$53)/(1-Parameters!$B$53)*X34*Parameters!$B$71,-10+W34*1000) -> -1.7839433 | AA34: =B34/E34-B33/E33 -> 0.00052445009 | AB34: =C34/F34-C33/F33 -> -0.0020637259 | AC34: =D34/G34-D33/G33 -> 0.00036347095 | AD34: =X34*(AA34^2+AB34^2+AC34^2) -> 2.9663394e-06 | AE34: =B34/E34-2*B33/E33+B32/E32 -> 3.0712944e-05 | AF34: =C34/F34-2*C33/F33+C32/F32 -> 0.00022159219 | AG34: =D34/G34-2*D33/G33+D32/G32 -> -1.8640018e-05 | AH34: =X34*(AE34^2+AF34^2+AG34^2) -> 3.2036275e-08 | AM34: =H34*I34*J34 -> 0.38965189 | AN34: =E34*I34*J34 -> 20.819359 | AO34: =U34*I34*J34 -> 50.61998 | AP34: =V34*J34*I34 -> 198.21047 | AQ34: =-X34*V34*W34^(-Parameters!B$53)*Parameters!B$47*Parameters!B$46*M34 -> -1.7537421e-05 | AR34: =1000*EXP(-(Parameters!$B$55)*'6states'!A34)*AP34*Parameters!B$47*Parameters!B$46*M34 -> 1.505676 | AS34: =SUM(AR34:AR$204)*EXP(Parameters!$B$55*A34) -> 344.42321 | AT34: =(B34+C34+D34)/V34 -> 0.22391241 | AU34: =(1/$S34-1/Parameters!$B$13) * LN(Parameters!$B$18) / LN(O34) -> 0.23417261 | AV34: =(Parameters!$B$18*'6states'!S34^+Parameters!$B$19*Parameters!$B$25^'6states'!S34)^((1-'6states'!S34)/'6states'!S34)*Parameters!$B$18*Parameters!$B$26^('6states'!S34-1) -> 0.26964768 | AW34: =(LN(AV34)-LN(AV$4))/ LN(O34) -> 0.2496459 | AX34: =1-2^-AU34 -> 0.14982756 | AY34: =1-2^-AV34 -> 0.1704779 | AZ34: =(1/$S34-1/Parameters!$B$13) * LN(Parameters!$B$18) / A34 -> 0.022876226
A35: =A34+Parameters!$B$71 -> 31 | B35: =B34+(B36-B34)/2 -> 0.0011212211 | C35: =C34+(C36-C34)/2 -> 0.088404858 | D35: =D34+(D36-D34)/2 -> 0.21484566 | E35: =MAX((1-Parameters!$B$4)^Parameters!B$71*E34 + B34*Parameters!B$71 - IF(B34>0,Parameters!$B$5,0)*B34^2/E34*Parameters!B$71, 0.0001) -> 0.13478122 | F35: =(1-Parameters!$B$4)^Parameters!B$71*F34+C34*Parameters!B$71-Parameters!$B$5*C34^2/F34*Parameters!B$71 -> 0.95421765 | G35: =(1-Parameters!$B$4)^Parameters!B$71*G34+D34*Parameters!B$71-Parameters!$B$5*D34^2/G34*Parameters!B$71 -> 3.4365054 | H35: =MAX(H34 * (1-Parameters!$B$4) ^ Parameters!B$71 + (LN(1+EXP(Parameters!$B$21*(-B34+0.004)))/Parameters!$B$21 -0.004) * Parameters!B$71,0) -> 0.0020736783 | I35: =I34*(1+Parameters!$B$52)^Parameters!B$71 -> 8.9264079 | J35: =J34*(1+Parameters!$B$54)^Parameters!B$71 -> 16.72546 | K35: =I35*J35*EXP(-Parameters!$B$43*'6states'!A35)*(Parameters!$B$38/Parameters!$B$39*('6states'!E35+'6states'!H35)/Parameters!$E$25*(EXP(-Parameters!$B$39*Parameters!$E$25*'6states'!H35/('6states'!E35+'6states'!H35))-EXP(-Parameters!$B$39*Parameters!$E$25)) + Parameters!$B$40*'6states'!E35) -> 12.449298 | L35: =L34+K35*Parameters!B$71 -> 3021.4237 | M35: =L35*Parameters!$B$46 -> 1.8128542 | N35: =EXP(-Parameters!$B$47/2*M35^2) -> 0.96751077 | O35: =MAX((Parameters!$B$63 + Parameters!$B$31*'6states'!A35 - '6states'!L35 + Parameters!$B$48/Parameters!$B$46)/Parameters!B$63,1) -> 19.555526 | P35: =Parameters!B$62*EXP(-Parameters!B$61*A35) -> 0.2165038 | Q35: =(1-Parameters!B$62)*O35^-Parameters!B$64 -> 0.37140099 | R35: =Parameters!B$62*EXP(-Parameters!B$61*A35)+(1-Parameters!B$62)*O35^-Parameters!B$64 -> 0.58790479 | S35: =1-R35/Parameters!$B$12 -> 0.70604761 | T35: =1/(1-S35) -> 3.4019114 | U35: =(Parameters!$B$19*(E35+Parameters!$B$20)^S35+Parameters!$B$18*F35^S35)^(1/S35) -> 0.34511831 | V35: =(Parameters!$B$10*G35^Parameters!$B$9+Parameters!$B$11*U35^Parameters!$B$9)^(Parameters!$B$7/Parameters!$B$9)*N35 -> 1.3558113 | W35: =V35 - C35 - D35 - LN(1+EXP(Parameters!$B$21*B35))/Parameters!$B$21 - IF(B35>0, 0,Parameters!$B$6*B35^2/E35) -> 1.050205 | X35: =EXP(-Parameters!$B$56*A35) -> 0.6261909 | Y35: =IF(W35>0,W35^(1-Parameters!$B$53)/(1-Parameters!$B$53)*X35*Parameters!$B$71,-10+W35*1000) -> -1.7587041 | AA35: =B35/E35-B34/E34 -> 0.00051631578 | AB35: =C35/F35-C34/F34 -> -0.001828649 | AC35: =D35/G35-D34/G34 -> 0.00028921759 | AD35: =X35*(AA35^2+AB35^2+AC35^2) -> 2.3132656e-06 | AE35: =B35/E35-2*B34/E34+B33/E33 -> -8.1343126e-06 | AF35: =C35/F35-2*C34/F34+C33/F33 -> 0.00023507691 | AG35: =D35/G35-2*D34/G34+D33/G33 -> -7.4253364e-05 | AH35: =X35*(AE35^2+AF35^2+AG35^2) -> 3.8098009e-08 | AM35: =H35*I35*J35 -> 0.30959659 | AN35: =E35*I35*J35 -> 20.122604 | AO35: =U35*I35*J35 -> 51.52557 | AP35: =V35*J35*I35 -> 202.42029 | AQ35: =-X35*V35*W35^(-Parameters!B$53)*Parameters!B$47*Parameters!B$46*M35 -> -1.7373855e-05 | AR35: =1000*EXP(-(Parameters!$B$55)*'6states'!A35)*AP35*Parameters!B$47*Parameters!B$46*M35 -> 1.4907623 | AS35: =SUM(AR35:AR$204)*EXP(Parameters!$B$55*A35) -> 352.25735 | AT35: =(B35+C35+D35)/V35 -> 0.22449417 | AU35: =(1/$S35-1/Parameters!$B$13) * LN(Parameters!$B$18) / LN(O35) -> 0.23385382 | AV35: =(Parameters!$B$18*'6states'!S35^+Parameters!$B$19*Parameters!$B$25^'6states'!S35)^((1-'6states'!S35)/'6states'!S35)*Parameters!$B$18*Parameters!$B$26^('6states'!S35-1) -> 0.27133834 | AW35: =(LN(AV35)-LN(AV$4))/ LN(O35) -> 0.24817371 | AX35: =1-2^-AU35 -> 0.14963968 | AY35: =1-2^-AV35 -> 0.17144943 | AZ35: =(1/$S35-1/Parameters!$B$13) * LN(Parameters!$B$18) / A35 -> 0.022429281
A36: =A35+Parameters!$B$71 -> 32 | B36: 0.0011294182 | C36: 0.088656557 | D36: 0.21486358 | E36: =MAX((1-Parameters!$B$4)^Parameters!B$71*E35 + B35*Parameters!B$71 - IF(B35>0,Parameters!$B$5,0)*B35^2/E35*Parameters!B$71, 0.0001) -> 0.12741537 | F36: =(1-Parameters!$B$4)^Parameters!B$71*F35+C35*Parameters!B$71-Parameters!$B$5*C35^2/F35*Parameters!B$71 -> 0.97441183 | G36: =(1-Parameters!$B$4)^Parameters!B$71*G35+D35*Parameters!B$71-Parameters!$B$5*D35^2/G35*Parameters!B$71 -> 3.4217631 | H36: =MAX(H35 * (1-Parameters!$B$4) ^ Parameters!B$71 + (LN(1+EXP(Parameters!$B$21*(-B35+0.004)))/Parameters!$B$21 -0.004) * Parameters!B$71,0) -> 0.001508816 | I36: =I35*(1+Parameters!$B$52)^Parameters!B$71 -> 8.9522945 | J36: =J35*(1+Parameters!$B$54)^Parameters!B$71 -> 17.059969 | K36: =I36*J36*EXP(-Parameters!$B$43*'6states'!A36)*(Parameters!$B$38/Parameters!$B$39*('6states'!E36+'6states'!H36)/Parameters!$E$25*(EXP(-Parameters!$B$39*Parameters!$E$25*'6states'!H36/('6states'!E36+'6states'!H36))-EXP(-Parameters!$B$39*Parameters!$E$25)) + Parameters!$B$40*'6states'!E36) -> 12.086063 | L36: =L35+K36*Parameters!B$71 -> 3033.5097 | M36: =L36*Parameters!$B$46 -> 1.8201058 | N36: =EXP(-Parameters!$B$47/2*M36^2) -> 0.96725464 | O36: =MAX((Parameters!$B$63 + Parameters!$B$31*'6states'!A36 - '6states'!L36 + Parameters!$B$48/Parameters!$B$46)/Parameters!B$63,1) -> 20.377805 | P36: =Parameters!B$62*EXP(-Parameters!B$61*A36) -> 0.21073641 | Q36: =(1-Parameters!B$62)*O36^-Parameters!B$64 -> 0.36987439 | R36: =Parameters!B$62*EXP(-Parameters!B$61*A36)+(1-Parameters!B$62)*O36^-Parameters!B$64 -> 0.5806108 | S36: =1-R36/Parameters!$B$12 -> 0.7096946 | T36: =1/(1-S36) -> 3.4446483 | U36: =(Parameters!$B$19*(E36+Parameters!$B$20)^S36+Parameters!$B$18*F36^S36)^(1/S36) -> 0.34356986 | V36: =(Parameters!$B$10*G36^Parameters!$B$9+Parameters!$B$11*U36^Parameters!$B$9)^(Parameters!$B$7/Parameters!$B$9)*N36 -> 1.3536768 | W36: =V36 - C36 - D36 - LN(1+EXP(Parameters!$B$21*B36))/Parameters!$B$21 - IF(B36>0, 0,Parameters!$B$6*B36^2/E36) -> 1.0477958 | X36: =EXP(-Parameters!$B$56*A36) -> 0.61680645 | Y36: =IF(W36>0,W36^(1-Parameters!$B$53)/(1-Parameters!$B$53)*X36*Parameters!$B$71,-10+W36*1000) -> -1.7337402 | AA36: =B36/E36-B35/E35 -> 0.00054524217 | AB36: =C36/F36-C35/F35 -> -0.0016617398 | AC36: =D36/G36-D35/G35 -> 0.00027459341 | AD36: =X36*(AA36^2+AB36^2+AC36^2) -> 1.9331144e-06 | AE36: =B36/E36-2*B35/E35+B34/E34 -> 2.8926397e-05 | AF36: =C36/F36-2*C35/F35+C34/F34 -> 0.00016690921 | AG36: =D36/G36-2*D35/G35+D34/G34 -> -1.4624183e-05 | AH36: =X36*(AE36^2+AF36^2+AG36^2) -> 1.7831435e-08 | AM36: =H36*I36*J36 -> 0.23043523 | AN36: =E36*I36*J36 -> 19.459624 | AO36: =U36*I36*J36 -> 52.472006 | AP36: =V36*J36*I36 -> 206.74146 | AQ36: =-X36*V36*W36^(-Parameters!B$53)*Parameters!B$47*Parameters!B$46*M36 -> -1.7208156e-05 | AR36: =1000*EXP(-(Parameters!$B$55)*'6states'!A36)*AP36*Parameters!B$47*Parameters!B$46*M36 -> 1.4759511 | AS36: =SUM(AR36:AR$204)*EXP(Parameters!$B$55*A36) -> 360.25752 | AT36: =(B36+C36+D36)/V36 -> 0.22505339 | AU36: =(1/$S36-1/Parameters!$B$13) * LN(Parameters!$B$18) / LN(O36) -> 0.23353482 | AV36: =(Parameters!$B$18*'6states'!S36^+Parameters!$B$19*Parameters!$B$25^'6states'!S36)^((1-'6states'!S36)/'6states'!S36)*Parameters!$B$18*Parameters!$B$26^('6states'!S36-1) -> 0.27294386 | AW36: =(LN(AV36)-LN(AV$4))/ LN(O36) -> 0.24673985 | AX36: =1-2^-AU36 -> 0.14945164 | AY36: =1-2^-AV36 -> 0.17237098 | AZ36: =(1/$S36-1/Parameters!$B$13) * LN(Parameters!$B$18) / A36 -> 0.021999318
A37: =A36+Parameters!$B$71 -> 33 | B37: =B36+(B38-B36)/2 -> 0.0011192362 | C37: =C36+(C38-C36)/2 -> 0.088690075 | D37: =D36+(D38-D36)/2 -> 0.21510846 | E37: =MAX((1-Parameters!$B$4)^Parameters!B$71*E36 + B36*Parameters!B$71 - IF(B36>0,Parameters!$B$5,0)*B36^2/E36*Parameters!B$71, 0.0001) -> 0.12052035 | F37: =(1-Parameters!$B$4)^Parameters!B$71*F36+C36*Parameters!B$71-Parameters!$B$5*C36^2/F36*Parameters!B$71 -> 0.99371149 | G37: =(1-Parameters!$B$4)^Parameters!B$71*G36+D36*Parameters!B$71-Parameters!$B$5*D36^2/G36*Parameters!B$71 -> 3.4079058 | H37: =MAX(H36 * (1-Parameters!$B$4) ^ Parameters!B$71 + (LN(1+EXP(Parameters!$B$21*(-B36+0.004)))/Parameters!$B$21 -0.004) * Parameters!B$71,0) -> 0.00097325792 | I37: =I36*(1+Parameters!$B$52)^Parameters!B$71 -> 8.9782562 | J37: =J36*(1+Parameters!$B$54)^Parameters!B$71 -> 17.401169 | K37: =I37*J37*EXP(-Parameters!$B$43*'6states'!A37)*(Parameters!$B$38/Parameters!$B$39*('6states'!E37+'6states'!H37)/Parameters!$E$25*(EXP(-Parameters!$B$39*Parameters!$E$25*'6states'!H37/('6states'!E37+'6states'!H37))-EXP(-Parameters!$B$39*Parameters!$E$25)) + Parameters!$B$40*'6states'!E37) -> 11.776506 | L37: =L36+K37*Parameters!B$71 -> 3045.2862 | M37: =L37*Parameters!$B$46 -> 1.8271717 | N37: =EXP(-Parameters!$B$47/2*M37^2) -> 0.96700415 | O37: =MAX((Parameters!$B$63 + Parameters!$B$31*'6states'!A37 - '6states'!L37 + Parameters!$B$48/Parameters!$B$46)/Parameters!B$63,1) -> 21.206275 | P37: =Parameters!B$62*EXP(-Parameters!B$61*A37) -> 0.20512265 | Q37: =(1-Parameters!B$62)*O37^-Parameters!B$64 -> 0.36840335 | R37: =Parameters!B$62*EXP(-Parameters!B$61*A37)+(1-Parameters!B$62)*O37^-Parameters!B$64 -> 0.573526 | S37: =1-R37/Parameters!$B$12 -> 0.713237 | T37: =1/(1-S37) -> 3.4872003 | U37: =(Parameters!$B$19*(E37+Parameters!$B$20)^S37+Parameters!$B$18*F37^S37)^(1/S37) -> 0.34218594 | V37: =(Parameters!$B$10*G37^Parameters!$B$9+Parameters!$B$11*U37^Parameters!$B$9)^(Parameters!$B$7/Parameters!$B$9)*N37 -> 1.3516828 | W37: =V37 - C37 - D37 - LN(1+EXP(Parameters!$B$21*B37))/Parameters!$B$21 - IF(B37>0, 0,Parameters!$B$6*B37^2/E37) -> 1.0455297 | X37: =EXP(-Parameters!$B$56*A37) -> 0.60756264 | Y37: =IF(W37>0,W37^(1-Parameters!$B$53)/(1-Parameters!$B$53)*X37*Parameters!$B$71,-10+W37*1000) -> -1.709052 | AA37: =B37/E37-B36/E36 -> 0.00042263354 | AB37: =C37/F37-C36/F36 -> -0.0017333555 | AC37: =D37/G37-D36/G36 -> 0.00032718754 | AD37: =X37*(AA37^2+AB37^2+AC37^2) -> 1.9989979e-06 | AE37: =B37/E37-2*B36/E36+B35/E35 -> -0.00012260863 | AF37: =C37/F37-2*C36/F36+C35/F35 -> -7.161575e-05 | AG37: =D37/G37-2*D36/G36+D35/G35 -> 5.2594135e-05 | AH37: =X37*(AE37^2+AF37^2+AG37^2) -> 1.3930096e-08 | AM37: =H37*I37*J37 -> 0.15205418 | AN37: =E37*I37*J37 -> 18.829154 | AO37: =U37*I37*J37 -> 53.460445 | AP37: =V37*J37*I37 -> 211.17632 | AQ37: =-X37*V37*W37^(-Parameters!B$53)*Parameters!B$47*Parameters!B$46*M37 -> -1.7040739e-05 | AR37: =1000*EXP(-(Parameters!$B$55)*'6states'!A37)*AP37*Parameters!B$47*Parameters!B$46*M37 -> 1.4612637 | AS37: =SUM(AR37:AR$204)*EXP(Parameters!$B$55*A37) -> 368.42691 | AT37: =(B37+C37+D37)/V37 -> 0.22558381 | AU37: =(1/$S37-1/Parameters!$B$13) * LN(Parameters!$B$18) / LN(O37) -> 0.23321736 | AV37: =(Parameters!$B$18*'6states'!S37^+Parameters!$B$19*Parameters!$B$25^'6states'!S37)^((1-'6states'!S37)/'6states'!S37)*Parameters!$B$18*Parameters!$B$26^('6states'!S37-1) -> 0.27446885 | AW37: =(LN(AV37)-LN(AV$4))/ LN(O37) -> 0.24534473 | AX37: =1-2^-AU37 -> 0.14926445 | AY37: =1-2^-AV37 -> 0.17324536 | AZ37: =(1/$S37-1/Parameters!$B$13) * LN(Parameters!$B$18) / A37 -> 0.021585306
A38: =A37+Parameters!$B$71 -> 34 | B38: 0.0011090543 | C38: 0.088723594 | D38: 0.21535334 | E38: =MAX((1-Parameters!$B$4)^Parameters!B$71*E37 + B37*Parameters!B$71 - IF(B37>0,Parameters!$B$5,0)*B37^2/E37*Parameters!B$71, 0.0001) -> 0.11404847 | F38: =(1-Parameters!$B$4)^Parameters!B$71*F37+C37*Parameters!B$71-Parameters!$B$5*C37^2/F37*Parameters!B$71 -> 1.0119814 | G38: =(1-Parameters!$B$4)^Parameters!B$71*G37+D37*Parameters!B$71-Parameters!$B$5*D37^2/G37*Parameters!B$71 -> 3.3950792 | H38: =MAX(H37 * (1-Parameters!$B$4) ^ Parameters!B$71 + (LN(1+EXP(Parameters!$B$21*(-B37+0.004)))/Parameters!$B$21 -0.004) * Parameters!B$71,0) -> 0.0004791203 | I38: =I37*(1+Parameters!$B$52)^Parameters!B$71 -> 9.0042931 | J38: =J37*(1+Parameters!$B$54)^Parameters!B$71 -> 17.749192 | K38: =I38*J38*EXP(-Parameters!$B$43*'6states'!A38)*(Parameters!$B$38/Parameters!$B$39*('6states'!E38+'6states'!H38)/Parameters!$E$25*(EXP(-Parameters!$B$39*Parameters!$E$25*'6states'!H38/('6states'!E38+'6states'!H38))-EXP(-Parameters!$B$39*Parameters!$E$25)) + Parameters!$B$40*'6states'!E38) -> 11.516989 | L38: =L37+K38*Parameters!B$71 -> 3056.8032 | M38: =L38*Parameters!$B$46 -> 1.8340819 | N38: =EXP(-Parameters!$B$47/2*M38^2) -> 0.9667583 | O38: =MAX((Parameters!$B$63 + Parameters!$B$31*'6states'!A38 - '6states'!L38 + Parameters!$B$48/Parameters!$B$46)/Parameters!B$63,1) -> 22.039935 | P38: =Parameters!B$62*EXP(-Parameters!B$61*A38) -> 0.19965844 | Q38: =(1-Parameters!B$62)*O38^-Parameters!B$64 -> 0.36698556 | R38: =Parameters!B$62*EXP(-Parameters!B$61*A38)+(1-Parameters!B$62)*O38^-Parameters!B$64 -> 0.566644 | S38: =1-R38/Parameters!$B$12 -> 0.716678 | T38: =1/(1-S38) -> 3.529553 | U38: =(Parameters!$B$19*(E38+Parameters!$B$20)^S38+Parameters!$B$18*F38^S38)^(1/S38) -> 0.34090417 | V38: =(Parameters!$B$10*G38^Parameters!$B$9+Parameters!$B$11*U38^Parameters!$B$9)^(Parameters!$B$7/Parameters!$B$9)*N38 -> 1.3498139 | W38: =V38 - C38 - D38 - LN(1+EXP(Parameters!$B$21*B38))/Parameters!$B$21 - IF(B38>0, 0,Parameters!$B$6*B38^2/E38) -> 1.0433886 | X38: =EXP(-Parameters!$B$56*A38) -> 0.59845736 | Y38: =IF(W38>0,W38^(1-Parameters!$B$53)/(1-Parameters!$B$53)*X38*Parameters!$B$71,-10+W38*1000) -> -1.6846475 | AA38: =B38/E38-B37/E37 -> 0.00043771313 | AB38: =C38/F38-C37/F37 -> -0.0015781868 | AC38: =D38/G38-D37/G37 -> 0.00031059573 | AD38: =X38*(AA38^2+AB38^2+AC38^2) -> 1.6629551e-06 | AE38: =B38/E38-2*B37/E37+B36/E36 -> 1.5079589e-05 | AF38: =C38/F38-2*C37/F37+C36/F36 -> 0.00015516873 | AG38: =D38/G38-2*D37/G37+D36/G36 -> -1.6591811e-05 | AH38: =X38*(AE38^2+AF38^2+AG38^2) -> 1.4710091e-08 | AM38: =H38*I38*J38 -> 0.076572493 | AN38: =E38*I38*J38 -> 18.227103 | AO38: =U38*I38*J38 -> 54.482939 | AP38: =V38*J38*I38 -> 215.72582 | AQ38: =-X38*V38*W38^(-Parameters!B$53)*Parameters!B$47*Parameters!B$46*M38 -> -1.687217e-05 | AR38: =1000*EXP(-(Parameters!$B$55)*'6states'!A38)*AP38*Parameters!B$47*Parameters!B$46*M38 -> 1.4467088 | AS38: =SUM(AR38:AR$204)*EXP(Parameters!$B$55*A38) -> 376.76867 | AT38: =(B38+C38+D38)/V38 -> 0.22609486 | AU38: =(1/$S38-1/Parameters!$B$13) * LN(Parameters!$B$18) / LN(O38) -> 0.23290269 | AV38: =(Parameters!$B$18*'6states'!S38^+Parameters!$B$19*Parameters!$B$25^'6states'!S38)^((1-'6states'!S38)/'6states'!S38)*Parameters!$B$18*Parameters!$B$26^('6states'!S38-1) -> 0.27591773 | AW38: =(LN(AV38)-LN(AV$4))/ LN(O38) -> 0.24398829 | AX38: =1-2^-AU38 -> 0.14907888 | AY38: =1-2^-AV38 -> 0.17407524 | AZ38: =(1/$S38-1/Parameters!$B$13) * LN(Parameters!$B$18) / A38 -> 0.021186308
A39: =A38+Parameters!$B$71 -> 35 | B39: =B38+(B40-B38)/2 -> 0.0010910541 | C39: =C38+(C40-C38)/2 -> 0.088783628 | D39: =D38+(D40-D38)/2 -> 0.21562044 | E39: =MAX((1-Parameters!$B$4)^Parameters!B$71*E38 + B38*Parameters!B$71 - IF(B38>0,Parameters!$B$5,0)*B38^2/E38*Parameters!B$71, 0.0001) -> 0.10797309 | F39: =(1-Parameters!$B$4)^Parameters!B$71*F38+C38*Parameters!B$71-Parameters!$B$5*C38^2/F38*Parameters!B$71 -> 1.0292727 | G39: =(1-Parameters!$B$4)^Parameters!B$71*G38+D38*Parameters!B$71-Parameters!$B$5*D38^2/G38*Parameters!B$71 -> 3.383222 | H39: =MAX(H38 * (1-Parameters!$B$4) ^ Parameters!B$71 + (LN(1+EXP(Parameters!$B$21*(-B38+0.004)))/Parameters!$B$21 -0.004) * Parameters!B$71,0) -> 2.3805318e-05 | I39: =I38*(1+Parameters!$B$52)^Parameters!B$71 -> 9.0304056 | J39: =J38*(1+Parameters!$B$54)^Parameters!B$71 -> 18.104176 | K39: =I39*J39*EXP(-Parameters!$B$43*'6states'!A39)*(Parameters!$B$38/Parameters!$B$39*('6states'!E39+'6states'!H39)/Parameters!$E$25*(EXP(-Parameters!$B$39*Parameters!$E$25*'6states'!H39/('6states'!E39+'6states'!H39))-EXP(-Parameters!$B$39*Parameters!$E$25)) + Parameters!$B$40*'6states'!E39) -> 11.311901 | L39: =L38+K39*Parameters!B$71 -> 3068.1151 | M39: =L39*Parameters!$B$46 -> 1.8408691 | N39: =EXP(-Parameters!$B$47/2*M39^2) -> 0.966516 | O39: =MAX((Parameters!$B$63 + Parameters!$B$31*'6states'!A39 - '6states'!L39 + Parameters!$B$48/Parameters!$B$46)/Parameters!B$63,1) -> 22.877697 | P39: =Parameters!B$62*EXP(-Parameters!B$61*A39) -> 0.19433979 | Q39: =(1-Parameters!B$62)*O39^-Parameters!B$64 -> 0.36561901 | R39: =Parameters!B$62*EXP(-Parameters!B$61*A39)+(1-Parameters!B$62)*O39^-Parameters!B$64 -> 0.5599588 | S39: =1-R39/Parameters!$B$12 -> 0.7200206 | T39: =1/(1-S39) -> 3.5716913 | U39: =(Parameters!$B$19*(E39+Parameters!$B$20)^S39+Parameters!$B$18*F39^S39)^(1/S39) -> 0.33972142 | V39: =(Parameters!$B$10*G39^Parameters!$B$9+Parameters!$B$11*U39^Parameters!$B$9)^(Parameters!$B$7/Parameters!$B$9)*N39 -> 1.3480633 | W39: =V39 - C39 - D39 - LN(1+EXP(Parameters!$B$21*B39))/Parameters!$B$21 - IF(B39>0, 0,Parameters!$B$6*B39^2/E39) -> 1.0413218 | X39: =EXP(-Parameters!$B$56*A39) -> 0.58948854 | Y39: =IF(W39>0,W39^(1-Parameters!$B$53)/(1-Parameters!$B$53)*X39*Parameters!$B$71,-10+W39*1000) -> -1.6605524 | AA39: =B39/E39-B38/E38 -> 0.0003804584 | AB39: =C39/F39-C38/F38 -> -0.0014145404 | AC39: =D39/G39-D38/G38 -> 0.00030125565 | AD39: =X39*(AA39^2+AB39^2+AC39^2) -> 1.3183487e-06 | AE39: =B39/E39-2*B38/E38+B37/E37 -> -5.7254729e-05 | AF39: =C39/F39-2*C38/F38+C37/F37 -> 0.00016364645 | AG39: =D39/G39-2*D38/G38+D37/G37 -> -9.3400784e-06 | AH39: =X39*(AE39^2+AF39^2+AG39^2) -> 1.7770428e-08 | AM39: =H39*I39*J39 -> 0.0038918851 | AN39: =E39*I39*J39 -> 17.652309 | AO39: =U39*I39*J39 -> 55.540393 | AP39: =V39*J39*I39 -> 220.39224 | AQ39: =-X39*V39*W39^(-Parameters!B$53)*Parameters!B$47*Parameters!B$46*M39 -> -1.6703834e-05 | AR39: =1000*EXP(-(Parameters!$B$55)*'6states'!A39)*AP39*Parameters!B$47*Parameters!B$46*M39 -> 1.4323058 | AS39: =SUM(AR39:AR$204)*EXP(Parameters!$B$55*A39) -> 385.28598 | AT39: =(B39+C39+D39)/V39 -> 0.22661778 | AU39: =(1/$S39-1/Parameters!$B$13) * LN(Parameters!$B$18) / LN(O39) -> 0.23259212 | AV39: =(Parameters!$B$18*'6states'!S39^+Parameters!$B$19*Parameters!$B$25^'6states'!S39)^((1-'6states'!S39)/'6states'!S39)*Parameters!$B$18*Parameters!$B$26^('6states'!S39-1) -> 0.2772946 | AW39: =(LN(AV39)-LN(AV$4))/ LN(O39) -> 0.24267059 | AX39: =1-2^-AU39 -> 0.14889568 | AY39: =1-2^-AV39 -> 0.1748631 | AZ39: =(1/$S39-1/Parameters!$B$13) * LN(Parameters!$B$18) / A39 -> 0.020801461
A40: =A39+Parameters!$B$71 -> 36 | B40: 0.0010730538 | C40: 0.088843661 | D40: 0.21588754 | E40: =MAX((1-Parameters!$B$4)^Parameters!B$71*E39 + B39*Parameters!B$71 - IF(B39>0,Parameters!$B$5,0)*B39^2/E39*Parameters!B$71, 0.0001) -> 0.10226161 | F40: =(1-Parameters!$B$4)^Parameters!B$71*F39+C39*Parameters!B$71-Parameters!$B$5*C39^2/F39*Parameters!B$71 -> 1.0456567 | G40: =(1-Parameters!$B$4)^Parameters!B$71*G39+D39*Parameters!B$71-Parameters!$B$5*D39^2/G39*Parameters!B$71 -> 3.3722958 | H40: =MAX(H39 * (1-Parameters!$B$4) ^ Parameters!B$71 + (LN(1+EXP(Parameters!$B$21*(-B39+0.004)))/Parameters!$B$21 -0.004) * Parameters!B$71,0) -> 0 | I40: =I39*(1+Parameters!$B$52)^Parameters!B$71 -> 9.0565937 | J40: =J39*(1+Parameters!$B$54)^Parameters!B$71 -> 18.466259 | K40: =I40*J40*EXP(-Parameters!$B$43*'6states'!A40)*(Parameters!$B$38/Parameters!$B$39*('6states'!E40+'6states'!H40)/Parameters!$E$25*(EXP(-Parameters!$B$39*Parameters!$E$25*'6states'!H40/('6states'!E40+'6states'!H40))-EXP(-Parameters!$B$39*Parameters!$E$25)) + Parameters!$B$40*'6states'!E40) -> 10.866089 | L40: =L39+K40*Parameters!B$71 -> 3078.9812 | M40: =L40*Parameters!$B$46 -> 1.8473887 | N40: =EXP(-Parameters!$B$47/2*M40^2) -> 0.96628245 | O40: =MAX((Parameters!$B$63 + Parameters!$B$31*'6states'!A40 - '6states'!L40 + Parameters!$B$48/Parameters!$B$46)/Parameters!B$63,1) -> 23.724375 | P40: =Parameters!B$62*EXP(-Parameters!B$61*A40) -> 0.18916281 | Q40: =(1-Parameters!B$62)*O40^-Parameters!B$64 -> 0.36429275 | R40: =Parameters!B$62*EXP(-Parameters!B$61*A40)+(1-Parameters!B$62)*O40^-Parameters!B$64 -> 0.55345556 | S40: =1-R40/Parameters!$B$12 -> 0.72327222 | T40: =1/(1-S40) -> 3.6136596 | U40: =(Parameters!$B$19*(E40+Parameters!$B$20)^S40+Parameters!$B$18*F40^S40)^(1/S40) -> 0.3386328 | V40: =(Parameters!$B$10*G40^Parameters!$B$9+Parameters!$B$11*U40^Parameters!$B$9)^(Parameters!$B$7/Parameters!$B$9)*N40 -> 1.3464339 | W40: =V40 - C40 - D40 - LN(1+EXP(Parameters!$B$21*B40))/Parameters!$B$21 - IF(B40>0, 0,Parameters!$B$6*B40^2/E40) -> 1.0393762 | X40: =EXP(-Parameters!$B$56*A40) -> 0.58065413 | Y40: =IF(W40>0,W40^(1-Parameters!$B$53)/(1-Parameters!$B$53)*X40*Parameters!$B$71,-10+W40*1000) -> -1.6367374 | AA40: =B40/E40-B39/E39 -> 0.00038835223 | AB40: =C40/F40-C39/F39 -> -0.0012941429 | AC40: =D40/G40-D39/G39 -> 0.00028569583 | AD40: =X40*(AA40^2+AB40^2+AC40^2) -> 1.10745e-06 | AE40: =B40/E40-2*B39/E39+B38/E38 -> 7.8938295e-06 | AF40: =C40/F40-2*C39/F39+C38/F38 -> 0.00012039742 | AG40: =D40/G40-2*D39/G39+D38/G38 -> -1.5559824e-05 | AH40: =X40*(AE40^2+AF40^2+AG40^2) -> 8.5936577e-09 | AM40: =H40*I40*J40 -> 0 | AN40: =E40*I40*J40 -> 17.102375 | AO40: =U40*I40*J40 -> 56.633426 | AP40: =V40*J40*I40 -> 225.17951 | AQ40: =-X40*V40*W40^(-Parameters!B$53)*Parameters!B$47*Parameters!B$46*M40 -> -1.6533505e-05 | AR40: =1000*EXP(-(Parameters!$B$55)*'6states'!A40)*AP40*Parameters!B$47*Parameters!B$46*M40 -> 1.4179469 | AS40: =SUM(AR40:AR$204)*EXP(Parameters!$B$55*A40) -> 393.98197 | AT40: =(B40+C40+D40)/V40 -> 0.22712162 | AU40: =(1/$S40-1/Parameters!$B$13) * LN(Parameters!$B$18) / LN(O40) -> 0.23227178 | AV40: =(Parameters!$B$18*'6states'!S40^+Parameters!$B$19*Parameters!$B$25^'6states'!S40)^((1-'6states'!S40)/'6states'!S40)*Parameters!$B$18*Parameters!$B$26^('6states'!S40-1) -> 0.27860515 | AW40: =(LN(AV40)-LN(AV$4))/ LN(O40) -> 0.24137462 | AX40: =1-2^-AU40 -> 0.14870668 | AY40: =1-2^-AV40 -> 0.17561232 | AZ40: =(1/$S40-1/Parameters!$B$13) * LN(Parameters!$B$18) / A40 -> 0.020430258
A41: =A40+Parameters!$B$71 -> 37 | B41: =B40+(B42-B40)/2 -> 0.0010862198 | C41: =C40+(C42-C40)/2 -> 0.088849398 | D41: =D40+(D42-D40)/2 -> 0.21615183 | E41: =MAX((1-Parameters!$B$4)^Parameters!B$71*E40 + B40*Parameters!B$71 - IF(B40>0,Parameters!$B$5,0)*B40^2/E40*Parameters!B$71, 0.0001) -> 0.096891147 | F41: =(1-Parameters!$B$4)^Parameters!B$71*F40+C40*Parameters!B$71-Parameters!$B$5*C40^2/F40*Parameters!B$71 -> 1.06118 | G41: =(1-Parameters!$B$4)^Parameters!B$71*G40+D40*Parameters!B$71-Parameters!$B$5*D40^2/G40*Parameters!B$71 -> 3.3622452 | H41: =MAX(H40 * (1-Parameters!$B$4) ^ Parameters!B$71 + (LN(1+EXP(Parameters!$B$21*(-B40+0.004)))/Parameters!$B$21 -0.004) * Parameters!B$71,0) -> 0 | I41: =I40*(1+Parameters!$B$52)^Parameters!B$71 -> 9.0828578 | J41: =J40*(1+Parameters!$B$54)^Parameters!B$71 -> 18.835585 | K41: =I41*J41*EXP(-Parameters!$B$43*'6states'!A41)*(Parameters!$B$38/Parameters!$B$39*('6states'!E41+'6states'!H41)/Parameters!$E$25*(EXP(-Parameters!$B$39*Parameters!$E$25*'6states'!H41/('6states'!E41+'6states'!H41))-EXP(-Parameters!$B$39*Parameters!$E$25)) + Parameters!$B$40*'6states'!E41) -> 10.427006 | L41: =L40+K41*Parameters!B$71 -> 3089.4082 | M41: =L41*Parameters!$B$46 -> 1.8536449 | N41: =EXP(-Parameters!$B$47/2*M41^2) -> 0.96605762 | O41: =MAX((Parameters!$B$63 + Parameters!$B$31*'6states'!A41 - '6states'!L41 + Parameters!$B$48/Parameters!$B$46)/Parameters!B$63,1) -> 24.579835 | P41: =Parameters!B$62*EXP(-Parameters!B$61*A41) -> 0.18412375 | Q41: =(1-Parameters!B$62)*O41^-Parameters!B$64 -> 0.36300458 | R41: =Parameters!B$62*EXP(-Parameters!B$61*A41)+(1-Parameters!B$62)*O41^-Parameters!B$64 -> 0.54712833 | S41: =1-R41/Parameters!$B$12 -> 0.72643583 | T41: =1/(1-S41) -> 3.6554495 | U41: =(Parameters!$B$19*(E41+Parameters!$B$20)^S41+Parameters!$B$18*F41^S41)^(1/S41) -> 0.33763479 | V41: =(Parameters!$B$10*G41^Parameters!$B$9+Parameters!$B$11*U41^Parameters!$B$9)^(Parameters!$B$7/Parameters!$B$9)*N41 -> 1.3449206 | W41: =V41 - C41 - D41 - LN(1+EXP(Parameters!$B$21*B41))/Parameters!$B$21 - IF(B41>0, 0,Parameters!$B$6*B41^2/E41) -> 1.0375849 | X41: =EXP(-Parameters!$B$56*A41) -> 0.57195212 | Y41: =IF(W41>0,W41^(1-Parameters!$B$53)/(1-Parameters!$B$53)*X41*Parameters!$B$71,-10+W41*1000) -> -1.613182 | AA41: =B41/E41-B40/E40 -> 0.00071750008 | AB41: =C41/F41-C40/F40 -> -0.0012374827 | AC41: =D41/G41-D40/G40 -> 0.00026997021 | AD41: =X41*(AA41^2+AB41^2+AC41^2) -> 1.2119973e-06 | AE41: =B41/E41-2*B40/E40+B39/E39 -> 0.00032914785 | AF41: =C41/F41-2*C40/F40+C39/F39 -> 5.6660222e-05 | AG41: =D41/G41-2*D40/G40+D39/G39 -> -1.572562e-05 | AH41: =X41*(AE41^2+AF41^2+AG41^2) -> 6.3941949e-08 | AM41: =H41*I41*J41 -> 0 | AN41: =E41*I41*J41 -> 16.576228 | AO41: =U41*I41*J41 -> 57.762876 | AP41: =V41*J41*I41 -> 230.09028 | AQ41: =-X41*V41*W41^(-Parameters!B$53)*Parameters!B$47*Parameters!B$46*M41 -> -1.6360564e-05 | AR41: =1000*EXP(-(Parameters!$B$55)*'6states'!A41)*AP41*Parameters!B$47*Parameters!B$46*M41 -> 1.403634 | AS41: =SUM(AR41:AR$204)*EXP(Parameters!$B$55*A41) -> 402.86018 | AT41: =(B41+C41+D41)/V41 -> 0.22758774 | AU41: =(1/$S41-1/Parameters!$B$13) * LN(Parameters!$B$18) / LN(O41) -> 0.23194232 | AV41: =(Parameters!$B$18*'6states'!S41^+Parameters!$B$19*Parameters!$B$25^'6states'!S41)^((1-'6states'!S41)/'6states'!S41)*Parameters!$B$18*Parameters!$B$26^('6states'!S41-1) -> 0.27985301 | AW41: =(LN(AV41)-LN(AV$4))/ LN(O41) -> 0.24009996 | AX41: =1-2^-AU41 -> 0.14851225 | AY41: =1-2^-AV41 -> 0.17632506 | AZ41: =(1/$S41-1/Parameters!$B$13) * LN(Parameters!$B$18) / A41 -> 0.020071953
A42: =A41+Parameters!$B$71 -> 38 | B42: 0.0010993858 | C42: 0.088855135 | D42: 0.21641612 | E42: =MAX((1-Parameters!$B$4)^Parameters!B$71*E41 + B41*Parameters!B$71 - IF(B41>0,Parameters!$B$5,0)*B41^2/E41*Parameters!B$71, 0.0001) -> 0.091870736 | F42: =(1-Parameters!$B$4)^Parameters!B$71*F41+C41*Parameters!B$71-Parameters!$B$5*C41^2/F41*Parameters!B$71 -> 1.0758421 | G42: =(1-Parameters!$B$4)^Parameters!B$71*G41+D41*Parameters!B$71-Parameters!$B$5*D41^2/G41*Parameters!B$71 -> 3.3530159 | H42: =MAX(H41 * (1-Parameters!$B$4) ^ Parameters!B$71 + (LN(1+EXP(Parameters!$B$21*(-B41+0.004)))/Parameters!$B$21 -0.004) * Parameters!B$71,0) -> 0 | I42: =I41*(1+Parameters!$B$52)^Parameters!B$71 -> 9.1091981 | J42: =J41*(1+Parameters!$B$54)^Parameters!B$71 -> 19.212296 | K42: =I42*J42*EXP(-Parameters!$B$43*'6states'!A42)*(Parameters!$B$38/Parameters!$B$39*('6states'!E42+'6states'!H42)/Parameters!$E$25*(EXP(-Parameters!$B$39*Parameters!$E$25*'6states'!H42/('6states'!E42+'6states'!H42))-EXP(-Parameters!$B$39*Parameters!$E$25)) + Parameters!$B$40*'6states'!E42) -> 10.013077 | L42: =L41+K42*Parameters!B$71 -> 3099.4213 | M42: =L42*Parameters!$B$46 -> 1.8596528 | N42: =EXP(-Parameters!$B$47/2*M42^2) -> 0.96584105 | O42: =MAX((Parameters!$B$63 + Parameters!$B$31*'6states'!A42 - '6states'!L42 + Parameters!$B$48/Parameters!$B$46)/Parameters!B$63,1) -> 25.443574 | P42: =Parameters!B$62*EXP(-Parameters!B$61*A42) -> 0.17921892 | Q42: =(1-Parameters!B$62)*O42^-Parameters!B$64 -> 0.36175304 | R42: =Parameters!B$62*EXP(-Parameters!B$61*A42)+(1-Parameters!B$62)*O42^-Parameters!B$64 -> 0.54097197 | S42: =1-R42/Parameters!$B$12 -> 0.72951402 | T42: =1/(1-S42) -> 3.6970492 | U42: =(Parameters!$B$19*(E42+Parameters!$B$20)^S42+Parameters!$B$18*F42^S42)^(1/S42) -> 0.33674296 | V42: =(Parameters!$B$10*G42^Parameters!$B$9+Parameters!$B$11*U42^Parameters!$B$9)^(Parameters!$B$7/Parameters!$B$9)*N42 -> 1.3435256 | W42: =V42 - C42 - D42 - LN(1+EXP(Parameters!$B$21*B42))/Parameters!$B$21 - IF(B42>0, 0,Parameters!$B$6*B42^2/E42) -> 1.0359118 | X42: =EXP(-Parameters!$B$56*A42) -> 0.56338052 | Y42: =IF(W42>0,W42^(1-Parameters!$B$53)/(1-Parameters!$B$53)*X42*Parameters!$B$71,-10+W42*1000) -> -1.5899036 | AA42: =B42/E42-B41/E41 -> 0.00075593597 | AB42: =C42/F42-C41/F41 -> -0.0011357383 | AC42: =D42/G42-D41/G41 -> 0.00025577761 | AD42: =X42*(AA42^2+AB42^2+AC42^2) -> 1.0855006e-06 | AE42: =B42/E42-2*B41/E41+B40/E40 -> 3.8435882e-05 | AF42: =C42/F42-2*C41/F41+C40/F40 -> 0.00010174444 | AG42: =D42/G42-2*D41/G41+D40/G40 -> -1.4192595e-05 | AH42: =X42*(AE42^2+AF42^2+AG42^2) -> 6.777849e-09 | AM42: =H42*I42*J42 -> 0 | AN42: =E42*I42*J42 -> 16.07817 | AO42: =U42*I42*J42 -> 58.932918 | AP42: =V42*J42*I42 -> 235.12855 | AQ42: =-X42*V42*W42^(-Parameters!B$53)*Parameters!B$47*Parameters!B$46*M42 -> -1.6186061e-05 | AR42: =1000*EXP(-(Parameters!$B$55)*'6states'!A42)*AP42*Parameters!B$47*Parameters!B$46*M42 -> 1.3893849 | AS42: =SUM(AR42:AR$204)*EXP(Parameters!$B$55*A42) -> 411.92426 | AT42: =(B42+C42+D42)/V42 -> 0.22803483 | AU42: =(1/$S42-1/Parameters!$B$13) * LN(Parameters!$B$18) / LN(O42) -> 0.23160523 | AV42: =(Parameters!$B$18*'6states'!S42^+Parameters!$B$19*Parameters!$B$25^'6states'!S42)^((1-'6states'!S42)/'6states'!S42)*Parameters!$B$18*Parameters!$B$26^('6states'!S42-1) -> 0.28104146 | AW42: =(LN(AV42)-LN(AV$4))/ LN(O42) -> 0.23884718 | AX42: =1-2^-AU42 -> 0.14831327 | AY42: =1-2^-AV42 -> 0.17700331 | AZ42: =(1/$S42-1/Parameters!$B$13) * LN(Parameters!$B$18) / A42 -> 0.019725837
A43: =A42+Parameters!$B$71 -> 39 | B43: =B42+(B44-B42)/2 -> 0.0011758841 | C43: =C42+(C44-C42)/2 -> 0.088851345 | D43: =D42+(D44-D42)/2 -> 0.2166271 | E43: =MAX((1-Parameters!$B$4)^Parameters!B$71*E42 + B42*Parameters!B$71 - IF(B42>0,Parameters!$B$5,0)*B42^2/E42*Parameters!B$71, 0.0001) -> 0.087178297 | F43: =(1-Parameters!$B$4)^Parameters!B$71*F42+C42*Parameters!B$71-Parameters!$B$5*C42^2/F42*Parameters!B$71 -> 1.0896881 | G43: =(1-Parameters!$B$4)^Parameters!B$71*G42+D42*Parameters!B$71-Parameters!$B$5*D42^2/G42*Parameters!B$71 -> 3.344559 | H43: =MAX(H42 * (1-Parameters!$B$4) ^ Parameters!B$71 + (LN(1+EXP(Parameters!$B$21*(-B42+0.004)))/Parameters!$B$21 -0.004) * Parameters!B$71,0) -> 0 | I43: =I42*(1+Parameters!$B$52)^Parameters!B$71 -> 9.1356148 | J43: =J42*(1+Parameters!$B$54)^Parameters!B$71 -> 19.596542 | K43: =I43*J43*EXP(-Parameters!$B$43*'6states'!A43)*(Parameters!$B$38/Parameters!$B$39*('6states'!E43+'6states'!H43)/Parameters!$E$25*(EXP(-Parameters!$B$39*Parameters!$E$25*'6states'!H43/('6states'!E43+'6states'!H43))-EXP(-Parameters!$B$39*Parameters!$E$25)) + Parameters!$B$40*'6states'!E43) -> 9.6230691 | L43: =L42+K43*Parameters!B$71 -> 3109.0444 | M43: =L43*Parameters!$B$46 -> 1.8654266 | N43: =EXP(-Parameters!$B$47/2*M43^2) -> 0.9656323 | O43: =MAX((Parameters!$B$63 + Parameters!$B$31*'6states'!A43 - '6states'!L43 + Parameters!$B$48/Parameters!$B$46)/Parameters!B$63,1) -> 26.315112 | P43: =Parameters!B$62*EXP(-Parameters!B$61*A43) -> 0.17444475 | Q43: =(1-Parameters!B$62)*O43^-Parameters!B$64 -> 0.3605367 | R43: =Parameters!B$62*EXP(-Parameters!B$61*A43)+(1-Parameters!B$62)*O43^-Parameters!B$64 -> 0.53498146 | S43: =1-R43/Parameters!$B$12 -> 0.73250927 | T43: =1/(1-S43) -> 3.7384473 | U43: =(Parameters!$B$19*(E43+Parameters!$B$20)^S43+Parameters!$B$18*F43^S43)^(1/S43) -> 0.33595282 | V43: =(Parameters!$B$10*G43^Parameters!$B$9+Parameters!$B$11*U43^Parameters!$B$9)^(Parameters!$B$7/Parameters!$B$9)*N43 -> 1.3422432 | W43: =V43 - C43 - D43 - LN(1+EXP(Parameters!$B$21*B43))/Parameters!$B$21 - IF(B43>0, 0,Parameters!$B$6*B43^2/E43) -> 1.0343754 | X43: =EXP(-Parameters!$B$56*A43) -> 0.55493738 | Y43: =IF(W43>0,W43^(1-Parameters!$B$53)/(1-Parameters!$B$53)*X43*Parameters!$B$71,-10+W43*1000) -> -1.5668902 | AA43: =B43/E43-B42/E42 -> 0.0015216072 | AB43: =C43/F43-C42/F42 -> -0.0010529157 | AC43: =D43/G43-D42/G42 -> 0.00022628434 | AD43: =X43*(AA43^2+AB43^2+AC43^2) -> 1.9284766e-06 | AE43: =B43/E43-2*B42/E42+B41/E41 -> 0.00076567124 | AF43: =C43/F43-2*C42/F42+C41/F41 -> 8.2822549e-05 | AG43: =D43/G43-2*D42/G42+D41/G41 -> -2.9493276e-05 | AH43: =X43*(AE43^2+AF43^2+AG43^2) -> 3.2962275e-07 | AM43: =H43*I43*J43 -> 0 | AN43: =E43*I43*J43 -> 15.607222 | AO43: =U43*I43*J43 -> 60.144445 | AP43: =V43*J43*I43 -> 240.29704 | AQ43: =-X43*V43*W43^(-Parameters!B$53)*Parameters!B$47*Parameters!B$46*M43 -> -1.6009771e-05 | AR43: =1000*EXP(-(Parameters!$B$55)*'6states'!A43)*AP43*Parameters!B$47*Parameters!B$46*M43 -> 1.3752074 | AS43: =SUM(AR43:AR$204)*EXP(Parameters!$B$55*A43) -> 421.17784 | AT43: =(B43+C43+D43)/V43 -> 0.22846407 | AU43: =(1/$S43-1/Parameters!$B$13) * LN(Parameters!$B$18) / LN(O43) -> 0.23126175 | AV43: =(Parameters!$B$18*'6states'!S43^+Parameters!$B$19*Parameters!$B$25^'6states'!S43)^((1-'6states'!S43)/'6states'!S43)*Parameters!$B$18*Parameters!$B$26^('6states'!S43-1) -> 0.28217363 | AW43: =(LN(AV43)-LN(AV$4))/ LN(O43) -> 0.23761665 | AX43: =1-2^-AU43 -> 0.14811048 | AY43: =1-2^-AV43 -> 0.17764891 | AZ43: =(1/$S43-1/Parameters!$B$13) * LN(Parameters!$B$18) / A43 -> 0.019391259
A44: =A43+Parameters!$B$71 -> 40 | B44: 0.0012523824 | C44: 0.088847554 | D44: 0.21683808 | E44: =MAX((1-Parameters!$B$4)^Parameters!B$71*E43 + B43*Parameters!B$71 - IF(B43>0,Parameters!$B$5,0)*B43^2/E43*Parameters!B$71, 0.0001) -> 0.082854805 | F44: =(1-Parameters!$B$4)^Parameters!B$71*F43+C43*Parameters!B$71-Parameters!$B$5*C43^2/F43*Parameters!B$71 -> 1.1027533 | G44: =(1-Parameters!$B$4)^Parameters!B$71*G43+D43*Parameters!B$71-Parameters!$B$5*D43^2/G43*Parameters!B$71 -> 3.3367824 | H44: =MAX(H43 * (1-Parameters!$B$4) ^ Parameters!B$71 + (LN(1+EXP(Parameters!$B$21*(-B43+0.004)))/Parameters!$B$21 -0.004) * Parameters!B$71,0) -> 0 | I44: =I43*(1+Parameters!$B$52)^Parameters!B$71 -> 9.1621081 | J44: =J43*(1+Parameters!$B$54)^Parameters!B$71 -> 19.988473 | K44: =I44*J44*EXP(-Parameters!$B$43*'6states'!A44)*(Parameters!$B$38/Parameters!$B$39*('6states'!E44+'6states'!H44)/Parameters!$E$25*(EXP(-Parameters!$B$39*Parameters!$E$25*'6states'!H44/('6states'!E44+'6states'!H44))-EXP(-Parameters!$B$39*Parameters!$E$25)) + Parameters!$B$40*'6states'!E44) -> 9.2627039 | L44: =L43+K44*Parameters!B$71 -> 3118.3071 | M44: =L44*Parameters!$B$46 -> 1.8709842 | N44: =EXP(-Parameters!$B$47/2*M44^2) -> 0.9654308 | O44: =MAX((Parameters!$B$63 + Parameters!$B$31*'6states'!A44 - '6states'!L44 + Parameters!$B$48/Parameters!$B$46)/Parameters!B$63,1) -> 27.193858 | P44: =Parameters!B$62*EXP(-Parameters!B$61*A44) -> 0.16979776 | Q44: =(1-Parameters!B$62)*O44^-Parameters!B$64 -> 0.35935436 | R44: =Parameters!B$62*EXP(-Parameters!B$61*A44)+(1-Parameters!B$62)*O44^-Parameters!B$64 -> 0.52915213 | S44: =1-R44/Parameters!$B$12 -> 0.73542394 | T44: =1/(1-S44) -> 3.7796314 | U44: =(Parameters!$B$19*(E44+Parameters!$B$20)^S44+Parameters!$B$18*F44^S44)^(1/S44) -> 0.33531833 | V44: =(Parameters!$B$10*G44^Parameters!$B$9+Parameters!$B$11*U44^Parameters!$B$9)^(Parameters!$B$7/Parameters!$B$9)*N44 -> 1.3410887 | W44: =V44 - C44 - D44 - LN(1+EXP(Parameters!$B$21*B44))/Parameters!$B$21 - IF(B44>0, 0,Parameters!$B$6*B44^2/E44) -> 1.0329664 | X44: =EXP(-Parameters!$B$56*A44) -> 0.54662077 | Y44: =IF(W44>0,W44^(1-Parameters!$B$53)/(1-Parameters!$B$53)*X44*Parameters!$B$71,-10+W44*1000) -> -1.5441445 | AA44: =B44/E44-B43/E43 -> 0.0016271199 | AB44: =C44/F44-C43/F43 -> -0.00096948504 | AC44: =D44/G44-D43/G43 -> 0.00021418028 | AD44: =X44*(AA44^2+AB44^2+AC44^2) -> 1.9860338e-06 | AE44: =B44/E44-2*B43/E43+B42/E42 -> 0.00010551272 | AF44: =C44/F44-2*C43/F43+C42/F42 -> 8.34307e-05 | AG44: =D44/G44-2*D43/G43+D42/G42 -> -1.2104053e-05 | AH44: =X44*(AE44^2+AF44^2+AG44^2) -> 9.9704302e-09 | AM44: =H44*I44*J44 -> 0 | AN44: =E44*I44*J44 -> 15.173743 | AO44: =U44*I44*J44 -> 61.409042 | AP44: =V44*J44*I44 -> 245.60235 | AQ44: =-X44*V44*W44^(-Parameters!B$53)*Parameters!B$47*Parameters!B$46*M44 -> -1.5832326e-05 | AR44: =1000*EXP(-(Parameters!$B$55)*'6states'!A44)*AP44*Parameters!B$47*Parameters!B$46*M44 -> 1.3611328 | AS44: =SUM(AR44:AR$204)*EXP(Parameters!$B$55*A44) -> 430.6246 | AT44: =(B44+C44+D44)/V44 -> 0.22887228 | AU44: =(1/$S44-1/Parameters!$B$13) * LN(Parameters!$B$18) / LN(O44) -> 0.23091328 | AV44: =(Parameters!$B$18*'6states'!S44^+Parameters!$B$19*Parameters!$B$25^'6states'!S44)^((1-'6states'!S44)/'6states'!S44)*Parameters!$B$18*Parameters!$B$26^('6states'!S44-1) -> 0.28325244 | AW44: =(LN(AV44)-LN(AV$4))/ LN(O44) -> 0.23640888 | AX44: =1-2^-AU44 -> 0.14790469 | AY44: =1-2^-AV44 -> 0.17826361 | AZ44: =(1/$S44-1/Parameters!$B$13) * LN(Parameters!$B$18) / A44 -> 0.019067613
A45: =A44+Parameters!$B$71 -> 41 | B45: =B44+(B$47-B$44)/3 -> 0.0012787997 | C45: =C44+(C$47-C$44)/3 -> 0.088817496 | D45: =D44+(D$47-D$44)/3 -> 0.21712732 | E45: =MAX((1-Parameters!$B$4)^Parameters!B$71*E44 + B44*Parameters!B$71 - IF(B44>0,Parameters!$B$5,0)*B44^2/E44*Parameters!B$71, 0.0001) -> 0.07887669 | F45: =(1-Parameters!$B$4)^Parameters!B$71*F44+C44*Parameters!B$71-Parameters!$B$5*C44^2/F44*Parameters!B$71 -> 1.1150793 | G45: =(1-Parameters!$B$4)^Parameters!B$71*G44+D44*Parameters!B$71-Parameters!$B$5*D44^2/G44*Parameters!B$71 -> 3.3296458 | H45: =MAX(H44 * (1-Parameters!$B$4) ^ Parameters!B$71 + (LN(1+EXP(Parameters!$B$21*(-B44+0.004)))/Parameters!$B$21 -0.004) * Parameters!B$71,0) -> 0 | I45: =I44*(1+Parameters!$B$52)^Parameters!B$71 -> 9.1886782 | J45: =J44*(1+Parameters!$B$54)^Parameters!B$71 -> 20.388242 | K45: =I45*J45*EXP(-Parameters!$B$43*'6states'!A45)*(Parameters!$B$38/Parameters!$B$39*('6states'!E45+'6states'!H45)/Parameters!$E$25*(EXP(-Parameters!$B$39*Parameters!$E$25*'6states'!H45/('6states'!E45+'6states'!H45))-EXP(-Parameters!$B$39*Parameters!$E$25)) + Parameters!$B$40*'6states'!E45) -> 8.9306613 | L45: =L44+K45*Parameters!B$71 -> 3127.2377 | M45: =L45*Parameters!$B$46 -> 1.8763426 | N45: =EXP(-Parameters!$B$47/2*M45^2) -> 0.965236 | O45: =MAX((Parameters!$B$63 + Parameters!$B$31*'6states'!A45 - '6states'!L45 + Parameters!$B$48/Parameters!$B$46)/Parameters!B$63,1) -> 28.079245 | P45: =Parameters!B$62*EXP(-Parameters!B$61*A45) -> 0.16527456 | Q45: =(1-Parameters!B$62)*O45^-Parameters!B$64 -> 0.35820485 | R45: =Parameters!B$62*EXP(-Parameters!B$61*A45)+(1-Parameters!B$62)*O45^-Parameters!B$64 -> 0.52347941 | S45: =1-R45/Parameters!$B$12 -> 0.73826029 | T45: =1/(1-S45) -> 3.8205896 | U45: =(Parameters!$B$19*(E45+Parameters!$B$20)^S45+Parameters!$B$18*F45^S45)^(1/S45) -> 0.33483219 | V45: =(Parameters!$B$10*G45^Parameters!$B$9+Parameters!$B$11*U45^Parameters!$B$9)^(Parameters!$B$7/Parameters!$B$9)*N45 -> 1.3400554 | W45: =V45 - C45 - D45 - LN(1+EXP(Parameters!$B$21*B45))/Parameters!$B$21 - IF(B45>0, 0,Parameters!$B$6*B45^2/E45) -> 1.0316575 | X45: =EXP(-Parameters!$B$56*A45) -> 0.53842881 | Y45: =IF(W45>0,W45^(1-Parameters!$B$53)/(1-Parameters!$B$53)*X45*Parameters!$B$71,-10+W45*1000) -> -1.5216782 | AA45: =B45/E45-B44/E44 -> 0.0010972577 | AB45: =C45/F45-C44/F44 -> -0.00091756017 | AC45: =D45/G45-D44/G44 -> 0.00022614983 | AD45: =X45*(AA45^2+AB45^2+AC45^2) -> 1.129104e-06 | AE45: =B45/E45-2*B44/E44+B43/E43 -> -0.00052986218 | AF45: =C45/F45-2*C44/F44+C43/F43 -> 5.1924871e-05 | AG45: =D45/G45-2*D44/G44+D43/G43 -> 1.196955e-05 | AH45: =X45*(AE45^2+AF45^2+AG45^2) -> 1.5269485e-07 | AM45: =H45*I45*J45 -> 0 | AN45: =E45*I45*J45 -> 14.776838 | AO45: =U45*I45*J45 -> 62.727797 | AP45: =V45*J45*I45 -> 251.04732 | AQ45: =-X45*V45*W45^(-Parameters!B$53)*Parameters!B$47*Parameters!B$46*M45 -> -1.5654441e-05 | AR45: =1000*EXP(-(Parameters!$B$55)*'6states'!A45)*AP45*Parameters!B$47*Parameters!B$46*M45 -> 1.3471683 | AS45: =SUM(AR45:AR$204)*EXP(Parameters!$B$55*A45) -> 440.26816 | AT45: =(B45+C45+D45)/V45 -> 0.22926187 | AU45: =(1/$S45-1/Parameters!$B$13) * LN(Parameters!$B$18) / LN(O45) -> 0.23056097 | AV45: =(Parameters!$B$18*'6states'!S45^+Parameters!$B$19*Parameters!$B$25^'6states'!S45)^((1-'6states'!S45)/'6states'!S45)*Parameters!$B$18*Parameters!$B$26^('6states'!S45-1) -> 0.28428065 | AW45: =(LN(AV45)-LN(AV$4))/ LN(O45) -> 0.23522418 | AX45: =1-2^-AU45 -> 0.14769658 | AY45: =1-2^-AV45 -> 0.17884905 | AZ45: =(1/$S45-1/Parameters!$B$13) * LN(Parameters!$B$18) / A45 -> 0.018754339
A46: =A45+Parameters!$B$71 -> 42 | B46: =B45+(B$47-B$44)/3 -> 0.001305217 | C46: =C45+(C$47-C$44)/3 -> 0.088787437 | D46: =D45+(D$47-D$44)/3 -> 0.21741655 | E46: =MAX((1-Parameters!$B$4)^Parameters!B$71*E45 + B45*Parameters!B$71 - IF(B45>0,Parameters!$B$5,0)*B45^2/E45*Parameters!B$71, 0.0001) -> 0.075173413 | F46: =(1-Parameters!$B$4)^Parameters!B$71*F45+C45*Parameters!B$71-Parameters!$B$5*C45^2/F45*Parameters!B$71 -> 1.1266839 | G46: =(1-Parameters!$B$4)^Parameters!B$71*G45+D45*Parameters!B$71-Parameters!$B$5*D45^2/G45*Parameters!B$71 -> 3.3231795 | H46: =MAX(H45 * (1-Parameters!$B$4) ^ Parameters!B$71 + (LN(1+EXP(Parameters!$B$21*(-B45+0.004)))/Parameters!$B$21 -0.004) * Parameters!B$71,0) -> 0 | I46: =I45*(1+Parameters!$B$52)^Parameters!B$71 -> 9.2153254 | J46: =J45*(1+Parameters!$B$54)^Parameters!B$71 -> 20.796007 | K46: =I46*J46*EXP(-Parameters!$B$43*'6states'!A46)*(Parameters!$B$38/Parameters!$B$39*('6states'!E46+'6states'!H46)/Parameters!$E$25*(EXP(-Parameters!$B$39*Parameters!$E$25*'6states'!H46/('6states'!E46+'6states'!H46))-EXP(-Parameters!$B$39*Parameters!$E$25)) + Parameters!$B$40*'6states'!E46) -> 8.620135 | L46: =L45+K46*Parameters!B$71 -> 3135.8579 | M46: =L46*Parameters!$B$46 -> 1.8815147 | N46: =EXP(-Parameters!$B$47/2*M46^2) -> 0.96504748 | O46: =MAX((Parameters!$B$63 + Parameters!$B$31*'6states'!A46 - '6states'!L46 + Parameters!$B$48/Parameters!$B$46)/Parameters!B$63,1) -> 28.970842 | P46: =Parameters!B$62*EXP(-Parameters!B$61*A46) -> 0.16087185 | Q46: =(1-Parameters!B$62)*O46^-Parameters!B$64 -> 0.35708688 | R46: =Parameters!B$62*EXP(-Parameters!B$61*A46)+(1-Parameters!B$62)*O46^-Parameters!B$64 -> 0.51795873 | S46: =1-R46/Parameters!$B$12 -> 0.74102063 | T46: =1/(1-S46) -> 3.8613115 | U46: =(Parameters!$B$19*(E46+Parameters!$B$20)^S46+Parameters!$B$18*F46^S46)^(1/S46) -> 0.33443419 | V46: =(Parameters!$B$10*G46^Parameters!$B$9+Parameters!$B$11*U46^Parameters!$B$9)^(Parameters!$B$7/Parameters!$B$9)*N46 -> 1.3391198 | W46: =V46 - C46 - D46 - LN(1+EXP(Parameters!$B$21*B46))/Parameters!$B$21 - IF(B46>0, 0,Parameters!$B$6*B46^2/E46) -> 1.0304461 | X46: =EXP(-Parameters!$B$56*A46) -> 0.53035961 | Y46: =IF(W46>0,W46^(1-Parameters!$B$53)/(1-Parameters!$B$53)*X46*Parameters!$B$71,-10+W46*1000) -> -1.4994899 | AA46: =B46/E46-B45/E45 -> 0.0011501037 | AB46: =C46/F46-C45/F45 -> -0.00084706828 | AC46: =D46/G46-D45/G45 -> 0.00021392378 | AD46: =X46*(AA46^2+AB46^2+AC46^2) -> 1.1063442e-06 | AE46: =B46/E46-2*B45/E45+B44/E44 -> 5.2845968e-05 | AF46: =C46/F46-2*C45/F45+C44/F44 -> 7.0491887e-05 | AG46: =D46/G46-2*D45/G45+D44/G44 -> -1.222605e-05 | AH46: =X46*(AE46^2+AF46^2+AG46^2) -> 4.1958227e-09 | AM46: =H46*I46*J46 -> 0 | AN46: =E46*I46*J46 -> 14.406381 | AO46: =U46*I46*J46 -> 64.091629 | AP46: =V46*J46*I46 -> 256.63156 | AQ46: =-X46*V46*W46^(-Parameters!B$53)*Parameters!B$47*Parameters!B$46*M46 -> -1.547607e-05 | AR46: =1000*EXP(-(Parameters!$B$55)*'6states'!A46)*AP46*Parameters!B$47*Parameters!B$46*M46 -> 1.3333006 | AS46: =SUM(AR46:AR$204)*EXP(Parameters!$B$55*A46) -> 450.11217 | AT46: =(B46+C46+D46)/V46 -> 0.22963532 | AU46: =(1/$S46-1/Parameters!$B$13) * LN(Parameters!$B$18) / LN(O46) -> 0.23020559 | AV46: =(Parameters!$B$18*'6states'!S46^+Parameters!$B$19*Parameters!$B$25^'6states'!S46)^((1-'6states'!S46)/'6states'!S46)*Parameters!$B$18*Parameters!$B$26^('6states'!S46-1) -> 0.28526089 | AW46: =(LN(AV46)-LN(AV$4))/ LN(O46) -> 0.23406246 | AX46: =1-2^-AU46 -> 0.1474866 | AY46: =1-2^-AV46 -> 0.1794068 | AZ46: =(1/$S46-1/Parameters!$B$13) * LN(Parameters!$B$18) / A46 -> 0.018450923
A47: =A46+Parameters!$B$71 -> 43 | B47: 0.0013316343 | C47: 0.088757379 | D47: 0.21770579 | E47: =MAX((1-Parameters!$B$4)^Parameters!B$71*E46 + B46*Parameters!B$71 - IF(B46>0,Parameters!$B$5,0)*B46^2/E46*Parameters!B$71, 0.0001) -> 0.07172756 | F47: =(1-Parameters!$B$4)^Parameters!B$71*F46+C46*Parameters!B$71-Parameters!$B$5*C46^2/F46*Parameters!B$71 -> 1.1376061 | G47: =(1-Parameters!$B$4)^Parameters!B$71*G46+D46*Parameters!B$71-Parameters!$B$5*D46^2/G46*Parameters!B$71 -> 3.3173437 | H47: =MAX(H46 * (1-Parameters!$B$4) ^ Parameters!B$71 + (LN(1+EXP(Parameters!$B$21*(-B46+0.004)))/Parameters!$B$21 -0.004) * Parameters!B$71,0) -> 0 | I47: =I46*(1+Parameters!$B$52)^Parameters!B$71 -> 9.2420498 | J47: =J46*(1+Parameters!$B$54)^Parameters!B$71 -> 21.211927 | K47: =I47*J47*EXP(-Parameters!$B$43*'6states'!A47)*(Parameters!$B$38/Parameters!$B$39*('6states'!E47+'6states'!H47)/Parameters!$E$25*(EXP(-Parameters!$B$39*Parameters!$E$25*'6states'!H47/('6states'!E47+'6states'!H47))-EXP(-Parameters!$B$39*Parameters!$E$25)) + Parameters!$B$40*'6states'!E47) -> 8.3301096 | L47: =L46+K47*Parameters!B$71 -> 3144.188 | M47: =L47*Parameters!$B$46 -> 1.8865128 | N47: =EXP(-Parameters!$B$47/2*M47^2) -> 0.96486484 | O47: =MAX((Parameters!$B$63 + Parameters!$B$31*'6states'!A47 - '6states'!L47 + Parameters!$B$48/Parameters!$B$46)/Parameters!B$63,1) -> 29.86824 | P47: =Parameters!B$62*EXP(-Parameters!B$61*A47) -> 0.15658643 | Q47: =(1-Parameters!B$62)*O47^-Parameters!B$64 -> 0.35599922 | R47: =Parameters!B$62*EXP(-Parameters!B$61*A47)+(1-Parameters!B$62)*O47^-Parameters!B$64 -> 0.51258564 | S47: =1-R47/Parameters!$B$12 -> 0.74370718 | T47: =1/(1-S47) -> 3.901787 | U47: =(Parameters!$B$19*(E47+Parameters!$B$20)^S47+Parameters!$B$18*F47^S47)^(1/S47) -> 0.33411969 | V47: =(Parameters!$B$10*G47^Parameters!$B$9+Parameters!$B$11*U47^Parameters!$B$9)^(Parameters!$B$7/Parameters!$B$9)*N47 -> 1.3382763 | W47: =V47 - C47 - D47 - LN(1+EXP(Parameters!$B$21*B47))/Parameters!$B$21 - IF(B47>0, 0,Parameters!$B$6*B47^2/E47) -> 1.0293268 | X47: =EXP(-Parameters!$B$56*A47) -> 0.52241134 | Y47: =IF(W47>0,W47^(1-Parameters!$B$53)/(1-Parameters!$B$53)*X47*Parameters!$B$71,-10+W47*1000) -> -1.4775796 | AA47: =B47/E47-B46/E46 -> 0.0012024218 | AB47: =C47/F47-C46/F46 -> -0.00078302467 | AC47: =D47/G47-D46/G46 -> 0.00020228056 | AD47: =X47*(AA47^2+AB47^2+AC47^2) -> 1.0969924e-06 | AE47: =B47/E47-2*B46/E46+B45/E45 -> 5.2318142e-05 | AF47: =C47/F47-2*C46/F46+C45/F45 -> 6.4043612e-05 | AG47: =D47/G47-2*D46/G46+D45/G45 -> -1.1643221e-05 | AH47: =X47*(AE47^2+AF47^2+AG47^2) -> 3.6434726e-09 | AM47: =H47*I47*J47 -> 0 | AN47: =E47*I47*J47 -> 14.061592 | AO47: =U47*I47*J47 -> 65.50139 | AP47: =V47*J47*I47 -> 262.35795 | AQ47: =-X47*V47*W47^(-Parameters!B$53)*Parameters!B$47*Parameters!B$46*M47 -> -1.5297431e-05 | AR47: =1000*EXP(-(Parameters!$B$55)*'6states'!A47)*AP47*Parameters!B$47*Parameters!B$46*M47 -> 1.3195341 | AS47: =SUM(AR47:AR$204)*EXP(Parameters!$B$55*A47) -> 460.16038 | AT47: =(B47+C47+D47)/V47 -> 0.22999346 | AU47: =(1/$S47-1/Parameters!$B$13) * LN(Parameters!$B$18) / LN(O47) -> 0.22984781 | AV47: =(Parameters!$B$18*'6states'!S47^+Parameters!$B$19*Parameters!$B$25^'6states'!S47)^((1-'6states'!S47)/'6states'!S47)*Parameters!$B$18*Parameters!$B$26^('6states'!S47-1) -> 0.28619567 | AW47: =(LN(AV47)-LN(AV$4))/ LN(O47) -> 0.23292353 | AX47: =1-2^-AU47 -> 0.14727516 | AY47: =1-2^-AV47 -> 0.17993832 | AZ47: =(1/$S47-1/Parameters!$B$13) * LN(Parameters!$B$18) / A47 -> 0.018156885
A48: =A47+Parameters!$B$71 -> 44 | B48: =B47+(B$50-B$47)/3 -> 0.00096407894 | C48: =C47+(C$50-C$47)/3 -> 0.089006402 | D48: =D47+(D$50-D$47)/3 -> 0.21778861 | E48: =MAX((1-Parameters!$B$4)^Parameters!B$71*E47 + B47*Parameters!B$71 - IF(B47>0,Parameters!$B$5,0)*B47^2/E47*Parameters!B$71, 0.0001) -> 0.068522809 | F48: =(1-Parameters!$B$4)^Parameters!B$71*F47+C47*Parameters!B$71-Parameters!$B$5*C47^2/F47*Parameters!B$71 -> 1.1478831 | G48: =(1-Parameters!$B$4)^Parameters!B$71*G47+D47*Parameters!B$71-Parameters!$B$5*D47^2/G47*Parameters!B$71 -> 3.3121013 | H48: =MAX(H47 * (1-Parameters!$B$4) ^ Parameters!B$71 + (LN(1+EXP(Parameters!$B$21*(-B47+0.004)))/Parameters!$B$21 -0.004) * Parameters!B$71,0) -> 0 | I48: =I47*(1+Parameters!$B$52)^Parameters!B$71 -> 9.2688518 | J48: =J47*(1+Parameters!$B$54)^Parameters!B$71 -> 21.636166 | K48: =I48*J48*EXP(-Parameters!$B$43*'6states'!A48)*(Parameters!$B$38/Parameters!$B$39*('6states'!E48+'6states'!H48)/Parameters!$E$25*(EXP(-Parameters!$B$39*Parameters!$E$25*'6states'!H48/('6states'!E48+'6states'!H48))-EXP(-Parameters!$B$39*Parameters!$E$25)) + Parameters!$B$40*'6states'!E48) -> 8.059622 | L48: =L47+K48*Parameters!B$71 -> 3152.2476 | M48: =L48*Parameters!$B$46 -> 1.8913486 | N48: =EXP(-Parameters!$B$47/2*M48^2) -> 0.9646877 | O48: =MAX((Parameters!$B$63 + Parameters!$B$31*'6states'!A48 - '6states'!L48 + Parameters!$B$48/Parameters!$B$46)/Parameters!B$63,1) -> 30.771048 | P48: =Parameters!B$62*EXP(-Parameters!B$61*A48) -> 0.15241516 | Q48: =(1-Parameters!B$62)*O48^-Parameters!B$64 -> 0.35494068 | R48: =Parameters!B$62*EXP(-Parameters!B$61*A48)+(1-Parameters!B$62)*O48^-Parameters!B$64 -> 0.50735584 | S48: =1-R48/Parameters!$B$12 -> 0.74632208 | T48: =1/(1-S48) -> 3.9420065 | U48: =(Parameters!$B$19*(E48+Parameters!$B$20)^S48+Parameters!$B$18*F48^S48)^(1/S48) -> 0.33388409 | V48: =(Parameters!$B$10*G48^Parameters!$B$9+Parameters!$B$11*U48^Parameters!$B$9)^(Parameters!$B$7/Parameters!$B$9)*N48 -> 1.3375197 | W48: =V48 - C48 - D48 - LN(1+EXP(Parameters!$B$21*B48))/Parameters!$B$21 - IF(B48>0, 0,Parameters!$B$6*B48^2/E48) -> 1.0284636 | X48: =EXP(-Parameters!$B$56*A48) -> 0.51458218 | Y48: =IF(W48>0,W48^(1-Parameters!$B$53)/(1-Parameters!$B$53)*X48*Parameters!$B$71,-10+W48*1000) -> -1.4558632 | AA48: =B48/E48-B47/E47 -> -0.0044957091 | AB48: =C48/F48-C47/F47 -> -0.00048158209 | AC48: =D48/G48-D47/G47 -> 0.00012887875 | AD48: =X48*(AA48^2+AB48^2+AC48^2) -> 1.0528316e-05 | AE48: =B48/E48-2*B47/E47+B46/E46 -> -0.0056981309 | AF48: =C48/F48-2*C47/F47+C46/F46 -> 0.00030144257 | AG48: =D48/G48-2*D47/G47+D46/G46 -> -7.340181e-05 | AH48: =X48*(AE48^2+AF48^2+AG48^2) -> 1.6757344e-05 | AM48: =H48*I48*J48 -> 0 | AN48: =E48*I48*J48 -> 13.74173 | AO48: =U48*I48*J48 -> 66.957922 | AP48: =V48*J48*I48 -> 268.22944 | AQ48: =-X48*V48*W48^(-Parameters!B$53)*Parameters!B$47*Parameters!B$46*M48 -> -1.5115369e-05 | AR48: =1000*EXP(-(Parameters!$B$55)*'6states'!A48)*AP48*Parameters!B$47*Parameters!B$46*M48 -> 1.3058729 | AS48: =SUM(AR48:AR$204)*EXP(Parameters!$B$55*A48) -> 470.41659 | AT48: =(B48+C48+D48)/V48 -> 0.23009686 | AU48: =(1/$S48-1/Parameters!$B$13) * LN(Parameters!$B$18) / LN(O48) -> 0.2294882 | AV48: =(Parameters!$B$18*'6states'!S48^+Parameters!$B$19*Parameters!$B$25^'6states'!S48)^((1-'6states'!S48)/'6states'!S48)*Parameters!$B$18*Parameters!$B$26^('6states'!S48-1) -> 0.28708734 | AW48: =(LN(AV48)-LN(AV$4))/ LN(O48) -> 0.23180715 | AX48: =1-2^-AU48 -> 0.14706258 | AY48: =1-2^-AV48 -> 0.18044501 | AZ48: =(1/$S48-1/Parameters!$B$13) * LN(Parameters!$B$18) / A48 -> 0.017871781
A49: =A48+Parameters!$B$71 -> 45 | B49: =B48+(B$50-B$47)/3 -> 0.00059652357 | C49: =C48+(C$50-C$47)/3 -> 0.089255426 | D49: =D48+(D$50-D$47)/3 -> 0.21787142 | E49: =MAX((1-Parameters!$B$4)^Parameters!B$71*E48 + B48*Parameters!B$71 - IF(B48>0,Parameters!$B$5,0)*B48^2/E48*Parameters!B$71, 0.0001) -> 0.065163239 | F49: =(1-Parameters!$B$4)^Parameters!B$71*F48+C48*Parameters!B$71-Parameters!$B$5*C48^2/F48*Parameters!B$71 -> 1.1577861 | G49: =(1-Parameters!$B$4)^Parameters!B$71*G48+D48*Parameters!B$71-Parameters!$B$5*D48^2/G48*Parameters!B$71 -> 3.307238 | H49: =MAX(H48 * (1-Parameters!$B$4) ^ Parameters!B$71 + (LN(1+EXP(Parameters!$B$21*(-B48+0.004)))/Parameters!$B$21 -0.004) * Parameters!B$71,0) -> 0 | I49: =I48*(1+Parameters!$B$52)^Parameters!B$71 -> 9.2957314 | J49: =J48*(1+Parameters!$B$54)^Parameters!B$71 -> 22.068889 | K49: =I49*J49*EXP(-Parameters!$B$43*'6states'!A49)*(Parameters!$B$38/Parameters!$B$39*('6states'!E49+'6states'!H49)/Parameters!$E$25*(EXP(-Parameters!$B$39*Parameters!$E$25*'6states'!H49/('6states'!E49+'6states'!H49))-EXP(-Parameters!$B$39*Parameters!$E$25)) + Parameters!$B$40*'6states'!E49) -> 7.7624182 | L49: =L48+K49*Parameters!B$71 -> 3160.01 | M49: =L49*Parameters!$B$46 -> 1.896006 | N49: =EXP(-Parameters!$B$47/2*M49^2) -> 0.9645167 | O49: =MAX((Parameters!$B$63 + Parameters!$B$31*'6states'!A49 - '6states'!L49 + Parameters!$B$48/Parameters!$B$46)/Parameters!B$63,1) -> 31.679799 | P49: =Parameters!B$62*EXP(-Parameters!B$61*A49) -> 0.14835501 | Q49: =(1-Parameters!B$62)*O49^-Parameters!B$64 -> 0.35390913 | R49: =Parameters!B$62*EXP(-Parameters!B$61*A49)+(1-Parameters!B$62)*O49^-Parameters!B$64 -> 0.50226413 | S49: =1-R49/Parameters!$B$12 -> 0.74886793 | T49: =1/(1-S49) -> 3.9819686 | U49: =(Parameters!$B$19*(E49+Parameters!$B$20)^S49+Parameters!$B$18*F49^S49)^(1/S49) -> 0.33339041 | V49: =(Parameters!$B$10*G49^Parameters!$B$9+Parameters!$B$11*U49^Parameters!$B$9)^(Parameters!$B$7/Parameters!$B$9)*N49 -> 1.3366918 | W49: =V49 - C49 - D49 - LN(1+EXP(Parameters!$B$21*B49))/Parameters!$B$21 - IF(B49>0, 0,Parameters!$B$6*B49^2/E49) -> 1.0275161 | X49: =EXP(-Parameters!$B$56*A49) -> 0.50687036 | Y49: =IF(W49>0,W49^(1-Parameters!$B$53)/(1-Parameters!$B$53)*X49*Parameters!$B$71,-10+W49*1000) -> -1.4345075 | AA49: =B49/E49-B48/E48 -> -0.0049151643 | AB49: =C49/F49-C48/F48 -> -0.00044814291 | AC49: =D49/G49-D48/G48 -> 0.00012173594 | AD49: =X49*(AA49^2+AB49^2+AC49^2) -> 1.2354708e-05 | AE49: =B49/E49-2*B48/E48+B47/E47 -> -0.00041945527 | AF49: =C49/F49-2*C48/F48+C47/F47 -> 3.3439183e-05 | AG49: =D49/G49-2*D48/G48+D47/G47 -> -7.142816e-06 | AH49: =X49*(AE49^2+AF49^2+AG49^2) -> 8.9772785e-08 | AM49: =H49*I49*J49 -> 0 | AN49: =E49*I49*J49 -> 13.368008 | AO49: =U49*I49*J49 -> 68.393866 | AP49: =V49*J49*I49 -> 274.2176 | AQ49: =-X49*V49*W49^(-Parameters!B$53)*Parameters!B$47*Parameters!B$46*M49 -> -1.493484e-05 | AR49: =1000*EXP(-(Parameters!$B$55)*'6states'!A49)*AP49*Parameters!B$47*Parameters!B$46*M49 -> 1.2921538 | AS49: =SUM(AR49:AR$204)*EXP(Parameters!$B$55*A49) -> 480.88463 | AT49: =(B49+C49+D49)/V49 -> 0.23021266 | AU49: =(1/$S49-1/Parameters!$B$13) * LN(Parameters!$B$18) / LN(O49) -> 0.22912567 | AV49: =(Parameters!$B$18*'6states'!S49^+Parameters!$B$19*Parameters!$B$25^'6states'!S49)^((1-'6states'!S49)/'6states'!S49)*Parameters!$B$18*Parameters!$B$26^('6states'!S49-1) -> 0.2879383 | AW49: =(LN(AV49)-LN(AV$4))/ LN(O49) -> 0.23071127 | AX49: =1-2^-AU49 -> 0.14684822 | AY49: =1-2^-AV49 -> 0.18092827 | AZ49: =(1/$S49-1/Parameters!$B$13) * LN(Parameters!$B$18) / A49 -> 0.017595218
A50: =A49+Parameters!$B$71 -> 46 | B50: 0.00022896821 | C50: 0.08950445 | D50: 0.21795424 | E50: =MAX((1-Parameters!$B$4)^Parameters!B$71*E49 + B49*Parameters!B$71 - IF(B49>0,Parameters!$B$5,0)*B49^2/E49*Parameters!B$71, 0.0001) -> 0.061655534 | F50: =(1-Parameters!$B$4)^Parameters!B$71*F49+C49*Parameters!B$71-Parameters!$B$5*C49^2/F49*Parameters!B$71 -> 1.167336 | G50: =(1-Parameters!$B$4)^Parameters!B$71*G49+D49*Parameters!B$71-Parameters!$B$5*D49^2/G49*Parameters!B$71 -> 3.3027314 | H50: =MAX(H49 * (1-Parameters!$B$4) ^ Parameters!B$71 + (LN(1+EXP(Parameters!$B$21*(-B49+0.004)))/Parameters!$B$21 -0.004) * Parameters!B$71,0) -> 0 | I50: =I49*(1+Parameters!$B$52)^Parameters!B$71 -> 9.3226891 | J50: =J49*(1+Parameters!$B$54)^Parameters!B$71 -> 22.510267 | K50: =I50*J50*EXP(-Parameters!$B$43*'6states'!A50)*(Parameters!$B$38/Parameters!$B$39*('6states'!E50+'6states'!H50)/Parameters!$E$25*(EXP(-Parameters!$B$39*Parameters!$E$25*'6states'!H50/('6states'!E50+'6states'!H50))-EXP(-Parameters!$B$39*Parameters!$E$25)) + Parameters!$B$40*'6states'!E50) -> 7.4384303 | L50: =L49+K50*Parameters!B$71 -> 3167.4485 | M50: =L50*Parameters!$B$46 -> 1.9004691 | N50: =EXP(-Parameters!$B$47/2*M50^2) -> 0.96435247 | O50: =MAX((Parameters!$B$63 + Parameters!$B$31*'6states'!A50 - '6states'!L50 + Parameters!$B$48/Parameters!$B$46)/Parameters!B$63,1) -> 32.595031 | P50: =Parameters!B$62*EXP(-Parameters!B$61*A50) -> 0.14440301 | Q50: =(1-Parameters!B$62)*O50^-Parameters!B$64 -> 0.35290261 | R50: =Parameters!B$62*EXP(-Parameters!B$61*A50)+(1-Parameters!B$62)*O50^-Parameters!B$64 -> 0.49730562 | S50: =1-R50/Parameters!$B$12 -> 0.75134719 | T50: =1/(1-S50) -> 4.0216718 | U50: =(Parameters!$B$19*(E50+Parameters!$B$20)^S50+Parameters!$B$18*F50^S50)^(1/S50) -> 0.33264537 | V50: =(Parameters!$B$10*G50^Parameters!$B$9+Parameters!$B$11*U50^Parameters!$B$9)^(Parameters!$B$7/Parameters!$B$9)*N50 -> 1.3357943 | W50: =V50 - C50 - D50 - LN(1+EXP(Parameters!$B$21*B50))/Parameters!$B$21 - IF(B50>0, 0,Parameters!$B$6*B50^2/E50) -> 1.0264856 | X50: =EXP(-Parameters!$B$56*A50) -> 0.49927412 | Y50: =IF(W50>0,W50^(1-Parameters!$B$53)/(1-Parameters!$B$53)*X50*Parameters!$B$71,-10+W50*1000) -> -1.4135055 | AA50: =B50/E50-B49/E49 -> -0.0054406275 | AB50: =C50/F50-C49/F49 -> -0.00041735025 | AC50: =D50/G50-D49/G49 -> 0.00011496539 | AD50: =X50*(AA50^2+AB50^2+AC50^2) -> 1.487229e-05 | AE50: =B50/E50-2*B49/E49+B48/E48 -> -0.00052546315 | AF50: =C50/F50-2*C49/F49+C48/F48 -> 3.0792664e-05 | AG50: =D50/G50-2*D49/G49+D48/G48 -> -6.7705472e-06 | AH50: =X50*(AE50^2+AF50^2+AG50^2) -> 1.3835163e-07 | AM50: =H50*I50*J50 -> 0 | AN50: =E50*I50*J50 -> 12.938797 | AO50: =U50*I50*J50 -> 69.807701 | AP50: =V50*J50*I50 -> 280.32474 | AQ50: =-X50*V50*W50^(-Parameters!B$53)*Parameters!B$47*Parameters!B$46*M50 -> -1.4755719e-05 | AR50: =1000*EXP(-(Parameters!$B$55)*'6states'!A50)*AP50*Parameters!B$47*Parameters!B$46*M50 -> 1.2783733 | AS50: =SUM(AR50:AR$204)*EXP(Parameters!$B$55*A50) -> 491.5692 | AT50: =(B50+C50+D50)/V50 -> 0.2303406 | AU50: =(1/$S50-1/Parameters!$B$13) * LN(Parameters!$B$18) / LN(O50) -> 0.2287593 | AV50: =(Parameters!$B$18*'6states'!S50^+Parameters!$B$19*Parameters!$B$25^'6states'!S50)^((1-'6states'!S50)/'6states'!S50)*Parameters!$B$18*Parameters!$B$26^('6states'!S50-1) -> 0.28875077 | AW50: =(LN(AV50)-LN(AV$4))/ LN(O50) -> 0.22963409 | AX50: =1-2^-AU50 -> 0.14663154 | AY50: =1-2^-AV50 -> 0.18138941 | AZ50: =(1/$S50-1/Parameters!$B$13) * LN(Parameters!$B$18) / A50 -> 0.017326825
A51: =A50+Parameters!$B$71 -> 47 | B51: =B50+(B$53-B$50)/3 -> 0.00066355232 | C51: =C50+(C$53-C$50)/3 -> 0.089251505 | D51: =D50+(D$53-D$50)/3 -> 0.21818366 | E51: =MAX((1-Parameters!$B$4)^Parameters!B$71*E50 + B50*Parameters!B$71 - IF(B50>0,Parameters!$B$5,0)*B50^2/E50*Parameters!B$71, 0.0001) -> 0.058005519 | F51: =(1-Parameters!$B$4)^Parameters!B$71*F50+C50*Parameters!B$71-Parameters!$B$5*C50^2/F50*Parameters!B$71 -> 1.1765523 | G51: =(1-Parameters!$B$4)^Parameters!B$71*G50+D50*Parameters!B$71-Parameters!$B$5*D50^2/G50*Parameters!B$71 -> 3.2985605 | H51: =MAX(H50 * (1-Parameters!$B$4) ^ Parameters!B$71 + (LN(1+EXP(Parameters!$B$21*(-B50+0.004)))/Parameters!$B$21 -0.004) * Parameters!B$71,0) -> 0.00027074142 | I51: =I50*(1+Parameters!$B$52)^Parameters!B$71 -> 9.3497249 | J51: =J50*(1+Parameters!$B$54)^Parameters!B$71 -> 22.960472 | K51: =I51*J51*EXP(-Parameters!$B$43*'6states'!A51)*(Parameters!$B$38/Parameters!$B$39*('6states'!E51+'6states'!H51)/Parameters!$E$25*(EXP(-Parameters!$B$39*Parameters!$E$25*'6states'!H51/('6states'!E51+'6states'!H51))-EXP(-Parameters!$B$39*Parameters!$E$25)) + Parameters!$B$40*'6states'!E51) -> 6.8910544 | L51: =L50+K51*Parameters!B$71 -> 3174.3395 | M51: =L51*Parameters!$B$46 -> 1.9046037 | N51: =EXP(-Parameters!$B$47/2*M51^2) -> 0.96420001 | O51: =MAX((Parameters!$B$63 + Parameters!$B$31*'6states'!A51 - '6states'!L51 + Parameters!$B$48/Parameters!$B$46)/Parameters!B$63,1) -> 33.52121 | P51: =Parameters!B$62*EXP(-Parameters!B$61*A51) -> 0.1405563 | Q51: =(1-Parameters!B$62)*O51^-Parameters!B$64 -> 0.35191521 | R51: =Parameters!B$62*EXP(-Parameters!B$61*A51)+(1-Parameters!B$62)*O51^-Parameters!B$64 -> 0.49247151 | S51: =1-R51/Parameters!$B$12 -> 0.75376425 | T51: =1/(1-S51) -> 4.0611487 | U51: =(Parameters!$B$19*(E51+Parameters!$B$20)^S51+Parameters!$B$18*F51^S51)^(1/S51) -> 0.33165472 | V51: =(Parameters!$B$10*G51^Parameters!$B$9+Parameters!$B$11*U51^Parameters!$B$9)^(Parameters!$B$7/Parameters!$B$9)*N51 -> 1.3348337 | W51: =V51 - C51 - D51 - LN(1+EXP(Parameters!$B$21*B51))/Parameters!$B$21 - IF(B51>0, 0,Parameters!$B$6*B51^2/E51) -> 1.0253119 | X51: =EXP(-Parameters!$B$56*A51) -> 0.49179171 | Y51: =IF(W51>0,W51^(1-Parameters!$B$53)/(1-Parameters!$B$53)*X51*Parameters!$B$71,-10+W51*1000) -> -1.3928796 | AA51: =B51/E51-B50/E50 -> 0.0077258003 | AB51: =C51/F51-C50/F50 -> -0.00081560316 | AC51: =D51/G51-D50/G50 -> 0.0001529938 | AD51: =X51*(AA51^2+AB51^2+AC51^2) -> 2.9692714e-05 | AE51: =B51/E51-2*B50/E50+B49/E49 -> 0.013166428 | AF51: =C51/F51-2*C50/F50+C49/F49 -> -0.00039825291 | AG51: =D51/G51-2*D50/G50+D49/G49 -> 3.8028409e-05 | AH51: =X51*(AE51^2+AF51^2+AG51^2) -> 8.5333176e-05 | AM51: =H51*I51*J51 -> 0.058121171 | AN51: =E51*I51*J51 -> 12.452283 | AO51: =U51*I51*J51 -> 71.197678 | AP51: =V51*J51*I51 -> 286.55421 | AQ51: =-X51*V51*W51^(-Parameters!B$53)*Parameters!B$47*Parameters!B$46*M51 -> -1.4578227e-05 | AR51: =1000*EXP(-(Parameters!$B$55)*'6states'!A51)*AP51*Parameters!B$47*Parameters!B$46*M51 -> 1.2644543 | AS51: =SUM(AR51:AR$204)*EXP(Parameters!$B$55*A51) -> 502.47519 | AT51: =(B51+C51+D51)/V51 -> 0.23081432 | AU51: =(1/$S51-1/Parameters!$B$13) * LN(Parameters!$B$18) / LN(O51) -> 0.22838196 | AV51: =(Parameters!$B$18*'6states'!S51^+Parameters!$B$19*Parameters!$B$25^'6states'!S51)^((1-'6states'!S51)/'6states'!S51)*Parameters!$B$18*Parameters!$B$26^('6states'!S51-1) -> 0.28952752 | AW51: =(LN(AV51)-LN(AV$4))/ LN(O51) -> 0.22856705 | AX51: =1-2^-AU51 -> 0.14640831 | AY51: =1-2^-AV51 -> 0.18183003 | AZ51: =(1/$S51-1/Parameters!$B$13) * LN(Parameters!$B$18) / A51 -> 0.017066344
A52: =A51+Parameters!$B$71 -> 48 | B52: =B51+(B$53-B$50)/3 -> 0.0010981364 | C52: =C51+(C$53-C$50)/3 -> 0.08899856 | D52: =D51+(D$53-D$50)/3 -> 0.21841308 | E52: =MAX((1-Parameters!$B$4)^Parameters!B$71*E51 + B51*Parameters!B$71 - IF(B51>0,Parameters!$B$5,0)*B51^2/E51*Parameters!B$71, 0.0001) -> 0.055012934 | F52: =(1-Parameters!$B$4)^Parameters!B$71*F51+C51*Parameters!B$71-Parameters!$B$5*C51^2/F51*Parameters!B$71 -> 1.1850282 | G52: =(1-Parameters!$B$4)^Parameters!B$71*G51+D51*Parameters!B$71-Parameters!$B$5*D51^2/G51*Parameters!B$71 -> 3.294833 | H52: =MAX(H51 * (1-Parameters!$B$4) ^ Parameters!B$71 + (LN(1+EXP(Parameters!$B$21*(-B51+0.004)))/Parameters!$B$21 -0.004) * Parameters!B$71,0) -> 0.00017441642 | I52: =I51*(1+Parameters!$B$52)^Parameters!B$71 -> 9.3768391 | J52: =J51*(1+Parameters!$B$54)^Parameters!B$71 -> 23.419682 | K52: =I52*J52*EXP(-Parameters!$B$43*'6states'!A52)*(Parameters!$B$38/Parameters!$B$39*('6states'!E52+'6states'!H52)/Parameters!$E$25*(EXP(-Parameters!$B$39*Parameters!$E$25*'6states'!H52/('6states'!E52+'6states'!H52))-EXP(-Parameters!$B$39*Parameters!$E$25)) + Parameters!$B$40*'6states'!E52) -> 6.6754685 | L52: =L51+K52*Parameters!B$71 -> 3181.015 | M52: =L52*Parameters!$B$46 -> 1.908609 | N52: =EXP(-Parameters!$B$47/2*M52^2) -> 0.96405202 | O52: =MAX((Parameters!$B$63 + Parameters!$B$31*'6states'!A52 - '6states'!L52 + Parameters!$B$48/Parameters!$B$46)/Parameters!B$63,1) -> 34.4517 | P52: =Parameters!B$62*EXP(-Parameters!B$61*A52) -> 0.13681205 | Q52: =(1-Parameters!B$62)*O52^-Parameters!B$64 -> 0.35095298 | R52: =Parameters!B$62*EXP(-Parameters!B$61*A52)+(1-Parameters!B$62)*O52^-Parameters!B$64 -> 0.48776503 | S52: =1-R52/Parameters!$B$12 -> 0.75611748 | T52: =1/(1-S52) -> 4.1003349 | U52: =(Parameters!$B$19*(E52+Parameters!$B$20)^S52+Parameters!$B$18*F52^S52)^(1/S52) -> 0.33115004 | V52: =(Parameters!$B$10*G52^Parameters!$B$9+Parameters!$B$11*U52^Parameters!$B$9)^(Parameters!$B$7/Parameters!$B$9)*N52 -> 1.3341205 | W52: =V52 - C52 - D52 - LN(1+EXP(Parameters!$B$21*B52))/Parameters!$B$21 - IF(B52>0, 0,Parameters!$B$6*B52^2/E52) -> 1.0243671 | X52: =EXP(-Parameters!$B$56*A52) -> 0.48442144 | Y52: =IF(W52>0,W52^(1-Parameters!$B$53)/(1-Parameters!$B$53)*X52*Parameters!$B$71,-10+W52*1000) -> -1.3724478 | AA52: =B52/E52-B51/E51 -> 0.0085219542 | AB52: =C52/F52-C51/F51 -> -0.00075602619 | AC52: =D52/G52-D51/G51 -> 0.00014446229 | AD52: =X52*(AA52^2+AB52^2+AC52^2) -> 3.5467472e-05 | AE52: =B52/E52-2*B51/E51+B50/E50 -> 0.00079615388 | AF52: =C52/F52-2*C51/F51+C50/F50 -> 5.9576963e-05 | AG52: =D52/G52-2*D51/G51+D50/G50 -> -8.5315076e-06 | AH52: =X52*(AE52^2+AF52^2+AG52^2) -> 3.0881053e-07 | AM52: =H52*I52*J52 -> 0.038302298 | AN52: =E52*I52*J52 -> 12.080983 | AO52: =U52*I52*J52 -> 72.721407 | AP52: =V52*J52*I52 -> 292.97632 | AQ52: =-X52*V52*W52^(-Parameters!B$53)*Parameters!B$47*Parameters!B$46*M52 -> -1.4400169e-05 | AR52: =1000*EXP(-(Parameters!$B$55)*'6states'!A52)*AP52*Parameters!B$47*Parameters!B$46*M52 -> 1.2508276 | AS52: =SUM(AR52:AR$204)*EXP(Parameters!$B$55*A52) -> 513.60811 | AT52: =(B52+C52+D52)/V52 -> 0.2312458 | AU52: =(1/$S52-1/Parameters!$B$13) * LN(Parameters!$B$18) / LN(O52) -> 0.22800498 | AV52: =(Parameters!$B$18*'6states'!S52^+Parameters!$B$19*Parameters!$B$25^'6states'!S52)^((1-'6states'!S52)/'6states'!S52)*Parameters!$B$18*Parameters!$B$26^('6states'!S52-1) -> 0.29026924 | AW52: =(LN(AV52)-LN(AV$4))/ LN(O52) -> 0.22752184 | AX52: =1-2^-AU52 -> 0.14618523 | AY52: =1-2^-AV52 -> 0.18225057 | AZ52: =(1/$S52-1/Parameters!$B$13) * LN(Parameters!$B$18) / A52 -> 0.016813269
A53: =A52+Parameters!$B$71 -> 49 | B53: 0.0015327205 | C53: 0.088745615 | D53: 0.2186425 | E53: =MAX((1-Parameters!$B$4)^Parameters!B$71*E52 + B52*Parameters!B$71 - IF(B52>0,Parameters!$B$5,0)*B52^2/E52*Parameters!B$71, 0.0001) -> 0.052628836 | F53: =(1-Parameters!$B$4)^Parameters!B$71*F52+C52*Parameters!B$71-Parameters!$B$5*C52^2/F52*Parameters!B$71 -> 1.1928045 | G53: =(1-Parameters!$B$4)^Parameters!B$71*G52+D52*Parameters!B$71-Parameters!$B$5*D52^2/G52*Parameters!B$71 -> 3.2915225 | H53: =MAX(H52 * (1-Parameters!$B$4) ^ Parameters!B$71 + (LN(1+EXP(Parameters!$B$21*(-B52+0.004)))/Parameters!$B$21 -0.004) * Parameters!B$71,0) -> 0 | I53: =I52*(1+Parameters!$B$52)^Parameters!B$71 -> 9.4040319 | J53: =J52*(1+Parameters!$B$54)^Parameters!B$71 -> 23.888076 | K53: =I53*J53*EXP(-Parameters!$B$43*'6states'!A53)*(Parameters!$B$38/Parameters!$B$39*('6states'!E53+'6states'!H53)/Parameters!$E$25*(EXP(-Parameters!$B$39*Parameters!$E$25*'6states'!H53/('6states'!E53+'6states'!H53))-EXP(-Parameters!$B$39*Parameters!$E$25)) + Parameters!$B$40*'6states'!E53) -> 6.5959533 | L53: =L52+K53*Parameters!B$71 -> 3187.6109 | M53: =L53*Parameters!$B$46 -> 1.9125666 | N53: =EXP(-Parameters!$B$47/2*M53^2) -> 0.96390551 | O53: =MAX((Parameters!$B$63 + Parameters!$B$31*'6states'!A53 - '6states'!L53 + Parameters!$B$48/Parameters!$B$46)/Parameters!B$63,1) -> 35.383781 | P53: =Parameters!B$62*EXP(-Parameters!B$61*A53) -> 0.13316755 | Q53: =(1-Parameters!B$62)*O53^-Parameters!B$64 -> 0.35001736 | R53: =Parameters!B$62*EXP(-Parameters!B$61*A53)+(1-Parameters!B$62)*O53^-Parameters!B$64 -> 0.4831849 | S53: =1-R53/Parameters!$B$12 -> 0.75840755 | T53: =1/(1-S53) -> 4.1392022 | U53: =(Parameters!$B$19*(E53+Parameters!$B$20)^S53+Parameters!$B$18*F53^S53)^(1/S53) -> 0.33110129 | V53: =(Parameters!$B$10*G53^Parameters!$B$9+Parameters!$B$11*U53^Parameters!$B$9)^(Parameters!$B$7/Parameters!$B$9)*N53 -> 1.3336371 | W53: =V53 - C53 - D53 - LN(1+EXP(Parameters!$B$21*B53))/Parameters!$B$21 - IF(B53>0, 0,Parameters!$B$6*B53^2/E53) -> 1.0236341 | X53: =EXP(-Parameters!$B$56*A53) -> 0.47716163 | Y53: =IF(W53>0,W53^(1-Parameters!$B$53)/(1-Parameters!$B$53)*X53*Parameters!$B$71,-10+W53*1000) -> -1.3522183 | AA53: =B53/E53-B52/E52 -> 0.0091617851 | AB53: =C53/F53-C52/F52 -> -0.00070167607 | AC53: =D53/G53-D52/G52 -> 0.00013636989 | AD53: =X53*(AA53^2+AB53^2+AC53^2) -> 4.0295943e-05 | AE53: =B53/E53-2*B52/E52+B51/E51 -> 0.00063983095 | AF53: =C53/F53-2*C52/F52+C51/F51 -> 5.4350129e-05 | AG53: =D53/G53-2*D52/G52+D51/G51 -> -8.0924027e-06 | AH53: =X53*(AE53^2+AF53^2+AG53^2) -> 1.9678292e-07 | AM53: =H53*I53*J53 -> 0 | AN53: =E53*I53*J53 -> 11.822764 | AO53: =U53*I53*J53 -> 74.379993 | AP53: =V53*J53*I53 -> 299.59388 | AQ53: =-X53*V53*W53^(-Parameters!B$53)*Parameters!B$47*Parameters!B$46*M53 -> -1.4222359e-05 | AR53: =1000*EXP(-(Parameters!$B$55)*'6states'!A53)*AP53*Parameters!B$47*Parameters!B$46*M53 -> 1.2375242 | AS53: =SUM(AR53:AR$204)*EXP(Parameters!$B$55*A53) -> 524.97129 | AT53: =(B53+C53+D53)/V53 -> 0.23163785 | AU53: =(1/$S53-1/Parameters!$B$13) * LN(Parameters!$B$18) / LN(O53) -> 0.22763225 | AV53: =(Parameters!$B$18*'6states'!S53^+Parameters!$B$19*Parameters!$B$25^'6states'!S53)^((1-'6states'!S53)/'6states'!S53)*Parameters!$B$18*Parameters!$B$26^('6states'!S53-1) -> 0.29097737 | AW53: =(LN(AV53)-LN(AV$4))/ LN(O53) -> 0.22650196 | AX53: =1-2^-AU53 -> 0.14596461 | AY53: =1-2^-AV53 -> 0.18265185 | AZ53: =(1/$S53-1/Parameters!$B$13) * LN(Parameters!$B$18) / A53 -> 0.016567231
A54: =A53+Parameters!$B$71 -> 50 | B54: =B53+(B$57-B$53)/4 -> 0.0013353907 | C54: =C53+(C$57-C$53)/4 -> 0.088793822 | D54: =D53+(D$57-D$53)/4 -> 0.21891855 | E54: =MAX((1-Parameters!$B$4)^Parameters!B$71*E53 + B53*Parameters!B$71 - IF(B53>0,Parameters!$B$5,0)*B53^2/E53*Parameters!B$71, 0.0001) -> 0.050806565 | F54: =(1-Parameters!$B$4)^Parameters!B$71*F53+C53*Parameters!B$71-Parameters!$B$5*C53^2/F53*Parameters!B$71 -> 1.1999199 | G54: =(1-Parameters!$B$4)^Parameters!B$71*G53+D53*Parameters!B$71-Parameters!$B$5*D53^2/G53*Parameters!B$71 -> 3.2886047 | H54: =MAX(H53 * (1-Parameters!$B$4) ^ Parameters!B$71 + (LN(1+EXP(Parameters!$B$21*(-B53+0.004)))/Parameters!$B$21 -0.004) * Parameters!B$71,0) -> 0 | I54: =I53*(1+Parameters!$B$52)^Parameters!B$71 -> 9.4313036 | J54: =J53*(1+Parameters!$B$54)^Parameters!B$71 -> 24.365837 | K54: =I54*J54*EXP(-Parameters!$B$43*'6states'!A54)*(Parameters!$B$38/Parameters!$B$39*('6states'!E54+'6states'!H54)/Parameters!$E$25*(EXP(-Parameters!$B$39*Parameters!$E$25*'6states'!H54/('6states'!E54+'6states'!H54))-EXP(-Parameters!$B$39*Parameters!$E$25)) + Parameters!$B$40*'6states'!E54) -> 6.4489424 | L54: =L53+K54*Parameters!B$71 -> 3194.0599 | M54: =L54*Parameters!$B$46 -> 1.9164359 | N54: =EXP(-Parameters!$B$47/2*M54^2) -> 0.963762 | O54: =MAX((Parameters!$B$63 + Parameters!$B$31*'6states'!A54 - '6states'!L54 + Parameters!$B$48/Parameters!$B$46)/Parameters!B$63,1) -> 36.318802 | P54: =Parameters!B$62*EXP(-Parameters!B$61*A54) -> 0.12962013 | Q54: =(1-Parameters!B$62)*O54^-Parameters!B$64 -> 0.34910563 | R54: =Parameters!B$62*EXP(-Parameters!B$61*A54)+(1-Parameters!B$62)*O54^-Parameters!B$64 -> 0.47872576 | S54: =1-R54/Parameters!$B$12 -> 0.76063712 | T54: =1/(1-S54) -> 4.1777572 | U54: =(Parameters!$B$19*(E54+Parameters!$B$20)^S54+Parameters!$B$18*F54^S54)^(1/S54) -> 0.3314772 | V54: =(Parameters!$B$10*G54^Parameters!$B$9+Parameters!$B$11*U54^Parameters!$B$9)^(Parameters!$B$7/Parameters!$B$9)*N54 -> 1.3333691 | W54: =V54 - C54 - D54 - LN(1+EXP(Parameters!$B$21*B54))/Parameters!$B$21 - IF(B54>0, 0,Parameters!$B$6*B54^2/E54) -> 1.023168 | X54: =EXP(-Parameters!$B$56*A54) -> 0.47001061 | Y54: =IF(W54>0,W54^(1-Parameters!$B$53)/(1-Parameters!$B$53)*X54*Parameters!$B$71,-10+W54*1000) -> -1.3321655 | AA54: =B54/E54-B53/E53 -> -0.0028393855 | AB54: =C54/F54-C53/F53 -> -0.00040101814 | AC54: =D54/G54-D53/G53 -> 0.00014287875 | AD54: =X54*(AA54^2+AB54^2+AC54^2) -> 3.8744572e-06 | AE54: =B54/E54-2*B53/E53+B52/E52 -> -0.012001171 | AF54: =C54/F54-2*C53/F53+C52/F52 -> 0.00030065793 | AG54: =D54/G54-2*D53/G53+D52/G52 -> 6.5088592e-06 | AH54: =X54*(AE54^2+AF54^2+AG54^2) -> 6.773724e-05 | AM54: =H54*I54*J54 -> 0 | AN54: =E54*I54*J54 -> 11.67543 | AO54: =U54*I54*J54 -> 76.173993 | AP54: =V54*J54*I54 -> 306.41036 | AQ54: =-X54*V54*W54^(-Parameters!B$53)*Parameters!B$47*Parameters!B$46*M54 -> -1.4043368e-05 | AR54: =1000*EXP(-(Parameters!$B$55)*'6states'!A54)*AP54*Parameters!B$47*Parameters!B$46*M54 -> 1.2244984 | AS54: =SUM(AR54:AR$204)*EXP(Parameters!$B$55*A54) -> 536.56783 | AT54: =(B54+C54+D54)/V54 -> 0.23177961 | AU54: =(1/$S54-1/Parameters!$B$13) * LN(Parameters!$B$18) / LN(O54) -> 0.22726121 | AV54: =(Parameters!$B$18*'6states'!S54^+Parameters!$B$19*Parameters!$B$25^'6states'!S54)^((1-'6states'!S54)/'6states'!S54)*Parameters!$B$18*Parameters!$B$26^('6states'!S54-1) -> 0.29165388 | AW54: =(LN(AV54)-LN(AV$4))/ LN(O54) -> 0.22550389 | AX54: =1-2^-AU54 -> 0.14574494 | AY54: =1-2^-AV54 -> 0.18303503 | AZ54: =(1/$S54-1/Parameters!$B$13) * LN(Parameters!$B$18) / A54 -> 0.01632797
A55: =A54+Parameters!$B$71 -> 51 | B55: =B54+(B$57-B$53)/4 -> 0.0011380609 | C55: =C54+(C$57-C$53)/4 -> 0.088842029 | D55: =D54+(D$57-D$53)/4 -> 0.2191946 | E55: =MAX((1-Parameters!$B$4)^Parameters!B$71*E54 + B54*Parameters!B$71 - IF(B54>0,Parameters!$B$5,0)*B54^2/E54*Parameters!B$71, 0.0001) -> 0.048911124 | F55: =(1-Parameters!$B$4)^Parameters!B$71*F54+C54*Parameters!B$71-Parameters!$B$5*C54^2/F54*Parameters!B$71 -> 1.2066681 | G55: =(1-Parameters!$B$4)^Parameters!B$71*G54+D54*Parameters!B$71-Parameters!$B$5*D54^2/G54*Parameters!B$71 -> 3.2860969 | H55: =MAX(H54 * (1-Parameters!$B$4) ^ Parameters!B$71 + (LN(1+EXP(Parameters!$B$21*(-B54+0.004)))/Parameters!$B$21 -0.004) * Parameters!B$71,0) -> 0 | I55: =I54*(1+Parameters!$B$52)^Parameters!B$71 -> 9.4586544 | J55: =J54*(1+Parameters!$B$54)^Parameters!B$71 -> 24.853154 | K55: =I55*J55*EXP(-Parameters!$B$43*'6states'!A55)*(Parameters!$B$38/Parameters!$B$39*('6states'!E55+'6states'!H55)/Parameters!$E$25*(EXP(-Parameters!$B$39*Parameters!$E$25*'6states'!H55/('6states'!E55+'6states'!H55))-EXP(-Parameters!$B$39*Parameters!$E$25)) + Parameters!$B$40*'6states'!E55) -> 6.2876906 | L55: =L54+K55*Parameters!B$71 -> 3200.3476 | M55: =L55*Parameters!$B$46 -> 1.9202085 | N55: =EXP(-Parameters!$B$47/2*M55^2) -> 0.96362182 | O55: =MAX((Parameters!$B$63 + Parameters!$B$31*'6states'!A55 - '6states'!L55 + Parameters!$B$48/Parameters!$B$46)/Parameters!B$63,1) -> 37.257049 | P55: =Parameters!B$62*EXP(-Parameters!B$61*A55) -> 0.12616721 | Q55: =(1-Parameters!B$62)*O55^-Parameters!B$64 -> 0.34821635 | R55: =Parameters!B$62*EXP(-Parameters!B$61*A55)+(1-Parameters!B$62)*O55^-Parameters!B$64 -> 0.47438356 | S55: =1-R55/Parameters!$B$12 -> 0.76280822 | T55: =1/(1-S55) -> 4.2159977 | U55: =(Parameters!$B$19*(E55+Parameters!$B$20)^S55+Parameters!$B$18*F55^S55)^(1/S55) -> 0.3316834 | V55: =(Parameters!$B$10*G55^Parameters!$B$9+Parameters!$B$11*U55^Parameters!$B$9)^(Parameters!$B$7/Parameters!$B$9)*N55 -> 1.3330645 | W55: =V55 - C55 - D55 - LN(1+EXP(Parameters!$B$21*B55))/Parameters!$B$21 - IF(B55>0, 0,Parameters!$B$6*B55^2/E55) -> 1.0226618 | X55: =EXP(-Parameters!$B$56*A55) -> 0.46296677 | Y55: =IF(W55>0,W55^(1-Parameters!$B$53)/(1-Parameters!$B$53)*X55*Parameters!$B$71,-10+W55*1000) -> -1.3124282 | AA55: =B55/E55-B54/E54 -> -0.0030158856 | AB55: =C55/F55-C54/F54 -> -0.00037388371 | AC55: =D55/G55-D54/G54 -> 0.00013480964 | AD55: =X55*(AA55^2+AB55^2+AC55^2) -> 4.2840764e-06 | AE55: =B55/E55-2*B54/E54+B53/E53 -> -0.00017650016 | AF55: =C55/F55-2*C54/F54+C53/F53 -> 2.7134429e-05 | AG55: =D55/G55-2*D54/G54+D53/G53 -> -8.0691055e-06 | AH55: =X55*(AE55^2+AF55^2+AG55^2) -> 1.4793498e-08 | AM55: =H55*I55*J55 -> 0 | AN55: =E55*I55*J55 -> 11.497899 | AO55: =U55*I55*J55 -> 77.971267 | AP55: =V55*J55*I55 -> 313.37333 | AQ55: =-X55*V55*W55^(-Parameters!B$53)*Parameters!B$47*Parameters!B$46*M55 -> -1.3866232e-05 | AR55: =1000*EXP(-(Parameters!$B$55)*'6states'!A55)*AP55*Parameters!B$47*Parameters!B$46*M55 -> 1.2115105 | AS55: =SUM(AR55:AR$204)*EXP(Parameters!$B$55*A55) -> 548.40098 | AT55: =(B55+C55+D55)/V55 -> 0.23192778 | AU55: =(1/$S55-1/Parameters!$B$13) * LN(Parameters!$B$18) / LN(O55) -> 0.22689114 | AV55: =(Parameters!$B$18*'6states'!S55^+Parameters!$B$19*Parameters!$B$25^'6states'!S55)^((1-'6states'!S55)/'6states'!S55)*Parameters!$B$18*Parameters!$B$26^('6states'!S55-1) -> 0.29230043 | AW55: =(LN(AV55)-LN(AV$4))/ LN(O55) -> 0.22452618 | AX55: =1-2^-AU55 -> 0.14552579 | AY55: =1-2^-AV55 -> 0.18340108 | AZ55: =(1/$S55-1/Parameters!$B$13) * LN(Parameters!$B$18) / A55 -> 0.016095218
A56: =A55+Parameters!$B$71 -> 52 | B56: =B55+(B$57-B$53)/4 -> 0.00094073114 | C56: =C55+(C$57-C$53)/4 -> 0.088890236 | D56: =D55+(D$57-D$53)/4 -> 0.21947066 | E56: =MAX((1-Parameters!$B$4)^Parameters!B$71*E55 + B55*Parameters!B$71 - IF(B55>0,Parameters!$B$5,0)*B55^2/E55*Parameters!B$71, 0.0001) -> 0.046946195 | F56: =(1-Parameters!$B$4)^Parameters!B$71*F55+C55*Parameters!B$71-Parameters!$B$5*C55^2/F55*Parameters!B$71 -> 1.2130696 | G56: =(1-Parameters!$B$4)^Parameters!B$71*G55+D55*Parameters!B$71-Parameters!$B$5*D55^2/G55*Parameters!B$71 -> 3.2839749 | H56: =MAX(H55 * (1-Parameters!$B$4) ^ Parameters!B$71 + (LN(1+EXP(Parameters!$B$21*(-B55+0.004)))/Parameters!$B$21 -0.004) * Parameters!B$71,0) -> 0 | I56: =I55*(1+Parameters!$B$52)^Parameters!B$71 -> 9.4860845 | J56: =J55*(1+Parameters!$B$54)^Parameters!B$71 -> 25.350217 | K56: =I56*J56*EXP(-Parameters!$B$43*'6states'!A56)*(Parameters!$B$38/Parameters!$B$39*('6states'!E56+'6states'!H56)/Parameters!$E$25*(EXP(-Parameters!$B$39*Parameters!$E$25*'6states'!H56/('6states'!E56+'6states'!H56))-EXP(-Parameters!$B$39*Parameters!$E$25)) + Parameters!$B$40*'6states'!E56) -> 6.1122172 | L56: =L55+K56*Parameters!B$71 -> 3206.4598 | M56: =L56*Parameters!$B$46 -> 1.9238759 | N56: =EXP(-Parameters!$B$47/2*M56^2) -> 0.9634853 | O56: =MAX((Parameters!$B$63 + Parameters!$B$31*'6states'!A56 - '6states'!L56 + Parameters!$B$48/Parameters!$B$46)/Parameters!B$63,1) -> 38.198804 | P56: =Parameters!B$62*EXP(-Parameters!B$61*A56) -> 0.12280627 | Q56: =(1-Parameters!B$62)*O56^-Parameters!B$64 -> 0.34734818 | R56: =Parameters!B$62*EXP(-Parameters!B$61*A56)+(1-Parameters!B$62)*O56^-Parameters!B$64 -> 0.47015445 | S56: =1-R56/Parameters!$B$12 -> 0.76492277 | T56: =1/(1-S56) -> 4.2539212 | U56: =(Parameters!$B$19*(E56+Parameters!$B$20)^S56+Parameters!$B$18*F56^S56)^(1/S56) -> 0.33172676 | V56: =(Parameters!$B$10*G56^Parameters!$B$9+Parameters!$B$11*U56^Parameters!$B$9)^(Parameters!$B$7/Parameters!$B$9)*N56 -> 1.3327262 | W56: =V56 - C56 - D56 - LN(1+EXP(Parameters!$B$21*B56))/Parameters!$B$21 - IF(B56>0, 0,Parameters!$B$6*B56^2/E56) -> 1.0221181 | X56: =EXP(-Parameters!$B$56*A56) -> 0.45602849 | Y56: =IF(W56>0,W56^(1-Parameters!$B$53)/(1-Parameters!$B$53)*X56*Parameters!$B$71,-10+W56*1000) -> -1.2930001 | AA56: =B56/E56-B55/E55 -> -0.0032294408 | AB56: =C56/F56-C55/F55 -> -0.00034879423 | AC56: =D56/G56-D55/G55 -> 0.00012716195 | AD56: =X56*(AA56^2+AB56^2+AC56^2) -> 4.8189056e-06 | AE56: =B56/E56-2*B55/E55+B54/E54 -> -0.00021355513 | AF56: =C56/F56-2*C55/F55+C54/F54 -> 2.5089481e-05 | AG56: =D56/G56-2*D55/G55+D54/G54 -> -7.6476922e-06 | AH56: =X56*(AE56^2+AF56^2+AG56^2) -> 2.1111274e-08 | AM56: =H56*I56*J56 -> 0 | AN56: =E56*I56*J56 -> 11.289353 | AO56: =U56*I56*J56 -> 79.771761 | AP56: =V56*J56*I56 -> 320.48639 | AQ56: =-X56*V56*W56^(-Parameters!B$53)*Parameters!B$47*Parameters!B$46*M56 -> -1.3690863e-05 | AR56: =1000*EXP(-(Parameters!$B$55)*'6states'!A56)*AP56*Parameters!B$47*Parameters!B$46*M56 -> 1.1985597 | AS56: =SUM(AR56:AR$204)*EXP(Parameters!$B$55*A56) -> 560.4754 | AT56: =(B56+C56+D56)/V56 -> 0.2320819 | AU56: =(1/$S56-1/Parameters!$B$13) * LN(Parameters!$B$18) / LN(O56) -> 0.22652145 | AV56: =(Parameters!$B$18*'6states'!S56^+Parameters!$B$19*Parameters!$B$25^'6states'!S56)^((1-'6states'!S56)/'6states'!S56)*Parameters!$B$18*Parameters!$B$26^('6states'!S56-1) -> 0.29291861 | AW56: =(LN(AV56)-LN(AV$4))/ LN(O56) -> 0.22356752 | AX56: =1-2^-AU56 -> 0.1453068 | AY56: =1-2^-AV56 -> 0.18375091 | AZ56: =(1/$S56-1/Parameters!$B$13) * LN(Parameters!$B$18) / A56 -> 0.015868717
A57: =A56+Parameters!$B$71 -> 53 | B57: 0.00074340134 | C57: 0.088938443 | D57: 0.21974671 | E57: =MAX((1-Parameters!$B$4)^Parameters!B$71*E56 + B56*Parameters!B$71 - IF(B56>0,Parameters!$B$5,0)*B56^2/E56*Parameters!B$71, 0.0001) -> 0.044915159 | F57: =(1-Parameters!$B$4)^Parameters!B$71*F56+C56*Parameters!B$71-Parameters!$B$5*C56^2/F56*Parameters!B$71 -> 1.2191441 | G57: =(1-Parameters!$B$4)^Parameters!B$71*G56+D56*Parameters!B$71-Parameters!$B$5*D56^2/G56*Parameters!B$71 -> 3.2822162 | H57: =MAX(H56 * (1-Parameters!$B$4) ^ Parameters!B$71 + (LN(1+EXP(Parameters!$B$21*(-B56+0.004)))/Parameters!$B$21 -0.004) * Parameters!B$71,0) -> 0 | I57: =I56*(1+Parameters!$B$52)^Parameters!B$71 -> 9.5135941 | J57: =J56*(1+Parameters!$B$54)^Parameters!B$71 -> 25.857221 | K57: =I57*J57*EXP(-Parameters!$B$43*'6states'!A57)*(Parameters!$B$38/Parameters!$B$39*('6states'!E57+'6states'!H57)/Parameters!$E$25*(EXP(-Parameters!$B$39*Parameters!$E$25*'6states'!H57/('6states'!E57+'6states'!H57))-EXP(-Parameters!$B$39*Parameters!$E$25)) + Parameters!$B$40*'6states'!E57) -> 5.9225152 | L57: =L56+K57*Parameters!B$71 -> 3212.3823 | M57: =L57*Parameters!$B$46 -> 1.9274294 | N57: =EXP(-Parameters!$B$47/2*M57^2) -> 0.96335279 | O57: =MAX((Parameters!$B$63 + Parameters!$B$31*'6states'!A57 - '6states'!L57 + Parameters!$B$48/Parameters!$B$46)/Parameters!B$63,1) -> 39.144354 | P57: =Parameters!B$62*EXP(-Parameters!B$61*A57) -> 0.11953487 | Q57: =(1-Parameters!B$62)*O57^-Parameters!B$64 -> 0.34649988 | R57: =Parameters!B$62*EXP(-Parameters!B$61*A57)+(1-Parameters!B$62)*O57^-Parameters!B$64 -> 0.46603475 | S57: =1-R57/Parameters!$B$12 -> 0.76698263 | T57: =1/(1-S57) -> 4.2915255 | U57: =(Parameters!$B$19*(E57+Parameters!$B$20)^S57+Parameters!$B$18*F57^S57)^(1/S57) -> 0.33161358 | V57: =(Parameters!$B$10*G57^Parameters!$B$9+Parameters!$B$11*U57^Parameters!$B$9)^(Parameters!$B$7/Parameters!$B$9)*N57 -> 1.3323559 | W57: =V57 - C57 - D57 - LN(1+EXP(Parameters!$B$21*B57))/Parameters!$B$21 - IF(B57>0, 0,Parameters!$B$6*B57^2/E57) -> 1.0215387 | X57: =EXP(-Parameters!$B$56*A57) -> 0.44919419 | Y57: =IF(W57>0,W57^(1-Parameters!$B$53)/(1-Parameters!$B$53)*X57*Parameters!$B$71,-10+W57*1000) -> -1.2738752 | AA57: =B57/E57-B56/E56 -> -0.0034872615 | AB57: =C57/F57-C56/F56 -> -0.00032557074 | AC57: =D57/G57-D56/G56 -> 0.00011991694 | AD57: =X57*(AA57^2+AB57^2+AC57^2) -> 5.5167197e-06 | AE57: =B57/E57-2*B56/E56+B55/E55 -> -0.00025782075 | AF57: =C57/F57-2*C56/F56+C55/F55 -> 2.3223489e-05 | AG57: =D57/G57-2*D56/G56+D55/G55 -> -7.2450098e-06 | AH57: =X57*(AE57^2+AF57^2+AG57^2) -> 3.0124472e-08 | AM57: =H57*I57*J57 -> 0 | AN57: =E57*I57*J57 -> 11.048909 | AO57: =U57*I57*J57 -> 81.575318 | AP57: =V57*J57*I57 -> 327.75304 | AQ57: =-X57*V57*W57^(-Parameters!B$53)*Parameters!B$47*Parameters!B$46*M57 -> -1.3517182e-05 | AR57: =1000*EXP(-(Parameters!$B$55)*'6states'!A57)*AP57*Parameters!B$47*Parameters!B$46*M57 -> 1.1856445 | AS57: =SUM(AR57:AR$204)*EXP(Parameters!$B$55*A57) -> 572.79588 | AT57: =(B57+C57+D57)/V57 -> 0.23224166 | AU57: =(1/$S57-1/Parameters!$B$13) * LN(Parameters!$B$18) / LN(O57) -> 0.22615161 | AV57: =(Parameters!$B$18*'6states'!S57^+Parameters!$B$19*Parameters!$B$25^'6states'!S57)^((1-'6states'!S57)/'6states'!S57)*Parameters!$B$18*Parameters!$B$26^('6states'!S57-1) -> 0.2935099 | AW57: =(LN(AV57)-LN(AV$4))/ LN(O57) -> 0.22262674 | AX57: =1-2^-AU57 -> 0.14508767 | AY57: =1-2^-AV57 -> 0.18408538 | AZ57: =(1/$S57-1/Parameters!$B$13) * LN(Parameters!$B$18) / A57 -> 0.015648224
